Workbook

Sheet БДДС
A1: Бюджет движения денежных средств 2021г. Чтобы пользоваться таблицей, сделайте себе ее копию на свой гугл-диск
A2: Наименование статьи | B2: янв | C2: фев | D2: мар | E2: апр | F2: май | G2: июн | H2: июл | I2: авг | J2: сен | K2: окт | L2: ноя | M2: дек | N2: ГОД
A3: Остаток денежных средств на начало периода | C3: =B98 -> 0 | D3: =C98 -> 0 | E3: =D98 -> 0 | F3: =E98 -> 0 | G3: =F98 -> 0 | H3: =G98 -> 0 | I3: =H98 -> 0 | J3: =I98 -> 0 | ... M3: =L98 -> 0 | N3: =B3
A4: Поступления по операционной деятельности | B4: =B5+B6 -> 0 | C4: =C5+C6 -> 0 | D4: =D5+D6 -> 0 | E4: =E5+E6 -> 0 | F4: =F5+F6 -> 0 | G4: =G5+G6 -> 0 | H4: =H5+H6 -> 0 | I4: =I5+I6 -> 0 | ... M4: =M5+M6 -> 0 | N4: =B4+C4+D4+E4+F4+G4+H4+I4+J4+K4+L4+M4 -> 0
A5: Поступления от реализации товаров и услуг | N5: =B5+C5+D5+E5+F5+G5+H5+I5+J5+K5+L5+M5 -> 0
A6: Поступления прочие | N6: =B6+C6+D6+E6+F6+G6+H6+I6+J6+K6+L6+M6 -> 0
A7: Выплаты по операционной деятельности | B7: =B8+B9+B13+B16+B21+B26+B27+B31+B30+B35+B40+B44+B47+B52+B62+B66 -> 0 | C7: =C8+C9+C13+C16+C21+C26+C27+C31+C30+C35+C40+C44+C47+C52+C62+C66 -> 0 | D7: =D8+D9+D13+D16+D21+D26+D27+D31+D30+D35+D40+D44+D47+D52+D62+D66 -> 0 | E7: =E8+E9+E13+E16+E21+E26+E27+E31+E30+E35+E40+E44+E47+E52+E62+E66 -> 0 | F7: =F8+F9+F13+F16+F21+F26+F27+F31+F30+F35+F40+F44+F47+F52+F62+F66 -> 0 | G7: =G8+G9+G13+G16+G21+G26+G27+G31+G30+G35+G40+G44+G47+G52+G62+G66 -> 0 | H7: =H8+H9+H13+H16+H21+H26+H27+H31+H30+H35+H40+H44+H47+H52+H62+H66 -> 0 | I7: =I8+I9+I13+I16+I21+I26+I27+I31+I30+I35+I40+I44+I47+I52+I62+I66 -> 0 | ... N7: =N8+N9+N13+N16+N21+N26+N27+N31+N30+N35+N40+N44+N47+N52+N62+N66 -> 0
A8: Выплата заработной платы | N8: =B8+C8+D8+E8+F8+G8+H8+I8+J8+K8+L8+M8 -> 0
A9: Материальные расходы | B9: =B10+B11+B12 -> 0 | C9: =C10+C11+C12 -> 0 | D9: =D10+D11+D12 -> 0 | E9: =E10+E11+E12 -> 0 | F9: =F10+F11+F12 -> 0 | G9: =G10+G11+G12 -> 0 | H9: =H10+H11+H12 -> 0 | I9: =I10+I11+I12 -> 0 | ... N9: =N10+N11+N12 -> 0
A10: основные материалы | N10: =B10+C10+D10+E10+F10+G10+H10+I10+J10+K10+L10+M10 -> 0
A11: вспомогательные материалы | N11: =B11+C11+D11+E11+F11+G11+H11+I11+J11+K11+L11+M11 -> 0
A12: расходы на оборудование | N12: =B12+C12+D12+E12+F12+G12+H12+I12+J12+K12+L12+M12 -> 0
A13: Приобретение товаров для перепродажи | B13: =SUM(B14:B15) -> 0 | C13: =SUM(C14:C15) -> 0 | D13: =SUM(D14:D15) -> 0 | E13: =SUM(E14:E15) -> 0 | F13: =SUM(F14:F15) -> 0 | G13: =SUM(G14:G15) -> 0 | H13: =SUM(H14:H15) -> 0 | I13: =SUM(I14:I15) -> 0 | ... M13: =SUM(M14:M15) -> 0 | N13: =B13+C13+D13+E13+F13+G13+H13+I13+J13+K13+L13+M13 -> 0
A16: Содержание зданий | B16: =B17+B18+B19+B20 -> 0 | C16: =C17+C18+C19+C20 -> 0 | D16: =D17+D18+D19+D20 -> 0 | E16: =E17+E18+E19+E20 -> 0 | F16: =F17+F18+F19+F20 -> 0 | G16: =G17+G18+G19+G20 -> 0 | H16: =H17+H18+H19+H20 -> 0 | I16: =I17+I18+I19+I20 -> 0 | ... N16: =N17+N18+N19+N20 -> 0
A17: аренда | N17: =B17+C17+D17+E17+F17+G17+H17+I17+J17+K17+L17+M17 -> 0
A18: коммунальные расходы | N18: =B18+C18+D18+E18+F18+G18+H18+I18+J18+K18+L18+M18 -> 0
A19: охрана | N19: =B19+C19+D19+E19+F19+G19+H19+I19+J19+K19+L19+M19 -> 0
A20: ремонт помещений | N20: =B20+C20+D20+E20+F20+G20+H20+I20+J20+K20+L20+M20 -> 0
A21: Транспортные расходы | B21: =B22+B23+B24+B25 -> 0 | C21: =C22+C23+C24+C25 -> 0 | D21: =D22+D23+D24+D25 -> 0 | E21: =E22+E23+E24+E25 -> 0 | F21: =F22+F23+F24+F25 -> 0 | G21: =G22+G23+G24+G25 -> 0 | H21: =H22+H23+H24+H25 -> 0 | I21: =I22+I23+I24+I25 -> 0 | ... N21: =N22+N23+N24+N25 -> 0
A22: ГСМ | N22: =B22+C22+D22+E22+F22+G22+H22+I22+J22+K22+L22+M22 -> 0
A23: Ремонт и обслуживание транспорта | N23: =B23+C23+D23+E23+F23+G23+H23+I23+J23+K23+L23+M23 -> 0
A24: страхование а/м | N24: =B24+C24+D24+E24+F24+G24+H24+I24+J24+K24+L24+M24 -> 0
A25: прочие транспортные расходы | N25: =B25+C25+D25+E25+F25+G25+H25+I25+J25+K25+L25+M25 -> 0
A26: Реклама и продвижение | N26: =B26+C26+D26+E26+F26+G26+H26+I26+J26+K26+L26+M26 -> 0
A27: Услуги связи | B27: =B28+B29 -> 0 | C27: =C28+C29 -> 0 | D27: =D28+D29 -> 0 | E27: =E28+E29 -> 0 | F27: =F28+F29 -> 0 | G27: =G28+G29 -> 0 | H27: =H28+H29 -> 0 | I27: =I28+I29 -> 0 | ... M27: =M28+M29 -> 0 | N27: =B27+C27+D27+E27+F27+G27+H27+I27+J27+K27+L27+M27 -> 0
A28: телефон | N28: =B28+C28+D28+E28+F28+G28+H28+I28+J28+K28+L28+M28 -> 0
A29: интернет | N29: =B29+C29+D29+E29+F29+G29+H29+I29+J29+K29+L29+M29 -> 0
A30: Спецодежда | N30: =B30+C30+D30+E30+F30+G30+H30+I30+J30+K30+L30+M30 -> 0
A31: Расходы на персонал | B31: =B32+B33+B34 -> 0 | C31: =C32+C33+C34 -> 0 | D31: =D32+D33+D34 -> 0 | E31: =E32+E33+E34 -> 0 | F31: =F32+F33+F34 -> 0 | G31: =G32+G33+G34 -> 0 | H31: =H32+H33+H34 -> 0 | I31: =I32+I33+I34 -> 0 | ... M31: =M32+M33+M34 -> 0 | N31: =B31+C31+D31+E31+F31+G31+H31+I31+J31+K31+L31+M31 -> 0
A32: обучение сотрудников | N32: =B32+C32+D32+E32+F32+G32+H32+I32+J32+K32+L32+M32 -> 0
A33: подбор персонала | N33: =B33+C33+D33+E33+F33+G33+H33+I33+J33+K33+L33+M33 -> 0
A34: прочие расходы на персонал | N34: =B34+C34+D34+E34+F34+G34+H34+I34+J34+K34+L34+M34 -> 0
A35: Информационные и консультационные услуги | B35: =B36+B37+B39+B38 -> 0 | C35: =C36+C37+C39+C38 -> 0 | D35: =D36+D37+D39+D38 -> 0 | E35: =E36+E37+E39+E38 -> 0 | F35: =F36+F37+F39+F38 -> 0 | G35: =G36+G37+G39+G38 -> 0 | H35: =H36+H37+H39+H38 -> 0 | I35: =I36+I37+I39+I38 -> 0 | ... N35: =N36+N37+N39+N38 -> 0
A36: поддержка ПО | N36: =B36+C36+D36+E36+F36+G36+H36+I36+J36+K36+L36+M36 -> 0
A37: аутсорсинг | N37: =B37+C37+D37+E37+F37+G37+H37+I37+J37+K37+L37+M37 -> 0
A38: услуги ИП | N38: =B38+C38+D38+E38+F38+G38+H38+I38+J38+K38+L38+M38 -> 0
A39: прочие информационные услуги | N39: =B39+C39+D39+E39+F39+G39+H39+I39+J39+K39+L39+M39 -> 0
A40: Расходы офиса | B40: =B41+B42+B43 -> 0 | C40: =C41+C42+C43 -> 0 | D40: =D41+D42+D43 -> 0 | E40: =E41+E42+E43 -> 0 | F40: =F41+F42+F43 -> 0 | G40: =G41+G42+G43 -> 0 | H40: =H41+H42+H43 -> 0 | I40: =I41+I42+I43 -> 0 | ... M40: =M41+M42+M43 -> 0 | N40: =B40+C40+D40+E40+F40+G40+H40+I40+J40+K40+L40+M40 -> 0
A41: хозяйственные расходы | N41: =B41+C41+D41+E41+F41+G41+H41+I41+J41+K41+L41+M41 -> 0
A42: канцелярские товары | N42: =B42+C42+D42+E42+F42+G42+H42+I42+J42+K42+L42+M42 -> 0
A43: содержание оргтехники | N43: =B43+C43+D43+E43+F43+G43+H43+I43+J43+K43+L43+M43 -> 0
A44: Расходы на денежное обращение | B44: =B45+B46 -> 0 | C44: =C45+C46 -> 0 | D44: =D45+D46 -> 0 | E44: =E45+E46 -> 0 | F44: =F45+F46 -> 0 | G44: =G45+G46 -> 0 | H44: =H45+H46 -> 0 | I44: =I45+I46 -> 0 | ... M44: =M45+M46 -> 0 | N44: =B44+C44+D44+E44+F44+G44+H44+I44+J44+K44+L44+M44 -> 0
A45: РКО | N45: =B45+C45+D45+E45+F45+G45+H45+I45+J45+K45+L45+M45 -> 0
A46: прочие расходы на ден.обращение | N46: =B46+C46+D46+E46+F46+G46+H46+I46+J46+K46+L46+M46 -> 0
A47: Прочие административные расходы | B47: =SUM(B48:B51) -> 0 | C47: =SUM(C48:C51) -> 0 | D47: =SUM(D48:D51) -> 0 | E47: =SUM(E48:E51) -> 0 | F47: =SUM(F48:F51) -> 0 | G47: =SUM(G48:G51) -> 0 | H47: =SUM(H48:H51) -> 0 | I47: =SUM(I48:I51) -> 0 | ... M47: =SUM(M48:M51) -> 0 | N47: =B47+C47+D47+E47+F47+G47+H47+I47+J47+K47+L47+M47 -> 0
A48: командировки | N48: =B48+C48+D48+E48+F48+G48+H48+I48+J48+K48+L48+M48 -> 0
A49: копировальные услуги | N49: =B49+C49+D49+E49+F49+G49+H49+I49+J49+K49+L49+M49 -> 0
A50: представительские расходы | N50: =B50+C50+D50+E50+F50+G50+H50+I50+J50+K50+L50+M50 -> 0
A51: почтовые расходы | N51: =B51+C51+D51+E51+F51+G51+H51+I51+J51+K51+L51+M51 -> 0
A52: Налоги | B52: =B53+B54+B55+B56+B57+B58+B59+B60+B61 -> 0 | C52: =C53+C54+C55+C56+C57+C58+C59+C60+C61 -> 0 | D52: =D53+D54+D55+D56+D57+D58+D59+D60+D61 -> 0 | E52: =E53+E54+E55+E56+E57+E58+E59+E60+E61 -> 0 | F52: =F53+F54+F55+F56+F57+F58+F59+F60+F61 -> 0 | G52: =G53+G54+G55+G56+G57+G58+G59+G60+G61 -> 0 | H52: =H53+H54+H55+H56+H57+H58+H59+H60+H61 -> 0 | I52: =I53+I54+I55+I56+I57+I58+I59+I60+I61 -> 0 | ... N52: =N53+N54+N55+N56+N57+N58+N59+N60+N61 -> 0
A53: Отчисления от ФОТ | N53: =B53+C53+D53+E53+F53+G53+H53+I53+J53+K53+L53+M53 -> 0
A54: НДФЛ | N54: =B54+C54+D54+E54+F54+G54+H54+I54+J54+K54+L54+M54 -> 0
A55: УСН | N55: =B55+C55+D55+E55+F55+G55+H55+I55+J55+K55+L55+M55 -> 0
A56: НДС | N56: =B56+C56+D56+E56+F56+G56+H56+I56+J56+K56+L56+M56 -> 0
A57: Налог на прибыль | N57: =B57+C57+D57+E57+F57+G57+H57+I57+J57+K57+L57+M57 -> 0
A58: Налог на имущество | N58: =B58+C58+D58+E58+F58+G58+H58+I58+J58+K58+L58+M58 -> 0
A59: Транспортный налог | N59: =B59+C59+D59+E59+F59+G59+H59+I59+J59+K59+L59+M59 -> 0
A60: ЕНВД | N60: =B60+C60+D60+E60+F60+G60+H60+I60+J60+K60+L60+M60 -> 0
A61: Прочие налоги, сборы | N61: =B61+C61+D61+E61+F61+G61+H61+I61+J61+K61+L61+M61 -> 0
A62: Штрафы, пени по налогам | B62: =SUM(B63:B65) -> 0 | C62: =SUM(C63:C65) -> 0 | D62: =SUM(D63:D65) -> 0 | E62: =SUM(E63:E65) -> 0 | F62: =SUM(F63:F65) -> 0 | G62: =SUM(G63:G65) -> 0 | H62: =SUM(H63:H65) -> 0 | I62: =SUM(I63:I65) -> 0 | ... M62: =SUM(M63:M65) -> 0 | N62: =B62+C62+D62+E62+F62+G62+H62+I62+J62+K62+L62+M62 -> 0
A63: штрафы в налоговую | B63: 0 | C63: 0 | D63: 0 | E63: 0 | F63: 0 | G63: 0 | H63: 0 | I63: 0 | J63: 0 | K63: 0 | L63: 0 | M63: 0 | N63: =B63+C63+D63+E63+F63+G63+H63+I63+J63+K63+L63+M63 -> 0
A64: штрафы в ГИБДД | B64: 0 | C64: 0 | D64: 0 | E64: 0 | F64: 0 | G64: 0 | H64: 0 | I64: 0 | J64: 0 | K64: 0 | L64: 0 | M64: 0 | N64: =B64+C64+D64+E64+F64+G64+H64+I64+J64+K64+L64+M64 -> 0
A65: прочие штрафы | B65: 0 | C65: 0 | D65: 0 | E65: 0 | F65: 0 | G65: 0 | H65: 0 | I65: 0 | J65: 0 | K65: 0 | L65: 0 | M65: 0 | N65: =B65+C65+D65+E65+F65+G65+H65+I65+J65+K65+L65+M65 -> 0
A66: Возврат денежных средств | B66: =SUM(B67) -> 0 | C66: =SUM(C67) -> 0 | D66: =SUM(D67) -> 0 | E66: =SUM(E67) -> 0 | F66: =SUM(F67) -> 0 | G66: =SUM(G67) -> 0 | H66: =SUM(H67) -> 0 | I66: =SUM(I67) -> 0 | ... M66: =SUM(M67) -> 0 | N66: =B66+C66+D66+E66+F66+G66+H66+I66+J66+K66+L66+M66 -> 0
A67: возврат покупателям | N67: =B67+C67+D67+E67+F67+G67+H67+I67+J67+K67+L67+M67 -> 0
A68: Денежный поток по операц. деятельности | B68: =B4-B7 -> 0 | C68: =C4-C7 -> 0 | D68: =D4-D7 -> 0 | E68: =E4-E7 -> 0 | F68: =F4-F7 -> 0 | G68: =G4-G7 -> 0 | H68: =H4-H7 -> 0 | I68: =I4-I7 -> 0 | ... N68: =N4-N7 -> 0
A69: Поступления по инвестиционной деятельности | B69: =B70+B71+B72 -> 0 | C69: =C70+C71+C72 -> 0 | D69: =D70+D71+D72 -> 0 | E69: =E70+E71+E72 -> 0 | F69: =F70+F71+F72 -> 0 | G69: =G70+G71+G72 -> 0 | H69: =H70+H71+H72 -> 0 | I69: =I70+I71+I72 -> 0 | ... M69: =M70+M71+M72 -> 0 | N69: =B69+C69+D69+E69+F69+G69+H69+I69+J69+K69+L69+M69 -> 0
N70: =B70+C70+D70+E70+F70+G70+H70+I70+J70+K70+L70+M70 -> 0
N71: =B71+C71+D71+E71+F71+G71+H71+I71+J71+K71+L71+M71 -> 0
N72: =B72+C72+D72+E72+F72+G72+H72+I72+J72+K72+L72+M72 -> 0
A73: Выбытие по инвестиционной деятельности | B73: =B74+B75+B76+B77 -> 0 | C73: =C74+C75+C76+C77 -> 0 | D73: =D74+D75+D76+D77 -> 0 | E73: =E74+E75+E76+E77 -> 0 | F73: =F74+F75+F76+F77 -> 0 | G73: =G74+G75+G76+G77 -> 0 | H73: =H74+H75+H76+H77 -> 0 | I73: =I74+I75+I76+I77 -> 0 | ... N73: =N74+N75+N76+N77 -> 0
N74: =B74+C74+D74+E74+F74+G74+H74+I74+J74+K74+L74+M74 -> 0
N75: =B75+C75+D75+E75+F75+G75+H75+I75+J75+K75+L75+M75 -> 0
N76: =B76+C76+D76+E76+F76+G76+H76+I76+J76+K76+L76+M76 -> 0
N77: =B77+C77+D77+E77+F77+G77+H77+I77+J77+K77+L77+M77 -> 0
A78: Денежный поток по инвест. деятельности | B78: =B69-B73 -> 0 | C78: =C69-C73 -> 0 | D78: =D69-D73 -> 0 | E78: =E69-E73 -> 0 | F78: =F69-F73 -> 0 | G78: =G69-G73 -> 0 | H78: =H69-H73 -> 0 | I78: =I69-I73 -> 0 | ... N78: =N69-N73 -> 0
A79: Поступления от финансовой деятельности | B79: =B80+B81+B82+B83 -> 0 | C79: =C80+C81+C82+C83 -> 0 | D79: =D80+D81+D82+D83 -> 0 | E79: =E80+E81+E82+E83 -> 0 | F79: =F80+F81+F82+F83 -> 0 | G79: =G80+G81+G82+G83 -> 0 | H79: =H80+H81+H82+H83 -> 0 | I79: =I80+I81+I82+I83 -> 0 | ... M79: =M80+M81+M82+M83 -> 0 | N79: =B79+C79+D79+E79+F79+G79+H79+I79+J79+K79+L79+M79 -> 0
A80: Поступление банковских кредитов | N80: =B80+C80+D80+E80+F80+G80+H80+I80+J80+K80+L80+M80 -> 0
A81: Поступление займов | N81: =B81+C81+D81+E81+F81+G81+H81+I81+J81+K81+L81+M81 -> 0
A82: Возвраты выданных займов | N82: =B82+C82+D82+E82+F82+G82+H82+I82+J82+K82+L82+M82 -> 0
A83: Поступление %% выданным займам | N83: =B83+C83+D83+E83+F83+G83+H83+I83+J83+K83+L83+M83 -> 0
A84: Выбытия по финансовой деятельности | B84: =SUM(B85:B88) -> 0 | C84: =SUM(C85:C88) -> 0 | D84: =SUM(D85:D88) -> 0 | E84: =SUM(E85:E88) -> 0 | F84: =SUM(F85:F88) -> 0 | G84: =SUM(G85:G88) -> 0 | H84: =SUM(H85:H88) -> 0 | I84: =SUM(I85:I88) -> 0 | ... M84: =SUM(M85:M88) -> 0 | N84: =B84+C84+D84+E84+F84+G84+H84+I84+J84+K84+L84+M84 -> 0
A85: Погашение банковских кредитов | N85: =B85+C85+D85+E85+F85+G85+H85+I85+J85+K85+L85+M85 -> 0
A86: Погашение займов | N86: =B86+C86+D86+E86+F86+G86+H86+I86+J86+K86+L86+M86 -> 0
A87: Погашение %% по банк. Кредитам (в т.ч. % за овердрафт) | N87: =B87+C87+D87+E87+F87+G87+H87+I87+J87+K87+L87+M87 -> 0
A88: Предоставление займов | N88: =B88+C88+D88+E88+F88+G88+H88+I88+J88+K88+L88+M88 -> 0
A89: Денежный поток по финансовой деятельности | B89: =B79-B84 -> 0 | C89: =C79-C84 -> 0 | D89: =D79-D84 -> 0 | E89: =E79-E84 -> 0 | F89: =F79-F84 -> 0 | G89: =G79-G84 -> 0 | H89: =H79-H84 -> 0 | I89: =I79-I84 -> 0 | ... N89: =N79-N84 -> 0
A90: Прочие поступления | B90: =B91 | C90: =C91 | D90: =D91 | E90: =E91 | F90: =F91 | G90: =G91 | H90: =H91 | I90: =I91 | ... M90: =M91 | N90: =B90+C90+D90+E90+F90+G90+H90+I90+J90+K90+L90+M90 -> 0
N91: =B91+C91+D91+E91+F91+G91+H91+I91+J91+K91+L91+M91 -> 0
A92: Прочие выплаты | B92: =B93 | C92: =C93 | D92: =D93 | E92: =E93 | F92: =F93 | G92: =G93 | H92: =H93 | I92: =I93 | ... M92: =M93 | N92: =B92+C92+D92+E92+F92+G92+H92+I92+J92+K92+L92+M92 -> 0
A93: Выплата дивидендов | N93: =B93+C93+D93+E93+F93+G93+H93+I93+J93+K93+L93+M93 -> 0
A94: Денежный поток по прочим поступл. и выплатам | B94: =B90-B92 -> 0 | C94: =C90-C92 -> 0 | D94: =D90-D92 -> 0 | E94: =E90-E92 -> 0 | F94: =F90-F92 -> 0 | G94: =G90-G92 -> 0 | H94: =H90-H92 -> 0 | I94: =I90-I92 -> 0 | ... N94: =N90-N92 -> 0
A95: Итого поступлений | B95: =B4+B69+B79+B90 -> 0 | C95: =C4+C69+C79+C90 -> 0 | D95: =D4+D69+D79+D90 -> 0 | E95: =E4+E69+E79+E90 -> 0 | F95: =F4+F69+F79+F90 -> 0 | G95: =G4+G69+G79+G90 -> 0 | H95: =H4+H69+H79+H90 -> 0 | I95: =I4+I69+I79+I90 -> 0 | ... N95: =N4+N69+N79+N90 -> 0
A96: Итого выплат | B96: =B7+B73+B84+B92 -> 0 | C96: =C7+C73+C84+C92 -> 0 | D96: =D7+D73+D84+D92 -> 0 | E96: =E7+E73+E84+E92 -> 0 | F96: =F7+F73+F84+F92 -> 0 | G96: =G7+G73+G84+G92 -> 0 | H96: =H7+H73+H84+H92 -> 0 | I96: =I7+I73+I84+I92 -> 0 | ... N96: =N7+N73+N84+N92 -> 0
A97: Чистый денежный поток | B97: =B95-B96 -> 0 | C97: =C95-C96 -> 0 | D97: =D95-D96 -> 0 | E97: =E95-E96 -> 0 | F97: =F95-F96 -> 0 | G97: =G95-G96 -> 0 | H97: =H95-H96 -> 0 | I97: =I95-I96 -> 0 | ... N97: =N95-N96 -> 0
A98: Остаток денежных средств на конец периода | B98: =B3+B97 -> 0 | C98: =C3+C97 -> 0 | D98: =D3+D97 -> 0 | E98: =E3+E97 -> 0 | F98: =F3+F97 -> 0 | G98: =G3+G97 -> 0 | H98: =H3+H97 -> 0 | I98: =I3+I97 -> 0 | ... N98: =N3+N97 -> 0

Sheet Баланс
A1: Прогнозный баланс 2021
A2: Наименование статьи | B2: янв | C2: фев | D2: мар | E2: апр | F2: май | G2: июн | H2: июл | I2: авг | J2: сен | K2: окт | L2: ноя | M2: дек
A3: Активы | B3: =B4+B8 -> 0 | C3: =C4+C8 -> 0 | D3: =D4+D8 -> 0 | E3: =E4+E8 -> 0 | F3: =F4+F8 -> 0 | G3: =G4+G8 -> 0 | H3: =H4+H8 -> 0 | I3: =I4+I8 -> 0 | ... M3: =M4+M8 -> 0
A4: Внеоборотные активы | B4: =SUM(B5:B7) -> 0 | C4: =SUM(C5:C7) -> 0 | D4: =SUM(D5:D7) -> 0 | E4: =SUM(E5:E7) -> 0 | F4: =SUM(F5:F7) -> 0 | G4: =SUM(G5:G7) -> 0 | H4: =SUM(H5:H7) -> 0 | I4: =SUM(I5:I7) -> 0 | ... M4: =SUM(M5:M7) -> 0
A5: Производственное оборудование
A6: Транспорт
A7: Мебель
A8: Оборотные активы | B8: =SUM(B9:B13) -> 0 | C8: =SUM(C9:C13) -> 0 | D8: =SUM(D9:D13) -> 0 | E8: =SUM(E9:E13) -> 0 | F8: =SUM(F9:F13) -> 0 | G8: =SUM(G9:G13) -> 0 | H8: =SUM(H9:H13) -> 0 | I8: =SUM(I9:I13) -> 0 | ... M8: =SUM(M9:M13) -> 0
A9: Запасы материалов
A10: Запасы готовой продукции
A11: Денежные средства
A12: Дебиторская задолженность
A13: Прочие оборотные активы
A14: Пассивы | B14: =B15+B20+B24 -> 0 | C14: =C15+C20+C24 -> 0 | D14: =D15+D20+D24 -> 0 | E14: =E15+E20+E24 -> 0 | F14: =F15+F20+F24 -> 0 | G14: =G15+G20+G24 -> 0 | H14: =H15+H20+H24 -> 0 | I14: =I15+I20+I24 -> 0 | ... M14: =M15+M20+M24 -> 0
A15: Собственный капитал | B15: =SUM(B16:B19) -> 0 | C15: =SUM(C16:C19) -> 0 | D15: =SUM(D16:D19) -> 0 | E15: =SUM(E16:E19) -> 0 | F15: =SUM(F16:F19) -> 0 | G15: =SUM(G16:G19) -> 0 | H15: =SUM(H16:H19) -> 0 | I15: =SUM(I16:I19) -> 0 | ... M15: =SUM(M16:M19) -> 0
A16: Уставный капитал
A17: Добавочный капитал
A18: Резервный капитал
A19: Нераспределенная прибыль
A20: Долгосрочные обязательства | B20: =SUM(B21:B23) -> 0 | C20: =SUM(C21:C23) -> 0 | D20: =SUM(D21:D23) -> 0 | E20: =SUM(E21:E23) -> 0 | F20: =SUM(F21:F23) -> 0 | G20: =SUM(G21:G23) -> 0 | H20: =SUM(H21:H23) -> 0 | I20: =SUM(I21:I23) -> 0 | ... M20: =SUM(M21:M23) -> 0
A21: Задолженность по кредитам и займам
A24: Краткосрчные обязательства | B24: =SUM(B25:B29) -> 0 | C24: =SUM(C25:C29) -> 0 | D24: =SUM(D25:D29) -> 0 | E24: =SUM(E25:E29) -> 0 | F24: =SUM(F25:F29) -> 0 | G24: =SUM(G25:G29) -> 0 | H24: =SUM(H25:H29) -> 0 | I24: =SUM(I25:I29) -> 0 | ... M24: =SUM(M25:M29) -> 0
A25: Кредиторская задолженность перед поставщиками
A26: Кредиторская задолженность перед покупателями
A27: Кредиторская задолженность перед сотрудниками
A28: Кредиторская задолженность по налогам и взносам
A30: контроль | B30: =IF(B3=B14,"","ОШИБКА") | C30: =IF(C3=C14,"","ОШИБКА") | D30: =IF(D3=D14,"","ОШИБКА") | E30: =IF(E3=E14,"","ОШИБКА") | F30: =IF(F3=F14,"","ОШИБКА") | G30: =IF(G3=G14,"","ОШИБКА") | H30: =IF(H3=H14,"","ОШИБКА") | I30: =IF(I3=I14,"","ОШИБКА") | ... M30: =IF(M3=M14,"","ОШИБКА")

Sheet ОПиУ
A1: Прогнозный отчет о прибылях и убытках 2021 г.
A2: Наименование статьи | B2: янв | C2: фев | D2: мар | E2: апр | F2: май | G2: июн | H2: июл | I2: авг | J2: сен | K2: окт | L2: ноя | M2: дек | N2: ГОД
A3: Доход | B3: =B4 | C3: =C4 | D3: =D4 | E3: =E4 | F3: =F4 | G3: =G4 | H3: =H4 | I3: =I4 | ... N3: =N4 -> 0
A4: Доход от продаж | N4: =B4+C4+D4+E4+F4+G4+H4+I4+J4+K4+L4+M4 -> 0
A5: Расход | B5: =B6+B9+B26+B30+B31+B34+B44+B43 -> 0 | C5: =C6+C9+C26+C30+C31+C34+C44+C43 -> 0 | D5: =D6+D9+D26+D30+D31+D34+D44+D43 -> 0 | E5: =E6+E9+E26+E30+E31+E34+E44+E43 -> 0 | F5: =F6+F9+F26+F30+F31+F34+F44+F43 -> 0 | G5: =G6+G9+G26+G30+G31+G34+G44+G43 -> 0 | H5: =H6+H9+H26+H30+H31+H34+H44+H43 -> 0 | I5: =I6+I9+I26+I30+I31+I34+I44+I43 -> 0 | ... N5: =N6+N9+N26+N30+N31+N34+N44+N43 -> 0
A6: Материальные расходы | B6: =SUM(B7:B8) -> 0 | C6: =SUM(C7:C8) -> 0 | D6: =SUM(D7:D8) -> 0 | E6: =SUM(E7:E8) -> 0 | F6: =SUM(F7:F8) -> 0 | G6: =SUM(G7:G8) -> 0 | H6: =SUM(H7:H8) -> 0 | I6: =SUM(I7:I8) -> 0 | ... M6: =SUM(M7:M8) -> 0 | N6: =B6+C6+D6+E6+F6+G6+H6+I6+J6+K6+L6+M6 -> 0
A7: сырье | N7: =B7+C7+D7+E7+F7+G7+H7+I7+J7+K7+L7+M7 -> 0
A8: основные материалы | N8: =B8+C8+D8+E8+F8+G8+H8+I8+J8+K8+L8+M8 -> 0
A9: Приобретение товаров для перепродажи | B9: =SUM(B10:B11) -> 0 | C9: =SUM(C10:C11) -> 0 | D9: =SUM(D10:D11) -> 0 | E9: =SUM(E10:E11) -> 0 | F9: =SUM(F10:F11) -> 0 | G9: =SUM(G10:G11) -> 0 | H9: =SUM(H10:H11) -> 0 | I9: =SUM(I10:I11) -> 0 | ... M9: =SUM(M10:M11) -> 0 | N9: =B9+C9+D9+E9+F9+G9+H9+I9+J9+K9+L9+M9 -> 0
N10: =B10+C10+D10+E10+F10+G10+H10+I10+J10+K10+L10+M10 -> 0
N11: =B11+C11+D11+E11+F11+G11+H11+I11+J11+K11+L11+M11 -> 0
A12: Маржинальная прибыль | B12: =B3-B6-B9 -> 0 | C12: =C3-C6-C9 -> 0 | D12: =D3-D6-D9 -> 0 | E12: =E3-E6-E9 -> 0 | F12: =F3-F6-F9 -> 0 | G12: =G3-G6-G9 -> 0 | H12: =H3-H6-H9 -> 0 | I12: =I3-I6-I9 -> 0 | ... N12: =N3-N6-N9 -> 0
A13: рентабельность маржинальной прибыли, % | B13: =IFERROR(B12/B3,) | C13: =IFERROR(C12/C3,) | D13: =IFERROR(D12/D3,) | E13: =IFERROR(E12/E3,) | F13: =IFERROR(F12/F3,) | G13: =IFERROR(G12/G3,) | H13: =IFERROR(H12/H3,) | I13: =IFERROR(I12/I3,) | ... N13: =IFERROR(N12/N3,)
A14: Общепроизводственные расходы
A15: Расходы на оплату труда
A16: Содержание зданий
A17: Транспортные расходы
A18: Расходы на содержание оборудования
A19: Расходы на персонал
A20: Прочие производственые расходы расходы
A21: Спецодежда
A22: Валовая прибыль | B22: =B13-B16-B19 -> 0 | C22: =C13-C16-C19 -> 0 | D22: =D13-D16-D19 -> 0 | E22: =E13-E16-E19 -> 0 | F22: =F13-F16-F19 -> 0 | G22: =G13-G16-G19 -> 0 | H22: =H13-H16-H19 -> 0 | I22: =I13-I16-I19 -> 0 | ... N22: =N13-N16-N19 -> 0
A23: рентабельность валовой прибыли, % | B23: =IFERROR(B22/B13,) | C23: =IFERROR(C22/C13,) | D23: =IFERROR(D22/D13,) | E23: =IFERROR(E22/E13,) | F23: =IFERROR(F22/F13,) | G23: =IFERROR(G22/G13,) | H23: =IFERROR(H22/H13,) | I23: =IFERROR(I22/I13,) | ... N23: =IFERROR(N22/N13,)
A24: Административные расходы | B24: =SUM(B25:B34) -> 0 | C24: =SUM(C25:C34) -> 0 | D24: =SUM(D25:D34) -> 0 | E24: =SUM(E25:E34) -> 0 | F24: =SUM(F25:F34) -> 0 | G24: =SUM(G25:G34) -> 0 | H24: =SUM(H25:H34) -> 0 | I24: =SUM(I25:I34) -> 0 | ... N24: =SUM(N25:N34) -> 0
A25: Расходы на оплату труда | B25: ='БДР-свод_БЕЗ НДС'!B50 -> 0 | C25: ='БДР-свод_БЕЗ НДС'!C50 -> 0 | D25: ='БДР-свод_БЕЗ НДС'!D50 -> 0 | E25: ='БДР-свод_БЕЗ НДС'!E50 -> 0 | F25: ='БДР-свод_БЕЗ НДС'!F50 -> 0 | G25: ='БДР-свод_БЕЗ НДС'!G50 -> 0 | H25: ='БДР-свод_БЕЗ НДС'!H50 -> 0 | I25: ='БДР-свод_БЕЗ НДС'!I50 -> 0 | ... M25: ='БДР-свод_БЕЗ НДС'!M50 -> 0
A26: Содержание зданий | B26: ='БДР-свод_БЕЗ НДС'!B54 -> 0 | C26: ='БДР-свод_БЕЗ НДС'!C54 -> 0 | D26: ='БДР-свод_БЕЗ НДС'!D54 -> 0 | E26: ='БДР-свод_БЕЗ НДС'!E54 -> 0 | F26: ='БДР-свод_БЕЗ НДС'!F54 -> 0 | G26: ='БДР-свод_БЕЗ НДС'!G54 -> 0 | H26: ='БДР-свод_БЕЗ НДС'!H54 -> 0 | I26: ='БДР-свод_БЕЗ НДС'!I54 -> 0 | ... M26: ='БДР-свод_БЕЗ НДС'!M54 -> 0 | N26: =B26+C26+D26+E26+F26+G26+H26+I26+J26+K26+L26+M26 -> 0
A27: Услуги связи | B27: ='БДР-свод_БЕЗ НДС'!B59 -> 0 | C27: ='БДР-свод_БЕЗ НДС'!C59 -> 0 | D27: ='БДР-свод_БЕЗ НДС'!D59 -> 0 | E27: ='БДР-свод_БЕЗ НДС'!E59 -> 0 | F27: ='БДР-свод_БЕЗ НДС'!F59 -> 0 | G27: ='БДР-свод_БЕЗ НДС'!G59 -> 0 | H27: ='БДР-свод_БЕЗ НДС'!H59 -> 0 | I27: ='БДР-свод_БЕЗ НДС'!I59 -> 0 | ... M27: ='БДР-свод_БЕЗ НДС'!M59 -> 0 | N27: =B27+C27+D27+E27+F27+G27+H27+I27+J27+K27+L27+M27 -> 0
A28: Расходы на персонал | B28: ='БДР-свод_БЕЗ НДС'!B62 -> 0 | C28: ='БДР-свод_БЕЗ НДС'!C62 -> 0 | D28: ='БДР-свод_БЕЗ НДС'!D62 -> 0 | E28: ='БДР-свод_БЕЗ НДС'!E62 -> 0 | F28: ='БДР-свод_БЕЗ НДС'!F62 -> 0 | G28: ='БДР-свод_БЕЗ НДС'!G62 -> 0 | H28: ='БДР-свод_БЕЗ НДС'!H62 -> 0 | I28: ='БДР-свод_БЕЗ НДС'!I62 -> 0 | ... M28: ='БДР-свод_БЕЗ НДС'!M62 -> 0 | N28: =B28+C28+D28+E28+F28+G28+H28+I28+J28+K28+L28+M28 -> 0
A29: Расходы офиса | B29: ='БДР-свод_БЕЗ НДС'!B66 -> 0 | C29: ='БДР-свод_БЕЗ НДС'!C66 -> 0 | D29: ='БДР-свод_БЕЗ НДС'!D66 -> 0 | E29: ='БДР-свод_БЕЗ НДС'!E66 -> 0 | F29: ='БДР-свод_БЕЗ НДС'!F66 -> 0 | G29: ='БДР-свод_БЕЗ НДС'!G66 -> 0 | H29: ='БДР-свод_БЕЗ НДС'!H66 -> 0 | I29: ='БДР-свод_БЕЗ НДС'!I66 -> 0 | ... M29: ='БДР-свод_БЕЗ НДС'!M66 -> 0 | N29: =B29+C29+D29+E29+F29+G29+H29+I29+J29+K29+L29+M29 -> 0
A30: Информац. и консультац. услуги | B30: ='БДР-свод_БЕЗ НДС'!B70 -> 0 | C30: ='БДР-свод_БЕЗ НДС'!C70 -> 0 | D30: ='БДР-свод_БЕЗ НДС'!D70 -> 0 | E30: ='БДР-свод_БЕЗ НДС'!E70 -> 0 | F30: ='БДР-свод_БЕЗ НДС'!F70 -> 0 | G30: ='БДР-свод_БЕЗ НДС'!G70 -> 0 | H30: ='БДР-свод_БЕЗ НДС'!H70 -> 0 | I30: ='БДР-свод_БЕЗ НДС'!I70 -> 0 | ... M30: ='БДР-свод_БЕЗ НДС'!M70 -> 0 | N30: =N3*3% -> 0
A31: Расходы на денежное обращение | B31: ='БДР-свод_БЕЗ НДС'!B74 -> 0 | C31: ='БДР-свод_БЕЗ НДС'!C74 -> 0 | D31: ='БДР-свод_БЕЗ НДС'!D74 -> 0 | E31: ='БДР-свод_БЕЗ НДС'!E74 -> 0 | F31: ='БДР-свод_БЕЗ НДС'!F74 -> 0 | G31: ='БДР-свод_БЕЗ НДС'!G74 -> 0 | H31: ='БДР-свод_БЕЗ НДС'!H74 -> 0 | I31: ='БДР-свод_БЕЗ НДС'!I74 -> 0 | ... M31: ='БДР-свод_БЕЗ НДС'!M74 -> 0 | N31: =B31+C31+D31+E31+F31+G31+H31+I31+J31+K31+L31+M31 -> 0
A32: Прочие административные расходы | B32: ='БДР-свод_БЕЗ НДС'!B78 -> 0 | C32: ='БДР-свод_БЕЗ НДС'!C78 -> 0 | D32: ='БДР-свод_БЕЗ НДС'!D78 -> 0 | E32: ='БДР-свод_БЕЗ НДС'!E78 -> 0 | F32: ='БДР-свод_БЕЗ НДС'!F78 -> 0 | G32: ='БДР-свод_БЕЗ НДС'!G78 -> 0 | H32: ='БДР-свод_БЕЗ НДС'!H78 -> 0 | I32: ='БДР-свод_БЕЗ НДС'!I78 -> 0 | ... M32: ='БДР-свод_БЕЗ НДС'!M78 -> 0 | N32: =B32+C32+D32+E32+F32+G32+H32+I32+J32+K32+L32+M32 -> 0
A33: Спецодежда | B33: ='БДР-свод_БЕЗ НДС'!B83 | C33: ='БДР-свод_БЕЗ НДС'!C83 | D33: ='БДР-свод_БЕЗ НДС'!D83 | E33: ='БДР-свод_БЕЗ НДС'!E83 | F33: ='БДР-свод_БЕЗ НДС'!F83 | G33: ='БДР-свод_БЕЗ НДС'!G83 | H33: ='БДР-свод_БЕЗ НДС'!H83 | I33: ='БДР-свод_БЕЗ НДС'!I83 | ... M33: ='БДР-свод_БЕЗ НДС'!M83 | N33: =B33+C33+D33+E33+F33+G33+H33+I33+J33+K33+L33+M33 -> 0
A34: Налоги по операционной деятельности | B34: ='БДР-свод_БЕЗ НДС'!B87 -> 0 | C34: ='БДР-свод_БЕЗ НДС'!C87 -> 0 | D34: ='БДР-свод_БЕЗ НДС'!D87 -> 0 | E34: ='БДР-свод_БЕЗ НДС'!E87 -> 0 | F34: ='БДР-свод_БЕЗ НДС'!F87 -> 0 | G34: ='БДР-свод_БЕЗ НДС'!G87 -> 0 | H34: ='БДР-свод_БЕЗ НДС'!H87 -> 0 | I34: ='БДР-свод_БЕЗ НДС'!I87 -> 0 | ... M34: ='БДР-свод_БЕЗ НДС'!M87 -> 0 | N34: =B34+C34+D34+E34+F34+G34+H34+I34+J34+K34+L34+M34 -> 0
A35: Коммерческие расходы | B35: =SUM(B36:B37) -> 0 | C35: =SUM(C36:C37) -> 0 | D35: =SUM(D36:D37) -> 0 | E35: =SUM(E36:E37) -> 0 | F35: =SUM(F36:F37) -> 0 | G35: =SUM(G36:G37) -> 0 | H35: =SUM(H36:H37) -> 0 | I35: =SUM(I36:I37) -> 0 | ... N35: =SUM(N36:N37) -> 0
A36: Расходы на оплату труда | B36: ='БДР-свод_БЕЗ НДС'!B41 -> 0 | C36: ='БДР-свод_БЕЗ НДС'!C41 -> 0 | D36: ='БДР-свод_БЕЗ НДС'!D41 -> 0 | E36: ='БДР-свод_БЕЗ НДС'!E41 -> 0 | F36: ='БДР-свод_БЕЗ НДС'!F41 -> 0 | G36: ='БДР-свод_БЕЗ НДС'!G41 -> 0 | H36: ='БДР-свод_БЕЗ НДС'!H41 -> 0 | I36: ='БДР-свод_БЕЗ НДС'!I41 -> 0 | ... N36: ='БДР-свод_БЕЗ НДС'!N41 -> 0
A37: Реклама и продвижение | B37: ='БДР-свод_БЕЗ НДС'!B45 -> 0 | C37: ='БДР-свод_БЕЗ НДС'!C45 -> 0 | D37: ='БДР-свод_БЕЗ НДС'!D45 -> 0 | E37: ='БДР-свод_БЕЗ НДС'!E45 -> 0 | F37: ='БДР-свод_БЕЗ НДС'!F45 -> 0 | G37: ='БДР-свод_БЕЗ НДС'!G45 -> 0 | H37: ='БДР-свод_БЕЗ НДС'!H45 -> 0 | I37: ='БДР-свод_БЕЗ НДС'!I45 -> 0 | ... N37: ='БДР-свод_БЕЗ НДС'!N45 -> 0
A38: Операционная прибыль | B38: =B22-B24-B35 -> 0 | C38: =C22-C24-C35 -> 0 | D38: =D22-D24-D35 -> 0 | E38: =E22-E24-E35 -> 0 | F38: =F22-F24-F35 -> 0 | G38: =G22-G24-G35 -> 0 | H38: =H22-H24-H35 -> 0 | I38: =I22-I24-I35 -> 0 | ... N38: =N22-N24-N35 -> 0
A39: рентабельность продаж, % | B39: =IFERROR(B38/B3,"") | C39: =IFERROR(C38/C3,"") | D39: =IFERROR(D38/D3,"") | E39: =IFERROR(E38/E3,"") | F39: =IFERROR(F38/F3,"") | G39: =IFERROR(G38/G3,"") | H39: =IFERROR(H38/H3,"") | I39: =IFERROR(I38/I3,"") | ... N39: =IFERROR(N38/N3,"")
A40: Доход от финансовой деятельности | N40: =B40+C40+D40+E40+F40+G40+H40+I40+J40+K40+L40+M40 -> 0
A41: Внереализационные доходы | N41: =B41+C41+D41+E41+F41+G41+H41+I41+J41+K41+L41+M41 -> 0
A42: Амортизация
A43: Проценты по кредитам и вкладам | N43: =B43+C43+D43+E43+F43+G43+H43+I43+J43+K43+L43+M43 -> 0
A44: Внереализационные расходы | N44: =B44+C44+D44+E44+F44+G44+H44+I44+J44+K44+L44+M44 -> 0
A45: Налоги | B45: =SUM(B46:B47) -> 0 | C45: =SUM(C46:C47) -> 0 | D45: =SUM(D46:D47) -> 0 | E45: =SUM(E46:E47) -> 0 | F45: =SUM(F46:F47) -> 0 | G45: =SUM(G46:G47) -> 0 | H45: =SUM(H46:H47) -> 0 | I45: =SUM(I46:I47) -> 0 | ... M45: =SUM(M46:M47) -> 0 | N45: =B45+C45+D45+E45+F45+G45+H45+I45+J45+K45+L45+M45 -> 0
A46: УСН | N46: =B46+C46+D46+E46+F46+G46+H46+I46+J46+K46+L46+M46 -> 0
A47: Налог на прибыль | N47: =B47+C47+D47+E47+F47+G47+H47+I47+J47+K47+L47+M47 -> 0
A48: Чистая прибыль | B48: =B38+B40+B41-B42-B43-B44-B45 -> 0 | C48: =C38+C40+C41-C42-C43-C44-C45 -> 0 | D48: =D38+D40+D41-D42-D43-D44-D45 -> 0 | E48: =E38+E40+E41-E42-E43-E44-E45 -> 0 | F48: =F38+F40+F41-F42-F43-F44-F45 -> 0 | G48: =G38+G40+G41-G42-G43-G44-G45 -> 0 | H48: =H38+H40+H41-H42-H43-H44-H45 -> 0 | I48: =I38+I40+I41-I42-I43-I44-I45 -> 0 | ... N48: =N38+N40+N41-N42-N43-N44-N45 -> 0
A49: рентабельность продаж, % | B49: =IFERROR(B48/B3,) | C49: =IFERROR(C48/C3,) | D49: =IFERROR(D48/D3,) | E49: =IFERROR(E48/E3,) | F49: =IFERROR(F48/F3,) | G49: =IFERROR(G48/G3,) | H49: =IFERROR(H48/H3,) | I49: =IFERROR(I48/I3,) | ... N49: =IFERROR(N48/N3,)
A50: Корректировки | B50: =B51 | C50: =C51 | D50: =D51 | E50: =E51 | F50: =F51 | G50: =G51 | H50: =H51 | I50: =I51 | ... M50: =M51 | N50: =B50+C50+D50+E50+F50+G50+H50+I50+J50+K50+L50+M50 -> 0
A51: убыток от списания ДЗ | N51: =B51+C51+D51+E51+F51+G51+H51+I51+J51+K51+L51+M51 -> 0
A52: Чистая прибыль с учетом корректировок | B52: =B48-B51 -> 0 | C52: =C48-C51 -> 0 | D52: =D48-D51 -> 0 | E52: =E48-E51 -> 0 | F52: =F48-F51 -> 0 | G52: =G48-G51 -> 0 | H52: =H48-H51 -> 0 | I52: =I48-I51 -> 0 | ... N52: =N48-N51 -> 0
A53: в % от дохода | B53: =IFERROR(B52/B3,) | C53: =IFERROR(C52/C3,) | D53: =IFERROR(D52/D3,) | E53: =IFERROR(E52/E3,) | F53: =IFERROR(F52/F3,) | G53: =IFERROR(G52/G3,) | H53: =IFERROR(H52/H3,) | I53: =IFERROR(I52/I3,) | ... N53: =IFERROR(N52/N3,)
A54: Распределение прибыли | B54: =B55 | C54: =C55 | D54: =D55 | E54: =E55 | F54: =F55 | G54: =G55 | H54: =H55 | I54: =I55 | ... M54: =M55 | N54: =B54+C54+D54+E54+F54+G54+H54+I54+J54+K54+L54+M54 -> 0
A55: дивиденды | N55: =B55+C55+D55+E55+F55+G55+H55+I55+J55+K55+L55+M55 -> 0
A56: Нераспределенная прибыль | B56: =B52-B54 -> 0 | C56: =C52-C54 -> 0 | D56: =D52-D54 -> 0 | E56: =E52-E54 -> 0 | F56: =F52-F54 -> 0 | G56: =G52-G54 -> 0 | H56: =H52-H54 -> 0 | I56: =I52-I54 -> 0 | ... M56: =M52-M54 -> 0 | N56: =B56+C56+D56+E56+F56+G56+H56+I56+J56+K56+L56+M56 -> 0

Sheet БДР-свод_БЕЗ НДС
A1: Бюджет доходов и расходов 2021 г.
A2: Наименование статьи | B2: янв | C2: фев | D2: мар | E2: апр | F2: май | G2: июн | H2: июл | I2: авг | J2: сен | K2: окт | L2: ноя | M2: дек | N2: ГОД
A3: Доходы от операционной деятельности | B3: =B4 | C3: =C4 | D3: =D4 | E3: =E4 | F3: =F4 | G3: =G4 | H3: =H4 | I3: =I4 | ... M3: =M4 | N3: =B3+C3+D3+E3+F3+G3+H3+I3+J3+K3+L3+M3 -> 0
A4: Доход от продажи воды | N4: =B4+C4+D4+E4+F4+G4+H4+I4+J4+K4+L4+M4 -> 0
A5: Расходы по операционной деятельности | B5: =B6+B40+B87+B49 -> 0 | C5: =C6+C40+C87+C49 -> 0 | D5: =D6+D40+D87+D49 -> 0 | E5: =E6+E40+E87+E49 -> 0 | F5: =F6+F40+F87+F49 -> 0 | G5: =G6+G40+G87+G49 -> 0 | H5: =H6+H40+H87+H49 -> 0 | I5: =I6+I40+I87+I49 -> 0 | ... N5: =N6+N40+N87+N49 -> 0
A6: Расходы по продаже | B6: =B7 -> 0 | C6: =C7 -> 0 | D6: =D7 -> 0 | E6: =E7 -> 0 | F6: =F7 -> 0 | G6: =G7 -> 0 | H6: =H7 -> 0 | I6: =I7 -> 0 | ... M6: =M7 -> 0 | N6: =B6+C6+D6+E6+F6+G6+H6+I6+J6+K6+L6+M6 -> 0
A7: Производственная себестоимость продукции | B7: =B8+B11+B15+B20+B24+B27+B31+B36+B37 -> 0 | C7: =C8+C11+C15+C20+C24+C27+C31+C36+C37 -> 0 | D7: =D8+D11+D15+D20+D24+D27+D31+D36+D37 -> 0 | E7: =E8+E11+E15+E20+E24+E27+E31+E36+E37 -> 0 | F7: =F8+F11+F15+F20+F24+F27+F31+F36+F37 -> 0 | G7: =G8+G11+G15+G20+G24+G27+G31+G36+G37 -> 0 | H7: =H8+H11+H15+H20+H24+H27+H31+H36+H37 -> 0 | I7: =I8+I11+I15+I20+I24+I27+I31+I36+I37 -> 0 | ... N7: =N8+N11+N15+N20+N24+N27+N31+N36+N37 -> 0
A8: Материальные расходы | B8: =B9+B10 -> 0 | C8: =C9+C10 -> 0 | D8: =D9+D10 -> 0 | E8: =E9+E10 -> 0 | F8: =F9+F10 -> 0 | G8: =G9+G10 -> 0 | H8: =H9+H10 -> 0 | I8: =I9+I10 -> 0 | ... N8: =N9+N10 -> 0
A9: основные материалы | B9: ='Бюджет производственных расходо'!B5 | C9: ='Бюджет производственных расходо'!C5 | D9: ='Бюджет производственных расходо'!D5 | E9: ='Бюджет производственных расходо'!E5 | F9: ='Бюджет производственных расходо'!F5 | G9: ='Бюджет производственных расходо'!G5 | H9: ='Бюджет производственных расходо'!H5 | I9: ='Бюджет производственных расходо'!I5 | ... M9: ='Бюджет производственных расходо'!M5 | N9: =B9+C9+D9+E9+F9+G9+H9+I9+J9+K9+L9+M9 -> 0
A10: вспомогательные материалы | B10: ='Бюджет производственных расходо'!B6 | C10: ='Бюджет производственных расходо'!C6 | D10: ='Бюджет производственных расходо'!D6 | E10: ='Бюджет производственных расходо'!E6 | F10: ='Бюджет производственных расходо'!F6 | G10: ='Бюджет производственных расходо'!G6 | H10: ='Бюджет производственных расходо'!H6 | I10: ='Бюджет производственных расходо'!I6 | ... M10: ='Бюджет производственных расходо'!M6 | N10: =B10+C10+D10+E10+F10+G10+H10+I10+J10+K10+L10+M10 -> 0
A11: Расходы на оплату труда | B11: =SUM(B12:B14) -> 0 | C11: =SUM(C12:C14) -> 0 | D11: =SUM(D12:D14) -> 0 | E11: =SUM(E12:E14) -> 0 | F11: =SUM(F12:F14) -> 0 | G11: =SUM(G12:G14) -> 0 | H11: =SUM(H12:H14) -> 0 | I11: =SUM(I12:I14) -> 0 | ... M11: =SUM(M12:M14) -> 0 | N11: =B11+C11+D11+E11+F11+G11+H11+I11+J11+K11+L11+M11 -> 0
A12: заработная плата | N12: =B12+C12+D12+E12+F12+G12+H12+I12+J12+K12+L12+M12 -> 0
A13: отчисления с ФОТ | N13: =B13+C13+D13+E13+F13+G13+H13+I13+J13+K13+L13+M13 -> 0
A14: НДФЛ | N14: =B14+C14+D14+E14+F14+G14+H14+I14+J14+K14+L14+M14 -> 0
A15: Содержание зданий | B15: =B16+B20+B21+B22 -> 0 | C15: =C16+C20+C21+C22 -> 0 | D15: =D16+D20+D21+D22 -> 0 | E15: =E16+E20+E21+E22 -> 0 | F15: =F16+F20+F21+F22 -> 0 | G15: =G16+G20+G21+G22 -> 0 | H15: =H16+H20+H21+H22 -> 0 | I15: =I16+I20+I21+I22 -> 0 | ... M15: =M16+M20+M21+M22 -> 0 | N15: =B15+C15+D15+E15+F15+G15+H15+I15+J15+K15+L15+M15 -> 0
A16: Аренда | B16: ='Бюджет производственных расходо'!B9 -> 0 | C16: ='Бюджет производственных расходо'!C9 -> 0 | D16: ='Бюджет производственных расходо'!D9 -> 0 | E16: ='Бюджет производственных расходо'!E9 -> 0 | F16: ='Бюджет производственных расходо'!F9 -> 0 | G16: ='Бюджет производственных расходо'!G9 -> 0 | H16: ='Бюджет производственных расходо'!H9 -> 0 | I16: ='Бюджет производственных расходо'!I9 -> 0 | ... M16: ='Бюджет производственных расходо'!M9 -> 0 | N16: =N17 -> 0
A17: Коммунальные расходы | B17: ='Бюджет производственных расходо'!B13 | C17: ='Бюджет производственных расходо'!C13 | D17: ='Бюджет производственных расходо'!D13 | E17: ='Бюджет производственных расходо'!E13 | F17: ='Бюджет производственных расходо'!F13 | G17: ='Бюджет производственных расходо'!G13 | H17: ='Бюджет производственных расходо'!H13 | I17: ='Бюджет производственных расходо'!I13 | ... M17: ='Бюджет производственных расходо'!M13 | N17: =B17+C17+D17+E17+F17+G17+H17+I17+J17+K17+L17+M17 -> 0
A18: Охрана помещений | B18: ='Бюджет производственных расходо'!B14 | C18: ='Бюджет производственных расходо'!C14 | D18: ='Бюджет производственных расходо'!D14 | E18: ='Бюджет производственных расходо'!E14 | F18: ='Бюджет производственных расходо'!F14 | G18: ='Бюджет производственных расходо'!G14 | H18: ='Бюджет производственных расходо'!H14 | I18: ='Бюджет производственных расходо'!I14 | ... M18: ='Бюджет производственных расходо'!M14 | N18: =B18+C18+D18+E18+F18+G18+H18+I18+J18+K18+L18+M18 -> 0
A19: Ремонт помещений | B19: ='Бюджет производственных расходо'!B15 | C19: ='Бюджет производственных расходо'!C15 | D19: ='Бюджет производственных расходо'!D15 | E19: ='Бюджет производственных расходо'!E15 | F19: ='Бюджет производственных расходо'!F15 | G19: ='Бюджет производственных расходо'!G15 | H19: ='Бюджет производственных расходо'!H15 | I19: ='Бюджет производственных расходо'!I15 | ... M19: ='Бюджет производственных расходо'!M15 | N19: =B19+C19+D19+E19+F19+G19+H19+I19+J19+K19+L19+M19 -> 0
A20: Транспортные расходы | B20: =B21+B23 -> 0 | C20: =C21+C23 -> 0 | D20: =D21+D23 -> 0 | E20: =E21+E23 -> 0 | F20: =F21+F23 -> 0 | G20: =G21+G23 -> 0 | H20: =H21+H23 -> 0 | I20: =I21+I23 -> 0 | ... M20: =M21+M23 -> 0 | N20: =B20+C20+D20+E20+F20+G20+H20+I20+J20+K20+L20+M20 -> 0
A21: ГСМ | B21: ='Бюджет производственных расходо'!B17 | C21: ='Бюджет производственных расходо'!C17 | D21: ='Бюджет производственных расходо'!D17 | E21: ='Бюджет производственных расходо'!E17 | F21: ='Бюджет производственных расходо'!F17 | G21: ='Бюджет производственных расходо'!G17 | H21: ='Бюджет производственных расходо'!H17 | I21: ='Бюджет производственных расходо'!I17 | ... M21: ='Бюджет производственных расходо'!M17 | N21: =B21+C21+D21+E21+F21+G21+H21+I21+J21+K21+L21+M21 -> 0
A22: Содержание транспорта | B22: ='Бюджет производственных расходо'!B18 | C22: ='Бюджет производственных расходо'!C18 | D22: ='Бюджет производственных расходо'!D18 | E22: ='Бюджет производственных расходо'!E18 | F22: ='Бюджет производственных расходо'!F18 | G22: ='Бюджет производственных расходо'!G18 | H22: ='Бюджет производственных расходо'!H18 | I22: ='Бюджет производственных расходо'!I18 | ... M22: ='Бюджет производственных расходо'!M18
A23: Прочие транспортные расходы | B23: ='Бюджет производственных расходо'!B19 | C23: ='Бюджет производственных расходо'!C19 | D23: ='Бюджет производственных расходо'!D19 | E23: ='Бюджет производственных расходо'!E19 | F23: ='Бюджет производственных расходо'!F19 | G23: ='Бюджет производственных расходо'!G19 | H23: ='Бюджет производственных расходо'!H19 | I23: ='Бюджет производственных расходо'!I19 | ... M23: ='Бюджет производственных расходо'!M19 | N23: =B23+C23+D23+E23+F23+G23+H23+I23+J23+K23+L23+M23 -> 0
A24: Расходы на содержание оборудования | B24: =B25+B26 -> 0 | C24: =C25+C26 -> 0 | D24: =D25+D26 -> 0 | E24: =E25+E26 -> 0 | F24: =F25+F26 -> 0 | G24: =G25+G26 -> 0 | H24: =H25+H26 -> 0 | I24: =I25+I26 -> 0 | ... N24: =N25+N26 -> 0
A25: Обслуживание оборудования | B25: ='Бюджет производственных расходо'!B21 | C25: ='Бюджет производственных расходо'!C21 | D25: ='Бюджет производственных расходо'!D21 | E25: ='Бюджет производственных расходо'!E21 | F25: ='Бюджет производственных расходо'!F21 | G25: ='Бюджет производственных расходо'!G21 | H25: ='Бюджет производственных расходо'!H21 | I25: ='Бюджет производственных расходо'!I21 | ... M25: ='Бюджет производственных расходо'!M21 | N25: =B25+C25+D25+E25+F25+G25+H25+I25+J25+K25+L25+M25 -> 0
A26: Ремонт оборудования | B26: ='Бюджет производственных расходо'!B22 | C26: ='Бюджет производственных расходо'!C22 | D26: ='Бюджет производственных расходо'!D22 | E26: ='Бюджет производственных расходо'!E22 | F26: ='Бюджет производственных расходо'!F22 | G26: ='Бюджет производственных расходо'!G22 | H26: ='Бюджет производственных расходо'!H22 | I26: ='Бюджет производственных расходо'!I22 | ... M26: ='Бюджет производственных расходо'!M22 | N26: =B26+C26+D26+E26+F26+G26+H26+I26+J26+K26+L26+M26 -> 0
A27: Расходы на персонал | B27: =SUM(B28:B30) -> 0 | C27: =SUM(C28:C30) -> 0 | D27: =SUM(D28:D30) -> 0 | E27: =SUM(E28:E30) -> 0 | F27: =SUM(F28:F30) -> 0 | G27: =SUM(G28:G30) -> 0 | H27: =SUM(H28:H30) -> 0 | I27: =SUM(I28:I30) -> 0 | ... N27: =SUM(N28:N30) -> 0
A28: обучение сотрудников | B28: ='Бюджет производственных расходо'!B24 | C28: ='Бюджет производственных расходо'!C24 | D28: ='Бюджет производственных расходо'!D24 | E28: ='Бюджет производственных расходо'!E24 | F28: ='Бюджет производственных расходо'!F24 | G28: ='Бюджет производственных расходо'!G24 | H28: ='Бюджет производственных расходо'!H24 | I28: ='Бюджет производственных расходо'!I24 | ... M28: ='Бюджет производственных расходо'!M24
A29: подбор персонала | B29: ='Бюджет производственных расходо'!B25 | C29: ='Бюджет производственных расходо'!C25 | D29: ='Бюджет производственных расходо'!D25 | E29: ='Бюджет производственных расходо'!E25 | F29: ='Бюджет производственных расходо'!F25 | G29: ='Бюджет производственных расходо'!G25 | H29: ='Бюджет производственных расходо'!H25 | I29: ='Бюджет производственных расходо'!I25 | ... M29: ='Бюджет производственных расходо'!M25
A30: прочие расходы на персонал | B30: ='Бюджет производственных расходо'!B26 | C30: ='Бюджет производственных расходо'!C26 | D30: ='Бюджет производственных расходо'!D26 | E30: ='Бюджет производственных расходо'!E26 | F30: ='Бюджет производственных расходо'!F26 | G30: ='Бюджет производственных расходо'!G26 | H30: ='Бюджет производственных расходо'!H26 | I30: ='Бюджет производственных расходо'!I26 | ... M30: ='Бюджет производственных расходо'!M26
A31: Прочие производственые расходы расходы | B31: =B32+B33+B34+B35 -> 0 | C31: =C32+C33+C34+C35 -> 0 | D31: =D32+D33+D34+D35 -> 0 | E31: =E32+E33+E34+E35 -> 0 | F31: =F32+F33+F34+F35 -> 0 | G31: =G32+G33+G34+G35 -> 0 | H31: =H32+H33+H34+H35 -> 0 | I31: =I32+I33+I34+I35 -> 0 | ... M31: =M32+M33+M34+M35 -> 0 | N31: =B31+C31+D31+E31+F31+G31+H31+I31+J31+K31+L31+M31 -> 0
B32: ='Бюджет производственных расходо'!B28 | C32: ='Бюджет производственных расходо'!C28 | D32: ='Бюджет производственных расходо'!D28 | E32: ='Бюджет производственных расходо'!E28 | F32: ='Бюджет производственных расходо'!F28 | G32: ='Бюджет производственных расходо'!G28 | H32: ='Бюджет производственных расходо'!H28 | I32: ='Бюджет производственных расходо'!I28 | ... M32: ='Бюджет производственных расходо'!M28
B33: ='Бюджет производственных расходо'!B29 | C33: ='Бюджет производственных расходо'!C29 | D33: ='Бюджет производственных расходо'!D29 | E33: ='Бюджет производственных расходо'!E29 | F33: ='Бюджет производственных расходо'!F29 | G33: ='Бюджет производственных расходо'!G29 | H33: ='Бюджет производственных расходо'!H29 | I33: ='Бюджет производственных расходо'!I29 | ... M33: ='Бюджет производственных расходо'!M29
B34: ='Бюджет производственных расходо'!B30 | C34: ='Бюджет производственных расходо'!C30 | D34: ='Бюджет производственных расходо'!D30 | E34: ='Бюджет производственных расходо'!E30 | F34: ='Бюджет производственных расходо'!F30 | G34: ='Бюджет производственных расходо'!G30 | H34: ='Бюджет производственных расходо'!H30 | I34: ='Бюджет производственных расходо'!I30 | ... M34: ='Бюджет производственных расходо'!M30
B35: ='Бюджет производственных расходо'!B31 | C35: ='Бюджет производственных расходо'!C31 | D35: ='Бюджет производственных расходо'!D31 | E35: ='Бюджет производственных расходо'!E31 | F35: ='Бюджет производственных расходо'!F31 | G35: ='Бюджет производственных расходо'!G31 | H35: ='Бюджет производственных расходо'!H31 | I35: ='Бюджет производственных расходо'!I31 | ... M35: ='Бюджет производственных расходо'!M31
A36: Спецодежда | B36: ='Бюджет производственных расходо'!B32 | C36: ='Бюджет производственных расходо'!C32 | D36: ='Бюджет производственных расходо'!D32 | E36: ='Бюджет производственных расходо'!E32 | F36: ='Бюджет производственных расходо'!F32 | G36: ='Бюджет производственных расходо'!G32 | H36: ='Бюджет производственных расходо'!H32 | I36: ='Бюджет производственных расходо'!I32 | ... M36: ='Бюджет производственных расходо'!M32
A37: Амортизация ОС и НМА | B37: ='Бюджет производственных расходо'!B33 -> 0 | C37: ='Бюджет производственных расходо'!C33 -> 0 | D37: ='Бюджет производственных расходо'!D33 -> 0 | E37: ='Бюджет производственных расходо'!E33 -> 0 | F37: ='Бюджет производственных расходо'!F33 -> 0 | G37: ='Бюджет производственных расходо'!G33 -> 0 | H37: ='Бюджет производственных расходо'!H33 -> 0 | I37: ='Бюджет производственных расходо'!I33 -> 0 | ... M37: ='Бюджет производственных расходо'!M33 -> 0 | N37: =B37+C37+D37+E37+F37+G37+H37+I37+J37+K37+L37+M37 -> 0
A38: Валовая прибыль | B38: =B4-B6 -> 0 | C38: =C4-C6 -> 0 | D38: =D4-D6 -> 0 | E38: =E4-E6 -> 0 | F38: =F4-F6 -> 0 | G38: =G4-G6 -> 0 | H38: =H4-H6 -> 0 | I38: =I4-I6 -> 0 | ... M38: =M4-M6 -> 0 | N38: =B38+C38+D38+E38+F38+G38+H38+I38+J38+K38+L38+M38 -> 0
A39: в % от дохода | B39: =IFERROR(B38/B4,) | C39: =IFERROR(C38/C4,) | D39: =IFERROR(D38/D4,) | E39: =IFERROR(E38/E4,) | F39: =IFERROR(F38/F4,) | G39: =IFERROR(G38/G4,) | H39: =IFERROR(H38/H4,) | I39: =IFERROR(I38/I4,) | ... N39: =IFERROR(N38/N4,)
A40: Коммерческие расходы | B40: =B41+B45+B46 -> 0 | C40: =C41+C45+C46 -> 0 | D40: =D41+D45+D46 -> 0 | E40: =E41+E45+E46 -> 0 | F40: =F41+F45+F46 -> 0 | G40: =G41+G45+G46 -> 0 | H40: =H41+H45+H46 -> 0 | I40: =I41+I45+I46 -> 0 | ... M40: =M41+M45+M46 -> 0 | N40: =B40+C40+D40+E40+F40+G40+H40+I40+J40+K40+L40+M40 -> 0
A41: Расходы на оплату труда | B41: =B42+B43+B44 -> 0 | C41: =C42+C43+C44 -> 0 | D41: =D42+D43+D44 -> 0 | E41: =E42+E43+E44 -> 0 | F41: =F42+F43+F44 -> 0 | G41: =G42+G43+G44 -> 0 | H41: =H42+H43+H44 -> 0 | I41: =I42+I43+I44 -> 0 | ... M41: =M42+M43+M44 -> 0 | N41: =B41+C41+D41+E41+F41+G41+H41+I41+J41+K41+L41+M41 -> 0
A42: заработная плата | N42: =B42+C42+D42+E42+F42+G42+H42+I42+J42+K42+L42+M42 -> 0
A43: отчисления с ФОТ | N43: =B43+C43+D43+E43+F43+G43+H43+I43+J43+K43+L43+M43 -> 0
A44: НДФЛ | N44: =B44+C44+D44+E44+F44+G44+H44+I44+J44+K44+L44+M44 -> 0
A45: Реклама и продвижение | B45: ='Бюджет коммер. расходов'!B63 -> 0 | C45: ='Бюджет коммер. расходов'!C63 -> 0 | D45: ='Бюджет коммер. расходов'!D63 -> 0 | E45: ='Бюджет коммер. расходов'!E63 -> 0 | F45: ='Бюджет коммер. расходов'!F63 -> 0 | G45: ='Бюджет коммер. расходов'!G63 -> 0 | H45: ='Бюджет коммер. расходов'!H63 -> 0 | I45: ='Бюджет коммер. расходов'!I63 -> 0 | ... N45: ='Бюджет коммер. расходов'!N63 -> 0
A46: Амортизация | B46: =B48+B47 -> 0 | C46: =C48+C47 -> 0 | D46: =D48+D47 -> 0 | E46: =E48+E47 -> 0 | F46: =F48+F47 -> 0 | G46: =G48+G47 -> 0 | H46: =H48+H47 -> 0 | I46: =I48+I47 -> 0 | ... M46: =M48+M47 -> 0 | N46: =B46+C46+D46+E46+F46+G46+H46+I46+J46+K46+L46+M46 -> 0
A47: амортизация ОС | B47: ='Инвест_бюджет'!B672 | C47: ='Инвест_бюджет'!C672 | D47: ='Инвест_бюджет'!D672 | E47: ='Инвест_бюджет'!E672 | F47: ='Инвест_бюджет'!F672 | G47: ='Инвест_бюджет'!G672 | H47: ='Инвест_бюджет'!H672 | I47: ='Инвест_бюджет'!I672 | ... M47: ='Инвест_бюджет'!M672 | N47: =B47+C47+D47+E47+F47+G47+H47+I47+J47+K47+L47+M47 -> 0
A48: списание МПЗ | B48: ='Инвест_бюджет'!B673 | C48: ='Инвест_бюджет'!C673 | D48: ='Инвест_бюджет'!D673 | E48: ='Инвест_бюджет'!E673 | F48: ='Инвест_бюджет'!F673 | G48: ='Инвест_бюджет'!G673 | H48: ='Инвест_бюджет'!H673 | I48: ='Инвест_бюджет'!I673 | ... M48: ='Инвест_бюджет'!M673 | N48: =B48+C48+D48+E48+F48+G48+H48+I48+J48+K48+L48+M48 -> 0
A49: Административные расходы | B49: =B50+B54+B59+B62+B66+B70+B74+B78+B84+B83 -> 0 | C49: =C50+C54+C59+C62+C66+C70+C74+C78+C84+C83 -> 0 | D49: =D50+D54+D59+D62+D66+D70+D74+D78+D84+D83 -> 0 | E49: =E50+E54+E59+E62+E66+E70+E74+E78+E84+E83 -> 0 | F49: =F50+F54+F59+F62+F66+F70+F74+F78+F84+F83 -> 0 | G49: =G50+G54+G59+G62+G66+G70+G74+G78+G84+G83 -> 0 | H49: =H50+H54+H59+H62+H66+H70+H74+H78+H84+H83 -> 0 | I49: =I50+I54+I59+I62+I66+I70+I74+I78+I84+I83 -> 0 | ... N49: =N50+N54+N59+N62+N66+N70+N74+N78+N84+N83 -> 0
A50: Расходы на оплату труда | B50: =B51+B52+B53 -> 0 | C50: =C51+C52+C53 -> 0 | D50: =D51+D52+D53 -> 0 | E50: =E51+E52+E53 -> 0 | F50: =F51+F52+F53 -> 0 | G50: =G51+G52+G53 -> 0 | H50: =H51+H52+H53 -> 0 | I50: =I51+I52+I53 -> 0 | ... M50: =M51+M52+M53 -> 0 | N50: =B50+C50+D50+E50+F50+G50+H50+I50+J50+K50+L50+M50 -> 0
A51: заработная плата | N51: =B51+C51+D51+E51+F51+G51+H51+I51+J51+K51+L51+M51 -> 0
A52: отчисления с ФОТ | N52: =B52+C52+D52+E52+F52+G52+H52+I52+J52+K52+L52+M52 -> 0
A53: НДФЛ | N53: =B53+C53+D53+E53+F53+G53+H53+I53+J53+K53+L53+M53 -> 0
A54: Содержание зданий | B54: =B55+B56+B57+B58 -> 0 | C54: =C55+C56+C57+C58 -> 0 | D54: =D55+D56+D57+D58 -> 0 | E54: =E55+E56+E57+E58 -> 0 | F54: =F55+F56+F57+F58 -> 0 | G54: =G55+G56+G57+G58 -> 0 | H54: =H55+H56+H57+H58 -> 0 | I54: =I55+I56+I57+I58 -> 0 | ... M54: =M55+M56+M57+M58 -> 0 | N54: =B54+C54+D54+E54+F54+G54+H54+I54+J54+K54+L54+M54 -> 0
A55: аренда | B55: ='Бюджет админ-управл.расходов'!B9 -> 0 | C55: ='Бюджет админ-управл.расходов'!C9 -> 0 | D55: ='Бюджет админ-управл.расходов'!D9 -> 0 | E55: ='Бюджет админ-управл.расходов'!E9 -> 0 | F55: ='Бюджет админ-управл.расходов'!F9 -> 0 | G55: ='Бюджет админ-управл.расходов'!G9 -> 0 | H55: ='Бюджет админ-управл.расходов'!H9 -> 0 | I55: ='Бюджет админ-управл.расходов'!I9 -> 0 | ... M55: ='Бюджет админ-управл.расходов'!M9 -> 0 | N55: =B55+C55+D55+E55+F55+G55+H55+I55+J55+K55+L55+M55 -> 0
A56: коммунальные расходы | B56: ='Бюджет админ-управл.расходов'!B16 | C56: ='Бюджет админ-управл.расходов'!C16 | D56: ='Бюджет админ-управл.расходов'!D16 | E56: ='Бюджет админ-управл.расходов'!E16 | F56: ='Бюджет админ-управл.расходов'!F16 | G56: ='Бюджет админ-управл.расходов'!G16 | H56: ='Бюджет админ-управл.расходов'!H16 | I56: ='Бюджет админ-управл.расходов'!I16 | ... M56: ='Бюджет админ-управл.расходов'!M16 | N56: =B56+C56+D56+E56+F56+G56+H56+I56+J56+K56+L56+M56 -> 0
A57: охрана помещений | B57: ='Бюджет админ-управл.расходов'!B17 | C57: ='Бюджет админ-управл.расходов'!C17 | D57: ='Бюджет админ-управл.расходов'!D17 | E57: ='Бюджет админ-управл.расходов'!E17 | F57: ='Бюджет админ-управл.расходов'!F17 | G57: ='Бюджет админ-управл.расходов'!G17 | H57: ='Бюджет админ-управл.расходов'!H17 | I57: ='Бюджет админ-управл.расходов'!I17 | ... M57: ='Бюджет админ-управл.расходов'!M17 | N57: =B57+C57+D57+E57+F57+G57+H57+I57+J57+K57+L57+M57 -> 0
A58: ремонт помещений | B58: ='Бюджет админ-управл.расходов'!B18 | C58: ='Бюджет админ-управл.расходов'!C18 | D58: ='Бюджет админ-управл.расходов'!D18 | E58: ='Бюджет админ-управл.расходов'!E18 | F58: ='Бюджет админ-управл.расходов'!F18 | G58: ='Бюджет админ-управл.расходов'!G18 | H58: ='Бюджет админ-управл.расходов'!H18 | I58: ='Бюджет админ-управл.расходов'!I18 | ... M58: ='Бюджет админ-управл.расходов'!M18 | N58: =B58+C58+D58+E58+F58+G58+H58+I58+J58+K58+L58+M58 -> 0
A59: Услуги связи | B59: =B60+B61 -> 0 | C59: =C60+C61 -> 0 | D59: =D60+D61 -> 0 | E59: =E60+E61 -> 0 | F59: =F60+F61 -> 0 | G59: =G60+G61 -> 0 | H59: =H60+H61 -> 0 | I59: =I60+I61 -> 0 | ... M59: =M60+M61 -> 0 | N59: =B59+C59+D59+E59+F59+G59+H59+I59+J59+K59+L59+M59 -> 0
A60: телефон | B60: ='Бюджет админ-управл.расходов'!B20 | C60: ='Бюджет админ-управл.расходов'!C20 | D60: ='Бюджет админ-управл.расходов'!D20 | E60: ='Бюджет админ-управл.расходов'!E20 | F60: ='Бюджет админ-управл.расходов'!F20 | G60: ='Бюджет админ-управл.расходов'!G20 | H60: ='Бюджет админ-управл.расходов'!H20 | I60: ='Бюджет админ-управл.расходов'!I20 | ... M60: ='Бюджет админ-управл.расходов'!M20 | N60: =B60+C60+D60+E60+F60+G60+H60+I60+J60+K60+L60+M60 -> 0
A61: интернет | B61: ='Бюджет админ-управл.расходов'!B21 | C61: ='Бюджет админ-управл.расходов'!C21 | D61: ='Бюджет админ-управл.расходов'!D21 | E61: ='Бюджет админ-управл.расходов'!E21 | F61: ='Бюджет админ-управл.расходов'!F21 | G61: ='Бюджет админ-управл.расходов'!G21 | H61: ='Бюджет админ-управл.расходов'!H21 | I61: ='Бюджет админ-управл.расходов'!I21 | ... M61: ='Бюджет админ-управл.расходов'!M21 | N61: =B61+C61+D61+E61+F61+G61+H61+I61+J61+K61+L61+M61 -> 0
A62: Расходы на персонал | B62: =B63+B64+B65 -> 0 | C62: =C63+C64+C65 -> 0 | D62: =D63+D64+D65 -> 0 | E62: =E63+E64+E65 -> 0 | F62: =F63+F64+F65 -> 0 | G62: =G63+G64+G65 -> 0 | H62: =H63+H64+H65 -> 0 | I62: =I63+I64+I65 -> 0 | ... M62: =M63+M64+M65 -> 0 | N62: =B62+C62+D62+E62+F62+G62+H62+I62+J62+K62+L62+M62 -> 0
A63: обучение сотрудников | N63: =B63+C63+D63+E63+F63+G63+H63+I63+J63+K63+L63+M63 -> 0
A64: подбор персонала | N64: =B64+C64+D64+E64+F64+G64+H64+I64+J64+K64+L64+M64 -> 0
A65: прочие расходы на персонал | N65: =B65+C65+D65+E65+F65+G65+H65+I65+J65+K65+L65+M65 -> 0
A66: Расходы офиса | B66: =B67+B68+B69 -> 0 | C66: =C67+C68+C69 -> 0 | D66: =D67+D68+D69 -> 0 | E66: =E67+E68+E69 -> 0 | F66: =F67+F68+F69 -> 0 | G66: =G67+G68+G69 -> 0 | H66: =H67+H68+H69 -> 0 | I66: =I67+I68+I69 -> 0 | ... M66: =M67+M68+M69 -> 0 | N66: =B66+C66+D66+E66+F66+G66+H66+I66+J66+K66+L66+M66 -> 0
A67: хозяйственные расходы | B67: ='Бюджет админ-управл.расходов'!B23 | C67: ='Бюджет админ-управл.расходов'!C23 | D67: ='Бюджет админ-управл.расходов'!D23 | E67: ='Бюджет админ-управл.расходов'!E23 | F67: ='Бюджет админ-управл.расходов'!F23 | G67: ='Бюджет админ-управл.расходов'!G23 | H67: ='Бюджет админ-управл.расходов'!H23 | I67: ='Бюджет админ-управл.расходов'!I23 | ... M67: ='Бюджет админ-управл.расходов'!M23 | N67: =B67+C67+D67+E67+F67+G67+H67+I67+J67+K67+L67+M67 -> 0
A68: канцелярские товары | B68: ='Бюджет админ-управл.расходов'!B24 | C68: ='Бюджет админ-управл.расходов'!C24 | D68: ='Бюджет админ-управл.расходов'!D24 | E68: ='Бюджет админ-управл.расходов'!E24 | F68: ='Бюджет админ-управл.расходов'!F24 | G68: ='Бюджет админ-управл.расходов'!G24 | H68: ='Бюджет админ-управл.расходов'!H24 | I68: ='Бюджет админ-управл.расходов'!I24 | ... M68: ='Бюджет админ-управл.расходов'!M24 | N68: =B68+C68+D68+E68+F68+G68+H68+I68+J68+K68+L68+M68 -> 0
A69: содержание оргтехники | B69: ='Бюджет админ-управл.расходов'!B72 | C69: ='Бюджет админ-управл.расходов'!C72 | D69: ='Бюджет админ-управл.расходов'!D72 | E69: ='Бюджет админ-управл.расходов'!E72 | F69: ='Бюджет админ-управл.расходов'!F72 | G69: ='Бюджет админ-управл.расходов'!G72 | H69: ='Бюджет админ-управл.расходов'!H72 | I69: ='Бюджет админ-управл.расходов'!I72 | ... M69: ='Бюджет админ-управл.расходов'!M72 | N69: =B69+C69+D69+E69+F69+G69+H69+I69+J69+K69+L69+M69 -> 0
A70: Информац. и консультац. услуги | B70: =SUM(B71:B73) -> 0 | C70: =SUM(C71:C73) -> 0 | D70: =SUM(D71:D73) -> 0 | E70: =SUM(E71:E73) -> 0 | F70: =SUM(F71:F73) -> 0 | G70: =SUM(G71:G73) -> 0 | H70: =SUM(H71:H73) -> 0 | I70: =SUM(I71:I73) -> 0 | ... M70: =SUM(M71:M73) -> 0 | N70: =B70+C70+D70+E70+F70+G70+H70+I70+J70+K70+L70+M70 -> 0
A71: поддержка ПО | B71: ='Бюджет админ-управл.расходов'!B27 | C71: ='Бюджет админ-управл.расходов'!C27 | D71: ='Бюджет админ-управл.расходов'!D27 | E71: ='Бюджет админ-управл.расходов'!E27 | F71: ='Бюджет админ-управл.расходов'!F27 | G71: ='Бюджет админ-управл.расходов'!G27 | H71: ='Бюджет админ-управл.расходов'!H27 | I71: ='Бюджет админ-управл.расходов'!I27 | ... M71: ='Бюджет админ-управл.расходов'!M27 | N71: =B71+C71+D71+E71+F71+G71+H71+I71+J71+K71+L71+M71 -> 0
A72: аутсорсинг | B72: ='Бюджет админ-управл.расходов'!B29 | C72: ='Бюджет админ-управл.расходов'!C29 | D72: ='Бюджет админ-управл.расходов'!D29 | E72: ='Бюджет админ-управл.расходов'!E29 | F72: ='Бюджет админ-управл.расходов'!F29 | G72: ='Бюджет админ-управл.расходов'!G29 | H72: ='Бюджет админ-управл.расходов'!H29 | I72: ='Бюджет админ-управл.расходов'!I29 | ... M72: ='Бюджет админ-управл.расходов'!M29 | N72: =B72+C72+D72+E72+F72+G72+H72+I72+J72+K72+L72+M72 -> 0
A73: прочие информационные услуги | B73: ='Бюджет админ-управл.расходов'!B30 | C73: ='Бюджет админ-управл.расходов'!C30 | D73: ='Бюджет админ-управл.расходов'!D30 | E73: ='Бюджет админ-управл.расходов'!E30 | F73: ='Бюджет админ-управл.расходов'!F30 | G73: ='Бюджет админ-управл.расходов'!G30 | H73: ='Бюджет админ-управл.расходов'!H30 | I73: ='Бюджет админ-управл.расходов'!I30 | ... M73: ='Бюджет админ-управл.расходов'!M30 | N73: =B73+C73+D73+E73+F73+G73+H73+I73+J73+K73+L73+M73 -> 0
A74: Расходы на денежное обращение | B74: =B75+B76+B77 -> 0 | C74: =C75+C76+C77 -> 0 | D74: =D75+D76+D77 -> 0 | E74: =E75+E76+E77 -> 0 | F74: =F75+F76+F77 -> 0 | G74: =G75+G76+G77 -> 0 | H74: =H75+H76+H77 -> 0 | I74: =I75+I76+I77 -> 0 | ... M74: =M75+M76+M77 -> 0 | N74: =B74+C74+D74+E74+F74+G74+H74+I74+J74+K74+L74+M74 -> 0
A75: РКО | B75: ='Бюджет админ-управл.расходов'!B32 | C75: ='Бюджет админ-управл.расходов'!C32 | D75: ='Бюджет админ-управл.расходов'!D32 | E75: ='Бюджет админ-управл.расходов'!E32 | F75: ='Бюджет админ-управл.расходов'!F32 | G75: ='Бюджет админ-управл.расходов'!G32 | H75: ='Бюджет админ-управл.расходов'!H32 | I75: ='Бюджет админ-управл.расходов'!I32 | ... M75: ='Бюджет админ-управл.расходов'!M32 | N75: =B75+C75+D75+E75+F75+G75+H75+I75+J75+K75+L75+M75 -> 0
A76: инкассация | B76: ='Бюджет админ-управл.расходов'!B33 | C76: ='Бюджет админ-управл.расходов'!C33 | D76: ='Бюджет админ-управл.расходов'!D33 | E76: ='Бюджет админ-управл.расходов'!E33 | F76: ='Бюджет админ-управл.расходов'!F33 | G76: ='Бюджет админ-управл.расходов'!G33 | H76: ='Бюджет админ-управл.расходов'!H33 | I76: ='Бюджет админ-управл.расходов'!I33 | ... M76: ='Бюджет админ-управл.расходов'!M33 | N76: =B76+C76+D76+E76+F76+G76+H76+I76+J76+K76+L76+M76 -> 0
A77: прочие расходы на ден.обращение | B77: ='Бюджет админ-управл.расходов'!B34 | C77: ='Бюджет админ-управл.расходов'!C34 | D77: ='Бюджет админ-управл.расходов'!D34 | E77: ='Бюджет админ-управл.расходов'!E34 | F77: ='Бюджет админ-управл.расходов'!F34 | G77: ='Бюджет админ-управл.расходов'!G34 | H77: ='Бюджет админ-управл.расходов'!H34 | I77: ='Бюджет админ-управл.расходов'!I34 | ... M77: ='Бюджет админ-управл.расходов'!M34 | N77: =B77+C77+D77+E77+F77+G77+H77+I77+J77+K77+L77+M77 -> 0
A78: Прочие административные расходы | B78: =B79+B80+B81+B82 -> 0 | C78: =C79+C80+C81+C82 -> 0 | D78: =D79+D80+D81+D82 -> 0 | E78: =E79+E80+E81+E82 -> 0 | F78: =F79+F80+F81+F82 -> 0 | G78: =G79+G80+G81+G82 -> 0 | H78: =H79+H80+H81+H82 -> 0 | I78: =I79+I80+I81+I82 -> 0 | ... M78: =M79+M80+M81+M82 -> 0 | N78: =B78+C78+D78+E78+F78+G78+H78+I78+J78+K78+L78+M78 -> 0
A79: командировки | B79: ='Бюджет админ-управл.расходов'!B42 | C79: ='Бюджет админ-управл.расходов'!C42 | D79: ='Бюджет админ-управл.расходов'!D42 | E79: ='Бюджет админ-управл.расходов'!E42 | F79: ='Бюджет админ-управл.расходов'!F42 | G79: ='Бюджет админ-управл.расходов'!G42 | H79: ='Бюджет админ-управл.расходов'!H42 | I79: ='Бюджет админ-управл.расходов'!I42 | ... M79: ='Бюджет админ-управл.расходов'!M42 | N79: =B79+C79+D79+E79+F79+G79+H79+I79+J79+K79+L79+M79 -> 0
A80: копировальные услуги | B80: ='Бюджет админ-управл.расходов'!B41 | C80: ='Бюджет админ-управл.расходов'!C41 | D80: ='Бюджет админ-управл.расходов'!D41 | E80: ='Бюджет админ-управл.расходов'!E41 | F80: ='Бюджет админ-управл.расходов'!F41 | G80: ='Бюджет админ-управл.расходов'!G41 | H80: ='Бюджет админ-управл.расходов'!H41 | I80: ='Бюджет админ-управл.расходов'!I41 | ... M80: ='Бюджет админ-управл.расходов'!M41 | N80: =B80+C80+D80+E80+F80+G80+H80+I80+J80+K80+L80+M80 -> 0
A81: представительские расходы | B81: ='Бюджет админ-управл.расходов'!B43 | C81: ='Бюджет админ-управл.расходов'!C43 | D81: ='Бюджет админ-управл.расходов'!D43 | E81: ='Бюджет админ-управл.расходов'!E43 | F81: ='Бюджет админ-управл.расходов'!F43 | G81: ='Бюджет админ-управл.расходов'!G43 | H81: ='Бюджет админ-управл.расходов'!H43 | I81: ='Бюджет админ-управл.расходов'!I43 | ... M81: ='Бюджет админ-управл.расходов'!M43 | N81: =B81+C81+D81+E81+F81+G81+H81+I81+J81+K81+L81+M81 -> 0
A82: почтовые расходы | B82: ='Бюджет админ-управл.расходов'!B40 | C82: ='Бюджет админ-управл.расходов'!C40 | D82: ='Бюджет админ-управл.расходов'!D40 | E82: ='Бюджет админ-управл.расходов'!E40 | F82: ='Бюджет админ-управл.расходов'!F40 | G82: ='Бюджет админ-управл.расходов'!G40 | H82: ='Бюджет админ-управл.расходов'!H40 | I82: ='Бюджет админ-управл.расходов'!I40 | ... M82: ='Бюджет админ-управл.расходов'!M40 | N82: =B82+C82+D82+E82+F82+G82+H82+I82+J82+K82+L82+M82 -> 0
A83: Спецодежда | N83: =B83+C83+D83+E83+F83+G83+H83+I83+J83+K83+L83+M83 -> 0
A84: Амортизация | B84: =B86+B85 -> 0 | C84: =C86+C85 -> 0 | D84: =D86+D85 -> 0 | E84: =E86+E85 -> 0 | F84: =F86+F85 -> 0 | G84: =G86+G85 -> 0 | H84: =H86+H85 -> 0 | I84: =I86+I85 -> 0 | ... M84: =M86+M85 -> 0 | N84: =B84+C84+D84+E84+F84+G84+H84+I84+J84+K84+L84+M84 -> 0
A85: амортизация ОС | B85: ='Инвест_бюджет'!B675 | C85: ='Инвест_бюджет'!C675 | D85: ='Инвест_бюджет'!D675 | E85: ='Инвест_бюджет'!E675 | F85: ='Инвест_бюджет'!F675 | G85: ='Инвест_бюджет'!G675 | H85: ='Инвест_бюджет'!H675 | I85: ='Инвест_бюджет'!I675 | ... M85: ='Инвест_бюджет'!M675 | N85: =B85+C85+D85+E85+F85+G85+H85+I85+J85+K85+L85+M85 -> 0
A86: списание МПЗ | B86: ='Инвест_бюджет'!B676 | C86: ='Инвест_бюджет'!C676 | D86: ='Инвест_бюджет'!D676 | E86: ='Инвест_бюджет'!E676 | F86: ='Инвест_бюджет'!F676 | G86: ='Инвест_бюджет'!G676 | H86: ='Инвест_бюджет'!H676 | I86: ='Инвест_бюджет'!I676 | ... M86: ='Инвест_бюджет'!M676 | N86: =B86+C86+D86+E86+F86+G86+H86+I86+J86+K86+L86+M86 -> 0
A87: Налоги по операционной деятельности | B87: =SUM(B88:B92) -> 0 | C87: =SUM(C88:C92) -> 0 | D87: =SUM(D88:D92) -> 0 | E87: =SUM(E88:E92) -> 0 | F87: =SUM(F88:F92) -> 0 | G87: =SUM(G88:G92) -> 0 | H87: =SUM(H88:H92) -> 0 | I87: =SUM(I88:I92) -> 0 | ... M87: =SUM(M88:M92) -> 0 | N87: =B87+C87+D87+E87+F87+G87+H87+I87+J87+K87+L87+M87 -> 0
A88: ЕНВД | N88: =B88+C88+D88+E88+F88+G88+H88+I88+J88+K88+L88+M88 -> 0
A89: Транспортный налог | N89: =B89+C89+D89+E89+F89+G89+H89+I89+J89+K89+L89+M89 -> 0
A90: Налог на имущество | N90: =B90+C90+D90+E90+F90+G90+H90+I90+J90+K90+L90+M90 -> 0
A91: Фиксированный платеж по ИП | N91: =B91+C91+D91+E91+F91+G91+H91+I91+J91+K91+L91+M91 -> 0
A92: Прочие налоги и сборы | N92: =B92+C92+D92+E92+F92+G92+H92+I92+J92+K92+L92+M92 -> 0
A93: Прибыль от операционной деятельности | B93: =B3-B5 -> 0 | C93: =C3-C5 -> 0 | D93: =D3-D5 -> 0 | E93: =E3-E5 -> 0 | F93: =F3-F5 -> 0 | G93: =G3-G5 -> 0 | H93: =H3-H5 -> 0 | I93: =I3-I5 -> 0 | ... M93: =M3-M5 -> 0 | N93: =B93+C93+D93+E93+F93+G93+H93+I93+J93+K93+L93+M93 -> 0
A94: в % от дохода | B94: =B93/B3 -> #DIV/0! | C94: =C93/C3 -> #DIV/0! | D94: =D93/D3 -> #DIV/0! | E94: =E93/E3 -> #DIV/0! | F94: =F93/F3 -> #DIV/0! | G94: =G93/G3 -> #DIV/0! | H94: =H93/H3 -> #DIV/0! | I94: =I93/I3 -> #DIV/0! | ... N94: =N93/N3 -> #DIV/0!
A95: Доходы от прочих видов деятельности | B95: =SUM(B96:B97) -> 0 | C95: =SUM(C96:C97) -> 0 | D95: =SUM(D96:D97) -> 0 | E95: =SUM(E96:E97) -> 0 | F95: =SUM(F96:F97) -> 0 | G95: =SUM(G96:G97) -> 0 | H95: =SUM(H96:H97) -> 0 | I95: =SUM(I96:I97) -> 0 | ... M95: =SUM(M96:M97) -> 0 | N95: =B95+C95+D95+E95+F95+G95+H95+I95+J95+K95+L95+M95 -> 0
A98: Расходы по прочим видам деятельности | B98: =B99 | C98: =C99 | D98: =D99 | E98: =E99 | F98: =F99 | G98: =G99 | H98: =H99 | I98: =I99 | ... M98: =M99 | N98: =B98+C98+D98+E98+F98+G98+H98+I98+J98+K98+L98+M98 -> 0
A100: Прибыль от прочих видов деятельности | B100: =B95-B98 -> 0 | C100: =C95-C98 -> 0 | D100: =D95-D98 -> 0 | E100: =E95-E98 -> 0 | F100: =F95-F98 -> 0 | G100: =G95-G98 -> 0 | H100: =H95-H98 -> 0 | I100: =I95-I98 -> 0 | ... M100: =M95-M98 -> 0 | N100: =B100+C100+D100+E100+F100+G100+H100+I100+J100+K100+L100+M100 -> 0
A101: в % от дохода | B101: =IF(B100=0,0,B100/B95) -> 0 | C101: =IF(C100=0,0,C100/C95) -> 0 | D101: =IF(D100=0,0,D100/D95) -> 0 | E101: =IF(E100=0,0,E100/E95) -> 0 | F101: =IF(F100=0,0,F100/F95) -> 0 | G101: =IF(G100=0,0,G100/G95) -> 0 | H101: =IF(H100=0,0,H100/H95) -> 0 | I101: =IF(I100=0,0,I100/I95) -> 0 | ... M101: =IF(M100=0,0,M100/M95) -> 0 | N101: =N100/#REF! -> #REF!
A102: Доходы от инвестиционной деятельности | B102: =B103 | C102: =C103 | D102: =D103 | E102: =E103 | F102: =F103 | G102: =G103 | H102: =H103 | I102: =I103 | ... N102: =N103
A104: Расходы по инвестиционной деятельности | B104: =SUM(B105:B106) -> 0 | C104: =SUM(C105:C106) -> 0 | D104: =SUM(D105:D106) -> 0 | E104: =SUM(E105:E106) -> 0 | F104: =SUM(F105:F106) -> 0 | G104: =SUM(G105:G106) -> 0 | H104: =SUM(H105:H106) -> 0 | I104: =SUM(I105:I106) -> 0 | ... M104: =SUM(M105:M106) -> 0 | N104: =B104+C104+D104+E104+F104+G104+H104+I104+J104+K104+L104+M104 -> 0
...

Sheet Бюджет-продаж
A1: Бюджет продаж 2021
A2: Наименование статьи | B2: янв | C2: фев | D2: мар | E2: апр | F2: май | G2: июн | H2: июл | I2: авг | J2: сен | K2: окт | L2: ноя | M2: дек | N2: ГОД
A3: ШАГ № 1:ВВОД ИСХОДНОЙ ИНФОРМАЦИИ
A4: Ввести запланированные продажи ГП по направлениям, единицы
A5: Направление 1
A6: Продукт 1 | N6: =SUM(B6,C6,D6,E6,F6,G6,H6,I6,J6,K6,L6,M6) -> 0
A7: Продукт 2 | N7: =SUM(B7,C7,D7,E7,F7,G7,H7,I7,J7,K7,L7,M7) -> 0
A8: Продукт 3 | N8: =SUM(B8,C8,D8,E8,F8,G8,H8,I8,J8,K8,L8,M8) -> 0
A9: Продукт 4 | N9: =SUM(B9,C9,D9,E9,F9,G9,H9,I9,J9,K9,L9,M9) -> 0
A10: Продукт 5 | N10: =SUM(B10,C10,D10,E10,F10,G10,H10,I10,J10,K10,L10,M10) -> 0
A11: Продукт.... | N11: =SUM(B11,C11,D11,E11,F11,G11,H11,I11,J11,K11,L11,M11) -> 0
N12: =SUM(B12,C12,D12,E12,F12,G12,H12,I12,J12,K12,L12,M12) -> 0
N13: =SUM(B13,C13,D13,E13,F13,G13,H13,I13,J13,K13,L13,M13) -> 0
N14: =SUM(B14,C14,D14,E14,F14,G14,H14,I14,J14,K14,L14,M14) -> 0
N15: =SUM(B15,C15,D15,E15,F15,G15,H15,I15,J15,K15,L15,M15) -> 0
N16: =SUM(B16,C16,D16,E16,F16,G16,H16,I16,J16,K16,L16,M16) -> 0
N17: =SUM(B17,C17,D17,E17,F17,G17,H17,I17,J17,K17,L17,M17) -> 0
N18: =SUM(B18,C18,D18,E18,F18,G18,H18,I18,J18,K18,L18,M18) -> 0
N19: =SUM(B19,C19,D19,E19,F19,G19,H19,I19,J19,K19,L19,M19) -> 0
N20: =SUM(B20,C20,D20,E20,F20,G20,H20,I20,J20,K20,L20,M20) -> 0
N21: =SUM(B21,C21,D21,E21,F21,G21,H21,I21,J21,K21,L21,M21) -> 0
N22: =SUM(B22,C22,D22,E22,F22,G22,H22,I22,J22,K22,L22,M22) -> 0
N23: =SUM(B23,C23,D23,E23,F23,G23,H23,I23,J23,K23,L23,M23) -> 0
... N25: =SUM(B25,C25,D25,E25,F25,G25,H25,I25,J25,K25,L25,M25) -> 0
A26: Итого по направлению 1, единицы | B26: =SUM(B6:B24) -> 0 | C26: =SUM(C6:C24) -> 0 | D26: =SUM(D6:D24) -> 0 | E26: =SUM(E6:E24) -> 0 | F26: =SUM(F6:F24) -> 0 | G26: =SUM(G6:G24) -> 0 | H26: =SUM(H6:H24) -> 0 | I26: =SUM(I6:I24) -> 0 | ... N26: =SUM(N6:N24) -> 0
A28: Направление 2
A29: Продукт 1
A30: Продукт 2 | N30: =SUM(B30,C30,D30,E30,F30,G30,H30,I30,J30,K30,L30,M30) -> 0
A31: Продукт 3 | N31: =SUM(B31,C31,D31,E31,F31,G31,H31,I31,J31,K31,L31,M31) -> 0
A32: Продукт 4 | N32: =SUM(B32,C32,D32,E32,F32,G32,H32,I32,J32,K32,L32,M32) -> 0
A33: Продукт 5 | N33: =SUM(B33,C33,D33,E33,F33,G33,H33,I33,J33,K33,L33,M33) -> 0
A34: Продукт.... | N34: =SUM(B34,C34,D34,E34,F34,G34,H34,I34,J34,K34,L34,M34) -> 0
N35: =SUM(B35,C35,D35,E35,F35,G35,H35,I35,J35,K35,L35,M35) -> 0
N36: =SUM(B36,C36,D36,E36,F36,G36,H36,I36,J36,K36,L36,M36) -> 0
N37: =SUM(B37,C37,D37,E37,F37,G37,H37,I37,J37,K37,L37,M37) -> 0
N38: =SUM(B38,C38,D38,E38,F38,G38,H38,I38,J38,K38,L38,M38) -> 0
N39: =SUM(B39,C39,D39,E39,F39,G39,H39,I39,J39,K39,L39,M39) -> 0
N40: =SUM(B40,C40,D40,E40,F40,G40,H40,I40,J40,K40,L40,M40) -> 0
N41: =SUM(B41,C41,D41,E41,F41,G41,H41,I41,J41,K41,L41,M41) -> 0
N42: =SUM(B42,C42,D42,E42,F42,G42,H42,I42,J42,K42,L42,M42) -> 0
N43: =SUM(B43,C43,D43,E43,F43,G43,H43,I43,J43,K43,L43,M43) -> 0
N44: =SUM(B44,C44,D44,E44,F44,G44,H44,I44,J44,K44,L44,M44) -> 0
N45: =SUM(B45,C45,D45,E45,F45,G45,H45,I45,J45,K45,L45,M45) -> 0
N46: =SUM(B46,C46,D46,E46,F46,G46,H46,I46,J46,K46,L46,M46) -> 0
... N48: =SUM(B48,C48,D48,E48,F48,G48,H48,I48,J48,K48,L48,M48) -> 0
A49: Итого по направлению 2, единицы | B49: =SUM(B29:B47) -> 0 | C49: =SUM(C29:C47) -> 0 | D49: =SUM(D29:D47) -> 0 | E49: =SUM(E29:E47) -> 0 | F49: =SUM(F29:F47) -> 0 | G49: =SUM(G29:G47) -> 0 | H49: =SUM(H29:H47) -> 0 | I49: =SUM(I29:I47) -> 0 | ... N49: =SUM(N29:N47) -> 0
A50: Итого запланированные продажи, единиц | B50: =B26+B49 -> 0 | C50: =C26+C49 -> 0 | D50: =D26+D49 -> 0 | E50: =E26+E49 -> 0 | F50: =F26+F49 -> 0 | G50: =G26+G49 -> 0 | H50: =H26+H49 -> 0 | I50: =I26+I49 -> 0 | ... N50: =N26+N49 -> 0
A52: Ввести цены реализации, руб / единица
A53: Направление 1
A54: Продукт 1 | N54: =IFERROR(AVERAGE(B54,C54,D54,E54,F54,I54,G54,H54,J54,K54,L54,M54),)
A55: Продукт 2 | N55: =IFERROR(AVERAGE(B55,C55,D55,E55,F55,I55,G55,H55,J55,K55,L55,M55),)
A56: Продукт 3 | N56: =IFERROR(AVERAGE(B56,C56,D56,E56,F56,I56,G56,H56,J56,K56,L56,M56),)
A57: Продукт 4 | N57: =IFERROR(AVERAGE(B57,C57,D57,E57,F57,I57,G57,H57,J57,K57,L57,M57),)
A58: Продукт 5 | N58: =IFERROR(AVERAGE(B58,C58,D58,E58,F58,I58,G58,H58,J58,K58,L58,M58),)
A59: Продукт.... | N59: =IFERROR(AVERAGE(B59,C59,D59,E59,F59,I59,G59,H59,J59,K59,L59,M59),)
N60: =IFERROR(AVERAGE(B60,C60,D60,E60,F60,I60,G60,H60,J60,K60,L60,M60),)
N61: =IFERROR(AVERAGE(B61,C61,D61,E61,F61,I61,G61,H61,J61,K61,L61,M61),)
N62: =IFERROR(AVERAGE(B62,C62,D62,E62,F62,I62,G62,H62,J62,K62,L62,M62),)
N63: =IFERROR(AVERAGE(B63,C63,D63,E63,F63,I63,G63,H63,J63,K63,L63,M63),)
N64: =IFERROR(AVERAGE(B64,C64,D64,E64,F64,I64,G64,H64,J64,K64,L64,M64),)
N65: =IFERROR(AVERAGE(B65,C65,D65,E65,F65,I65,G65,H65,J65,K65,L65,M65),)
N66: =IFERROR(AVERAGE(B66,C66,D66,E66,F66,I66,G66,H66,J66,K66,L66,M66),)
N67: =IFERROR(AVERAGE(B67,C67,D67,E67,F67,I67,G67,H67,J67,K67,L67,M67),)
N68: =IFERROR(AVERAGE(B68,C68,D68,E68,F68,I68,G68,H68,J68,K68,L68,M68),)
N69: =IFERROR(AVERAGE(B69,C69,D69,E69,F69,I69,G69,H69,J69,K69,L69,M69),)
N70: =IFERROR(AVERAGE(B70,C70,D70,E70,F70,I70,G70,H70,J70,K70,L70,M70),)
N71: =IFERROR(AVERAGE(B71,C71,D71,E71,F71,I71,G71,H71,J71,K71,L71,M71),)
... N73: =IFERROR(AVERAGE(B73,C73,D73,E73,F73,I73,G73,H73,J73,K73,L73,M73),)
A74: Направление 2
A75: Продукт 1 | N75: =IFERROR(AVERAGE(B75,C75,D75,E75,F75,I75,G75,H75,J75,K75,L75,M75),)
A76: Продукт 2 | N76: =IFERROR(AVERAGE(B76,C76,D76,E76,F76,I76,G76,H76,J76,K76,L76,M76),)
A77: Продукт 3 | N77: =IFERROR(AVERAGE(B77,C77,D77,E77,F77,I77,G77,H77,J77,K77,L77,M77),)
A78: Продукт 4 | N78: =IFERROR(AVERAGE(B78,C78,D78,E78,F78,I78,G78,H78,J78,K78,L78,M78),)
A79: Продукт 5 | N79: =IFERROR(AVERAGE(B79,C79,D79,E79,F79,I79,G79,H79,J79,K79,L79,M79),)
A80: Продукт.... | N80: =IFERROR(AVERAGE(B80,C80,D80,E80,F80,I80,G80,H80,J80,K80,L80,M80),)
N81: =IFERROR(AVERAGE(B81,C81,D81,E81,F81,I81,G81,H81,J81,K81,L81,M81),)
N82: =IFERROR(AVERAGE(B82,C82,D82,E82,F82,I82,G82,H82,J82,K82,L82,M82),)
N83: =IFERROR(AVERAGE(B83,C83,D83,E83,F83,I83,G83,H83,J83,K83,L83,M83),)
N84: =IFERROR(AVERAGE(B84,C84,D84,E84,F84,I84,G84,H84,J84,K84,L84,M84),)
N85: =IFERROR(AVERAGE(B85,C85,D85,E85,F85,I85,G85,H85,J85,K85,L85,M85),)
N86: =IFERROR(AVERAGE(B86,C86,D86,E86,F86,I86,G86,H86,J86,K86,L86,M86),)
N87: =IFERROR(AVERAGE(B87,C87,D87,E87,F87,I87,G87,H87,J87,K87,L87,M87),)
N88: =IFERROR(AVERAGE(B88,C88,D88,E88,F88,I88,G88,H88,J88,K88,L88,M88),)
N89: =IFERROR(AVERAGE(B89,C89,D89,E89,F89,I89,G89,H89,J89,K89,L89,M89),)
N90: =IFERROR(AVERAGE(B90,C90,D90,E90,F90,I90,G90,H90,J90,K90,L90,M90),)
N91: =IFERROR(AVERAGE(B91,C91,D91,E91,F91,I91,G91,H91,J91,K91,L91,M91),)
N92: =IFERROR(AVERAGE(B92,C92,D92,E92,F92,I92,G92,H92,J92,K92,L92,M92),)
... N94: =IFERROR(AVERAGE(B94,C94,D94,E94,F94,I94,G94,H94,J94,K94,L94,M94),)
A96: ШАГ № 2:РАСЧЕТНАЯ ЧАСТЬ ТАБЛИЦЫ
A97: Плановая реализация , тыс. руб.
A98: Направление 1
A99: Продукт 1 | B99: =B6*B54 -> 0 | C99: =C6*C54 -> 0 | D99: =D6*D54 -> 0 | E99: =E6*E54 -> 0 | F99: =F6*F54 -> 0 | G99: =G6*G54 -> 0 | H99: =H6*H54 -> 0 | I99: =I6*I54 -> 0 | ... M99: =M6*M54 -> 0 | N99: =SUM(B99,C99,D99,E99,F99,G99,H99,I99,J99,K99,L99,M99) -> 0
A100: Продукт 2 | B100: =B7*B55 -> 0 | C100: =C7*C55 -> 0 | D100: =D7*D55 -> 0 | E100: =E7*E55 -> 0 | F100: =F7*F55 -> 0 | G100: =G7*G55 -> 0 | H100: =H7*H55 -> 0 | I100: =I7*I55 -> 0 | ... M100: =M7*M55 -> 0 | N100: =SUM(B100,C100,D100,E100,F100,G100,H100,I100,J100,K100,L100,M100) -> 0
A101: Продукт 3 | B101: =B8*B56 -> 0 | C101: =C8*C56 -> 0 | D101: =D8*D56 -> 0 | E101: =E8*E56 -> 0 | F101: =F8*F56 -> 0 | G101: =G8*G56 -> 0 | H101: =H8*H56 -> 0 | I101: =I8*I56 -> 0 | ... M101: =M8*M56 -> 0 | N101: =SUM(B101,C101,D101,E101,F101,G101,H101,I101,J101,K101,L101,M101) -> 0
A102: Продукт 4 | B102: =B9*B57 -> 0 | C102: =C9*C57 -> 0 | D102: =D9*D57 -> 0 | E102: =E9*E57 -> 0 | F102: =F9*F57 -> 0 | G102: =G9*G57 -> 0 | H102: =H9*H57 -> 0 | I102: =I9*I57 -> 0 | ... M102: =M9*M57 -> 0 | N102: =SUM(B102,C102,D102,E102,F102,G102,H102,I102,J102,K102,L102,M102) -> 0
A103: Продукт 5 | B103: =B10*B58 -> 0 | C103: =C10*C58 -> 0 | D103: =D10*D58 -> 0 | E103: =E10*E58 -> 0 | F103: =F10*F58 -> 0 | G103: =G10*G58 -> 0 | H103: =H10*H58 -> 0 | I103: =I10*I58 -> 0 | ... M103: =M10*M58 -> 0 | N103: =SUM(B103,C103,D103,E103,F103,G103,H103,I103,J103,K103,L103,M103) -> 0
A104: Продукт.... | B104: =B11*B59 -> 0 | C104: =C11*C59 -> 0 | D104: =D11*D59 -> 0 | E104: =E11*E59 -> 0 | F104: =F11*F59 -> 0 | G104: =G11*G59 -> 0 | H104: =H11*H59 -> 0 | I104: =I11*I59 -> 0 | ... M104: =M11*M59 -> 0 | N104: =SUM(B104,C104,D104,E104,F104,G104,H104,I104,J104,K104,L104,M104) -> 0
B105: =B12*B60 -> 0 | C105: =C12*C60 -> 0 | D105: =D12*D60 -> 0 | E105: =E12*E60 -> 0 | F105: =F12*F60 -> 0 | G105: =G12*G60 -> 0 | H105: =H12*H60 -> 0 | I105: =I12*I60 -> 0 | ... M105: =M12*M60 -> 0 | N105: =SUM(B105,C105,D105,E105,F105,G105,H105,I105,J105,K105,L105,M105) -> 0
B106: =B13*B61 -> 0 | C106: =C13*C61 -> 0 | D106: =D13*D61 -> 0 | E106: =E13*E61 -> 0 | F106: =F13*F61 -> 0 | G106: =G13*G61 -> 0 | H106: =H13*H61 -> 0 | I106: =I13*I61 -> 0 | ... M106: =M13*M61 -> 0 | N106: =SUM(B106,C106,D106,E106,F106,G106,H106,I106,J106,K106,L106,M106) -> 0
B107: =B14*B62 -> 0 | C107: =C14*C62 -> 0 | D107: =D14*D62 -> 0 | E107: =E14*E62 -> 0 | F107: =F14*F62 -> 0 | G107: =G14*G62 -> 0 | H107: =H14*H62 -> 0 | I107: =I14*I62 -> 0 | ... M107: =M14*M62 -> 0 | N107: =SUM(B107,C107,D107,E107,F107,G107,H107,I107,J107,K107,L107,M107) -> 0
...

Sheet Бюджет производства
A1: Бюджет производства 2021
A2: Наименование статьи | B2: янв | C2: фев | D2: мар | E2: апр | F2: май | G2: июн | H2: июл | I2: авг | J2: сен | K2: окт | L2: ноя | M2: дек | N2: ГОД
A3: Объем производства продукции
A4: Продукт 1 | B4: ='Бюджет-продаж'!B6+'Бюджет-продаж'!B29 -> 0 | C4: ='Бюджет-продаж'!C6+'Бюджет-продаж'!C29 -> 0 | D4: ='Бюджет-продаж'!D6+'Бюджет-продаж'!D29 -> 0 | E4: ='Бюджет-продаж'!E6+'Бюджет-продаж'!E29 -> 0 | F4: ='Бюджет-продаж'!F6+'Бюджет-продаж'!F29 -> 0 | G4: ='Бюджет-продаж'!G6+'Бюджет-продаж'!G29 -> 0 | H4: ='Бюджет-продаж'!H6+'Бюджет-продаж'!H29 -> 0 | I4: ='Бюджет-продаж'!I6+'Бюджет-продаж'!I29 -> 0 | ... M4: ='Бюджет-продаж'!M6+'Бюджет-продаж'!M29 -> 0 | N4: =SUM(B4,C4,D4,E4,F4,G4,H4,I4,J4,K4,L4,M4) -> 0
A5: Продукт 2 | B5: ='Бюджет-продаж'!B7+'Бюджет-продаж'!B30 -> 0 | C5: ='Бюджет-продаж'!C7+'Бюджет-продаж'!C30 -> 0 | D5: ='Бюджет-продаж'!D7+'Бюджет-продаж'!D30 -> 0 | E5: ='Бюджет-продаж'!E7+'Бюджет-продаж'!E30 -> 0 | F5: ='Бюджет-продаж'!F7+'Бюджет-продаж'!F30 -> 0 | G5: ='Бюджет-продаж'!G7+'Бюджет-продаж'!G30 -> 0 | H5: ='Бюджет-продаж'!H7+'Бюджет-продаж'!H30 -> 0 | I5: ='Бюджет-продаж'!I7+'Бюджет-продаж'!I30 -> 0 | ... M5: ='Бюджет-продаж'!M7+'Бюджет-продаж'!M30 -> 0 | N5: =SUM(B5,C5,D5,E5,F5,G5,H5,I5,J5,K5,L5,M5) -> 0
A6: Продукт 3 | B6: ='Бюджет-продаж'!B8+'Бюджет-продаж'!B31 -> 0 | C6: ='Бюджет-продаж'!C8+'Бюджет-продаж'!C31 -> 0 | D6: ='Бюджет-продаж'!D8+'Бюджет-продаж'!D31 -> 0 | E6: ='Бюджет-продаж'!E8+'Бюджет-продаж'!E31 -> 0 | F6: ='Бюджет-продаж'!F8+'Бюджет-продаж'!F31 -> 0 | G6: ='Бюджет-продаж'!G8+'Бюджет-продаж'!G31 -> 0 | H6: ='Бюджет-продаж'!H8+'Бюджет-продаж'!H31 -> 0 | I6: ='Бюджет-продаж'!I8+'Бюджет-продаж'!I31 -> 0 | ... M6: ='Бюджет-продаж'!M8+'Бюджет-продаж'!M31 -> 0 | N6: =SUM(B6,C6,D6,E6,F6,G6,H6,I6,J6,K6,L6,M6) -> 0
A7: Продукт 4 | B7: ='Бюджет-продаж'!B9+'Бюджет-продаж'!B32 -> 0 | C7: ='Бюджет-продаж'!C9+'Бюджет-продаж'!C32 -> 0 | D7: ='Бюджет-продаж'!D9+'Бюджет-продаж'!D32 -> 0 | E7: ='Бюджет-продаж'!E9+'Бюджет-продаж'!E32 -> 0 | F7: ='Бюджет-продаж'!F9+'Бюджет-продаж'!F32 -> 0 | G7: ='Бюджет-продаж'!G9+'Бюджет-продаж'!G32 -> 0 | H7: ='Бюджет-продаж'!H9+'Бюджет-продаж'!H32 -> 0 | I7: ='Бюджет-продаж'!I9+'Бюджет-продаж'!I32 -> 0 | ... M7: ='Бюджет-продаж'!M9+'Бюджет-продаж'!M32 -> 0 | N7: =SUM(B7,C7,D7,E7,F7,G7,H7,I7,J7,K7,L7,M7) -> 0
A8: Продукт 5 | B8: ='Бюджет-продаж'!B10+'Бюджет-продаж'!B33 -> 0 | C8: ='Бюджет-продаж'!C10+'Бюджет-продаж'!C33 -> 0 | D8: ='Бюджет-продаж'!D10+'Бюджет-продаж'!D33 -> 0 | E8: ='Бюджет-продаж'!E10+'Бюджет-продаж'!E33 -> 0 | F8: ='Бюджет-продаж'!F10+'Бюджет-продаж'!F33 -> 0 | G8: ='Бюджет-продаж'!G10+'Бюджет-продаж'!G33 -> 0 | H8: ='Бюджет-продаж'!H10+'Бюджет-продаж'!H33 -> 0 | I8: ='Бюджет-продаж'!I10+'Бюджет-продаж'!I33 -> 0 | ... M8: ='Бюджет-продаж'!M10+'Бюджет-продаж'!M33 -> 0 | N8: =SUM(B8,C8,D8,E8,F8,G8,H8,I8,J8,K8,L8,M8) -> 0
A9: Продукт.... | B9: ='Бюджет-продаж'!B11+'Бюджет-продаж'!B34 -> 0 | C9: ='Бюджет-продаж'!C11+'Бюджет-продаж'!C34 -> 0 | D9: ='Бюджет-продаж'!D11+'Бюджет-продаж'!D34 -> 0 | E9: ='Бюджет-продаж'!E11+'Бюджет-продаж'!E34 -> 0 | F9: ='Бюджет-продаж'!F11+'Бюджет-продаж'!F34 -> 0 | G9: ='Бюджет-продаж'!G11+'Бюджет-продаж'!G34 -> 0 | H9: ='Бюджет-продаж'!H11+'Бюджет-продаж'!H34 -> 0 | I9: ='Бюджет-продаж'!I11+'Бюджет-продаж'!I34 -> 0 | ... M9: ='Бюджет-продаж'!M11+'Бюджет-продаж'!M34 -> 0 | N9: =SUM(B9,C9,D9,E9,F9,G9,H9,I9,J9,K9,L9,M9) -> 0
B10: ='Бюджет-продаж'!B12+'Бюджет-продаж'!B35 -> 0 | C10: ='Бюджет-продаж'!C12+'Бюджет-продаж'!C35 -> 0 | D10: ='Бюджет-продаж'!D12+'Бюджет-продаж'!D35 -> 0 | E10: ='Бюджет-продаж'!E12+'Бюджет-продаж'!E35 -> 0 | F10: ='Бюджет-продаж'!F12+'Бюджет-продаж'!F35 -> 0 | G10: ='Бюджет-продаж'!G12+'Бюджет-продаж'!G35 -> 0 | H10: ='Бюджет-продаж'!H12+'Бюджет-продаж'!H35 -> 0 | I10: ='Бюджет-продаж'!I12+'Бюджет-продаж'!I35 -> 0 | ... M10: ='Бюджет-продаж'!M12+'Бюджет-продаж'!M35 -> 0 | N10: =SUM(B10,C10,D10,E10,F10,G10,H10,I10,J10,K10,L10,M10) -> 0
B11: ='Бюджет-продаж'!B13+'Бюджет-продаж'!B36 -> 0 | C11: ='Бюджет-продаж'!C13+'Бюджет-продаж'!C36 -> 0 | D11: ='Бюджет-продаж'!D13+'Бюджет-продаж'!D36 -> 0 | E11: ='Бюджет-продаж'!E13+'Бюджет-продаж'!E36 -> 0 | F11: ='Бюджет-продаж'!F13+'Бюджет-продаж'!F36 -> 0 | G11: ='Бюджет-продаж'!G13+'Бюджет-продаж'!G36 -> 0 | H11: ='Бюджет-продаж'!H13+'Бюджет-продаж'!H36 -> 0 | I11: ='Бюджет-продаж'!I13+'Бюджет-продаж'!I36 -> 0 | ... M11: ='Бюджет-продаж'!M13+'Бюджет-продаж'!M36 -> 0 | N11: =SUM(B11,C11,D11,E11,F11,G11,H11,I11,J11,K11,L11,M11) -> 0
B12: ='Бюджет-продаж'!B14+'Бюджет-продаж'!B37 -> 0 | C12: ='Бюджет-продаж'!C14+'Бюджет-продаж'!C37 -> 0 | D12: ='Бюджет-продаж'!D14+'Бюджет-продаж'!D37 -> 0 | E12: ='Бюджет-продаж'!E14+'Бюджет-продаж'!E37 -> 0 | F12: ='Бюджет-продаж'!F14+'Бюджет-продаж'!F37 -> 0 | G12: ='Бюджет-продаж'!G14+'Бюджет-продаж'!G37 -> 0 | H12: ='Бюджет-продаж'!H14+'Бюджет-продаж'!H37 -> 0 | I12: ='Бюджет-продаж'!I14+'Бюджет-продаж'!I37 -> 0 | ... M12: ='Бюджет-продаж'!M14+'Бюджет-продаж'!M37 -> 0 | N12: =SUM(B12,C12,D12,E12,F12,G12,H12,I12,J12,K12,L12,M12) -> 0
B13: ='Бюджет-продаж'!B15+'Бюджет-продаж'!B38 -> 0 | C13: ='Бюджет-продаж'!C15+'Бюджет-продаж'!C38 -> 0 | D13: ='Бюджет-продаж'!D15+'Бюджет-продаж'!D38 -> 0 | E13: ='Бюджет-продаж'!E15+'Бюджет-продаж'!E38 -> 0 | F13: ='Бюджет-продаж'!F15+'Бюджет-продаж'!F38 -> 0 | G13: ='Бюджет-продаж'!G15+'Бюджет-продаж'!G38 -> 0 | H13: ='Бюджет-продаж'!H15+'Бюджет-продаж'!H38 -> 0 | I13: ='Бюджет-продаж'!I15+'Бюджет-продаж'!I38 -> 0 | ... M13: ='Бюджет-продаж'!M15+'Бюджет-продаж'!M38 -> 0 | N13: =SUM(B13,C13,D13,E13,F13,G13,H13,I13,J13,K13,L13,M13) -> 0
B14: ='Бюджет-продаж'!B16+'Бюджет-продаж'!B39 -> 0 | C14: ='Бюджет-продаж'!C16+'Бюджет-продаж'!C39 -> 0 | D14: ='Бюджет-продаж'!D16+'Бюджет-продаж'!D39 -> 0 | E14: ='Бюджет-продаж'!E16+'Бюджет-продаж'!E39 -> 0 | F14: ='Бюджет-продаж'!F16+'Бюджет-продаж'!F39 -> 0 | G14: ='Бюджет-продаж'!G16+'Бюджет-продаж'!G39 -> 0 | H14: ='Бюджет-продаж'!H16+'Бюджет-продаж'!H39 -> 0 | I14: ='Бюджет-продаж'!I16+'Бюджет-продаж'!I39 -> 0 | ... M14: ='Бюджет-продаж'!M16+'Бюджет-продаж'!M39 -> 0 | N14: =SUM(B14,C14,D14,E14,F14,G14,H14,I14,J14,K14,L14,M14) -> 0
B15: ='Бюджет-продаж'!B17+'Бюджет-продаж'!B40 -> 0 | C15: ='Бюджет-продаж'!C17+'Бюджет-продаж'!C40 -> 0 | D15: ='Бюджет-продаж'!D17+'Бюджет-продаж'!D40 -> 0 | E15: ='Бюджет-продаж'!E17+'Бюджет-продаж'!E40 -> 0 | F15: ='Бюджет-продаж'!F17+'Бюджет-продаж'!F40 -> 0 | G15: ='Бюджет-продаж'!G17+'Бюджет-продаж'!G40 -> 0 | H15: ='Бюджет-продаж'!H17+'Бюджет-продаж'!H40 -> 0 | I15: ='Бюджет-продаж'!I17+'Бюджет-продаж'!I40 -> 0 | ... M15: ='Бюджет-продаж'!M17+'Бюджет-продаж'!M40 -> 0 | N15: =SUM(B15,C15,D15,E15,F15,G15,H15,I15,J15,K15,L15,M15) -> 0
B16: ='Бюджет-продаж'!B18+'Бюджет-продаж'!B41 -> 0 | C16: ='Бюджет-продаж'!C18+'Бюджет-продаж'!C41 -> 0 | D16: ='Бюджет-продаж'!D18+'Бюджет-продаж'!D41 -> 0 | E16: ='Бюджет-продаж'!E18+'Бюджет-продаж'!E41 -> 0 | F16: ='Бюджет-продаж'!F18+'Бюджет-продаж'!F41 -> 0 | G16: ='Бюджет-продаж'!G18+'Бюджет-продаж'!G41 -> 0 | H16: ='Бюджет-продаж'!H18+'Бюджет-продаж'!H41 -> 0 | I16: ='Бюджет-продаж'!I18+'Бюджет-продаж'!I41 -> 0 | ... M16: ='Бюджет-продаж'!M18+'Бюджет-продаж'!M41 -> 0 | N16: =SUM(B16,C16,D16,E16,F16,G16,H16,I16,J16,K16,L16,M16) -> 0
B17: ='Бюджет-продаж'!B19+'Бюджет-продаж'!B42 -> 0 | C17: ='Бюджет-продаж'!C19+'Бюджет-продаж'!C42 -> 0 | D17: ='Бюджет-продаж'!D19+'Бюджет-продаж'!D42 -> 0 | E17: ='Бюджет-продаж'!E19+'Бюджет-продаж'!E42 -> 0 | F17: ='Бюджет-продаж'!F19+'Бюджет-продаж'!F42 -> 0 | G17: ='Бюджет-продаж'!G19+'Бюджет-продаж'!G42 -> 0 | H17: ='Бюджет-продаж'!H19+'Бюджет-продаж'!H42 -> 0 | I17: ='Бюджет-продаж'!I19+'Бюджет-продаж'!I42 -> 0 | ... M17: ='Бюджет-продаж'!M19+'Бюджет-продаж'!M42 -> 0 | N17: =SUM(B17,C17,D17,E17,F17,G17,H17,I17,J17,K17,L17,M17) -> 0
B18: ='Бюджет-продаж'!B20+'Бюджет-продаж'!B43 -> 0 | C18: ='Бюджет-продаж'!C20+'Бюджет-продаж'!C43 -> 0 | D18: ='Бюджет-продаж'!D20+'Бюджет-продаж'!D43 -> 0 | E18: ='Бюджет-продаж'!E20+'Бюджет-продаж'!E43 -> 0 | F18: ='Бюджет-продаж'!F20+'Бюджет-продаж'!F43 -> 0 | G18: ='Бюджет-продаж'!G20+'Бюджет-продаж'!G43 -> 0 | H18: ='Бюджет-продаж'!H20+'Бюджет-продаж'!H43 -> 0 | I18: ='Бюджет-продаж'!I20+'Бюджет-продаж'!I43 -> 0 | ... M18: ='Бюджет-продаж'!M20+'Бюджет-продаж'!M43 -> 0 | N18: =SUM(B18,C18,D18,E18,F18,G18,H18,I18,J18,K18,L18,M18) -> 0
B19: ='Бюджет-продаж'!B21+'Бюджет-продаж'!B44 -> 0 | C19: ='Бюджет-продаж'!C21+'Бюджет-продаж'!C44 -> 0 | D19: ='Бюджет-продаж'!D21+'Бюджет-продаж'!D44 -> 0 | E19: ='Бюджет-продаж'!E21+'Бюджет-продаж'!E44 -> 0 | F19: ='Бюджет-продаж'!F21+'Бюджет-продаж'!F44 -> 0 | G19: ='Бюджет-продаж'!G21+'Бюджет-продаж'!G44 -> 0 | H19: ='Бюджет-продаж'!H21+'Бюджет-продаж'!H44 -> 0 | I19: ='Бюджет-продаж'!I21+'Бюджет-продаж'!I44 -> 0 | ... M19: ='Бюджет-продаж'!M21+'Бюджет-продаж'!M44 -> 0 | N19: =SUM(B19,C19,D19,E19,F19,G19,H19,I19,J19,K19,L19,M19) -> 0
B20: ='Бюджет-продаж'!B22+'Бюджет-продаж'!B45 -> 0 | C20: ='Бюджет-продаж'!C22+'Бюджет-продаж'!C45 -> 0 | D20: ='Бюджет-продаж'!D22+'Бюджет-продаж'!D45 -> 0 | E20: ='Бюджет-продаж'!E22+'Бюджет-продаж'!E45 -> 0 | F20: ='Бюджет-продаж'!F22+'Бюджет-продаж'!F45 -> 0 | G20: ='Бюджет-продаж'!G22+'Бюджет-продаж'!G45 -> 0 | H20: ='Бюджет-продаж'!H22+'Бюджет-продаж'!H45 -> 0 | I20: ='Бюджет-продаж'!I22+'Бюджет-продаж'!I45 -> 0 | ... M20: ='Бюджет-продаж'!M22+'Бюджет-продаж'!M45 -> 0 | N20: =SUM(B20,C20,D20,E20,F20,G20,H20,I20,J20,K20,L20,M20) -> 0
B21: ='Бюджет-продаж'!B23+'Бюджет-продаж'!B46 -> 0 | C21: ='Бюджет-продаж'!C23+'Бюджет-продаж'!C46 -> 0 | D21: ='Бюджет-продаж'!D23+'Бюджет-продаж'!D46 -> 0 | E21: ='Бюджет-продаж'!E23+'Бюджет-продаж'!E46 -> 0 | F21: ='Бюджет-продаж'!F23+'Бюджет-продаж'!F46 -> 0 | G21: ='Бюджет-продаж'!G23+'Бюджет-продаж'!G46 -> 0 | H21: ='Бюджет-продаж'!H23+'Бюджет-продаж'!H46 -> 0 | I21: ='Бюджет-продаж'!I23+'Бюджет-продаж'!I46 -> 0 | ... M21: ='Бюджет-продаж'!M23+'Бюджет-продаж'!M46 -> 0 | N21: =SUM(B21,C21,D21,E21,F21,G21,H21,I21,J21,K21,L21,M21) -> 0
... B23: ='Бюджет-продаж'!B25+'Бюджет-продаж'!B48 -> 0 | C23: ='Бюджет-продаж'!C25+'Бюджет-продаж'!C48 -> 0 | D23: ='Бюджет-продаж'!D25+'Бюджет-продаж'!D48 -> 0 | E23: ='Бюджет-продаж'!E25+'Бюджет-продаж'!E48 -> 0 | F23: ='Бюджет-продаж'!F25+'Бюджет-продаж'!F48 -> 0 | G23: ='Бюджет-продаж'!G25+'Бюджет-продаж'!G48 -> 0 | H23: ='Бюджет-продаж'!H25+'Бюджет-продаж'!H48 -> 0 | I23: ='Бюджет-продаж'!I25+'Бюджет-продаж'!I48 -> 0 | ... M23: ='Бюджет-продаж'!M25+'Бюджет-продаж'!M48 -> 0 | N23: =SUM(B23,C23,D23,E23,F23,G23,H23,I23,J23,K23,L23,M23) -> 0
A24: Итого продукции, единицы | B24: =SUM(B4:B22) -> 0 | C24: =SUM(C4:C22) -> 0 | D24: =SUM(D4:D22) -> 0 | E24: =SUM(E4:E22) -> 0 | F24: =SUM(F4:F22) -> 0 | G24: =SUM(G4:G22) -> 0 | H24: =SUM(H4:H22) -> 0 | I24: =SUM(I4:I22) -> 0 | ... N24: =SUM(N4:N22) -> 0
A27: Производственная мощность
A28: Продукт 1 | N28: =SUM(B28,C28,D28,E28,F28,G28,H28,I28,J28,K28,L28,M28) -> 0
A29: Продукт 2 | N29: =SUM(B29,C29,D29,E29,F29,G29,H29,I29,J29,K29,L29,M29) -> 0
A30: Продукт 3 | N30: =SUM(B30,C30,D30,E30,F30,G30,H30,I30,J30,K30,L30,M30) -> 0
A31: Продукт 4 | N31: =SUM(B31,C31,D31,E31,F31,G31,H31,I31,J31,K31,L31,M31) -> 0
A32: Продукт 5 | N32: =SUM(B32,C32,D32,E32,F32,G32,H32,I32,J32,K32,L32,M32) -> 0
A33: Продукт.... | N33: =SUM(B33,C33,D33,E33,F33,G33,H33,I33,J33,K33,L33,M33) -> 0
N34: =SUM(B34,C34,D34,E34,F34,G34,H34,I34,J34,K34,L34,M34) -> 0
N35: =SUM(B35,C35,D35,E35,F35,G35,H35,I35,J35,K35,L35,M35) -> 0
N36: =SUM(B36,C36,D36,E36,F36,G36,H36,I36,J36,K36,L36,M36) -> 0
N37: =SUM(B37,C37,D37,E37,F37,G37,H37,I37,J37,K37,L37,M37) -> 0
N38: =SUM(B38,C38,D38,E38,F38,G38,H38,I38,J38,K38,L38,M38) -> 0
N39: =SUM(B39,C39,D39,E39,F39,G39,H39,I39,J39,K39,L39,M39) -> 0
N40: =SUM(B40,C40,D40,E40,F40,G40,H40,I40,J40,K40,L40,M40) -> 0
N41: =SUM(B41,C41,D41,E41,F41,G41,H41,I41,J41,K41,L41,M41) -> 0
N42: =SUM(B42,C42,D42,E42,F42,G42,H42,I42,J42,K42,L42,M42) -> 0
N43: =SUM(B43,C43,D43,E43,F43,G43,H43,I43,J43,K43,L43,M43) -> 0
N44: =SUM(B44,C44,D44,E44,F44,G44,H44,I44,J44,K44,L44,M44) -> 0
N45: =SUM(B45,C45,D45,E45,F45,G45,H45,I45,J45,K45,L45,M45) -> 0
... N47: =SUM(B47,C47,D47,E47,F47,G47,H47,I47,J47,K47,L47,M47) -> 0
A48: Итого производственная мощность, единицы | B48: =SUM(B28:B47) -> 0 | C48: =SUM(C28:C47) -> 0 | D48: =SUM(D28:D47) -> 0 | E48: =SUM(E28:E47) -> 0 | F48: =SUM(F28:F47) -> 0 | G48: =SUM(G28:G47) -> 0 | H48: =SUM(H28:H47) -> 0 | I48: =SUM(I28:I47) -> 0 | ... M48: =SUM(M28:M47) -> 0 | N48: =SUM(B48,C48,D48,E48,F48,G48,H48,I48,J48,K48,L48,M48) -> 0

Sheet Бюджет запасов ГП
A1: Бюджет запасов готовой продукции 2021
A2: Наименование статьи | B2: Объем запасов ГП на 01.01.2021 | C2: янв | D2: фев | E2: мар | F2: апр | G2: май | H2: июн | I2: июл | J2: авг | K2: сен | L2: окт | M2: ноя | N2: дек | O2: ГОД
A3: Объем запасов ГП, единиц
A4: Продукт 1 | C4: =B4+'Бюджет производства'!B4-'Бюджет-продаж'!B6-'Бюджет-продаж'!B29 -> 0 | D4: =C4+'Бюджет производства'!C4-'Бюджет-продаж'!C6-'Бюджет-продаж'!C29 -> 0 | E4: =D4+'Бюджет производства'!D4-'Бюджет-продаж'!D6-'Бюджет-продаж'!D29 -> 0 | F4: =E4+'Бюджет производства'!E4-'Бюджет-продаж'!E6-'Бюджет-продаж'!E29 -> 0 | G4: =F4+'Бюджет производства'!F4-'Бюджет-продаж'!F6-'Бюджет-продаж'!F29 -> 0 | H4: =G4+'Бюджет производства'!G4-'Бюджет-продаж'!G6-'Бюджет-продаж'!G29 -> 0 | I4: =H4+'Бюджет производства'!H4-'Бюджет-продаж'!H6-'Бюджет-продаж'!H29 -> 0 | J4: =I4+'Бюджет производства'!I4-'Бюджет-продаж'!I6-'Бюджет-продаж'!I29 -> 0 | ... N4: =M4+'Бюджет производства'!M4-'Бюджет-продаж'!M6-'Бюджет-продаж'!M29 -> 0
A5: Продукт 2 | C5: =B5+'Бюджет производства'!B5-'Бюджет-продаж'!B7-'Бюджет-продаж'!B30 -> 0 | D5: =C5+'Бюджет производства'!C5-'Бюджет-продаж'!C7-'Бюджет-продаж'!C30 -> 0 | E5: =D5+'Бюджет производства'!D5-'Бюджет-продаж'!D7-'Бюджет-продаж'!D30 -> 0 | F5: =E5+'Бюджет производства'!E5-'Бюджет-продаж'!E7-'Бюджет-продаж'!E30 -> 0 | G5: =F5+'Бюджет производства'!F5-'Бюджет-продаж'!F7-'Бюджет-продаж'!F30 -> 0 | H5: =G5+'Бюджет производства'!G5-'Бюджет-продаж'!G7-'Бюджет-продаж'!G30 -> 0 | I5: =H5+'Бюджет производства'!H5-'Бюджет-продаж'!H7-'Бюджет-продаж'!H30 -> 0 | J5: =I5+'Бюджет производства'!I5-'Бюджет-продаж'!I7-'Бюджет-продаж'!I30 -> 0 | ... N5: =M5+'Бюджет производства'!M5-'Бюджет-продаж'!M7-'Бюджет-продаж'!M30 -> 0
A6: Продукт 3 | C6: =B6+'Бюджет производства'!B6-'Бюджет-продаж'!B8-'Бюджет-продаж'!B31 -> 0 | D6: =C6+'Бюджет производства'!C6-'Бюджет-продаж'!C8-'Бюджет-продаж'!C31 -> 0 | E6: =D6+'Бюджет производства'!D6-'Бюджет-продаж'!D8-'Бюджет-продаж'!D31 -> 0 | F6: =E6+'Бюджет производства'!E6-'Бюджет-продаж'!E8-'Бюджет-продаж'!E31 -> 0 | G6: =F6+'Бюджет производства'!F6-'Бюджет-продаж'!F8-'Бюджет-продаж'!F31 -> 0 | H6: =G6+'Бюджет производства'!G6-'Бюджет-продаж'!G8-'Бюджет-продаж'!G31 -> 0 | I6: =H6+'Бюджет производства'!H6-'Бюджет-продаж'!H8-'Бюджет-продаж'!H31 -> 0 | J6: =I6+'Бюджет производства'!I6-'Бюджет-продаж'!I8-'Бюджет-продаж'!I31 -> 0 | ... N6: =M6+'Бюджет производства'!M6-'Бюджет-продаж'!M8-'Бюджет-продаж'!M31 -> 0
A7: Продукт 4 | C7: =B7+'Бюджет производства'!B7-'Бюджет-продаж'!B9-'Бюджет-продаж'!B32 -> 0 | D7: =C7+'Бюджет производства'!C7-'Бюджет-продаж'!C9-'Бюджет-продаж'!C32 -> 0 | E7: =D7+'Бюджет производства'!D7-'Бюджет-продаж'!D9-'Бюджет-продаж'!D32 -> 0 | F7: =E7+'Бюджет производства'!E7-'Бюджет-продаж'!E9-'Бюджет-продаж'!E32 -> 0 | G7: =F7+'Бюджет производства'!F7-'Бюджет-продаж'!F9-'Бюджет-продаж'!F32 -> 0 | H7: =G7+'Бюджет производства'!G7-'Бюджет-продаж'!G9-'Бюджет-продаж'!G32 -> 0 | I7: =H7+'Бюджет производства'!H7-'Бюджет-продаж'!H9-'Бюджет-продаж'!H32 -> 0 | J7: =I7+'Бюджет производства'!I7-'Бюджет-продаж'!I9-'Бюджет-продаж'!I32 -> 0 | ... N7: =M7+'Бюджет производства'!M7-'Бюджет-продаж'!M9-'Бюджет-продаж'!M32 -> 0
A8: Продукт 5 | C8: =B8+'Бюджет производства'!B8-'Бюджет-продаж'!B10-'Бюджет-продаж'!B33 -> 0 | D8: =C8+'Бюджет производства'!C8-'Бюджет-продаж'!C10-'Бюджет-продаж'!C33 -> 0 | E8: =D8+'Бюджет производства'!D8-'Бюджет-продаж'!D10-'Бюджет-продаж'!D33 -> 0 | F8: =E8+'Бюджет производства'!E8-'Бюджет-продаж'!E10-'Бюджет-продаж'!E33 -> 0 | G8: =F8+'Бюджет производства'!F8-'Бюджет-продаж'!F10-'Бюджет-продаж'!F33 -> 0 | H8: =G8+'Бюджет производства'!G8-'Бюджет-продаж'!G10-'Бюджет-продаж'!G33 -> 0 | I8: =H8+'Бюджет производства'!H8-'Бюджет-продаж'!H10-'Бюджет-продаж'!H33 -> 0 | J8: =I8+'Бюджет производства'!I8-'Бюджет-продаж'!I10-'Бюджет-продаж'!I33 -> 0 | ... N8: =M8+'Бюджет производства'!M8-'Бюджет-продаж'!M10-'Бюджет-продаж'!M33 -> 0
A9: Продукт.... | C9: =B9+'Бюджет производства'!B9-'Бюджет-продаж'!B11-'Бюджет-продаж'!B34 -> 0 | D9: =C9+'Бюджет производства'!C9-'Бюджет-продаж'!C11-'Бюджет-продаж'!C34 -> 0 | E9: =D9+'Бюджет производства'!D9-'Бюджет-продаж'!D11-'Бюджет-продаж'!D34 -> 0 | F9: =E9+'Бюджет производства'!E9-'Бюджет-продаж'!E11-'Бюджет-продаж'!E34 -> 0 | G9: =F9+'Бюджет производства'!F9-'Бюджет-продаж'!F11-'Бюджет-продаж'!F34 -> 0 | H9: =G9+'Бюджет производства'!G9-'Бюджет-продаж'!G11-'Бюджет-продаж'!G34 -> 0 | I9: =H9+'Бюджет производства'!H9-'Бюджет-продаж'!H11-'Бюджет-продаж'!H34 -> 0 | J9: =I9+'Бюджет производства'!I9-'Бюджет-продаж'!I11-'Бюджет-продаж'!I34 -> 0 | ... N9: =M9+'Бюджет производства'!M9-'Бюджет-продаж'!M11-'Бюджет-продаж'!M34 -> 0
C10: =B10+'Бюджет производства'!B10-'Бюджет-продаж'!B12-'Бюджет-продаж'!B35 -> 0 | D10: =C10+'Бюджет производства'!C10-'Бюджет-продаж'!C12-'Бюджет-продаж'!C35 -> 0 | E10: =D10+'Бюджет производства'!D10-'Бюджет-продаж'!D12-'Бюджет-продаж'!D35 -> 0 | F10: =E10+'Бюджет производства'!E10-'Бюджет-продаж'!E12-'Бюджет-продаж'!E35 -> 0 | G10: =F10+'Бюджет производства'!F10-'Бюджет-продаж'!F12-'Бюджет-продаж'!F35 -> 0 | H10: =G10+'Бюджет производства'!G10-'Бюджет-продаж'!G12-'Бюджет-продаж'!G35 -> 0 | I10: =H10+'Бюджет производства'!H10-'Бюджет-продаж'!H12-'Бюджет-продаж'!H35 -> 0 | J10: =I10+'Бюджет производства'!I10-'Бюджет-продаж'!I12-'Бюджет-продаж'!I35 -> 0 | ... N10: =M10+'Бюджет производства'!M10-'Бюджет-продаж'!M12-'Бюджет-продаж'!M35 -> 0
C11: =B11+'Бюджет производства'!B11-'Бюджет-продаж'!B13-'Бюджет-продаж'!B36 -> 0 | D11: =C11+'Бюджет производства'!C11-'Бюджет-продаж'!C13-'Бюджет-продаж'!C36 -> 0 | E11: =D11+'Бюджет производства'!D11-'Бюджет-продаж'!D13-'Бюджет-продаж'!D36 -> 0 | F11: =E11+'Бюджет производства'!E11-'Бюджет-продаж'!E13-'Бюджет-продаж'!E36 -> 0 | G11: =F11+'Бюджет производства'!F11-'Бюджет-продаж'!F13-'Бюджет-продаж'!F36 -> 0 | H11: =G11+'Бюджет производства'!G11-'Бюджет-продаж'!G13-'Бюджет-продаж'!G36 -> 0 | I11: =H11+'Бюджет производства'!H11-'Бюджет-продаж'!H13-'Бюджет-продаж'!H36 -> 0 | J11: =I11+'Бюджет производства'!I11-'Бюджет-продаж'!I13-'Бюджет-продаж'!I36 -> 0 | ... N11: =M11+'Бюджет производства'!M11-'Бюджет-продаж'!M13-'Бюджет-продаж'!M36 -> 0
C12: =B12+'Бюджет производства'!B12-'Бюджет-продаж'!B14-'Бюджет-продаж'!B37 -> 0 | D12: =C12+'Бюджет производства'!C12-'Бюджет-продаж'!C14-'Бюджет-продаж'!C37 -> 0 | E12: =D12+'Бюджет производства'!D12-'Бюджет-продаж'!D14-'Бюджет-продаж'!D37 -> 0 | F12: =E12+'Бюджет производства'!E12-'Бюджет-продаж'!E14-'Бюджет-продаж'!E37 -> 0 | G12: =F12+'Бюджет производства'!F12-'Бюджет-продаж'!F14-'Бюджет-продаж'!F37 -> 0 | H12: =G12+'Бюджет производства'!G12-'Бюджет-продаж'!G14-'Бюджет-продаж'!G37 -> 0 | I12: =H12+'Бюджет производства'!H12-'Бюджет-продаж'!H14-'Бюджет-продаж'!H37 -> 0 | J12: =I12+'Бюджет производства'!I12-'Бюджет-продаж'!I14-'Бюджет-продаж'!I37 -> 0 | ... N12: =M12+'Бюджет производства'!M12-'Бюджет-продаж'!M14-'Бюджет-продаж'!M37 -> 0
C13: =B13+'Бюджет производства'!B13-'Бюджет-продаж'!B15-'Бюджет-продаж'!B38 -> 0 | D13: =C13+'Бюджет производства'!C13-'Бюджет-продаж'!C15-'Бюджет-продаж'!C38 -> 0 | E13: =D13+'Бюджет производства'!D13-'Бюджет-продаж'!D15-'Бюджет-продаж'!D38 -> 0 | F13: =E13+'Бюджет производства'!E13-'Бюджет-продаж'!E15-'Бюджет-продаж'!E38 -> 0 | G13: =F13+'Бюджет производства'!F13-'Бюджет-продаж'!F15-'Бюджет-продаж'!F38 -> 0 | H13: =G13+'Бюджет производства'!G13-'Бюджет-продаж'!G15-'Бюджет-продаж'!G38 -> 0 | I13: =H13+'Бюджет производства'!H13-'Бюджет-продаж'!H15-'Бюджет-продаж'!H38 -> 0 | J13: =I13+'Бюджет производства'!I13-'Бюджет-продаж'!I15-'Бюджет-продаж'!I38 -> 0 | ... N13: =M13+'Бюджет производства'!M13-'Бюджет-продаж'!M15-'Бюджет-продаж'!M38 -> 0
C14: =B14+'Бюджет производства'!B14-'Бюджет-продаж'!B16-'Бюджет-продаж'!B39 -> 0 | D14: =C14+'Бюджет производства'!C14-'Бюджет-продаж'!C16-'Бюджет-продаж'!C39 -> 0 | E14: =D14+'Бюджет производства'!D14-'Бюджет-продаж'!D16-'Бюджет-продаж'!D39 -> 0 | F14: =E14+'Бюджет производства'!E14-'Бюджет-продаж'!E16-'Бюджет-продаж'!E39 -> 0 | G14: =F14+'Бюджет производства'!F14-'Бюджет-продаж'!F16-'Бюджет-продаж'!F39 -> 0 | H14: =G14+'Бюджет производства'!G14-'Бюджет-продаж'!G16-'Бюджет-продаж'!G39 -> 0 | I14: =H14+'Бюджет производства'!H14-'Бюджет-продаж'!H16-'Бюджет-продаж'!H39 -> 0 | J14: =I14+'Бюджет производства'!I14-'Бюджет-продаж'!I16-'Бюджет-продаж'!I39 -> 0 | ... N14: =M14+'Бюджет производства'!M14-'Бюджет-продаж'!M16-'Бюджет-продаж'!M39 -> 0
C15: =B15+'Бюджет производства'!B15-'Бюджет-продаж'!B17-'Бюджет-продаж'!B40 -> 0 | D15: =C15+'Бюджет производства'!C15-'Бюджет-продаж'!C17-'Бюджет-продаж'!C40 -> 0 | E15: =D15+'Бюджет производства'!D15-'Бюджет-продаж'!D17-'Бюджет-продаж'!D40 -> 0 | F15: =E15+'Бюджет производства'!E15-'Бюджет-продаж'!E17-'Бюджет-продаж'!E40 -> 0 | G15: =F15+'Бюджет производства'!F15-'Бюджет-продаж'!F17-'Бюджет-продаж'!F40 -> 0 | H15: =G15+'Бюджет производства'!G15-'Бюджет-продаж'!G17-'Бюджет-продаж'!G40 -> 0 | I15: =H15+'Бюджет производства'!H15-'Бюджет-продаж'!H17-'Бюджет-продаж'!H40 -> 0 | J15: =I15+'Бюджет производства'!I15-'Бюджет-продаж'!I17-'Бюджет-продаж'!I40 -> 0 | ... N15: =M15+'Бюджет производства'!M15-'Бюджет-продаж'!M17-'Бюджет-продаж'!M40 -> 0
C16: =B16+'Бюджет производства'!B16-'Бюджет-продаж'!B18-'Бюджет-продаж'!B41 -> 0 | D16: =C16+'Бюджет производства'!C16-'Бюджет-продаж'!C18-'Бюджет-продаж'!C41 -> 0 | E16: =D16+'Бюджет производства'!D16-'Бюджет-продаж'!D18-'Бюджет-продаж'!D41 -> 0 | F16: =E16+'Бюджет производства'!E16-'Бюджет-продаж'!E18-'Бюджет-продаж'!E41 -> 0 | G16: =F16+'Бюджет производства'!F16-'Бюджет-продаж'!F18-'Бюджет-продаж'!F41 -> 0 | H16: =G16+'Бюджет производства'!G16-'Бюджет-продаж'!G18-'Бюджет-продаж'!G41 -> 0 | I16: =H16+'Бюджет производства'!H16-'Бюджет-продаж'!H18-'Бюджет-продаж'!H41 -> 0 | J16: =I16+'Бюджет производства'!I16-'Бюджет-продаж'!I18-'Бюджет-продаж'!I41 -> 0 | ... N16: =M16+'Бюджет производства'!M16-'Бюджет-продаж'!M18-'Бюджет-продаж'!M41 -> 0
C17: =B17+'Бюджет производства'!B17-'Бюджет-продаж'!B19-'Бюджет-продаж'!B42 -> 0 | D17: =C17+'Бюджет производства'!C17-'Бюджет-продаж'!C19-'Бюджет-продаж'!C42 -> 0 | E17: =D17+'Бюджет производства'!D17-'Бюджет-продаж'!D19-'Бюджет-продаж'!D42 -> 0 | F17: =E17+'Бюджет производства'!E17-'Бюджет-продаж'!E19-'Бюджет-продаж'!E42 -> 0 | G17: =F17+'Бюджет производства'!F17-'Бюджет-продаж'!F19-'Бюджет-продаж'!F42 -> 0 | H17: =G17+'Бюджет производства'!G17-'Бюджет-продаж'!G19-'Бюджет-продаж'!G42 -> 0 | I17: =H17+'Бюджет производства'!H17-'Бюджет-продаж'!H19-'Бюджет-продаж'!H42 -> 0 | J17: =I17+'Бюджет производства'!I17-'Бюджет-продаж'!I19-'Бюджет-продаж'!I42 -> 0 | ... N17: =M17+'Бюджет производства'!M17-'Бюджет-продаж'!M19-'Бюджет-продаж'!M42 -> 0
C18: =B18+'Бюджет производства'!B18-'Бюджет-продаж'!B20-'Бюджет-продаж'!B43 -> 0 | D18: =C18+'Бюджет производства'!C18-'Бюджет-продаж'!C20-'Бюджет-продаж'!C43 -> 0 | E18: =D18+'Бюджет производства'!D18-'Бюджет-продаж'!D20-'Бюджет-продаж'!D43 -> 0 | F18: =E18+'Бюджет производства'!E18-'Бюджет-продаж'!E20-'Бюджет-продаж'!E43 -> 0 | G18: =F18+'Бюджет производства'!F18-'Бюджет-продаж'!F20-'Бюджет-продаж'!F43 -> 0 | H18: =G18+'Бюджет производства'!G18-'Бюджет-продаж'!G20-'Бюджет-продаж'!G43 -> 0 | I18: =H18+'Бюджет производства'!H18-'Бюджет-продаж'!H20-'Бюджет-продаж'!H43 -> 0 | J18: =I18+'Бюджет производства'!I18-'Бюджет-продаж'!I20-'Бюджет-продаж'!I43 -> 0 | ... N18: =M18+'Бюджет производства'!M18-'Бюджет-продаж'!M20-'Бюджет-продаж'!M43 -> 0
C19: =B19+'Бюджет производства'!B19-'Бюджет-продаж'!B21-'Бюджет-продаж'!B44 -> 0 | D19: =C19+'Бюджет производства'!C19-'Бюджет-продаж'!C21-'Бюджет-продаж'!C44 -> 0 | E19: =D19+'Бюджет производства'!D19-'Бюджет-продаж'!D21-'Бюджет-продаж'!D44 -> 0 | F19: =E19+'Бюджет производства'!E19-'Бюджет-продаж'!E21-'Бюджет-продаж'!E44 -> 0 | G19: =F19+'Бюджет производства'!F19-'Бюджет-продаж'!F21-'Бюджет-продаж'!F44 -> 0 | H19: =G19+'Бюджет производства'!G19-'Бюджет-продаж'!G21-'Бюджет-продаж'!G44 -> 0 | I19: =H19+'Бюджет производства'!H19-'Бюджет-продаж'!H21-'Бюджет-продаж'!H44 -> 0 | J19: =I19+'Бюджет производства'!I19-'Бюджет-продаж'!I21-'Бюджет-продаж'!I44 -> 0 | ... N19: =M19+'Бюджет производства'!M19-'Бюджет-продаж'!M21-'Бюджет-продаж'!M44 -> 0
C20: =B20+'Бюджет производства'!B20-'Бюджет-продаж'!B22-'Бюджет-продаж'!B45 -> 0 | D20: =C20+'Бюджет производства'!C20-'Бюджет-продаж'!C22-'Бюджет-продаж'!C45 -> 0 | E20: =D20+'Бюджет производства'!D20-'Бюджет-продаж'!D22-'Бюджет-продаж'!D45 -> 0 | F20: =E20+'Бюджет производства'!E20-'Бюджет-продаж'!E22-'Бюджет-продаж'!E45 -> 0 | G20: =F20+'Бюджет производства'!F20-'Бюджет-продаж'!F22-'Бюджет-продаж'!F45 -> 0 | H20: =G20+'Бюджет производства'!G20-'Бюджет-продаж'!G22-'Бюджет-продаж'!G45 -> 0 | I20: =H20+'Бюджет производства'!H20-'Бюджет-продаж'!H22-'Бюджет-продаж'!H45 -> 0 | J20: =I20+'Бюджет производства'!I20-'Бюджет-продаж'!I22-'Бюджет-продаж'!I45 -> 0 | ... N20: =M20+'Бюджет производства'!M20-'Бюджет-продаж'!M22-'Бюджет-продаж'!M45 -> 0
C21: =B21+'Бюджет производства'!B21-'Бюджет-продаж'!B23-'Бюджет-продаж'!B46 -> 0 | D21: =C21+'Бюджет производства'!C21-'Бюджет-продаж'!C23-'Бюджет-продаж'!C46 -> 0 | E21: =D21+'Бюджет производства'!D21-'Бюджет-продаж'!D23-'Бюджет-продаж'!D46 -> 0 | F21: =E21+'Бюджет производства'!E21-'Бюджет-продаж'!E23-'Бюджет-продаж'!E46 -> 0 | G21: =F21+'Бюджет производства'!F21-'Бюджет-продаж'!F23-'Бюджет-продаж'!F46 -> 0 | H21: =G21+'Бюджет производства'!G21-'Бюджет-продаж'!G23-'Бюджет-продаж'!G46 -> 0 | I21: =H21+'Бюджет производства'!H21-'Бюджет-продаж'!H23-'Бюджет-продаж'!H46 -> 0 | J21: =I21+'Бюджет производства'!I21-'Бюджет-продаж'!I23-'Бюджет-продаж'!I46 -> 0 | ... N21: =M21+'Бюджет производства'!M21-'Бюджет-продаж'!M23-'Бюджет-продаж'!M46 -> 0
... C23: =B23+'Бюджет производства'!B23-'Бюджет-продаж'!B25-'Бюджет-продаж'!B48 -> 0 | D23: =C23+'Бюджет производства'!C23-'Бюджет-продаж'!C25-'Бюджет-продаж'!C48 -> 0 | E23: =D23+'Бюджет производства'!D23-'Бюджет-продаж'!D25-'Бюджет-продаж'!D48 -> 0 | F23: =E23+'Бюджет производства'!E23-'Бюджет-продаж'!E25-'Бюджет-продаж'!E48 -> 0 | G23: =F23+'Бюджет производства'!F23-'Бюджет-продаж'!F25-'Бюджет-продаж'!F48 -> 0 | H23: =G23+'Бюджет производства'!G23-'Бюджет-продаж'!G25-'Бюджет-продаж'!G48 -> 0 | I23: =H23+'Бюджет производства'!H23-'Бюджет-продаж'!H25-'Бюджет-продаж'!H48 -> 0 | J23: =I23+'Бюджет производства'!I23-'Бюджет-продаж'!I25-'Бюджет-продаж'!I48 -> 0 | ... N23: =M23+'Бюджет производства'!M23-'Бюджет-продаж'!M25-'Бюджет-продаж'!M48 -> 0
A24: Итого продукции, единицы | C24: =SUM(C4:C22) -> 0 | D24: =SUM(D4:D22) -> 0 | E24: =SUM(E4:E22) -> 0 | F24: =SUM(F4:F22) -> 0 | G24: =SUM(G4:G22) -> 0 | H24: =SUM(H4:H22) -> 0 | I24: =SUM(I4:I22) -> 0 | J24: =SUM(J4:J22) -> 0 | ... O24: =SUM(O4:O22) -> 0
A27: Себестоимость прдукции, руб. / единица
A28: Продукт 1 | O28: =IFERROR(AVERAGE(C28,D28,E28,F28,G28,H28,I28,J28,K28,L28,M28,N28),)
A29: Продукт 2 | O29: =IFERROR(AVERAGE(C29,D29,E29,F29,G29,H29,I29,J29,K29,L29,M29,N29),)
A30: Продукт 3 | O30: =IFERROR(AVERAGE(C30,D30,E30,F30,G30,H30,I30,J30,K30,L30,M30,N30),)
A31: Продукт 4 | O31: =IFERROR(AVERAGE(C31,D31,E31,F31,G31,H31,I31,J31,K31,L31,M31,N31),)
A32: Продукт 5 | O32: =IFERROR(AVERAGE(C32,D32,E32,F32,G32,H32,I32,J32,K32,L32,M32,N32),)
A33: Продукт.... | O33: =IFERROR(AVERAGE(C33,D33,E33,F33,G33,H33,I33,J33,K33,L33,M33,N33),)
O34: =IFERROR(AVERAGE(C34,D34,E34,F34,G34,H34,I34,J34,K34,L34,M34,N34),)
O35: =IFERROR(AVERAGE(C35,D35,E35,F35,G35,H35,I35,J35,K35,L35,M35,N35),)
O36: =IFERROR(AVERAGE(C36,D36,E36,F36,G36,H36,I36,J36,K36,L36,M36,N36),)
O37: =IFERROR(AVERAGE(C37,D37,E37,F37,G37,H37,I37,J37,K37,L37,M37,N37),)
O38: =IFERROR(AVERAGE(C38,D38,E38,F38,G38,H38,I38,J38,K38,L38,M38,N38),)
O39: =IFERROR(AVERAGE(C39,D39,E39,F39,G39,H39,I39,J39,K39,L39,M39,N39),)
O40: =IFERROR(AVERAGE(C40,D40,E40,F40,G40,H40,I40,J40,K40,L40,M40,N40),)
O41: =IFERROR(AVERAGE(C41,D41,E41,F41,G41,H41,I41,J41,K41,L41,M41,N41),)
O42: =IFERROR(AVERAGE(C42,D42,E42,F42,G42,H42,I42,J42,K42,L42,M42,N42),)
O43: =IFERROR(AVERAGE(C43,D43,E43,F43,G43,H43,I43,J43,K43,L43,M43,N43),)
O44: =IFERROR(AVERAGE(C44,D44,E44,F44,G44,H44,I44,J44,K44,L44,M44,N44),)
O45: =IFERROR(AVERAGE(C45,D45,E45,F45,G45,H45,I45,J45,K45,L45,M45,N45),)
... O47: =IFERROR(AVERAGE(C47,D47,E47,F47,G47,H47,I47,J47,K47,L47,M47,N47),)
A50: Объем запасов ГП, тыс.руб.
A51: Продукт 1 | B51: =B4*B28/1000 -> 0 | C51: =C4*C28/1000 -> 0 | D51: =D4*D28/1000 -> 0 | E51: =E4*E28/1000 -> 0 | F51: =F4*F28/1000 -> 0 | G51: =G4*G28/1000 -> 0 | H51: =H4*H28/1000 -> 0 | I51: =I4*I28/1000 -> 0 | ... N51: =N4*N28/1000 -> 0
A52: Продукт 2 | B52: =B5*B29/1000 -> 0 | C52: =C5*C29/1000 -> 0 | D52: =D5*D29/1000 -> 0 | E52: =E5*E29/1000 -> 0 | F52: =F5*F29/1000 -> 0 | G52: =G5*G29/1000 -> 0 | H52: =H5*H29/1000 -> 0 | I52: =I5*I29/1000 -> 0 | ... N52: =N5*N29/1000 -> 0
A53: Продукт 3 | B53: =B6*B30/1000 -> 0 | C53: =C6*C30/1000 -> 0 | D53: =D6*D30/1000 -> 0 | E53: =E6*E30/1000 -> 0 | F53: =F6*F30/1000 -> 0 | G53: =G6*G30/1000 -> 0 | H53: =H6*H30/1000 -> 0 | I53: =I6*I30/1000 -> 0 | ... N53: =N6*N30/1000 -> 0
A54: Продукт 4 | B54: =B7*B31/1000 -> 0 | C54: =C7*C31/1000 -> 0 | D54: =D7*D31/1000 -> 0 | E54: =E7*E31/1000 -> 0 | F54: =F7*F31/1000 -> 0 | G54: =G7*G31/1000 -> 0 | H54: =H7*H31/1000 -> 0 | I54: =I7*I31/1000 -> 0 | ... N54: =N7*N31/1000 -> 0
A55: Продукт 5 | B55: =B8*B32/1000 -> 0 | C55: =C8*C32/1000 -> 0 | D55: =D8*D32/1000 -> 0 | E55: =E8*E32/1000 -> 0 | F55: =F8*F32/1000 -> 0 | G55: =G8*G32/1000 -> 0 | H55: =H8*H32/1000 -> 0 | I55: =I8*I32/1000 -> 0 | ... N55: =N8*N32/1000 -> 0
A56: Продукт.... | B56: =B9*B33/1000 -> 0 | C56: =C9*C33/1000 -> 0 | D56: =D9*D33/1000 -> 0 | E56: =E9*E33/1000 -> 0 | F56: =F9*F33/1000 -> 0 | G56: =G9*G33/1000 -> 0 | H56: =H9*H33/1000 -> 0 | I56: =I9*I33/1000 -> 0 | ... N56: =N9*N33/1000 -> 0
B57: =B10*B34/1000 -> 0 | C57: =C10*C34/1000 -> 0 | D57: =D10*D34/1000 -> 0 | E57: =E10*E34/1000 -> 0 | F57: =F10*F34/1000 -> 0 | G57: =G10*G34/1000 -> 0 | H57: =H10*H34/1000 -> 0 | I57: =I10*I34/1000 -> 0 | ... N57: =N10*N34/1000 -> 0
B58: =B11*B35/1000 -> 0 | C58: =C11*C35/1000 -> 0 | D58: =D11*D35/1000 -> 0 | E58: =E11*E35/1000 -> 0 | F58: =F11*F35/1000 -> 0 | G58: =G11*G35/1000 -> 0 | H58: =H11*H35/1000 -> 0 | I58: =I11*I35/1000 -> 0 | ... N58: =N11*N35/1000 -> 0
B59: =B12*B36/1000 -> 0 | C59: =C12*C36/1000 -> 0 | D59: =D12*D36/1000 -> 0 | E59: =E12*E36/1000 -> 0 | F59: =F12*F36/1000 -> 0 | G59: =G12*G36/1000 -> 0 | H59: =H12*H36/1000 -> 0 | I59: =I12*I36/1000 -> 0 | ... N59: =N12*N36/1000 -> 0
B60: =B13*B37/1000 -> 0 | C60: =C13*C37/1000 -> 0 | D60: =D13*D37/1000 -> 0 | E60: =E13*E37/1000 -> 0 | F60: =F13*F37/1000 -> 0 | G60: =G13*G37/1000 -> 0 | H60: =H13*H37/1000 -> 0 | I60: =I13*I37/1000 -> 0 | ... N60: =N13*N37/1000 -> 0
B61: =B14*B38/1000 -> 0 | C61: =C14*C38/1000 -> 0 | D61: =D14*D38/1000 -> 0 | E61: =E14*E38/1000 -> 0 | F61: =F14*F38/1000 -> 0 | G61: =G14*G38/1000 -> 0 | H61: =H14*H38/1000 -> 0 | I61: =I14*I38/1000 -> 0 | ... N61: =N14*N38/1000 -> 0
B62: =B15*B39/1000 -> 0 | C62: =C15*C39/1000 -> 0 | D62: =D15*D39/1000 -> 0 | E62: =E15*E39/1000 -> 0 | F62: =F15*F39/1000 -> 0 | G62: =G15*G39/1000 -> 0 | H62: =H15*H39/1000 -> 0 | I62: =I15*I39/1000 -> 0 | ... N62: =N15*N39/1000 -> 0
B63: =B16*B40/1000 -> 0 | C63: =C16*C40/1000 -> 0 | D63: =D16*D40/1000 -> 0 | E63: =E16*E40/1000 -> 0 | F63: =F16*F40/1000 -> 0 | G63: =G16*G40/1000 -> 0 | H63: =H16*H40/1000 -> 0 | I63: =I16*I40/1000 -> 0 | ... N63: =N16*N40/1000 -> 0
B64: =B17*B41/1000 -> 0 | C64: =C17*C41/1000 -> 0 | D64: =D17*D41/1000 -> 0 | E64: =E17*E41/1000 -> 0 | F64: =F17*F41/1000 -> 0 | G64: =G17*G41/1000 -> 0 | H64: =H17*H41/1000 -> 0 | I64: =I17*I41/1000 -> 0 | ... N64: =N17*N41/1000 -> 0
B65: =B18*B42/1000 -> 0 | C65: =C18*C42/1000 -> 0 | D65: =D18*D42/1000 -> 0 | E65: =E18*E42/1000 -> 0 | F65: =F18*F42/1000 -> 0 | G65: =G18*G42/1000 -> 0 | H65: =H18*H42/1000 -> 0 | I65: =I18*I42/1000 -> 0 | ... N65: =N18*N42/1000 -> 0
B66: =B19*B43/1000 -> 0 | C66: =C19*C43/1000 -> 0 | D66: =D19*D43/1000 -> 0 | E66: =E19*E43/1000 -> 0 | F66: =F19*F43/1000 -> 0 | G66: =G19*G43/1000 -> 0 | H66: =H19*H43/1000 -> 0 | I66: =I19*I43/1000 -> 0 | ... N66: =N19*N43/1000 -> 0
B67: =B20*B44/1000 -> 0 | C67: =C20*C44/1000 -> 0 | D67: =D20*D44/1000 -> 0 | E67: =E20*E44/1000 -> 0 | F67: =F20*F44/1000 -> 0 | G67: =G20*G44/1000 -> 0 | H67: =H20*H44/1000 -> 0 | I67: =I20*I44/1000 -> 0 | ... N67: =N20*N44/1000 -> 0
B68: =B21*B45/1000 -> 0 | C68: =C21*C45/1000 -> 0 | D68: =D21*D45/1000 -> 0 | E68: =E21*E45/1000 -> 0 | F68: =F21*F45/1000 -> 0 | G68: =G21*G45/1000 -> 0 | H68: =H21*H45/1000 -> 0 | I68: =I21*I45/1000 -> 0 | ... N68: =N21*N45/1000 -> 0
... B70: =B23*B47/1000 -> 0 | C70: =C23*C47/1000 -> 0 | D70: =D23*D47/1000 -> 0 | E70: =E23*E47/1000 -> 0 | F70: =F23*F47/1000 -> 0 | G70: =G23*G47/1000 -> 0 | H70: =H23*H47/1000 -> 0 | I70: =I23*I47/1000 -> 0 | ... N70: =N23*N47/1000 -> 0
A71: Итого объем запасов, тыс. руб. | B71: =SUM(B51:B70) -> 0 | C71: =SUM(C51:C70) -> 0 | D71: =SUM(D51:D70) -> 0 | E71: =SUM(E51:E70) -> 0 | F71: =SUM(F51:F70) -> 0 | G71: =SUM(G51:G70) -> 0 | H71: =SUM(H51:H70) -> 0 | I71: =SUM(I51:I70) -> 0 | ... O71: =SUM(O51:O70) -> 0

Sheet Бюджет закупок
A1: Бюджет закупок 2021 г.
D2: 31 | E2: 28 | F2: 31 | G2: 30 | H2: 31 | I2: 30 | J2: 31 | K2: 31 | L2: 30 | M2: 31 | N2: 30 | O2: 31
A3: Наименование | D3: янв | E3: фев | F3: мар | G3: апр | H3: май | I3: июн | J3: июл | K3: авг | L3: сен | M3: окт | N3: ноя | O3: дек | P3: ГОД
A4: ШАГ № 1:ВВОД ИСХОДНОЙ ИНФОРМАЦИИ
A5: Расчет потребности в материалах для производства ( в натур.выражении) | B5: ед.изм.
A6: Основные материалы
A7: ОМ 1 | D7: ='Исх.данные-произв'!$C8*'Бюджет производства'!B$4+'Бюджет производства'!B$5*'Исх.данные-произв'!$D8+'Исх.данные-произв'!$E$8*'Бюджет производства'!B$6+'Бюджет производства'!B$7*'Исх.данные-произв'!$F8+'Исх.данные-произв'!$G8*'Бюджет производства'!B$8+'Бюджет производства'!B$9*'Исх.данные-произв'!$H8 -> 0 | E7: ='Исх.данные-произв'!$C8*'Бюджет производства'!C$4+'Бюджет производства'!C$5*'Исх.данные-произв'!$D8+'Исх.данные-произв'!$E$8*'Бюджет производства'!C$6+'Бюджет производства'!C$7*'Исх.данные-произв'!$F8+'Исх.данные-произв'!$G8*'Бюджет производства'!C$8+'Бюджет производства'!C$9*'Исх.данные-произв'!$H8 -> 0 | F7: ='Исх.данные-произв'!$C8*'Бюджет производства'!D$4+'Бюджет производства'!D$5*'Исх.данные-произв'!$D8+'Исх.данные-произв'!$E$8*'Бюджет производства'!D$6+'Бюджет производства'!D$7*'Исх.данные-произв'!$F8+'Исх.данные-произв'!$G8*'Бюджет производства'!D$8+'Бюджет производства'!D$9*'Исх.данные-произв'!$H8 -> 0 | G7: ='Исх.данные-произв'!$C8*'Бюджет производства'!E$4+'Бюджет производства'!E$5*'Исх.данные-произв'!$D8+'Исх.данные-произв'!$E$8*'Бюджет производства'!E$6+'Бюджет производства'!E$7*'Исх.данные-произв'!$F8+'Исх.данные-произв'!$G8*'Бюджет производства'!E$8+'Бюджет производства'!E$9*'Исх.данные-произв'!$H8 -> 0 | H7: ='Исх.данные-произв'!$C8*'Бюджет производства'!F$4+'Бюджет производства'!F$5*'Исх.данные-произв'!$D8+'Исх.данные-произв'!$E$8*'Бюджет производства'!F$6+'Бюджет производства'!F$7*'Исх.данные-произв'!$F8+'Исх.данные-произв'!$G8*'Бюджет производства'!F$8+'Бюджет производства'!F$9*'Исх.данные-произв'!$H8 -> 0 | I7: ='Исх.данные-произв'!$C8*'Бюджет производства'!G$4+'Бюджет производства'!G$5*'Исх.данные-произв'!$D8+'Исх.данные-произв'!$E$8*'Бюджет производства'!G$6+'Бюджет производства'!G$7*'Исх.данные-произв'!$F8+'Исх.данные-произв'!$G8*'Бюджет производства'!G$8+'Бюджет производства'!G$9*'Исх.данные-произв'!$H8 -> 0 | J7: ='Исх.данные-произв'!$C8*'Бюджет производства'!H$4+'Бюджет производства'!H$5*'Исх.данные-произв'!$D8+'Исх.данные-произв'!$E$8*'Бюджет производства'!H$6+'Бюджет производства'!H$7*'Исх.данные-произв'!$F8+'Исх.данные-произв'!$G8*'Бюджет производства'!H$8+'Бюджет производства'!H$9*'Исх.данные-произв'!$H8 -> 0 | K7: ='Исх.данные-произв'!$C8*'Бюджет производства'!I$4+'Бюджет производства'!I$5*'Исх.данные-произв'!$D8+'Исх.данные-произв'!$E$8*'Бюджет производства'!I$6+'Бюджет производства'!I$7*'Исх.данные-произв'!$F8+'Исх.данные-произв'!$G8*'Бюджет производства'!I$8+'Бюджет производства'!I$9*'Исх.данные-произв'!$H8 -> 0 | ... O7: ='Исх.данные-произв'!$C8*'Бюджет производства'!M$4+'Бюджет производства'!M$5*'Исх.данные-произв'!$D8+'Исх.данные-произв'!$E$8*'Бюджет производства'!M$6+'Бюджет производства'!M$7*'Исх.данные-произв'!$F8+'Исх.данные-произв'!$G8*'Бюджет производства'!M$8+'Бюджет производства'!M$9*'Исх.данные-произв'!$H8 -> 0
A8: ОМ 2 | D8: ='Исх.данные-произв'!$C9*'Бюджет производства'!B$4+'Бюджет производства'!B$5*'Исх.данные-произв'!$D9+'Исх.данные-произв'!$E$8*'Бюджет производства'!B$6+'Бюджет производства'!B$7*'Исх.данные-произв'!$F9+'Исх.данные-произв'!$G9*'Бюджет производства'!B$8+'Бюджет производства'!B$9*'Исх.данные-произв'!$H9 -> 0 | E8: ='Исх.данные-произв'!$C9*'Бюджет производства'!C$4+'Бюджет производства'!C$5*'Исх.данные-произв'!$D9+'Исх.данные-произв'!$E$8*'Бюджет производства'!C$6+'Бюджет производства'!C$7*'Исх.данные-произв'!$F9+'Исх.данные-произв'!$G9*'Бюджет производства'!C$8+'Бюджет производства'!C$9*'Исх.данные-произв'!$H9 -> 0 | F8: ='Исх.данные-произв'!$C9*'Бюджет производства'!D$4+'Бюджет производства'!D$5*'Исх.данные-произв'!$D9+'Исх.данные-произв'!$E$8*'Бюджет производства'!D$6+'Бюджет производства'!D$7*'Исх.данные-произв'!$F9+'Исх.данные-произв'!$G9*'Бюджет производства'!D$8+'Бюджет производства'!D$9*'Исх.данные-произв'!$H9 -> 0 | G8: ='Исх.данные-произв'!$C9*'Бюджет производства'!E$4+'Бюджет производства'!E$5*'Исх.данные-произв'!$D9+'Исх.данные-произв'!$E$8*'Бюджет производства'!E$6+'Бюджет производства'!E$7*'Исх.данные-произв'!$F9+'Исх.данные-произв'!$G9*'Бюджет производства'!E$8+'Бюджет производства'!E$9*'Исх.данные-произв'!$H9 -> 0 | H8: ='Исх.данные-произв'!$C9*'Бюджет производства'!F$4+'Бюджет производства'!F$5*'Исх.данные-произв'!$D9+'Исх.данные-произв'!$E$8*'Бюджет производства'!F$6+'Бюджет производства'!F$7*'Исх.данные-произв'!$F9+'Исх.данные-произв'!$G9*'Бюджет производства'!F$8+'Бюджет производства'!F$9*'Исх.данные-произв'!$H9 -> 0 | I8: ='Исх.данные-произв'!$C9*'Бюджет производства'!G$4+'Бюджет производства'!G$5*'Исх.данные-произв'!$D9+'Исх.данные-произв'!$E$8*'Бюджет производства'!G$6+'Бюджет производства'!G$7*'Исх.данные-произв'!$F9+'Исх.данные-произв'!$G9*'Бюджет производства'!G$8+'Бюджет производства'!G$9*'Исх.данные-произв'!$H9 -> 0 | J8: ='Исх.данные-произв'!$C9*'Бюджет производства'!H$4+'Бюджет производства'!H$5*'Исх.данные-произв'!$D9+'Исх.данные-произв'!$E$8*'Бюджет производства'!H$6+'Бюджет производства'!H$7*'Исх.данные-произв'!$F9+'Исх.данные-произв'!$G9*'Бюджет производства'!H$8+'Бюджет производства'!H$9*'Исх.данные-произв'!$H9 -> 0 | K8: ='Исх.данные-произв'!$C9*'Бюджет производства'!I$4+'Бюджет производства'!I$5*'Исх.данные-произв'!$D9+'Исх.данные-произв'!$E$8*'Бюджет производства'!I$6+'Бюджет производства'!I$7*'Исх.данные-произв'!$F9+'Исх.данные-произв'!$G9*'Бюджет производства'!I$8+'Бюджет производства'!I$9*'Исх.данные-произв'!$H9 -> 0 | ... O8: ='Исх.данные-произв'!$C9*'Бюджет производства'!M$4+'Бюджет производства'!M$5*'Исх.данные-произв'!$D9+'Исх.данные-произв'!$E$8*'Бюджет производства'!M$6+'Бюджет производства'!M$7*'Исх.данные-произв'!$F9+'Исх.данные-произв'!$G9*'Бюджет производства'!M$8+'Бюджет производства'!M$9*'Исх.данные-произв'!$H9 -> 0
A9: ОМ 3 | D9: ='Исх.данные-произв'!$C10*'Бюджет производства'!B$4+'Бюджет производства'!B$5*'Исх.данные-произв'!$D10+'Исх.данные-произв'!$E$8*'Бюджет производства'!B$6+'Бюджет производства'!B$7*'Исх.данные-произв'!$F10+'Исх.данные-произв'!$G10*'Бюджет производства'!B$8+'Бюджет производства'!B$9*'Исх.данные-произв'!$H10 -> 0 | E9: ='Исх.данные-произв'!$C10*'Бюджет производства'!C$4+'Бюджет производства'!C$5*'Исх.данные-произв'!$D10+'Исх.данные-произв'!$E$8*'Бюджет производства'!C$6+'Бюджет производства'!C$7*'Исх.данные-произв'!$F10+'Исх.данные-произв'!$G10*'Бюджет производства'!C$8+'Бюджет производства'!C$9*'Исх.данные-произв'!$H10 -> 0 | F9: ='Исх.данные-произв'!$C10*'Бюджет производства'!D$4+'Бюджет производства'!D$5*'Исх.данные-произв'!$D10+'Исх.данные-произв'!$E$8*'Бюджет производства'!D$6+'Бюджет производства'!D$7*'Исх.данные-произв'!$F10+'Исх.данные-произв'!$G10*'Бюджет производства'!D$8+'Бюджет производства'!D$9*'Исх.данные-произв'!$H10 -> 0 | G9: ='Исх.данные-произв'!$C10*'Бюджет производства'!E$4+'Бюджет производства'!E$5*'Исх.данные-произв'!$D10+'Исх.данные-произв'!$E$8*'Бюджет производства'!E$6+'Бюджет производства'!E$7*'Исх.данные-произв'!$F10+'Исх.данные-произв'!$G10*'Бюджет производства'!E$8+'Бюджет производства'!E$9*'Исх.данные-произв'!$H10 -> 0 | H9: ='Исх.данные-произв'!$C10*'Бюджет производства'!F$4+'Бюджет производства'!F$5*'Исх.данные-произв'!$D10+'Исх.данные-произв'!$E$8*'Бюджет производства'!F$6+'Бюджет производства'!F$7*'Исх.данные-произв'!$F10+'Исх.данные-произв'!$G10*'Бюджет производства'!F$8+'Бюджет производства'!F$9*'Исх.данные-произв'!$H10 -> 0 | I9: ='Исх.данные-произв'!$C10*'Бюджет производства'!G$4+'Бюджет производства'!G$5*'Исх.данные-произв'!$D10+'Исх.данные-произв'!$E$8*'Бюджет производства'!G$6+'Бюджет производства'!G$7*'Исх.данные-произв'!$F10+'Исх.данные-произв'!$G10*'Бюджет производства'!G$8+'Бюджет производства'!G$9*'Исх.данные-произв'!$H10 -> 0 | J9: ='Исх.данные-произв'!$C10*'Бюджет производства'!H$4+'Бюджет производства'!H$5*'Исх.данные-произв'!$D10+'Исх.данные-произв'!$E$8*'Бюджет производства'!H$6+'Бюджет производства'!H$7*'Исх.данные-произв'!$F10+'Исх.данные-произв'!$G10*'Бюджет производства'!H$8+'Бюджет производства'!H$9*'Исх.данные-произв'!$H10 -> 0 | K9: ='Исх.данные-произв'!$C10*'Бюджет производства'!I$4+'Бюджет производства'!I$5*'Исх.данные-произв'!$D10+'Исх.данные-произв'!$E$8*'Бюджет производства'!I$6+'Бюджет производства'!I$7*'Исх.данные-произв'!$F10+'Исх.данные-произв'!$G10*'Бюджет производства'!I$8+'Бюджет производства'!I$9*'Исх.данные-произв'!$H10 -> 0 | ... O9: ='Исх.данные-произв'!$C10*'Бюджет производства'!M$4+'Бюджет производства'!M$5*'Исх.данные-произв'!$D10+'Исх.данные-произв'!$E$8*'Бюджет производства'!M$6+'Бюджет производства'!M$7*'Исх.данные-произв'!$F10+'Исх.данные-произв'!$G10*'Бюджет производства'!M$8+'Бюджет производства'!M$9*'Исх.данные-произв'!$H10 -> 0
A10: ОМ 4 | D10: ='Исх.данные-произв'!$C11*'Бюджет производства'!B$4+'Бюджет производства'!B$5*'Исх.данные-произв'!$D11+'Исх.данные-произв'!$E$8*'Бюджет производства'!B$6+'Бюджет производства'!B$7*'Исх.данные-произв'!$F11+'Исх.данные-произв'!$G11*'Бюджет производства'!B$8+'Бюджет производства'!B$9*'Исх.данные-произв'!$H11 -> 0 | E10: ='Исх.данные-произв'!$C11*'Бюджет производства'!C$4+'Бюджет производства'!C$5*'Исх.данные-произв'!$D11+'Исх.данные-произв'!$E$8*'Бюджет производства'!C$6+'Бюджет производства'!C$7*'Исх.данные-произв'!$F11+'Исх.данные-произв'!$G11*'Бюджет производства'!C$8+'Бюджет производства'!C$9*'Исх.данные-произв'!$H11 -> 0 | F10: ='Исх.данные-произв'!$C11*'Бюджет производства'!D$4+'Бюджет производства'!D$5*'Исх.данные-произв'!$D11+'Исх.данные-произв'!$E$8*'Бюджет производства'!D$6+'Бюджет производства'!D$7*'Исх.данные-произв'!$F11+'Исх.данные-произв'!$G11*'Бюджет производства'!D$8+'Бюджет производства'!D$9*'Исх.данные-произв'!$H11 -> 0 | G10: ='Исх.данные-произв'!$C11*'Бюджет производства'!E$4+'Бюджет производства'!E$5*'Исх.данные-произв'!$D11+'Исх.данные-произв'!$E$8*'Бюджет производства'!E$6+'Бюджет производства'!E$7*'Исх.данные-произв'!$F11+'Исх.данные-произв'!$G11*'Бюджет производства'!E$8+'Бюджет производства'!E$9*'Исх.данные-произв'!$H11 -> 0 | H10: ='Исх.данные-произв'!$C11*'Бюджет производства'!F$4+'Бюджет производства'!F$5*'Исх.данные-произв'!$D11+'Исх.данные-произв'!$E$8*'Бюджет производства'!F$6+'Бюджет производства'!F$7*'Исх.данные-произв'!$F11+'Исх.данные-произв'!$G11*'Бюджет производства'!F$8+'Бюджет производства'!F$9*'Исх.данные-произв'!$H11 -> 0 | I10: ='Исх.данные-произв'!$C11*'Бюджет производства'!G$4+'Бюджет производства'!G$5*'Исх.данные-произв'!$D11+'Исх.данные-произв'!$E$8*'Бюджет производства'!G$6+'Бюджет производства'!G$7*'Исх.данные-произв'!$F11+'Исх.данные-произв'!$G11*'Бюджет производства'!G$8+'Бюджет производства'!G$9*'Исх.данные-произв'!$H11 -> 0 | J10: ='Исх.данные-произв'!$C11*'Бюджет производства'!H$4+'Бюджет производства'!H$5*'Исх.данные-произв'!$D11+'Исх.данные-произв'!$E$8*'Бюджет производства'!H$6+'Бюджет производства'!H$7*'Исх.данные-произв'!$F11+'Исх.данные-произв'!$G11*'Бюджет производства'!H$8+'Бюджет производства'!H$9*'Исх.данные-произв'!$H11 -> 0 | K10: ='Исх.данные-произв'!$C11*'Бюджет производства'!I$4+'Бюджет производства'!I$5*'Исх.данные-произв'!$D11+'Исх.данные-произв'!$E$8*'Бюджет производства'!I$6+'Бюджет производства'!I$7*'Исх.данные-произв'!$F11+'Исх.данные-произв'!$G11*'Бюджет производства'!I$8+'Бюджет производства'!I$9*'Исх.данные-произв'!$H11 -> 0 | ... O10: ='Исх.данные-произв'!$C11*'Бюджет производства'!M$4+'Бюджет производства'!M$5*'Исх.данные-произв'!$D11+'Исх.данные-произв'!$E$8*'Бюджет производства'!M$6+'Бюджет производства'!M$7*'Исх.данные-произв'!$F11+'Исх.данные-произв'!$G11*'Бюджет производства'!M$8+'Бюджет производства'!M$9*'Исх.данные-произв'!$H11 -> 0
A11: ОМ 5 | D11: ='Исх.данные-произв'!$C12*'Бюджет производства'!B$4+'Бюджет производства'!B$5*'Исх.данные-произв'!$D12+'Исх.данные-произв'!$E$8*'Бюджет производства'!B$6+'Бюджет производства'!B$7*'Исх.данные-произв'!$F12+'Исх.данные-произв'!$G12*'Бюджет производства'!B$8+'Бюджет производства'!B$9*'Исх.данные-произв'!$H12 -> 0 | E11: ='Исх.данные-произв'!$C12*'Бюджет производства'!C$4+'Бюджет производства'!C$5*'Исх.данные-произв'!$D12+'Исх.данные-произв'!$E$8*'Бюджет производства'!C$6+'Бюджет производства'!C$7*'Исх.данные-произв'!$F12+'Исх.данные-произв'!$G12*'Бюджет производства'!C$8+'Бюджет производства'!C$9*'Исх.данные-произв'!$H12 -> 0 | F11: ='Исх.данные-произв'!$C12*'Бюджет производства'!D$4+'Бюджет производства'!D$5*'Исх.данные-произв'!$D12+'Исх.данные-произв'!$E$8*'Бюджет производства'!D$6+'Бюджет производства'!D$7*'Исх.данные-произв'!$F12+'Исх.данные-произв'!$G12*'Бюджет производства'!D$8+'Бюджет производства'!D$9*'Исх.данные-произв'!$H12 -> 0 | G11: ='Исх.данные-произв'!$C12*'Бюджет производства'!E$4+'Бюджет производства'!E$5*'Исх.данные-произв'!$D12+'Исх.данные-произв'!$E$8*'Бюджет производства'!E$6+'Бюджет производства'!E$7*'Исх.данные-произв'!$F12+'Исх.данные-произв'!$G12*'Бюджет производства'!E$8+'Бюджет производства'!E$9*'Исх.данные-произв'!$H12 -> 0 | H11: ='Исх.данные-произв'!$C12*'Бюджет производства'!F$4+'Бюджет производства'!F$5*'Исх.данные-произв'!$D12+'Исх.данные-произв'!$E$8*'Бюджет производства'!F$6+'Бюджет производства'!F$7*'Исх.данные-произв'!$F12+'Исх.данные-произв'!$G12*'Бюджет производства'!F$8+'Бюджет производства'!F$9*'Исх.данные-произв'!$H12 -> 0 | I11: ='Исх.данные-произв'!$C12*'Бюджет производства'!G$4+'Бюджет производства'!G$5*'Исх.данные-произв'!$D12+'Исх.данные-произв'!$E$8*'Бюджет производства'!G$6+'Бюджет производства'!G$7*'Исх.данные-произв'!$F12+'Исх.данные-произв'!$G12*'Бюджет производства'!G$8+'Бюджет производства'!G$9*'Исх.данные-произв'!$H12 -> 0 | J11: ='Исх.данные-произв'!$C12*'Бюджет производства'!H$4+'Бюджет производства'!H$5*'Исх.данные-произв'!$D12+'Исх.данные-произв'!$E$8*'Бюджет производства'!H$6+'Бюджет производства'!H$7*'Исх.данные-произв'!$F12+'Исх.данные-произв'!$G12*'Бюджет производства'!H$8+'Бюджет производства'!H$9*'Исх.данные-произв'!$H12 -> 0 | K11: ='Исх.данные-произв'!$C12*'Бюджет производства'!I$4+'Бюджет производства'!I$5*'Исх.данные-произв'!$D12+'Исх.данные-произв'!$E$8*'Бюджет производства'!I$6+'Бюджет производства'!I$7*'Исх.данные-произв'!$F12+'Исх.данные-произв'!$G12*'Бюджет производства'!I$8+'Бюджет производства'!I$9*'Исх.данные-произв'!$H12 -> 0 | ... O11: ='Исх.данные-произв'!$C12*'Бюджет производства'!M$4+'Бюджет производства'!M$5*'Исх.данные-произв'!$D12+'Исх.данные-произв'!$E$8*'Бюджет производства'!M$6+'Бюджет производства'!M$7*'Исх.данные-произв'!$F12+'Исх.данные-произв'!$G12*'Бюджет производства'!M$8+'Бюджет производства'!M$9*'Исх.данные-произв'!$H12 -> 0
A12: ОМ 6 | D12: ='Исх.данные-произв'!$C13*'Бюджет производства'!B$4+'Бюджет производства'!B$5*'Исх.данные-произв'!$D13+'Исх.данные-произв'!$E$8*'Бюджет производства'!B$6+'Бюджет производства'!B$7*'Исх.данные-произв'!$F13+'Исх.данные-произв'!$G13*'Бюджет производства'!B$8+'Бюджет производства'!B$9*'Исх.данные-произв'!$H13 -> 0 | E12: ='Исх.данные-произв'!$C13*'Бюджет производства'!C$4+'Бюджет производства'!C$5*'Исх.данные-произв'!$D13+'Исх.данные-произв'!$E$8*'Бюджет производства'!C$6+'Бюджет производства'!C$7*'Исх.данные-произв'!$F13+'Исх.данные-произв'!$G13*'Бюджет производства'!C$8+'Бюджет производства'!C$9*'Исх.данные-произв'!$H13 -> 0 | F12: ='Исх.данные-произв'!$C13*'Бюджет производства'!D$4+'Бюджет производства'!D$5*'Исх.данные-произв'!$D13+'Исх.данные-произв'!$E$8*'Бюджет производства'!D$6+'Бюджет производства'!D$7*'Исх.данные-произв'!$F13+'Исх.данные-произв'!$G13*'Бюджет производства'!D$8+'Бюджет производства'!D$9*'Исх.данные-произв'!$H13 -> 0 | G12: ='Исх.данные-произв'!$C13*'Бюджет производства'!E$4+'Бюджет производства'!E$5*'Исх.данные-произв'!$D13+'Исх.данные-произв'!$E$8*'Бюджет производства'!E$6+'Бюджет производства'!E$7*'Исх.данные-произв'!$F13+'Исх.данные-произв'!$G13*'Бюджет производства'!E$8+'Бюджет производства'!E$9*'Исх.данные-произв'!$H13 -> 0 | H12: ='Исх.данные-произв'!$C13*'Бюджет производства'!F$4+'Бюджет производства'!F$5*'Исх.данные-произв'!$D13+'Исх.данные-произв'!$E$8*'Бюджет производства'!F$6+'Бюджет производства'!F$7*'Исх.данные-произв'!$F13+'Исх.данные-произв'!$G13*'Бюджет производства'!F$8+'Бюджет производства'!F$9*'Исх.данные-произв'!$H13 -> 0 | I12: ='Исх.данные-произв'!$C13*'Бюджет производства'!G$4+'Бюджет производства'!G$5*'Исх.данные-произв'!$D13+'Исх.данные-произв'!$E$8*'Бюджет производства'!G$6+'Бюджет производства'!G$7*'Исх.данные-произв'!$F13+'Исх.данные-произв'!$G13*'Бюджет производства'!G$8+'Бюджет производства'!G$9*'Исх.данные-произв'!$H13 -> 0 | J12: ='Исх.данные-произв'!$C13*'Бюджет производства'!H$4+'Бюджет производства'!H$5*'Исх.данные-произв'!$D13+'Исх.данные-произв'!$E$8*'Бюджет производства'!H$6+'Бюджет производства'!H$7*'Исх.данные-произв'!$F13+'Исх.данные-произв'!$G13*'Бюджет производства'!H$8+'Бюджет производства'!H$9*'Исх.данные-произв'!$H13 -> 0 | K12: ='Исх.данные-произв'!$C13*'Бюджет производства'!I$4+'Бюджет производства'!I$5*'Исх.данные-произв'!$D13+'Исх.данные-произв'!$E$8*'Бюджет производства'!I$6+'Бюджет производства'!I$7*'Исх.данные-произв'!$F13+'Исх.данные-произв'!$G13*'Бюджет производства'!I$8+'Бюджет производства'!I$9*'Исх.данные-произв'!$H13 -> 0 | ... O12: ='Исх.данные-произв'!$C13*'Бюджет производства'!M$4+'Бюджет производства'!M$5*'Исх.данные-произв'!$D13+'Исх.данные-произв'!$E$8*'Бюджет производства'!M$6+'Бюджет производства'!M$7*'Исх.данные-произв'!$F13+'Исх.данные-произв'!$G13*'Бюджет производства'!M$8+'Бюджет производства'!M$9*'Исх.данные-произв'!$H13 -> 0
A13: ОМ 7 | D13: ='Исх.данные-произв'!$C14*'Бюджет производства'!B$4+'Бюджет производства'!B$5*'Исх.данные-произв'!$D14+'Исх.данные-произв'!$E$8*'Бюджет производства'!B$6+'Бюджет производства'!B$7*'Исх.данные-произв'!$F14+'Исх.данные-произв'!$G14*'Бюджет производства'!B$8+'Бюджет производства'!B$9*'Исх.данные-произв'!$H14 -> 0 | E13: ='Исх.данные-произв'!$C14*'Бюджет производства'!C$4+'Бюджет производства'!C$5*'Исх.данные-произв'!$D14+'Исх.данные-произв'!$E$8*'Бюджет производства'!C$6+'Бюджет производства'!C$7*'Исх.данные-произв'!$F14+'Исх.данные-произв'!$G14*'Бюджет производства'!C$8+'Бюджет производства'!C$9*'Исх.данные-произв'!$H14 -> 0 | F13: ='Исх.данные-произв'!$C14*'Бюджет производства'!D$4+'Бюджет производства'!D$5*'Исх.данные-произв'!$D14+'Исх.данные-произв'!$E$8*'Бюджет производства'!D$6+'Бюджет производства'!D$7*'Исх.данные-произв'!$F14+'Исх.данные-произв'!$G14*'Бюджет производства'!D$8+'Бюджет производства'!D$9*'Исх.данные-произв'!$H14 -> 0 | G13: ='Исх.данные-произв'!$C14*'Бюджет производства'!E$4+'Бюджет производства'!E$5*'Исх.данные-произв'!$D14+'Исх.данные-произв'!$E$8*'Бюджет производства'!E$6+'Бюджет производства'!E$7*'Исх.данные-произв'!$F14+'Исх.данные-произв'!$G14*'Бюджет производства'!E$8+'Бюджет производства'!E$9*'Исх.данные-произв'!$H14 -> 0 | H13: ='Исх.данные-произв'!$C14*'Бюджет производства'!F$4+'Бюджет производства'!F$5*'Исх.данные-произв'!$D14+'Исх.данные-произв'!$E$8*'Бюджет производства'!F$6+'Бюджет производства'!F$7*'Исх.данные-произв'!$F14+'Исх.данные-произв'!$G14*'Бюджет производства'!F$8+'Бюджет производства'!F$9*'Исх.данные-произв'!$H14 -> 0 | I13: ='Исх.данные-произв'!$C14*'Бюджет производства'!G$4+'Бюджет производства'!G$5*'Исх.данные-произв'!$D14+'Исх.данные-произв'!$E$8*'Бюджет производства'!G$6+'Бюджет производства'!G$7*'Исх.данные-произв'!$F14+'Исх.данные-произв'!$G14*'Бюджет производства'!G$8+'Бюджет производства'!G$9*'Исх.данные-произв'!$H14 -> 0 | J13: ='Исх.данные-произв'!$C14*'Бюджет производства'!H$4+'Бюджет производства'!H$5*'Исх.данные-произв'!$D14+'Исх.данные-произв'!$E$8*'Бюджет производства'!H$6+'Бюджет производства'!H$7*'Исх.данные-произв'!$F14+'Исх.данные-произв'!$G14*'Бюджет производства'!H$8+'Бюджет производства'!H$9*'Исх.данные-произв'!$H14 -> 0 | K13: ='Исх.данные-произв'!$C14*'Бюджет производства'!I$4+'Бюджет производства'!I$5*'Исх.данные-произв'!$D14+'Исх.данные-произв'!$E$8*'Бюджет производства'!I$6+'Бюджет производства'!I$7*'Исх.данные-произв'!$F14+'Исх.данные-произв'!$G14*'Бюджет производства'!I$8+'Бюджет производства'!I$9*'Исх.данные-произв'!$H14 -> 0 | ... O13: ='Исх.данные-произв'!$C14*'Бюджет производства'!M$4+'Бюджет производства'!M$5*'Исх.данные-произв'!$D14+'Исх.данные-произв'!$E$8*'Бюджет производства'!M$6+'Бюджет производства'!M$7*'Исх.данные-произв'!$F14+'Исх.данные-произв'!$G14*'Бюджет производства'!M$8+'Бюджет производства'!M$9*'Исх.данные-произв'!$H14 -> 0
A14: ОМ 8 | D14: ='Исх.данные-произв'!$C15*'Бюджет производства'!B$4+'Бюджет производства'!B$5*'Исх.данные-произв'!$D15+'Исх.данные-произв'!$E$8*'Бюджет производства'!B$6+'Бюджет производства'!B$7*'Исх.данные-произв'!$F15+'Исх.данные-произв'!$G15*'Бюджет производства'!B$8+'Бюджет производства'!B$9*'Исх.данные-произв'!$H15 -> 0 | E14: ='Исх.данные-произв'!$C15*'Бюджет производства'!C$4+'Бюджет производства'!C$5*'Исх.данные-произв'!$D15+'Исх.данные-произв'!$E$8*'Бюджет производства'!C$6+'Бюджет производства'!C$7*'Исх.данные-произв'!$F15+'Исх.данные-произв'!$G15*'Бюджет производства'!C$8+'Бюджет производства'!C$9*'Исх.данные-произв'!$H15 -> 0 | F14: ='Исх.данные-произв'!$C15*'Бюджет производства'!D$4+'Бюджет производства'!D$5*'Исх.данные-произв'!$D15+'Исх.данные-произв'!$E$8*'Бюджет производства'!D$6+'Бюджет производства'!D$7*'Исх.данные-произв'!$F15+'Исх.данные-произв'!$G15*'Бюджет производства'!D$8+'Бюджет производства'!D$9*'Исх.данные-произв'!$H15 -> 0 | G14: ='Исх.данные-произв'!$C15*'Бюджет производства'!E$4+'Бюджет производства'!E$5*'Исх.данные-произв'!$D15+'Исх.данные-произв'!$E$8*'Бюджет производства'!E$6+'Бюджет производства'!E$7*'Исх.данные-произв'!$F15+'Исх.данные-произв'!$G15*'Бюджет производства'!E$8+'Бюджет производства'!E$9*'Исх.данные-произв'!$H15 -> 0 | H14: ='Исх.данные-произв'!$C15*'Бюджет производства'!F$4+'Бюджет производства'!F$5*'Исх.данные-произв'!$D15+'Исх.данные-произв'!$E$8*'Бюджет производства'!F$6+'Бюджет производства'!F$7*'Исх.данные-произв'!$F15+'Исх.данные-произв'!$G15*'Бюджет производства'!F$8+'Бюджет производства'!F$9*'Исх.данные-произв'!$H15 -> 0 | I14: ='Исх.данные-произв'!$C15*'Бюджет производства'!G$4+'Бюджет производства'!G$5*'Исх.данные-произв'!$D15+'Исх.данные-произв'!$E$8*'Бюджет производства'!G$6+'Бюджет производства'!G$7*'Исх.данные-произв'!$F15+'Исх.данные-произв'!$G15*'Бюджет производства'!G$8+'Бюджет производства'!G$9*'Исх.данные-произв'!$H15 -> 0 | J14: ='Исх.данные-произв'!$C15*'Бюджет производства'!H$4+'Бюджет производства'!H$5*'Исх.данные-произв'!$D15+'Исх.данные-произв'!$E$8*'Бюджет производства'!H$6+'Бюджет производства'!H$7*'Исх.данные-произв'!$F15+'Исх.данные-произв'!$G15*'Бюджет производства'!H$8+'Бюджет производства'!H$9*'Исх.данные-произв'!$H15 -> 0 | K14: ='Исх.данные-произв'!$C15*'Бюджет производства'!I$4+'Бюджет производства'!I$5*'Исх.данные-произв'!$D15+'Исх.данные-произв'!$E$8*'Бюджет производства'!I$6+'Бюджет производства'!I$7*'Исх.данные-произв'!$F15+'Исх.данные-произв'!$G15*'Бюджет производства'!I$8+'Бюджет производства'!I$9*'Исх.данные-произв'!$H15 -> 0 | ... O14: ='Исх.данные-произв'!$C15*'Бюджет производства'!M$4+'Бюджет производства'!M$5*'Исх.данные-произв'!$D15+'Исх.данные-произв'!$E$8*'Бюджет производства'!M$6+'Бюджет производства'!M$7*'Исх.данные-произв'!$F15+'Исх.данные-произв'!$G15*'Бюджет производства'!M$8+'Бюджет производства'!M$9*'Исх.данные-произв'!$H15 -> 0
A15: ОМ 9 | D15: ='Исх.данные-произв'!$C16*'Бюджет производства'!B$4+'Бюджет производства'!B$5*'Исх.данные-произв'!$D16+'Исх.данные-произв'!$E$8*'Бюджет производства'!B$6+'Бюджет производства'!B$7*'Исх.данные-произв'!$F16+'Исх.данные-произв'!$G16*'Бюджет производства'!B$8+'Бюджет производства'!B$9*'Исх.данные-произв'!$H16 -> 0 | E15: ='Исх.данные-произв'!$C16*'Бюджет производства'!C$4+'Бюджет производства'!C$5*'Исх.данные-произв'!$D16+'Исх.данные-произв'!$E$8*'Бюджет производства'!C$6+'Бюджет производства'!C$7*'Исх.данные-произв'!$F16+'Исх.данные-произв'!$G16*'Бюджет производства'!C$8+'Бюджет производства'!C$9*'Исх.данные-произв'!$H16 -> 0 | F15: ='Исх.данные-произв'!$C16*'Бюджет производства'!D$4+'Бюджет производства'!D$5*'Исх.данные-произв'!$D16+'Исх.данные-произв'!$E$8*'Бюджет производства'!D$6+'Бюджет производства'!D$7*'Исх.данные-произв'!$F16+'Исх.данные-произв'!$G16*'Бюджет производства'!D$8+'Бюджет производства'!D$9*'Исх.данные-произв'!$H16 -> 0 | G15: ='Исх.данные-произв'!$C16*'Бюджет производства'!E$4+'Бюджет производства'!E$5*'Исх.данные-произв'!$D16+'Исх.данные-произв'!$E$8*'Бюджет производства'!E$6+'Бюджет производства'!E$7*'Исх.данные-произв'!$F16+'Исх.данные-произв'!$G16*'Бюджет производства'!E$8+'Бюджет производства'!E$9*'Исх.данные-произв'!$H16 -> 0 | H15: ='Исх.данные-произв'!$C16*'Бюджет производства'!F$4+'Бюджет производства'!F$5*'Исх.данные-произв'!$D16+'Исх.данные-произв'!$E$8*'Бюджет производства'!F$6+'Бюджет производства'!F$7*'Исх.данные-произв'!$F16+'Исх.данные-произв'!$G16*'Бюджет производства'!F$8+'Бюджет производства'!F$9*'Исх.данные-произв'!$H16 -> 0 | I15: ='Исх.данные-произв'!$C16*'Бюджет производства'!G$4+'Бюджет производства'!G$5*'Исх.данные-произв'!$D16+'Исх.данные-произв'!$E$8*'Бюджет производства'!G$6+'Бюджет производства'!G$7*'Исх.данные-произв'!$F16+'Исх.данные-произв'!$G16*'Бюджет производства'!G$8+'Бюджет производства'!G$9*'Исх.данные-произв'!$H16 -> 0 | J15: ='Исх.данные-произв'!$C16*'Бюджет производства'!H$4+'Бюджет производства'!H$5*'Исх.данные-произв'!$D16+'Исх.данные-произв'!$E$8*'Бюджет производства'!H$6+'Бюджет производства'!H$7*'Исх.данные-произв'!$F16+'Исх.данные-произв'!$G16*'Бюджет производства'!H$8+'Бюджет производства'!H$9*'Исх.данные-произв'!$H16 -> 0 | K15: ='Исх.данные-произв'!$C16*'Бюджет производства'!I$4+'Бюджет производства'!I$5*'Исх.данные-произв'!$D16+'Исх.данные-произв'!$E$8*'Бюджет производства'!I$6+'Бюджет производства'!I$7*'Исх.данные-произв'!$F16+'Исх.данные-произв'!$G16*'Бюджет производства'!I$8+'Бюджет производства'!I$9*'Исх.данные-произв'!$H16 -> 0 | ... O15: ='Исх.данные-произв'!$C16*'Бюджет производства'!M$4+'Бюджет производства'!M$5*'Исх.данные-произв'!$D16+'Исх.данные-произв'!$E$8*'Бюджет производства'!M$6+'Бюджет производства'!M$7*'Исх.данные-произв'!$F16+'Исх.данные-произв'!$G16*'Бюджет производства'!M$8+'Бюджет производства'!M$9*'Исх.данные-произв'!$H16 -> 0
A16: ОМ 10 | D16: ='Исх.данные-произв'!$C17*'Бюджет производства'!B$4+'Бюджет производства'!B$5*'Исх.данные-произв'!$D17+'Исх.данные-произв'!$E$8*'Бюджет производства'!B$6+'Бюджет производства'!B$7*'Исх.данные-произв'!$F17+'Исх.данные-произв'!$G17*'Бюджет производства'!B$8+'Бюджет производства'!B$9*'Исх.данные-произв'!$H17 -> 0 | E16: ='Исх.данные-произв'!$C17*'Бюджет производства'!C$4+'Бюджет производства'!C$5*'Исх.данные-произв'!$D17+'Исх.данные-произв'!$E$8*'Бюджет производства'!C$6+'Бюджет производства'!C$7*'Исх.данные-произв'!$F17+'Исх.данные-произв'!$G17*'Бюджет производства'!C$8+'Бюджет производства'!C$9*'Исх.данные-произв'!$H17 -> 0 | F16: ='Исх.данные-произв'!$C17*'Бюджет производства'!D$4+'Бюджет производства'!D$5*'Исх.данные-произв'!$D17+'Исх.данные-произв'!$E$8*'Бюджет производства'!D$6+'Бюджет производства'!D$7*'Исх.данные-произв'!$F17+'Исх.данные-произв'!$G17*'Бюджет производства'!D$8+'Бюджет производства'!D$9*'Исх.данные-произв'!$H17 -> 0 | G16: ='Исх.данные-произв'!$C17*'Бюджет производства'!E$4+'Бюджет производства'!E$5*'Исх.данные-произв'!$D17+'Исх.данные-произв'!$E$8*'Бюджет производства'!E$6+'Бюджет производства'!E$7*'Исх.данные-произв'!$F17+'Исх.данные-произв'!$G17*'Бюджет производства'!E$8+'Бюджет производства'!E$9*'Исх.данные-произв'!$H17 -> 0 | H16: ='Исх.данные-произв'!$C17*'Бюджет производства'!F$4+'Бюджет производства'!F$5*'Исх.данные-произв'!$D17+'Исх.данные-произв'!$E$8*'Бюджет производства'!F$6+'Бюджет производства'!F$7*'Исх.данные-произв'!$F17+'Исх.данные-произв'!$G17*'Бюджет производства'!F$8+'Бюджет производства'!F$9*'Исх.данные-произв'!$H17 -> 0 | I16: ='Исх.данные-произв'!$C17*'Бюджет производства'!G$4+'Бюджет производства'!G$5*'Исх.данные-произв'!$D17+'Исх.данные-произв'!$E$8*'Бюджет производства'!G$6+'Бюджет производства'!G$7*'Исх.данные-произв'!$F17+'Исх.данные-произв'!$G17*'Бюджет производства'!G$8+'Бюджет производства'!G$9*'Исх.данные-произв'!$H17 -> 0 | J16: ='Исх.данные-произв'!$C17*'Бюджет производства'!H$4+'Бюджет производства'!H$5*'Исх.данные-произв'!$D17+'Исх.данные-произв'!$E$8*'Бюджет производства'!H$6+'Бюджет производства'!H$7*'Исх.данные-произв'!$F17+'Исх.данные-произв'!$G17*'Бюджет производства'!H$8+'Бюджет производства'!H$9*'Исх.данные-произв'!$H17 -> 0 | K16: ='Исх.данные-произв'!$C17*'Бюджет производства'!I$4+'Бюджет производства'!I$5*'Исх.данные-произв'!$D17+'Исх.данные-произв'!$E$8*'Бюджет производства'!I$6+'Бюджет производства'!I$7*'Исх.данные-произв'!$F17+'Исх.данные-произв'!$G17*'Бюджет производства'!I$8+'Бюджет производства'!I$9*'Исх.данные-произв'!$H17 -> 0 | ... O16: ='Исх.данные-произв'!$C17*'Бюджет производства'!M$4+'Бюджет производства'!M$5*'Исх.данные-произв'!$D17+'Исх.данные-произв'!$E$8*'Бюджет производства'!M$6+'Бюджет производства'!M$7*'Исх.данные-произв'!$F17+'Исх.данные-произв'!$G17*'Бюджет производства'!M$8+'Бюджет производства'!M$9*'Исх.данные-произв'!$H17 -> 0
A17: ОМ 11 | D17: ='Исх.данные-произв'!$C18*'Бюджет производства'!B$4+'Бюджет производства'!B$5*'Исх.данные-произв'!$D18+'Исх.данные-произв'!$E$8*'Бюджет производства'!B$6+'Бюджет производства'!B$7*'Исх.данные-произв'!$F18+'Исх.данные-произв'!$G18*'Бюджет производства'!B$8+'Бюджет производства'!B$9*'Исх.данные-произв'!$H18 -> 0 | E17: ='Исх.данные-произв'!$C18*'Бюджет производства'!C$4+'Бюджет производства'!C$5*'Исх.данные-произв'!$D18+'Исх.данные-произв'!$E$8*'Бюджет производства'!C$6+'Бюджет производства'!C$7*'Исх.данные-произв'!$F18+'Исх.данные-произв'!$G18*'Бюджет производства'!C$8+'Бюджет производства'!C$9*'Исх.данные-произв'!$H18 -> 0 | F17: ='Исх.данные-произв'!$C18*'Бюджет производства'!D$4+'Бюджет производства'!D$5*'Исх.данные-произв'!$D18+'Исх.данные-произв'!$E$8*'Бюджет производства'!D$6+'Бюджет производства'!D$7*'Исх.данные-произв'!$F18+'Исх.данные-произв'!$G18*'Бюджет производства'!D$8+'Бюджет производства'!D$9*'Исх.данные-произв'!$H18 -> 0 | G17: ='Исх.данные-произв'!$C18*'Бюджет производства'!E$4+'Бюджет производства'!E$5*'Исх.данные-произв'!$D18+'Исх.данные-произв'!$E$8*'Бюджет производства'!E$6+'Бюджет производства'!E$7*'Исх.данные-произв'!$F18+'Исх.данные-произв'!$G18*'Бюджет производства'!E$8+'Бюджет производства'!E$9*'Исх.данные-произв'!$H18 -> 0 | H17: ='Исх.данные-произв'!$C18*'Бюджет производства'!F$4+'Бюджет производства'!F$5*'Исх.данные-произв'!$D18+'Исх.данные-произв'!$E$8*'Бюджет производства'!F$6+'Бюджет производства'!F$7*'Исх.данные-произв'!$F18+'Исх.данные-произв'!$G18*'Бюджет производства'!F$8+'Бюджет производства'!F$9*'Исх.данные-произв'!$H18 -> 0 | I17: ='Исх.данные-произв'!$C18*'Бюджет производства'!G$4+'Бюджет производства'!G$5*'Исх.данные-произв'!$D18+'Исх.данные-произв'!$E$8*'Бюджет производства'!G$6+'Бюджет производства'!G$7*'Исх.данные-произв'!$F18+'Исх.данные-произв'!$G18*'Бюджет производства'!G$8+'Бюджет производства'!G$9*'Исх.данные-произв'!$H18 -> 0 | J17: ='Исх.данные-произв'!$C18*'Бюджет производства'!H$4+'Бюджет производства'!H$5*'Исх.данные-произв'!$D18+'Исх.данные-произв'!$E$8*'Бюджет производства'!H$6+'Бюджет производства'!H$7*'Исх.данные-произв'!$F18+'Исх.данные-произв'!$G18*'Бюджет производства'!H$8+'Бюджет производства'!H$9*'Исх.данные-произв'!$H18 -> 0 | K17: ='Исх.данные-произв'!$C18*'Бюджет производства'!I$4+'Бюджет производства'!I$5*'Исх.данные-произв'!$D18+'Исх.данные-произв'!$E$8*'Бюджет производства'!I$6+'Бюджет производства'!I$7*'Исх.данные-произв'!$F18+'Исх.данные-произв'!$G18*'Бюджет производства'!I$8+'Бюджет производства'!I$9*'Исх.данные-произв'!$H18 -> 0 | ... O17: ='Исх.данные-произв'!$C18*'Бюджет производства'!M$4+'Бюджет производства'!M$5*'Исх.данные-произв'!$D18+'Исх.данные-произв'!$E$8*'Бюджет производства'!M$6+'Бюджет производства'!M$7*'Исх.данные-произв'!$F18+'Исх.данные-произв'!$G18*'Бюджет производства'!M$8+'Бюджет производства'!M$9*'Исх.данные-произв'!$H18 -> 0
A18: ОМ 12 | D18: ='Исх.данные-произв'!$C19*'Бюджет производства'!B$4+'Бюджет производства'!B$5*'Исх.данные-произв'!$D19+'Исх.данные-произв'!$E$8*'Бюджет производства'!B$6+'Бюджет производства'!B$7*'Исх.данные-произв'!$F19+'Исх.данные-произв'!$G19*'Бюджет производства'!B$8+'Бюджет производства'!B$9*'Исх.данные-произв'!$H19 -> 0 | E18: ='Исх.данные-произв'!$C19*'Бюджет производства'!C$4+'Бюджет производства'!C$5*'Исх.данные-произв'!$D19+'Исх.данные-произв'!$E$8*'Бюджет производства'!C$6+'Бюджет производства'!C$7*'Исх.данные-произв'!$F19+'Исх.данные-произв'!$G19*'Бюджет производства'!C$8+'Бюджет производства'!C$9*'Исх.данные-произв'!$H19 -> 0 | F18: ='Исх.данные-произв'!$C19*'Бюджет производства'!D$4+'Бюджет производства'!D$5*'Исх.данные-произв'!$D19+'Исх.данные-произв'!$E$8*'Бюджет производства'!D$6+'Бюджет производства'!D$7*'Исх.данные-произв'!$F19+'Исх.данные-произв'!$G19*'Бюджет производства'!D$8+'Бюджет производства'!D$9*'Исх.данные-произв'!$H19 -> 0 | G18: ='Исх.данные-произв'!$C19*'Бюджет производства'!E$4+'Бюджет производства'!E$5*'Исх.данные-произв'!$D19+'Исх.данные-произв'!$E$8*'Бюджет производства'!E$6+'Бюджет производства'!E$7*'Исх.данные-произв'!$F19+'Исх.данные-произв'!$G19*'Бюджет производства'!E$8+'Бюджет производства'!E$9*'Исх.данные-произв'!$H19 -> 0 | H18: ='Исх.данные-произв'!$C19*'Бюджет производства'!F$4+'Бюджет производства'!F$5*'Исх.данные-произв'!$D19+'Исх.данные-произв'!$E$8*'Бюджет производства'!F$6+'Бюджет производства'!F$7*'Исх.данные-произв'!$F19+'Исх.данные-произв'!$G19*'Бюджет производства'!F$8+'Бюджет производства'!F$9*'Исх.данные-произв'!$H19 -> 0 | I18: ='Исх.данные-произв'!$C19*'Бюджет производства'!G$4+'Бюджет производства'!G$5*'Исх.данные-произв'!$D19+'Исх.данные-произв'!$E$8*'Бюджет производства'!G$6+'Бюджет производства'!G$7*'Исх.данные-произв'!$F19+'Исх.данные-произв'!$G19*'Бюджет производства'!G$8+'Бюджет производства'!G$9*'Исх.данные-произв'!$H19 -> 0 | J18: ='Исх.данные-произв'!$C19*'Бюджет производства'!H$4+'Бюджет производства'!H$5*'Исх.данные-произв'!$D19+'Исх.данные-произв'!$E$8*'Бюджет производства'!H$6+'Бюджет производства'!H$7*'Исх.данные-произв'!$F19+'Исх.данные-произв'!$G19*'Бюджет производства'!H$8+'Бюджет производства'!H$9*'Исх.данные-произв'!$H19 -> 0 | K18: ='Исх.данные-произв'!$C19*'Бюджет производства'!I$4+'Бюджет производства'!I$5*'Исх.данные-произв'!$D19+'Исх.данные-произв'!$E$8*'Бюджет производства'!I$6+'Бюджет производства'!I$7*'Исх.данные-произв'!$F19+'Исх.данные-произв'!$G19*'Бюджет производства'!I$8+'Бюджет производства'!I$9*'Исх.данные-произв'!$H19 -> 0 | ... O18: ='Исх.данные-произв'!$C19*'Бюджет производства'!M$4+'Бюджет производства'!M$5*'Исх.данные-произв'!$D19+'Исх.данные-произв'!$E$8*'Бюджет производства'!M$6+'Бюджет производства'!M$7*'Исх.данные-произв'!$F19+'Исх.данные-произв'!$G19*'Бюджет производства'!M$8+'Бюджет производства'!M$9*'Исх.данные-произв'!$H19 -> 0
... A21: ОМ 15 | D21: ='Исх.данные-произв'!$C22*'Бюджет производства'!B$4+'Бюджет производства'!B$5*'Исх.данные-произв'!$D22+'Исх.данные-произв'!$E$8*'Бюджет производства'!B$6+'Бюджет производства'!B$7*'Исх.данные-произв'!$F22+'Исх.данные-произв'!$G22*'Бюджет производства'!B$8+'Бюджет производства'!B$9*'Исх.данные-произв'!$H22 -> 0 | E21: ='Исх.данные-произв'!$C22*'Бюджет производства'!C$4+'Бюджет производства'!C$5*'Исх.данные-произв'!$D22+'Исх.данные-произв'!$E$8*'Бюджет производства'!C$6+'Бюджет производства'!C$7*'Исх.данные-произв'!$F22+'Исх.данные-произв'!$G22*'Бюджет производства'!C$8+'Бюджет производства'!C$9*'Исх.данные-произв'!$H22 -> 0 | F21: ='Исх.данные-произв'!$C22*'Бюджет производства'!D$4+'Бюджет производства'!D$5*'Исх.данные-произв'!$D22+'Исх.данные-произв'!$E$8*'Бюджет производства'!D$6+'Бюджет производства'!D$7*'Исх.данные-произв'!$F22+'Исх.данные-произв'!$G22*'Бюджет производства'!D$8+'Бюджет производства'!D$9*'Исх.данные-произв'!$H22 -> 0 | G21: ='Исх.данные-произв'!$C22*'Бюджет производства'!E$4+'Бюджет производства'!E$5*'Исх.данные-произв'!$D22+'Исх.данные-произв'!$E$8*'Бюджет производства'!E$6+'Бюджет производства'!E$7*'Исх.данные-произв'!$F22+'Исх.данные-произв'!$G22*'Бюджет производства'!E$8+'Бюджет производства'!E$9*'Исх.данные-произв'!$H22 -> 0 | H21: ='Исх.данные-произв'!$C22*'Бюджет производства'!F$4+'Бюджет производства'!F$5*'Исх.данные-произв'!$D22+'Исх.данные-произв'!$E$8*'Бюджет производства'!F$6+'Бюджет производства'!F$7*'Исх.данные-произв'!$F22+'Исх.данные-произв'!$G22*'Бюджет производства'!F$8+'Бюджет производства'!F$9*'Исх.данные-произв'!$H22 -> 0 | I21: ='Исх.данные-произв'!$C22*'Бюджет производства'!G$4+'Бюджет производства'!G$5*'Исх.данные-произв'!$D22+'Исх.данные-произв'!$E$8*'Бюджет производства'!G$6+'Бюджет производства'!G$7*'Исх.данные-произв'!$F22+'Исх.данные-произв'!$G22*'Бюджет производства'!G$8+'Бюджет производства'!G$9*'Исх.данные-произв'!$H22 -> 0 | J21: ='Исх.данные-произв'!$C22*'Бюджет производства'!H$4+'Бюджет производства'!H$5*'Исх.данные-произв'!$D22+'Исх.данные-произв'!$E$8*'Бюджет производства'!H$6+'Бюджет производства'!H$7*'Исх.данные-произв'!$F22+'Исх.данные-произв'!$G22*'Бюджет производства'!H$8+'Бюджет производства'!H$9*'Исх.данные-произв'!$H22 -> 0 | K21: ='Исх.данные-произв'!$C22*'Бюджет производства'!I$4+'Бюджет производства'!I$5*'Исх.данные-произв'!$D22+'Исх.данные-произв'!$E$8*'Бюджет производства'!I$6+'Бюджет производства'!I$7*'Исх.данные-произв'!$F22+'Исх.данные-произв'!$G22*'Бюджет производства'!I$8+'Бюджет производства'!I$9*'Исх.данные-произв'!$H22 -> 0 | ... O21: ='Исх.данные-произв'!$C22*'Бюджет производства'!M$4+'Бюджет производства'!M$5*'Исх.данные-произв'!$D22+'Исх.данные-произв'!$E$8*'Бюджет производства'!M$6+'Бюджет производства'!M$7*'Исх.данные-произв'!$F22+'Исх.данные-произв'!$G22*'Бюджет производства'!M$8+'Бюджет производства'!M$9*'Исх.данные-произв'!$H22 -> 0
A23: Вспомогательные материалы
A24: ВМ 1 | D24: ='Исх.данные-произв'!$C25*'Бюджет производства'!B$4+'Бюджет производства'!B$5*'Исх.данные-произв'!$D25+'Исх.данные-произв'!$E$8*'Бюджет производства'!B$6+'Бюджет производства'!B$7*'Исх.данные-произв'!$F25+'Исх.данные-произв'!$G25*'Бюджет производства'!B$8+'Бюджет производства'!B$9*'Исх.данные-произв'!$H25 -> 0 | E24: ='Исх.данные-произв'!$C25*'Бюджет производства'!C$4+'Бюджет производства'!C$5*'Исх.данные-произв'!$D25+'Исх.данные-произв'!$E$8*'Бюджет производства'!C$6+'Бюджет производства'!C$7*'Исх.данные-произв'!$F25+'Исх.данные-произв'!$G25*'Бюджет производства'!C$8+'Бюджет производства'!C$9*'Исх.данные-произв'!$H25 -> 0 | F24: ='Исх.данные-произв'!$C25*'Бюджет производства'!D$4+'Бюджет производства'!D$5*'Исх.данные-произв'!$D25+'Исх.данные-произв'!$E$8*'Бюджет производства'!D$6+'Бюджет производства'!D$7*'Исх.данные-произв'!$F25+'Исх.данные-произв'!$G25*'Бюджет производства'!D$8+'Бюджет производства'!D$9*'Исх.данные-произв'!$H25 -> 0 | G24: ='Исх.данные-произв'!$C25*'Бюджет производства'!E$4+'Бюджет производства'!E$5*'Исх.данные-произв'!$D25+'Исх.данные-произв'!$E$8*'Бюджет производства'!E$6+'Бюджет производства'!E$7*'Исх.данные-произв'!$F25+'Исх.данные-произв'!$G25*'Бюджет производства'!E$8+'Бюджет производства'!E$9*'Исх.данные-произв'!$H25 -> 0 | H24: ='Исх.данные-произв'!$C25*'Бюджет производства'!F$4+'Бюджет производства'!F$5*'Исх.данные-произв'!$D25+'Исх.данные-произв'!$E$8*'Бюджет производства'!F$6+'Бюджет производства'!F$7*'Исх.данные-произв'!$F25+'Исх.данные-произв'!$G25*'Бюджет производства'!F$8+'Бюджет производства'!F$9*'Исх.данные-произв'!$H25 -> 0 | I24: ='Исх.данные-произв'!$C25*'Бюджет производства'!G$4+'Бюджет производства'!G$5*'Исх.данные-произв'!$D25+'Исх.данные-произв'!$E$8*'Бюджет производства'!G$6+'Бюджет производства'!G$7*'Исх.данные-произв'!$F25+'Исх.данные-произв'!$G25*'Бюджет производства'!G$8+'Бюджет производства'!G$9*'Исх.данные-произв'!$H25 -> 0 | J24: ='Исх.данные-произв'!$C25*'Бюджет производства'!H$4+'Бюджет производства'!H$5*'Исх.данные-произв'!$D25+'Исх.данные-произв'!$E$8*'Бюджет производства'!H$6+'Бюджет производства'!H$7*'Исх.данные-произв'!$F25+'Исх.данные-произв'!$G25*'Бюджет производства'!H$8+'Бюджет производства'!H$9*'Исх.данные-произв'!$H25 -> 0 | K24: ='Исх.данные-произв'!$C25*'Бюджет производства'!I$4+'Бюджет производства'!I$5*'Исх.данные-произв'!$D25+'Исх.данные-произв'!$E$8*'Бюджет производства'!I$6+'Бюджет производства'!I$7*'Исх.данные-произв'!$F25+'Исх.данные-произв'!$G25*'Бюджет производства'!I$8+'Бюджет производства'!I$9*'Исх.данные-произв'!$H25 -> 0 | ... O24: ='Исх.данные-произв'!$C25*'Бюджет производства'!M$4+'Бюджет производства'!M$5*'Исх.данные-произв'!$D25+'Исх.данные-произв'!$E$8*'Бюджет производства'!M$6+'Бюджет производства'!M$7*'Исх.данные-произв'!$F25+'Исх.данные-произв'!$G25*'Бюджет производства'!M$8+'Бюджет производства'!M$9*'Исх.данные-произв'!$H25 -> 0
A25: ВМ 2 | D25: ='Исх.данные-произв'!$C26*'Бюджет производства'!B$4+'Бюджет производства'!B$5*'Исх.данные-произв'!$D26+'Исх.данные-произв'!$E$8*'Бюджет производства'!B$6+'Бюджет производства'!B$7*'Исх.данные-произв'!$F26+'Исх.данные-произв'!$G26*'Бюджет производства'!B$8+'Бюджет производства'!B$9*'Исх.данные-произв'!$H26 -> 0 | E25: ='Исх.данные-произв'!$C26*'Бюджет производства'!C$4+'Бюджет производства'!C$5*'Исх.данные-произв'!$D26+'Исх.данные-произв'!$E$8*'Бюджет производства'!C$6+'Бюджет производства'!C$7*'Исх.данные-произв'!$F26+'Исх.данные-произв'!$G26*'Бюджет производства'!C$8+'Бюджет производства'!C$9*'Исх.данные-произв'!$H26 -> 0 | F25: ='Исх.данные-произв'!$C26*'Бюджет производства'!D$4+'Бюджет производства'!D$5*'Исх.данные-произв'!$D26+'Исх.данные-произв'!$E$8*'Бюджет производства'!D$6+'Бюджет производства'!D$7*'Исх.данные-произв'!$F26+'Исх.данные-произв'!$G26*'Бюджет производства'!D$8+'Бюджет производства'!D$9*'Исх.данные-произв'!$H26 -> 0 | G25: ='Исх.данные-произв'!$C26*'Бюджет производства'!E$4+'Бюджет производства'!E$5*'Исх.данные-произв'!$D26+'Исх.данные-произв'!$E$8*'Бюджет производства'!E$6+'Бюджет производства'!E$7*'Исх.данные-произв'!$F26+'Исх.данные-произв'!$G26*'Бюджет производства'!E$8+'Бюджет производства'!E$9*'Исх.данные-произв'!$H26 -> 0 | H25: ='Исх.данные-произв'!$C26*'Бюджет производства'!F$4+'Бюджет производства'!F$5*'Исх.данные-произв'!$D26+'Исх.данные-произв'!$E$8*'Бюджет производства'!F$6+'Бюджет производства'!F$7*'Исх.данные-произв'!$F26+'Исх.данные-произв'!$G26*'Бюджет производства'!F$8+'Бюджет производства'!F$9*'Исх.данные-произв'!$H26 -> 0 | I25: ='Исх.данные-произв'!$C26*'Бюджет производства'!G$4+'Бюджет производства'!G$5*'Исх.данные-произв'!$D26+'Исх.данные-произв'!$E$8*'Бюджет производства'!G$6+'Бюджет производства'!G$7*'Исх.данные-произв'!$F26+'Исх.данные-произв'!$G26*'Бюджет производства'!G$8+'Бюджет производства'!G$9*'Исх.данные-произв'!$H26 -> 0 | J25: ='Исх.данные-произв'!$C26*'Бюджет производства'!H$4+'Бюджет производства'!H$5*'Исх.данные-произв'!$D26+'Исх.данные-произв'!$E$8*'Бюджет производства'!H$6+'Бюджет производства'!H$7*'Исх.данные-произв'!$F26+'Исх.данные-произв'!$G26*'Бюджет производства'!H$8+'Бюджет производства'!H$9*'Исх.данные-произв'!$H26 -> 0 | K25: ='Исх.данные-произв'!$C26*'Бюджет производства'!I$4+'Бюджет производства'!I$5*'Исх.данные-произв'!$D26+'Исх.данные-произв'!$E$8*'Бюджет производства'!I$6+'Бюджет производства'!I$7*'Исх.данные-произв'!$F26+'Исх.данные-произв'!$G26*'Бюджет производства'!I$8+'Бюджет производства'!I$9*'Исх.данные-произв'!$H26 -> 0 | ... O25: ='Исх.данные-произв'!$C26*'Бюджет производства'!M$4+'Бюджет производства'!M$5*'Исх.данные-произв'!$D26+'Исх.данные-произв'!$E$8*'Бюджет производства'!M$6+'Бюджет производства'!M$7*'Исх.данные-произв'!$F26+'Исх.данные-произв'!$G26*'Бюджет производства'!M$8+'Бюджет производства'!M$9*'Исх.данные-произв'!$H26 -> 0
A26: ВМ 3 | D26: ='Исх.данные-произв'!$C27*'Бюджет производства'!B$4+'Бюджет производства'!B$5*'Исх.данные-произв'!$D27+'Исх.данные-произв'!$E$8*'Бюджет производства'!B$6+'Бюджет производства'!B$7*'Исх.данные-произв'!$F27+'Исх.данные-произв'!$G27*'Бюджет производства'!B$8+'Бюджет производства'!B$9*'Исх.данные-произв'!$H27 -> 0 | E26: ='Исх.данные-произв'!$C27*'Бюджет производства'!C$4+'Бюджет производства'!C$5*'Исх.данные-произв'!$D27+'Исх.данные-произв'!$E$8*'Бюджет производства'!C$6+'Бюджет производства'!C$7*'Исх.данные-произв'!$F27+'Исх.данные-произв'!$G27*'Бюджет производства'!C$8+'Бюджет производства'!C$9*'Исх.данные-произв'!$H27 -> 0 | F26: ='Исх.данные-произв'!$C27*'Бюджет производства'!D$4+'Бюджет производства'!D$5*'Исх.данные-произв'!$D27+'Исх.данные-произв'!$E$8*'Бюджет производства'!D$6+'Бюджет производства'!D$7*'Исх.данные-произв'!$F27+'Исх.данные-произв'!$G27*'Бюджет производства'!D$8+'Бюджет производства'!D$9*'Исх.данные-произв'!$H27 -> 0 | G26: ='Исх.данные-произв'!$C27*'Бюджет производства'!E$4+'Бюджет производства'!E$5*'Исх.данные-произв'!$D27+'Исх.данные-произв'!$E$8*'Бюджет производства'!E$6+'Бюджет производства'!E$7*'Исх.данные-произв'!$F27+'Исх.данные-произв'!$G27*'Бюджет производства'!E$8+'Бюджет производства'!E$9*'Исх.данные-произв'!$H27 -> 0 | H26: ='Исх.данные-произв'!$C27*'Бюджет производства'!F$4+'Бюджет производства'!F$5*'Исх.данные-произв'!$D27+'Исх.данные-произв'!$E$8*'Бюджет производства'!F$6+'Бюджет производства'!F$7*'Исх.данные-произв'!$F27+'Исх.данные-произв'!$G27*'Бюджет производства'!F$8+'Бюджет производства'!F$9*'Исх.данные-произв'!$H27 -> 0 | I26: ='Исх.данные-произв'!$C27*'Бюджет производства'!G$4+'Бюджет производства'!G$5*'Исх.данные-произв'!$D27+'Исх.данные-произв'!$E$8*'Бюджет производства'!G$6+'Бюджет производства'!G$7*'Исх.данные-произв'!$F27+'Исх.данные-произв'!$G27*'Бюджет производства'!G$8+'Бюджет производства'!G$9*'Исх.данные-произв'!$H27 -> 0 | J26: ='Исх.данные-произв'!$C27*'Бюджет производства'!H$4+'Бюджет производства'!H$5*'Исх.данные-произв'!$D27+'Исх.данные-произв'!$E$8*'Бюджет производства'!H$6+'Бюджет производства'!H$7*'Исх.данные-произв'!$F27+'Исх.данные-произв'!$G27*'Бюджет производства'!H$8+'Бюджет производства'!H$9*'Исх.данные-произв'!$H27 -> 0 | K26: ='Исх.данные-произв'!$C27*'Бюджет производства'!I$4+'Бюджет производства'!I$5*'Исх.данные-произв'!$D27+'Исх.данные-произв'!$E$8*'Бюджет производства'!I$6+'Бюджет производства'!I$7*'Исх.данные-произв'!$F27+'Исх.данные-произв'!$G27*'Бюджет производства'!I$8+'Бюджет производства'!I$9*'Исх.данные-произв'!$H27 -> 0 | ... O26: ='Исх.данные-произв'!$C27*'Бюджет производства'!M$4+'Бюджет производства'!M$5*'Исх.данные-произв'!$D27+'Исх.данные-произв'!$E$8*'Бюджет производства'!M$6+'Бюджет производства'!M$7*'Исх.данные-произв'!$F27+'Исх.данные-произв'!$G27*'Бюджет производства'!M$8+'Бюджет производства'!M$9*'Исх.данные-произв'!$H27 -> 0
A27: ВМ 4 | D27: ='Исх.данные-произв'!$C28*'Бюджет производства'!B$4+'Бюджет производства'!B$5*'Исх.данные-произв'!$D28+'Исх.данные-произв'!$E$8*'Бюджет производства'!B$6+'Бюджет производства'!B$7*'Исх.данные-произв'!$F28+'Исх.данные-произв'!$G28*'Бюджет производства'!B$8+'Бюджет производства'!B$9*'Исх.данные-произв'!$H28 -> 0 | E27: ='Исх.данные-произв'!$C28*'Бюджет производства'!C$4+'Бюджет производства'!C$5*'Исх.данные-произв'!$D28+'Исх.данные-произв'!$E$8*'Бюджет производства'!C$6+'Бюджет производства'!C$7*'Исх.данные-произв'!$F28+'Исх.данные-произв'!$G28*'Бюджет производства'!C$8+'Бюджет производства'!C$9*'Исх.данные-произв'!$H28 -> 0 | F27: ='Исх.данные-произв'!$C28*'Бюджет производства'!D$4+'Бюджет производства'!D$5*'Исх.данные-произв'!$D28+'Исх.данные-произв'!$E$8*'Бюджет производства'!D$6+'Бюджет производства'!D$7*'Исх.данные-произв'!$F28+'Исх.данные-произв'!$G28*'Бюджет производства'!D$8+'Бюджет производства'!D$9*'Исх.данные-произв'!$H28 -> 0 | G27: ='Исх.данные-произв'!$C28*'Бюджет производства'!E$4+'Бюджет производства'!E$5*'Исх.данные-произв'!$D28+'Исх.данные-произв'!$E$8*'Бюджет производства'!E$6+'Бюджет производства'!E$7*'Исх.данные-произв'!$F28+'Исх.данные-произв'!$G28*'Бюджет производства'!E$8+'Бюджет производства'!E$9*'Исх.данные-произв'!$H28 -> 0 | H27: ='Исх.данные-произв'!$C28*'Бюджет производства'!F$4+'Бюджет производства'!F$5*'Исх.данные-произв'!$D28+'Исх.данные-произв'!$E$8*'Бюджет производства'!F$6+'Бюджет производства'!F$7*'Исх.данные-произв'!$F28+'Исх.данные-произв'!$G28*'Бюджет производства'!F$8+'Бюджет производства'!F$9*'Исх.данные-произв'!$H28 -> 0 | I27: ='Исх.данные-произв'!$C28*'Бюджет производства'!G$4+'Бюджет производства'!G$5*'Исх.данные-произв'!$D28+'Исх.данные-произв'!$E$8*'Бюджет производства'!G$6+'Бюджет производства'!G$7*'Исх.данные-произв'!$F28+'Исх.данные-произв'!$G28*'Бюджет производства'!G$8+'Бюджет производства'!G$9*'Исх.данные-произв'!$H28 -> 0 | J27: ='Исх.данные-произв'!$C28*'Бюджет производства'!H$4+'Бюджет производства'!H$5*'Исх.данные-произв'!$D28+'Исх.данные-произв'!$E$8*'Бюджет производства'!H$6+'Бюджет производства'!H$7*'Исх.данные-произв'!$F28+'Исх.данные-произв'!$G28*'Бюджет производства'!H$8+'Бюджет производства'!H$9*'Исх.данные-произв'!$H28 -> 0 | K27: ='Исх.данные-произв'!$C28*'Бюджет производства'!I$4+'Бюджет производства'!I$5*'Исх.данные-произв'!$D28+'Исх.данные-произв'!$E$8*'Бюджет производства'!I$6+'Бюджет производства'!I$7*'Исх.данные-произв'!$F28+'Исх.данные-произв'!$G28*'Бюджет производства'!I$8+'Бюджет производства'!I$9*'Исх.данные-произв'!$H28 -> 0 | ... O27: ='Исх.данные-произв'!$C28*'Бюджет производства'!M$4+'Бюджет производства'!M$5*'Исх.данные-произв'!$D28+'Исх.данные-произв'!$E$8*'Бюджет производства'!M$6+'Бюджет производства'!M$7*'Исх.данные-произв'!$F28+'Исх.данные-произв'!$G28*'Бюджет производства'!M$8+'Бюджет производства'!M$9*'Исх.данные-произв'!$H28 -> 0
A28: ВМ 5 | D28: ='Исх.данные-произв'!$C29*'Бюджет производства'!B$4+'Бюджет производства'!B$5*'Исх.данные-произв'!$D29+'Исх.данные-произв'!$E$8*'Бюджет производства'!B$6+'Бюджет производства'!B$7*'Исх.данные-произв'!$F29+'Исх.данные-произв'!$G29*'Бюджет производства'!B$8+'Бюджет производства'!B$9*'Исх.данные-произв'!$H29 -> 0 | E28: ='Исх.данные-произв'!$C29*'Бюджет производства'!C$4+'Бюджет производства'!C$5*'Исх.данные-произв'!$D29+'Исх.данные-произв'!$E$8*'Бюджет производства'!C$6+'Бюджет производства'!C$7*'Исх.данные-произв'!$F29+'Исх.данные-произв'!$G29*'Бюджет производства'!C$8+'Бюджет производства'!C$9*'Исх.данные-произв'!$H29 -> 0 | F28: ='Исх.данные-произв'!$C29*'Бюджет производства'!D$4+'Бюджет производства'!D$5*'Исх.данные-произв'!$D29+'Исх.данные-произв'!$E$8*'Бюджет производства'!D$6+'Бюджет производства'!D$7*'Исх.данные-произв'!$F29+'Исх.данные-произв'!$G29*'Бюджет производства'!D$8+'Бюджет производства'!D$9*'Исх.данные-произв'!$H29 -> 0 | G28: ='Исх.данные-произв'!$C29*'Бюджет производства'!E$4+'Бюджет производства'!E$5*'Исх.данные-произв'!$D29+'Исх.данные-произв'!$E$8*'Бюджет производства'!E$6+'Бюджет производства'!E$7*'Исх.данные-произв'!$F29+'Исх.данные-произв'!$G29*'Бюджет производства'!E$8+'Бюджет производства'!E$9*'Исх.данные-произв'!$H29 -> 0 | H28: ='Исх.данные-произв'!$C29*'Бюджет производства'!F$4+'Бюджет производства'!F$5*'Исх.данные-произв'!$D29+'Исх.данные-произв'!$E$8*'Бюджет производства'!F$6+'Бюджет производства'!F$7*'Исх.данные-произв'!$F29+'Исх.данные-произв'!$G29*'Бюджет производства'!F$8+'Бюджет производства'!F$9*'Исх.данные-произв'!$H29 -> 0 | I28: ='Исх.данные-произв'!$C29*'Бюджет производства'!G$4+'Бюджет производства'!G$5*'Исх.данные-произв'!$D29+'Исх.данные-произв'!$E$8*'Бюджет производства'!G$6+'Бюджет производства'!G$7*'Исх.данные-произв'!$F29+'Исх.данные-произв'!$G29*'Бюджет производства'!G$8+'Бюджет производства'!G$9*'Исх.данные-произв'!$H29 -> 0 | J28: ='Исх.данные-произв'!$C29*'Бюджет производства'!H$4+'Бюджет производства'!H$5*'Исх.данные-произв'!$D29+'Исх.данные-произв'!$E$8*'Бюджет производства'!H$6+'Бюджет производства'!H$7*'Исх.данные-произв'!$F29+'Исх.данные-произв'!$G29*'Бюджет производства'!H$8+'Бюджет производства'!H$9*'Исх.данные-произв'!$H29 -> 0 | K28: ='Исх.данные-произв'!$C29*'Бюджет производства'!I$4+'Бюджет производства'!I$5*'Исх.данные-произв'!$D29+'Исх.данные-произв'!$E$8*'Бюджет производства'!I$6+'Бюджет производства'!I$7*'Исх.данные-произв'!$F29+'Исх.данные-произв'!$G29*'Бюджет производства'!I$8+'Бюджет производства'!I$9*'Исх.данные-произв'!$H29 -> 0 | ... O28: ='Исх.данные-произв'!$C29*'Бюджет производства'!M$4+'Бюджет производства'!M$5*'Исх.данные-произв'!$D29+'Исх.данные-произв'!$E$8*'Бюджет производства'!M$6+'Бюджет производства'!M$7*'Исх.данные-произв'!$F29+'Исх.данные-произв'!$G29*'Бюджет производства'!M$8+'Бюджет производства'!M$9*'Исх.данные-произв'!$H29 -> 0
A29: ВМ 6 | D29: ='Исх.данные-произв'!$C30*'Бюджет производства'!B$4+'Бюджет производства'!B$5*'Исх.данные-произв'!$D30+'Исх.данные-произв'!$E$8*'Бюджет производства'!B$6+'Бюджет производства'!B$7*'Исх.данные-произв'!$F30+'Исх.данные-произв'!$G30*'Бюджет производства'!B$8+'Бюджет производства'!B$9*'Исх.данные-произв'!$H30 -> 0 | E29: ='Исх.данные-произв'!$C30*'Бюджет производства'!C$4+'Бюджет производства'!C$5*'Исх.данные-произв'!$D30+'Исх.данные-произв'!$E$8*'Бюджет производства'!C$6+'Бюджет производства'!C$7*'Исх.данные-произв'!$F30+'Исх.данные-произв'!$G30*'Бюджет производства'!C$8+'Бюджет производства'!C$9*'Исх.данные-произв'!$H30 -> 0 | F29: ='Исх.данные-произв'!$C30*'Бюджет производства'!D$4+'Бюджет производства'!D$5*'Исх.данные-произв'!$D30+'Исх.данные-произв'!$E$8*'Бюджет производства'!D$6+'Бюджет производства'!D$7*'Исх.данные-произв'!$F30+'Исх.данные-произв'!$G30*'Бюджет производства'!D$8+'Бюджет производства'!D$9*'Исх.данные-произв'!$H30 -> 0 | G29: ='Исх.данные-произв'!$C30*'Бюджет производства'!E$4+'Бюджет производства'!E$5*'Исх.данные-произв'!$D30+'Исх.данные-произв'!$E$8*'Бюджет производства'!E$6+'Бюджет производства'!E$7*'Исх.данные-произв'!$F30+'Исх.данные-произв'!$G30*'Бюджет производства'!E$8+'Бюджет производства'!E$9*'Исх.данные-произв'!$H30 -> 0 | H29: ='Исх.данные-произв'!$C30*'Бюджет производства'!F$4+'Бюджет производства'!F$5*'Исх.данные-произв'!$D30+'Исх.данные-произв'!$E$8*'Бюджет производства'!F$6+'Бюджет производства'!F$7*'Исх.данные-произв'!$F30+'Исх.данные-произв'!$G30*'Бюджет производства'!F$8+'Бюджет производства'!F$9*'Исх.данные-произв'!$H30 -> 0 | I29: ='Исх.данные-произв'!$C30*'Бюджет производства'!G$4+'Бюджет производства'!G$5*'Исх.данные-произв'!$D30+'Исх.данные-произв'!$E$8*'Бюджет производства'!G$6+'Бюджет производства'!G$7*'Исх.данные-произв'!$F30+'Исх.данные-произв'!$G30*'Бюджет производства'!G$8+'Бюджет производства'!G$9*'Исх.данные-произв'!$H30 -> 0 | J29: ='Исх.данные-произв'!$C30*'Бюджет производства'!H$4+'Бюджет производства'!H$5*'Исх.данные-произв'!$D30+'Исх.данные-произв'!$E$8*'Бюджет производства'!H$6+'Бюджет производства'!H$7*'Исх.данные-произв'!$F30+'Исх.данные-произв'!$G30*'Бюджет производства'!H$8+'Бюджет производства'!H$9*'Исх.данные-произв'!$H30 -> 0 | K29: ='Исх.данные-произв'!$C30*'Бюджет производства'!I$4+'Бюджет производства'!I$5*'Исх.данные-произв'!$D30+'Исх.данные-произв'!$E$8*'Бюджет производства'!I$6+'Бюджет производства'!I$7*'Исх.данные-произв'!$F30+'Исх.данные-произв'!$G30*'Бюджет производства'!I$8+'Бюджет производства'!I$9*'Исх.данные-произв'!$H30 -> 0 | ... O29: ='Исх.данные-произв'!$C30*'Бюджет производства'!M$4+'Бюджет производства'!M$5*'Исх.данные-произв'!$D30+'Исх.данные-произв'!$E$8*'Бюджет производства'!M$6+'Бюджет производства'!M$7*'Исх.данные-произв'!$F30+'Исх.данные-произв'!$G30*'Бюджет производства'!M$8+'Бюджет производства'!M$9*'Исх.данные-произв'!$H30 -> 0
A30: ВМ 7 | D30: ='Исх.данные-произв'!$C31*'Бюджет производства'!B$4+'Бюджет производства'!B$5*'Исх.данные-произв'!$D31+'Исх.данные-произв'!$E$8*'Бюджет производства'!B$6+'Бюджет производства'!B$7*'Исх.данные-произв'!$F31+'Исх.данные-произв'!$G31*'Бюджет производства'!B$8+'Бюджет производства'!B$9*'Исх.данные-произв'!$H31 -> 0 | E30: ='Исх.данные-произв'!$C31*'Бюджет производства'!C$4+'Бюджет производства'!C$5*'Исх.данные-произв'!$D31+'Исх.данные-произв'!$E$8*'Бюджет производства'!C$6+'Бюджет производства'!C$7*'Исх.данные-произв'!$F31+'Исх.данные-произв'!$G31*'Бюджет производства'!C$8+'Бюджет производства'!C$9*'Исх.данные-произв'!$H31 -> 0 | F30: ='Исх.данные-произв'!$C31*'Бюджет производства'!D$4+'Бюджет производства'!D$5*'Исх.данные-произв'!$D31+'Исх.данные-произв'!$E$8*'Бюджет производства'!D$6+'Бюджет производства'!D$7*'Исх.данные-произв'!$F31+'Исх.данные-произв'!$G31*'Бюджет производства'!D$8+'Бюджет производства'!D$9*'Исх.данные-произв'!$H31 -> 0 | G30: ='Исх.данные-произв'!$C31*'Бюджет производства'!E$4+'Бюджет производства'!E$5*'Исх.данные-произв'!$D31+'Исх.данные-произв'!$E$8*'Бюджет производства'!E$6+'Бюджет производства'!E$7*'Исх.данные-произв'!$F31+'Исх.данные-произв'!$G31*'Бюджет производства'!E$8+'Бюджет производства'!E$9*'Исх.данные-произв'!$H31 -> 0 | H30: ='Исх.данные-произв'!$C31*'Бюджет производства'!F$4+'Бюджет производства'!F$5*'Исх.данные-произв'!$D31+'Исх.данные-произв'!$E$8*'Бюджет производства'!F$6+'Бюджет производства'!F$7*'Исх.данные-произв'!$F31+'Исх.данные-произв'!$G31*'Бюджет производства'!F$8+'Бюджет производства'!F$9*'Исх.данные-произв'!$H31 -> 0 | I30: ='Исх.данные-произв'!$C31*'Бюджет производства'!G$4+'Бюджет производства'!G$5*'Исх.данные-произв'!$D31+'Исх.данные-произв'!$E$8*'Бюджет производства'!G$6+'Бюджет производства'!G$7*'Исх.данные-произв'!$F31+'Исх.данные-произв'!$G31*'Бюджет производства'!G$8+'Бюджет производства'!G$9*'Исх.данные-произв'!$H31 -> 0 | J30: ='Исх.данные-произв'!$C31*'Бюджет производства'!H$4+'Бюджет производства'!H$5*'Исх.данные-произв'!$D31+'Исх.данные-произв'!$E$8*'Бюджет производства'!H$6+'Бюджет производства'!H$7*'Исх.данные-произв'!$F31+'Исх.данные-произв'!$G31*'Бюджет производства'!H$8+'Бюджет производства'!H$9*'Исх.данные-произв'!$H31 -> 0 | K30: ='Исх.данные-произв'!$C31*'Бюджет производства'!I$4+'Бюджет производства'!I$5*'Исх.данные-произв'!$D31+'Исх.данные-произв'!$E$8*'Бюджет производства'!I$6+'Бюджет производства'!I$7*'Исх.данные-произв'!$F31+'Исх.данные-произв'!$G31*'Бюджет производства'!I$8+'Бюджет производства'!I$9*'Исх.данные-произв'!$H31 -> 0 | ... O30: ='Исх.данные-произв'!$C31*'Бюджет производства'!M$4+'Бюджет производства'!M$5*'Исх.данные-произв'!$D31+'Исх.данные-произв'!$E$8*'Бюджет производства'!M$6+'Бюджет производства'!M$7*'Исх.данные-произв'!$F31+'Исх.данные-произв'!$G31*'Бюджет производства'!M$8+'Бюджет производства'!M$9*'Исх.данные-произв'!$H31 -> 0
A31: ВМ 8 | D31: ='Исх.данные-произв'!$C32*'Бюджет производства'!B$4+'Бюджет производства'!B$5*'Исх.данные-произв'!$D32+'Исх.данные-произв'!$E$8*'Бюджет производства'!B$6+'Бюджет производства'!B$7*'Исх.данные-произв'!$F32+'Исх.данные-произв'!$G32*'Бюджет производства'!B$8+'Бюджет производства'!B$9*'Исх.данные-произв'!$H32 -> 0 | E31: ='Исх.данные-произв'!$C32*'Бюджет производства'!C$4+'Бюджет производства'!C$5*'Исх.данные-произв'!$D32+'Исх.данные-произв'!$E$8*'Бюджет производства'!C$6+'Бюджет производства'!C$7*'Исх.данные-произв'!$F32+'Исх.данные-произв'!$G32*'Бюджет производства'!C$8+'Бюджет производства'!C$9*'Исх.данные-произв'!$H32 -> 0 | F31: ='Исх.данные-произв'!$C32*'Бюджет производства'!D$4+'Бюджет производства'!D$5*'Исх.данные-произв'!$D32+'Исх.данные-произв'!$E$8*'Бюджет производства'!D$6+'Бюджет производства'!D$7*'Исх.данные-произв'!$F32+'Исх.данные-произв'!$G32*'Бюджет производства'!D$8+'Бюджет производства'!D$9*'Исх.данные-произв'!$H32 -> 0 | G31: ='Исх.данные-произв'!$C32*'Бюджет производства'!E$4+'Бюджет производства'!E$5*'Исх.данные-произв'!$D32+'Исх.данные-произв'!$E$8*'Бюджет производства'!E$6+'Бюджет производства'!E$7*'Исх.данные-произв'!$F32+'Исх.данные-произв'!$G32*'Бюджет производства'!E$8+'Бюджет производства'!E$9*'Исх.данные-произв'!$H32 -> 0 | H31: ='Исх.данные-произв'!$C32*'Бюджет производства'!F$4+'Бюджет производства'!F$5*'Исх.данные-произв'!$D32+'Исх.данные-произв'!$E$8*'Бюджет производства'!F$6+'Бюджет производства'!F$7*'Исх.данные-произв'!$F32+'Исх.данные-произв'!$G32*'Бюджет производства'!F$8+'Бюджет производства'!F$9*'Исх.данные-произв'!$H32 -> 0 | I31: ='Исх.данные-произв'!$C32*'Бюджет производства'!G$4+'Бюджет производства'!G$5*'Исх.данные-произв'!$D32+'Исх.данные-произв'!$E$8*'Бюджет производства'!G$6+'Бюджет производства'!G$7*'Исх.данные-произв'!$F32+'Исх.данные-произв'!$G32*'Бюджет производства'!G$8+'Бюджет производства'!G$9*'Исх.данные-произв'!$H32 -> 0 | J31: ='Исх.данные-произв'!$C32*'Бюджет производства'!H$4+'Бюджет производства'!H$5*'Исх.данные-произв'!$D32+'Исх.данные-произв'!$E$8*'Бюджет производства'!H$6+'Бюджет производства'!H$7*'Исх.данные-произв'!$F32+'Исх.данные-произв'!$G32*'Бюджет производства'!H$8+'Бюджет производства'!H$9*'Исх.данные-произв'!$H32 -> 0 | K31: ='Исх.данные-произв'!$C32*'Бюджет производства'!I$4+'Бюджет производства'!I$5*'Исх.данные-произв'!$D32+'Исх.данные-произв'!$E$8*'Бюджет производства'!I$6+'Бюджет производства'!I$7*'Исх.данные-произв'!$F32+'Исх.данные-произв'!$G32*'Бюджет производства'!I$8+'Бюджет производства'!I$9*'Исх.данные-произв'!$H32 -> 0 | ... O31: ='Исх.данные-произв'!$C32*'Бюджет производства'!M$4+'Бюджет производства'!M$5*'Исх.данные-произв'!$D32+'Исх.данные-произв'!$E$8*'Бюджет производства'!M$6+'Бюджет производства'!M$7*'Исх.данные-произв'!$F32+'Исх.данные-произв'!$G32*'Бюджет производства'!M$8+'Бюджет производства'!M$9*'Исх.данные-произв'!$H32 -> 0
A32: ВМ 9 | D32: ='Исх.данные-произв'!$C33*'Бюджет производства'!B$4+'Бюджет производства'!B$5*'Исх.данные-произв'!$D33+'Исх.данные-произв'!$E$8*'Бюджет производства'!B$6+'Бюджет производства'!B$7*'Исх.данные-произв'!$F33+'Исх.данные-произв'!$G33*'Бюджет производства'!B$8+'Бюджет производства'!B$9*'Исх.данные-произв'!$H33 -> 0 | E32: ='Исх.данные-произв'!$C33*'Бюджет производства'!C$4+'Бюджет производства'!C$5*'Исх.данные-произв'!$D33+'Исх.данные-произв'!$E$8*'Бюджет производства'!C$6+'Бюджет производства'!C$7*'Исх.данные-произв'!$F33+'Исх.данные-произв'!$G33*'Бюджет производства'!C$8+'Бюджет производства'!C$9*'Исх.данные-произв'!$H33 -> 0 | F32: ='Исх.данные-произв'!$C33*'Бюджет производства'!D$4+'Бюджет производства'!D$5*'Исх.данные-произв'!$D33+'Исх.данные-произв'!$E$8*'Бюджет производства'!D$6+'Бюджет производства'!D$7*'Исх.данные-произв'!$F33+'Исх.данные-произв'!$G33*'Бюджет производства'!D$8+'Бюджет производства'!D$9*'Исх.данные-произв'!$H33 -> 0 | G32: ='Исх.данные-произв'!$C33*'Бюджет производства'!E$4+'Бюджет производства'!E$5*'Исх.данные-произв'!$D33+'Исх.данные-произв'!$E$8*'Бюджет производства'!E$6+'Бюджет производства'!E$7*'Исх.данные-произв'!$F33+'Исх.данные-произв'!$G33*'Бюджет производства'!E$8+'Бюджет производства'!E$9*'Исх.данные-произв'!$H33 -> 0 | H32: ='Исх.данные-произв'!$C33*'Бюджет производства'!F$4+'Бюджет производства'!F$5*'Исх.данные-произв'!$D33+'Исх.данные-произв'!$E$8*'Бюджет производства'!F$6+'Бюджет производства'!F$7*'Исх.данные-произв'!$F33+'Исх.данные-произв'!$G33*'Бюджет производства'!F$8+'Бюджет производства'!F$9*'Исх.данные-произв'!$H33 -> 0 | I32: ='Исх.данные-произв'!$C33*'Бюджет производства'!G$4+'Бюджет производства'!G$5*'Исх.данные-произв'!$D33+'Исх.данные-произв'!$E$8*'Бюджет производства'!G$6+'Бюджет производства'!G$7*'Исх.данные-произв'!$F33+'Исх.данные-произв'!$G33*'Бюджет производства'!G$8+'Бюджет производства'!G$9*'Исх.данные-произв'!$H33 -> 0 | J32: ='Исх.данные-произв'!$C33*'Бюджет производства'!H$4+'Бюджет производства'!H$5*'Исх.данные-произв'!$D33+'Исх.данные-произв'!$E$8*'Бюджет производства'!H$6+'Бюджет производства'!H$7*'Исх.данные-произв'!$F33+'Исх.данные-произв'!$G33*'Бюджет производства'!H$8+'Бюджет производства'!H$9*'Исх.данные-произв'!$H33 -> 0 | K32: ='Исх.данные-произв'!$C33*'Бюджет производства'!I$4+'Бюджет производства'!I$5*'Исх.данные-произв'!$D33+'Исх.данные-произв'!$E$8*'Бюджет производства'!I$6+'Бюджет производства'!I$7*'Исх.данные-произв'!$F33+'Исх.данные-произв'!$G33*'Бюджет производства'!I$8+'Бюджет производства'!I$9*'Исх.данные-произв'!$H33 -> 0 | ... O32: ='Исх.данные-произв'!$C33*'Бюджет производства'!M$4+'Бюджет производства'!M$5*'Исх.данные-произв'!$D33+'Исх.данные-произв'!$E$8*'Бюджет производства'!M$6+'Бюджет производства'!M$7*'Исх.данные-произв'!$F33+'Исх.данные-произв'!$G33*'Бюджет производства'!M$8+'Бюджет производства'!M$9*'Исх.данные-произв'!$H33 -> 0
A33: ВМ 10 | D33: ='Исх.данные-произв'!$C34*'Бюджет производства'!B$4+'Бюджет производства'!B$5*'Исх.данные-произв'!$D34+'Исх.данные-произв'!$E$8*'Бюджет производства'!B$6+'Бюджет производства'!B$7*'Исх.данные-произв'!$F34+'Исх.данные-произв'!$G34*'Бюджет производства'!B$8+'Бюджет производства'!B$9*'Исх.данные-произв'!$H34 -> 0 | E33: ='Исх.данные-произв'!$C34*'Бюджет производства'!C$4+'Бюджет производства'!C$5*'Исх.данные-произв'!$D34+'Исх.данные-произв'!$E$8*'Бюджет производства'!C$6+'Бюджет производства'!C$7*'Исх.данные-произв'!$F34+'Исх.данные-произв'!$G34*'Бюджет производства'!C$8+'Бюджет производства'!C$9*'Исх.данные-произв'!$H34 -> 0 | F33: ='Исх.данные-произв'!$C34*'Бюджет производства'!D$4+'Бюджет производства'!D$5*'Исх.данные-произв'!$D34+'Исх.данные-произв'!$E$8*'Бюджет производства'!D$6+'Бюджет производства'!D$7*'Исх.данные-произв'!$F34+'Исх.данные-произв'!$G34*'Бюджет производства'!D$8+'Бюджет производства'!D$9*'Исх.данные-произв'!$H34 -> 0 | G33: ='Исх.данные-произв'!$C34*'Бюджет производства'!E$4+'Бюджет производства'!E$5*'Исх.данные-произв'!$D34+'Исх.данные-произв'!$E$8*'Бюджет производства'!E$6+'Бюджет производства'!E$7*'Исх.данные-произв'!$F34+'Исх.данные-произв'!$G34*'Бюджет производства'!E$8+'Бюджет производства'!E$9*'Исх.данные-произв'!$H34 -> 0 | H33: ='Исх.данные-произв'!$C34*'Бюджет производства'!F$4+'Бюджет производства'!F$5*'Исх.данные-произв'!$D34+'Исх.данные-произв'!$E$8*'Бюджет производства'!F$6+'Бюджет производства'!F$7*'Исх.данные-произв'!$F34+'Исх.данные-произв'!$G34*'Бюджет производства'!F$8+'Бюджет производства'!F$9*'Исх.данные-произв'!$H34 -> 0 | I33: ='Исх.данные-произв'!$C34*'Бюджет производства'!G$4+'Бюджет производства'!G$5*'Исх.данные-произв'!$D34+'Исх.данные-произв'!$E$8*'Бюджет производства'!G$6+'Бюджет производства'!G$7*'Исх.данные-произв'!$F34+'Исх.данные-произв'!$G34*'Бюджет производства'!G$8+'Бюджет производства'!G$9*'Исх.данные-произв'!$H34 -> 0 | J33: ='Исх.данные-произв'!$C34*'Бюджет производства'!H$4+'Бюджет производства'!H$5*'Исх.данные-произв'!$D34+'Исх.данные-произв'!$E$8*'Бюджет производства'!H$6+'Бюджет производства'!H$7*'Исх.данные-произв'!$F34+'Исх.данные-произв'!$G34*'Бюджет производства'!H$8+'Бюджет производства'!H$9*'Исх.данные-произв'!$H34 -> 0 | K33: ='Исх.данные-произв'!$C34*'Бюджет производства'!I$4+'Бюджет производства'!I$5*'Исх.данные-произв'!$D34+'Исх.данные-произв'!$E$8*'Бюджет производства'!I$6+'Бюджет производства'!I$7*'Исх.данные-произв'!$F34+'Исх.данные-произв'!$G34*'Бюджет производства'!I$8+'Бюджет производства'!I$9*'Исх.данные-произв'!$H34 -> 0 | ... O33: ='Исх.данные-произв'!$C34*'Бюджет производства'!M$4+'Бюджет производства'!M$5*'Исх.данные-произв'!$D34+'Исх.данные-произв'!$E$8*'Бюджет производства'!M$6+'Бюджет производства'!M$7*'Исх.данные-произв'!$F34+'Исх.данные-произв'!$G34*'Бюджет производства'!M$8+'Бюджет производства'!M$9*'Исх.данные-произв'!$H34 -> 0
A35: Нормативные запасы материалов на складе на конец периода (с учетом оборачиваемости) | B35: оборачиваемость (дни) | C35: остаток на конец 2020 г.
A36: Основные материалы
A37: ОМ 1
A38: ОМ 2
A39: ОМ 3
A40: ОМ 4
A41: ОМ 5
A42: ОМ 6
A43: ОМ 7
A44: ОМ 8
A45: ОМ 9
A46: ОМ 10
A47: ОМ 11
... A63: ВМ 10
A65: Объем закупок сырья и материалов (в натур.выражении) | B65: ед.изм.
A66: Основные материалы | P66: =SUM(D66:O66) -> 0
A67: ОМ 1 | D67: =IF((SUM($D7:D7)-$C37+D37)<0,0,(D7-C37+D37)) -> 0 | E67: =IF((SUM($D7:E7)-$C37+E37)<0,0,(E7-D37+E37)) -> 0 | F67: =IF((SUM($D7:F7)-$C37+F37)<0,0,(F7-E37+F37)) -> 0 | G67: =IF((SUM($D7:G7)-$C37+G37)<0,0,(G7-F37+G37)) -> 0 | H67: =IF((SUM($D7:H7)-$C37+H37)<0,0,(H7-G37+H37)) -> 0 | I67: =IF((SUM($D7:I7)-$C37+I37)<0,0,(I7-H37+I37)) -> 0 | J67: =IF((SUM($D7:J7)-$C37+J37)<0,0,(J7-I37+J37)) -> 0 | K67: =IF((SUM($D7:K7)-$C37+K37)<0,0,(K7-J37+K37)) -> 0 | ... O67: =IF((SUM($D7:O7)-$C37+O37)<0,0,(O7-N37+O37)) -> 0 | P67: =SUM(D67:O67) -> 0
A68: ОМ 2 | D68: =IF((SUM($D8:D8)-$C38+D38)<0,0,(D8-C38+D38)) -> 0 | E68: =IF((SUM($D8:E8)-$C38+E38)<0,0,(E8-D38+E38)) -> 0 | F68: =IF((SUM($D8:F8)-$C38+F38)<0,0,(F8-E38+F38)) -> 0 | G68: =IF((SUM($D8:G8)-$C38+G38)<0,0,(G8-F38+G38)) -> 0 | H68: =IF((SUM($D8:H8)-$C38+H38)<0,0,(H8-G38+H38)) -> 0 | I68: =IF((SUM($D8:I8)-$C38+I38)<0,0,(I8-H38+I38)) -> 0 | J68: =IF((SUM($D8:J8)-$C38+J38)<0,0,(J8-I38+J38)) -> 0 | K68: =IF((SUM($D8:K8)-$C38+K38)<0,0,(K8-J38+K38)) -> 0 | ... O68: =IF((SUM($D8:O8)-$C38+O38)<0,0,(O8-N38+O38)) -> 0 | P68: =SUM(D68:O68) -> 0
A69: ОМ 3 | D69: =IF((SUM($D9:D9)-$C39+D39)<0,0,(D9-C39+D39)) -> 0 | E69: =IF((SUM($D9:E9)-$C39+E39)<0,0,(E9-D39+E39)) -> 0 | F69: =IF((SUM($D9:F9)-$C39+F39)<0,0,(F9-E39+F39)) -> 0 | G69: =IF((SUM($D9:G9)-$C39+G39)<0,0,(G9-F39+G39)) -> 0 | H69: =IF((SUM($D9:H9)-$C39+H39)<0,0,(H9-G39+H39)) -> 0 | I69: =IF((SUM($D9:I9)-$C39+I39)<0,0,(I9-H39+I39)) -> 0 | J69: =IF((SUM($D9:J9)-$C39+J39)<0,0,(J9-I39+J39)) -> 0 | K69: =IF((SUM($D9:K9)-$C39+K39)<0,0,(K9-J39+K39)) -> 0 | ... O69: =IF((SUM($D9:O9)-$C39+O39)<0,0,(O9-N39+O39)) -> 0 | P69: =SUM(D69:O69) -> 0
A70: ОМ 4 | D70: =IF((SUM($D10:D10)-$C40+D40)<0,0,(D10-C40+D40)) -> 0 | E70: =IF((SUM($D10:E10)-$C40+E40)<0,0,(E10-D40+E40)) -> 0 | F70: =IF((SUM($D10:F10)-$C40+F40)<0,0,(F10-E40+F40)) -> 0 | G70: =IF((SUM($D10:G10)-$C40+G40)<0,0,(G10-F40+G40)) -> 0 | H70: =IF((SUM($D10:H10)-$C40+H40)<0,0,(H10-G40+H40)) -> 0 | I70: =IF((SUM($D10:I10)-$C40+I40)<0,0,(I10-H40+I40)) -> 0 | J70: =IF((SUM($D10:J10)-$C40+J40)<0,0,(J10-I40+J40)) -> 0 | K70: =IF((SUM($D10:K10)-$C40+K40)<0,0,(K10-J40+K40)) -> 0 | ... O70: =IF((SUM($D10:O10)-$C40+O40)<0,0,(O10-N40+O40)) -> 0 | P70: =SUM(D70:O70) -> 0
A71: ОМ 5 | D71: =IF((SUM($D11:D11)-$C41+D41)<0,0,(D11-C41+D41)) -> 0 | E71: =IF((SUM($D11:E11)-$C41+E41)<0,0,(E11-D41+E41)) -> 0 | F71: =IF((SUM($D11:F11)-$C41+F41)<0,0,(F11-E41+F41)) -> 0 | G71: =IF((SUM($D11:G11)-$C41+G41)<0,0,(G11-F41+G41)) -> 0 | H71: =IF((SUM($D11:H11)-$C41+H41)<0,0,(H11-G41+H41)) -> 0 | I71: =IF((SUM($D11:I11)-$C41+I41)<0,0,(I11-H41+I41)) -> 0 | J71: =IF((SUM($D11:J11)-$C41+J41)<0,0,(J11-I41+J41)) -> 0 | K71: =IF((SUM($D11:K11)-$C41+K41)<0,0,(K11-J41+K41)) -> 0 | ... O71: =IF((SUM($D11:O11)-$C41+O41)<0,0,(O11-N41+O41)) -> 0 | P71: =SUM(D71:O71) -> 0
A72: ОМ 6 | D72: =IF((SUM($D12:D12)-$C42+D42)<0,0,(D12-C42+D42)) -> 0 | E72: =IF((SUM($D12:E12)-$C42+E42)<0,0,(E12-D42+E42)) -> 0 | F72: =IF((SUM($D12:F12)-$C42+F42)<0,0,(F12-E42+F42)) -> 0 | G72: =IF((SUM($D12:G12)-$C42+G42)<0,0,(G12-F42+G42)) -> 0 | H72: =IF((SUM($D12:H12)-$C42+H42)<0,0,(H12-G42+H42)) -> 0 | I72: =IF((SUM($D12:I12)-$C42+I42)<0,0,(I12-H42+I42)) -> 0 | J72: =IF((SUM($D12:J12)-$C42+J42)<0,0,(J12-I42+J42)) -> 0 | K72: =IF((SUM($D12:K12)-$C42+K42)<0,0,(K12-J42+K42)) -> 0 | ... O72: =IF((SUM($D12:O12)-$C42+O42)<0,0,(O12-N42+O42)) -> 0 | P72: =SUM(D72:O72) -> 0
A73: ОМ 7 | D73: =IF((SUM($D13:D13)-$C43+D43)<0,0,(D13-C43+D43)) -> 0 | E73: =IF((SUM($D13:E13)-$C43+E43)<0,0,(E13-D43+E43)) -> 0 | F73: =IF((SUM($D13:F13)-$C43+F43)<0,0,(F13-E43+F43)) -> 0 | G73: =IF((SUM($D13:G13)-$C43+G43)<0,0,(G13-F43+G43)) -> 0 | H73: =IF((SUM($D13:H13)-$C43+H43)<0,0,(H13-G43+H43)) -> 0 | I73: =IF((SUM($D13:I13)-$C43+I43)<0,0,(I13-H43+I43)) -> 0 | J73: =IF((SUM($D13:J13)-$C43+J43)<0,0,(J13-I43+J43)) -> 0 | K73: =IF((SUM($D13:K13)-$C43+K43)<0,0,(K13-J43+K43)) -> 0 | ... O73: =IF((SUM($D13:O13)-$C43+O43)<0,0,(O13-N43+O43)) -> 0 | P73: =SUM(D73:O73) -> 0
A74: ОМ 8 | D74: =IF((SUM($D14:D14)-$C44+D44)<0,0,(D14-C44+D44)) -> 0 | E74: =IF((SUM($D14:E14)-$C44+E44)<0,0,(E14-D44+E44)) -> 0 | F74: =IF((SUM($D14:F14)-$C44+F44)<0,0,(F14-E44+F44)) -> 0 | G74: =IF((SUM($D14:G14)-$C44+G44)<0,0,(G14-F44+G44)) -> 0 | H74: =IF((SUM($D14:H14)-$C44+H44)<0,0,(H14-G44+H44)) -> 0 | I74: =IF((SUM($D14:I14)-$C44+I44)<0,0,(I14-H44+I44)) -> 0 | J74: =IF((SUM($D14:J14)-$C44+J44)<0,0,(J14-I44+J44)) -> 0 | K74: =IF((SUM($D14:K14)-$C44+K44)<0,0,(K14-J44+K44)) -> 0 | ... O74: =IF((SUM($D14:O14)-$C44+O44)<0,0,(O14-N44+O44)) -> 0 | P74: =SUM(D74:O74) -> 0
A75: ОМ 9 | D75: =IF((SUM($D15:D15)-$C45+D45)<0,0,(D15-C45+D45)) -> 0 | E75: =IF((SUM($D15:E15)-$C45+E45)<0,0,(E15-D45+E45)) -> 0 | F75: =IF((SUM($D15:F15)-$C45+F45)<0,0,(F15-E45+F45)) -> 0 | G75: =IF((SUM($D15:G15)-$C45+G45)<0,0,(G15-F45+G45)) -> 0 | H75: =IF((SUM($D15:H15)-$C45+H45)<0,0,(H15-G45+H45)) -> 0 | I75: =IF((SUM($D15:I15)-$C45+I45)<0,0,(I15-H45+I45)) -> 0 | J75: =IF((SUM($D15:J15)-$C45+J45)<0,0,(J15-I45+J45)) -> 0 | K75: =IF((SUM($D15:K15)-$C45+K45)<0,0,(K15-J45+K45)) -> 0 | ... O75: =IF((SUM($D15:O15)-$C45+O45)<0,0,(O15-N45+O45)) -> 0 | P75: =SUM(D75:O75) -> 0
A76: ОМ 10 | D76: =IF((SUM($D16:D16)-$C46+D46)<0,0,(D16-C46+D46)) -> 0 | E76: =IF((SUM($D16:E16)-$C46+E46)<0,0,(E16-D46+E46)) -> 0 | F76: =IF((SUM($D16:F16)-$C46+F46)<0,0,(F16-E46+F46)) -> 0 | G76: =IF((SUM($D16:G16)-$C46+G46)<0,0,(G16-F46+G46)) -> 0 | H76: =IF((SUM($D16:H16)-$C46+H46)<0,0,(H16-G46+H46)) -> 0 | I76: =IF((SUM($D16:I16)-$C46+I46)<0,0,(I16-H46+I46)) -> 0 | J76: =IF((SUM($D16:J16)-$C46+J46)<0,0,(J16-I46+J46)) -> 0 | K76: =IF((SUM($D16:K16)-$C46+K46)<0,0,(K16-J46+K46)) -> 0 | ... O76: =IF((SUM($D16:O16)-$C46+O46)<0,0,(O16-N46+O46)) -> 0 | P76: =SUM(D76:O76) -> 0
A77: ОМ 11 | D77: =IF((SUM($D17:D17)-$C47+D47)<0,0,(D17-C47+D47)) -> 0 | E77: =IF((SUM($D17:E17)-$C47+E47)<0,0,(E17-D47+E47)) -> 0 | F77: =IF((SUM($D17:F17)-$C47+F47)<0,0,(F17-E47+F47)) -> 0 | G77: =IF((SUM($D17:G17)-$C47+G47)<0,0,(G17-F47+G47)) -> 0 | H77: =IF((SUM($D17:H17)-$C47+H47)<0,0,(H17-G47+H47)) -> 0 | I77: =IF((SUM($D17:I17)-$C47+I47)<0,0,(I17-H47+I47)) -> 0 | J77: =IF((SUM($D17:J17)-$C47+J47)<0,0,(J17-I47+J47)) -> 0 | K77: =IF((SUM($D17:K17)-$C47+K47)<0,0,(K17-J47+K47)) -> 0 | ... O77: =IF((SUM($D17:O17)-$C47+O47)<0,0,(O17-N47+O47)) -> 0 | P77: =SUM(D77:O77) -> 0
A78: ОМ 12 | D78: =IF((SUM($D18:D18)-$C48+D48)<0,0,(D18-C48+D48)) -> 0 | E78: =IF((SUM($D18:E18)-$C48+E48)<0,0,(E18-D48+E48)) -> 0 | F78: =IF((SUM($D18:F18)-$C48+F48)<0,0,(F18-E48+F48)) -> 0 | G78: =IF((SUM($D18:G18)-$C48+G48)<0,0,(G18-F48+G48)) -> 0 | H78: =IF((SUM($D18:H18)-$C48+H48)<0,0,(H18-G48+H48)) -> 0 | I78: =IF((SUM($D18:I18)-$C48+I48)<0,0,(I18-H48+I48)) -> 0 | J78: =IF((SUM($D18:J18)-$C48+J48)<0,0,(J18-I48+J48)) -> 0 | K78: =IF((SUM($D18:K18)-$C48+K48)<0,0,(K18-J48+K48)) -> 0 | ... O78: =IF((SUM($D18:O18)-$C48+O48)<0,0,(O18-N48+O48)) -> 0 | P78: =SUM(D78:O78) -> 0
... A81: ОМ 15 | D81: =IF((SUM($D21:D21)-$C51+D51)<0,0,(D21-C51+D51)) -> 0 | E81: =IF((SUM($D21:E21)-$C51+E51)<0,0,(E21-D51+E51)) -> 0 | F81: =IF((SUM($D21:F21)-$C51+F51)<0,0,(F21-E51+F51)) -> 0 | G81: =IF((SUM($D21:G21)-$C51+G51)<0,0,(G21-F51+G51)) -> 0 | H81: =IF((SUM($D21:H21)-$C51+H51)<0,0,(H21-G51+H51)) -> 0 | I81: =IF((SUM($D21:I21)-$C51+I51)<0,0,(I21-H51+I51)) -> 0 | J81: =IF((SUM($D21:J21)-$C51+J51)<0,0,(J21-I51+J51)) -> 0 | K81: =IF((SUM($D21:K21)-$C51+K51)<0,0,(K21-J51+K51)) -> 0 | ... O81: =IF((SUM($D21:O21)-$C51+O51)<0,0,(O21-N51+O51)) -> 0 | P81: =SUM(D81:O81) -> 0
D82: =IF((SUM($D22:D22)-$C52+D52)<0,0,(D22-C52+D52)) -> 0 | E82: =IF((SUM($D22:E22)-$C52+E52)<0,0,(E22-D52+E52)) -> 0 | F82: =IF((SUM($D22:F22)-$C52+F52)<0,0,(F22-E52+F52)) -> 0 | G82: =IF((SUM($D22:G22)-$C52+G52)<0,0,(G22-F52+G52)) -> 0 | H82: =IF((SUM($D22:H22)-$C52+H52)<0,0,(H22-G52+H52)) -> 0 | I82: =IF((SUM($D22:I22)-$C52+I52)<0,0,(I22-H52+I52)) -> 0 | J82: =IF((SUM($D22:J22)-$C52+J52)<0,0,(J22-I52+J52)) -> 0 | K82: =IF((SUM($D22:K22)-$C52+K52)<0,0,(K22-J52+K52)) -> 0 | ... O82: =IF((SUM($D22:O22)-$C52+O52)<0,0,(O22-N52+O52)) -> 0 | P82: =SUM(D82:O82) -> 0
A83: Вспомогательные материалы | P83: =SUM(D83:O83) -> 0
A84: ВМ 1 | D84: =IF((SUM($D24:D24)-$C54+D54)<0,0,(D24-C54+D54)) -> 0 | E84: =IF((SUM($D24:E24)-$C54+E54)<0,0,(E24-D54+E54)) -> 0 | F84: =IF((SUM($D24:F24)-$C54+F54)<0,0,(F24-E54+F54)) -> 0 | G84: =IF((SUM($D24:G24)-$C54+G54)<0,0,(G24-F54+G54)) -> 0 | H84: =IF((SUM($D24:H24)-$C54+H54)<0,0,(H24-G54+H54)) -> 0 | I84: =IF((SUM($D24:I24)-$C54+I54)<0,0,(I24-H54+I54)) -> 0 | J84: =IF((SUM($D24:J24)-$C54+J54)<0,0,(J24-I54+J54)) -> 0 | K84: =IF((SUM($D24:K24)-$C54+K54)<0,0,(K24-J54+K54)) -> 0 | ... O84: =IF((SUM($D24:O24)-$C54+O54)<0,0,(O24-N54+O54)) -> 0 | P84: =SUM(D84:O84) -> 0
A85: ВМ 2 | D85: =IF((SUM($D25:D25)-$C55+D55)<0,0,(D25-C55+D55)) -> 0 | E85: =IF((SUM($D25:E25)-$C55+E55)<0,0,(E25-D55+E55)) -> 0 | F85: =IF((SUM($D25:F25)-$C55+F55)<0,0,(F25-E55+F55)) -> 0 | G85: =IF((SUM($D25:G25)-$C55+G55)<0,0,(G25-F55+G55)) -> 0 | H85: =IF((SUM($D25:H25)-$C55+H55)<0,0,(H25-G55+H55)) -> 0 | I85: =IF((SUM($D25:I25)-$C55+I55)<0,0,(I25-H55+I55)) -> 0 | J85: =IF((SUM($D25:J25)-$C55+J55)<0,0,(J25-I55+J55)) -> 0 | K85: =IF((SUM($D25:K25)-$C55+K55)<0,0,(K25-J55+K55)) -> 0 | ... O85: =IF((SUM($D25:O25)-$C55+O55)<0,0,(O25-N55+O55)) -> 0 | P85: =SUM(D85:O85) -> 0
A86: ВМ 3 | D86: =IF((SUM($D26:D26)-$C56+D56)<0,0,(D26-C56+D56)) -> 0 | E86: =IF((SUM($D26:E26)-$C56+E56)<0,0,(E26-D56+E56)) -> 0 | F86: =IF((SUM($D26:F26)-$C56+F56)<0,0,(F26-E56+F56)) -> 0 | G86: =IF((SUM($D26:G26)-$C56+G56)<0,0,(G26-F56+G56)) -> 0 | H86: =IF((SUM($D26:H26)-$C56+H56)<0,0,(H26-G56+H56)) -> 0 | I86: =IF((SUM($D26:I26)-$C56+I56)<0,0,(I26-H56+I56)) -> 0 | J86: =IF((SUM($D26:J26)-$C56+J56)<0,0,(J26-I56+J56)) -> 0 | K86: =IF((SUM($D26:K26)-$C56+K56)<0,0,(K26-J56+K56)) -> 0 | ... O86: =IF((SUM($D26:O26)-$C56+O56)<0,0,(O26-N56+O56)) -> 0 | P86: =SUM(D86:O86) -> 0
A87: ВМ 4 | D87: =IF((SUM($D27:D27)-$C57+D57)<0,0,(D27-C57+D57)) -> 0 | E87: =IF((SUM($D27:E27)-$C57+E57)<0,0,(E27-D57+E57)) -> 0 | F87: =IF((SUM($D27:F27)-$C57+F57)<0,0,(F27-E57+F57)) -> 0 | G87: =IF((SUM($D27:G27)-$C57+G57)<0,0,(G27-F57+G57)) -> 0 | H87: =IF((SUM($D27:H27)-$C57+H57)<0,0,(H27-G57+H57)) -> 0 | I87: =IF((SUM($D27:I27)-$C57+I57)<0,0,(I27-H57+I57)) -> 0 | J87: =IF((SUM($D27:J27)-$C57+J57)<0,0,(J27-I57+J57)) -> 0 | K87: =IF((SUM($D27:K27)-$C57+K57)<0,0,(K27-J57+K57)) -> 0 | ... O87: =IF((SUM($D27:O27)-$C57+O57)<0,0,(O27-N57+O57)) -> 0 | P87: =SUM(D87:O87) -> 0
A88: ВМ 5 | D88: =IF((SUM($D28:D28)-$C58+D58)<0,0,(D28-C58+D58)) -> 0 | E88: =IF((SUM($D28:E28)-$C58+E58)<0,0,(E28-D58+E58)) -> 0 | F88: =IF((SUM($D28:F28)-$C58+F58)<0,0,(F28-E58+F58)) -> 0 | G88: =IF((SUM($D28:G28)-$C58+G58)<0,0,(G28-F58+G58)) -> 0 | H88: =IF((SUM($D28:H28)-$C58+H58)<0,0,(H28-G58+H58)) -> 0 | I88: =IF((SUM($D28:I28)-$C58+I58)<0,0,(I28-H58+I58)) -> 0 | J88: =IF((SUM($D28:J28)-$C58+J58)<0,0,(J28-I58+J58)) -> 0 | K88: =IF((SUM($D28:K28)-$C58+K58)<0,0,(K28-J58+K58)) -> 0 | ... O88: =IF((SUM($D28:O28)-$C58+O58)<0,0,(O28-N58+O58)) -> 0 | P88: =SUM(D88:O88) -> 0
A89: ВМ 6 | D89: =IF((SUM($D29:D29)-$C59+D59)<0,0,(D29-C59+D59)) -> 0 | E89: =IF((SUM($D29:E29)-$C59+E59)<0,0,(E29-D59+E59)) -> 0 | F89: =IF((SUM($D29:F29)-$C59+F59)<0,0,(F29-E59+F59)) -> 0 | G89: =IF((SUM($D29:G29)-$C59+G59)<0,0,(G29-F59+G59)) -> 0 | H89: =IF((SUM($D29:H29)-$C59+H59)<0,0,(H29-G59+H59)) -> 0 | I89: =IF((SUM($D29:I29)-$C59+I59)<0,0,(I29-H59+I59)) -> 0 | J89: =IF((SUM($D29:J29)-$C59+J59)<0,0,(J29-I59+J59)) -> 0 | K89: =IF((SUM($D29:K29)-$C59+K59)<0,0,(K29-J59+K59)) -> 0 | ... O89: =IF((SUM($D29:O29)-$C59+O59)<0,0,(O29-N59+O59)) -> 0 | P89: =SUM(D89:O89) -> 0
A90: ВМ 7 | D90: =IF((SUM($D30:D30)-$C60+D60)<0,0,(D30-C60+D60)) -> 0 | E90: =IF((SUM($D30:E30)-$C60+E60)<0,0,(E30-D60+E60)) -> 0 | F90: =IF((SUM($D30:F30)-$C60+F60)<0,0,(F30-E60+F60)) -> 0 | G90: =IF((SUM($D30:G30)-$C60+G60)<0,0,(G30-F60+G60)) -> 0 | H90: =IF((SUM($D30:H30)-$C60+H60)<0,0,(H30-G60+H60)) -> 0 | I90: =IF((SUM($D30:I30)-$C60+I60)<0,0,(I30-H60+I60)) -> 0 | J90: =IF((SUM($D30:J30)-$C60+J60)<0,0,(J30-I60+J60)) -> 0 | K90: =IF((SUM($D30:K30)-$C60+K60)<0,0,(K30-J60+K60)) -> 0 | ... O90: =IF((SUM($D30:O30)-$C60+O60)<0,0,(O30-N60+O60)) -> 0 | P90: =SUM(D90:O90) -> 0
A91: ВМ 8 | D91: =IF((SUM($D31:D31)-$C61+D61)<0,0,(D31-C61+D61)) -> 0 | E91: =IF((SUM($D31:E31)-$C61+E61)<0,0,(E31-D61+E61)) -> 0 | F91: =IF((SUM($D31:F31)-$C61+F61)<0,0,(F31-E61+F61)) -> 0 | G91: =IF((SUM($D31:G31)-$C61+G61)<0,0,(G31-F61+G61)) -> 0 | H91: =IF((SUM($D31:H31)-$C61+H61)<0,0,(H31-G61+H61)) -> 0 | I91: =IF((SUM($D31:I31)-$C61+I61)<0,0,(I31-H61+I61)) -> 0 | J91: =IF((SUM($D31:J31)-$C61+J61)<0,0,(J31-I61+J61)) -> 0 | K91: =IF((SUM($D31:K31)-$C61+K61)<0,0,(K31-J61+K61)) -> 0 | ... O91: =IF((SUM($D31:O31)-$C61+O61)<0,0,(O31-N61+O61)) -> 0 | P91: =SUM(D91:O91) -> 0
A92: ВМ 9 | D92: =IF((SUM($D32:D32)-$C62+D62)<0,0,(D32-C62+D62)) -> 0 | E92: =IF((SUM($D32:E32)-$C62+E62)<0,0,(E32-D62+E62)) -> 0 | F92: =IF((SUM($D32:F32)-$C62+F62)<0,0,(F32-E62+F62)) -> 0 | G92: =IF((SUM($D32:G32)-$C62+G62)<0,0,(G32-F62+G62)) -> 0 | H92: =IF((SUM($D32:H32)-$C62+H62)<0,0,(H32-G62+H62)) -> 0 | I92: =IF((SUM($D32:I32)-$C62+I62)<0,0,(I32-H62+I62)) -> 0 | J92: =IF((SUM($D32:J32)-$C62+J62)<0,0,(J32-I62+J62)) -> 0 | K92: =IF((SUM($D32:K32)-$C62+K62)<0,0,(K32-J62+K62)) -> 0 | ... O92: =IF((SUM($D32:O32)-$C62+O62)<0,0,(O32-N62+O62)) -> 0 | P92: =SUM(D92:O92) -> 0
A93: ВМ 10 | D93: =IF((SUM($D33:D33)-$C63+D63)<0,0,(D33-C63+D63)) -> 0 | E93: =IF((SUM($D33:E33)-$C63+E63)<0,0,(E33-D63+E63)) -> 0 | F93: =IF((SUM($D33:F33)-$C63+F63)<0,0,(F33-E63+F63)) -> 0 | G93: =IF((SUM($D33:G33)-$C63+G63)<0,0,(G33-F63+G63)) -> 0 | H93: =IF((SUM($D33:H33)-$C63+H63)<0,0,(H33-G63+H63)) -> 0 | I93: =IF((SUM($D33:I33)-$C63+I63)<0,0,(I33-H63+I63)) -> 0 | J93: =IF((SUM($D33:J33)-$C63+J63)<0,0,(J33-I63+J63)) -> 0 | K93: =IF((SUM($D33:K33)-$C63+K63)<0,0,(K33-J63+K63)) -> 0 | ... O93: =IF((SUM($D33:O33)-$C63+O63)<0,0,(O33-N63+O63)) -> 0 | P93: =SUM(D93:O93) -> 0
D94: =IF((SUM($D34:D34)-$C64+D64)<0,0,(D34-C64+D64)) -> 0 | E94: =IF((SUM($D34:E34)-$C64+E64)<0,0,(E34-D64+E64)) -> 0 | F94: =IF((SUM($D34:F34)-$C64+F64)<0,0,(F34-E64+F64)) -> 0 | G94: =IF((SUM($D34:G34)-$C64+G64)<0,0,(G34-F64+G64)) -> 0 | H94: =IF((SUM($D34:H34)-$C64+H64)<0,0,(H34-G64+H64)) -> 0 | I94: =IF((SUM($D34:I34)-$C64+I64)<0,0,(I34-H64+I64)) -> 0 | J94: =IF((SUM($D34:J34)-$C64+J64)<0,0,(J34-I64+J64)) -> 0 | K94: =IF((SUM($D34:K34)-$C64+K64)<0,0,(K34-J64+K64)) -> 0 | ... O94: =IF((SUM($D34:O34)-$C64+O64)<0,0,(O34-N64+O64)) -> 0 | P94: =SUM(D94:O94) -> 0
A95: Объем закупок сырья и материалов (в натур.выражении) - партия | B95: ед.изм. | C95: мин.партия закупки
A96: Основные материалы
A97: ОМ 1
A98: ОМ 2
A99: ОМ 3
A100: ОМ 4
A101: ОМ 5
A102: ОМ 6
A103: ОМ 7
A104: ОМ 8
A105: ОМ 9
A106: ОМ 10
A107: ОМ 11
... A123: ВМ 10
A125: Объем закупок сырья и материалов, руб. | B125: ед.изм. | C125: стоимость, руб.
A126: Основные материалы
A127: ОМ 1 | D127: =D67*$C$127/1000 -> 0 | E127: =E67*$C$127/1000 -> 0 | F127: =F67*$C$127/1000 -> 0 | G127: =G67*$C$127/1000 -> 0 | H127: =H67*$C$127/1000 -> 0 | I127: =I67*$C$127/1000 -> 0 | J127: =J67*$C$127/1000 -> 0 | K127: =K67*$C$127/1000 -> 0 | ... O127: =O67*$C$127/1000 -> 0
A128: ОМ 2 | D128: =D68*$C$127/1000 -> 0 | E128: =E68*$C$127/1000 -> 0 | F128: =F68*$C$127/1000 -> 0 | G128: =G68*$C$127/1000 -> 0 | H128: =H68*$C$127/1000 -> 0 | I128: =I68*$C$127/1000 -> 0 | J128: =J68*$C$127/1000 -> 0 | K128: =K68*$C$127/1000 -> 0 | ... O128: =O68*$C$127/1000 -> 0
A129: ОМ 3 | D129: =D69*$C$127/1000 -> 0 | E129: =E69*$C$127/1000 -> 0 | F129: =F69*$C$127/1000 -> 0 | G129: =G69*$C$127/1000 -> 0 | H129: =H69*$C$127/1000 -> 0 | I129: =I69*$C$127/1000 -> 0 | J129: =J69*$C$127/1000 -> 0 | K129: =K69*$C$127/1000 -> 0 | ... O129: =O69*$C$127/1000 -> 0
A130: ОМ 4 | D130: =D70*$C$127/1000 -> 0 | E130: =E70*$C$127/1000 -> 0 | F130: =F70*$C$127/1000 -> 0 | G130: =G70*$C$127/1000 -> 0 | H130: =H70*$C$127/1000 -> 0 | I130: =I70*$C$127/1000 -> 0 | J130: =J70*$C$127/1000 -> 0 | K130: =K70*$C$127/1000 -> 0 | ... O130: =O70*$C$127/1000 -> 0
A131: ОМ 5 | D131: =D71*$C$127/1000 -> 0 | E131: =E71*$C$127/1000 -> 0 | F131: =F71*$C$127/1000 -> 0 | G131: =G71*$C$127/1000 -> 0 | H131: =H71*$C$127/1000 -> 0 | I131: =I71*$C$127/1000 -> 0 | J131: =J71*$C$127/1000 -> 0 | K131: =K71*$C$127/1000 -> 0 | ... O131: =O71*$C$127/1000 -> 0
A132: ОМ 6 | D132: =D72*$C$127/1000 -> 0 | E132: =E72*$C$127/1000 -> 0 | F132: =F72*$C$127/1000 -> 0 | G132: =G72*$C$127/1000 -> 0 | H132: =H72*$C$127/1000 -> 0 | I132: =I72*$C$127/1000 -> 0 | J132: =J72*$C$127/1000 -> 0 | K132: =K72*$C$127/1000 -> 0 | ... O132: =O72*$C$127/1000 -> 0
A133: ОМ 7 | D133: =D73*$C$127/1000 -> 0 | E133: =E73*$C$127/1000 -> 0 | F133: =F73*$C$127/1000 -> 0 | G133: =G73*$C$127/1000 -> 0 | H133: =H73*$C$127/1000 -> 0 | I133: =I73*$C$127/1000 -> 0 | J133: =J73*$C$127/1000 -> 0 | K133: =K73*$C$127/1000 -> 0 | ... O133: =O73*$C$127/1000 -> 0
A134: ОМ 8 | D134: =D74*$C$127/1000 -> 0 | E134: =E74*$C$127/1000 -> 0 | F134: =F74*$C$127/1000 -> 0 | G134: =G74*$C$127/1000 -> 0 | H134: =H74*$C$127/1000 -> 0 | I134: =I74*$C$127/1000 -> 0 | J134: =J74*$C$127/1000 -> 0 | K134: =K74*$C$127/1000 -> 0 | ... O134: =O74*$C$127/1000 -> 0
A135: ОМ 9 | D135: =D75*$C$127/1000 -> 0 | E135: =E75*$C$127/1000 -> 0 | F135: =F75*$C$127/1000 -> 0 | G135: =G75*$C$127/1000 -> 0 | H135: =H75*$C$127/1000 -> 0 | I135: =I75*$C$127/1000 -> 0 | J135: =J75*$C$127/1000 -> 0 | K135: =K75*$C$127/1000 -> 0 | ... O135: =O75*$C$127/1000 -> 0
A136: ОМ 10 | D136: =D76*$C$127/1000 -> 0 | E136: =E76*$C$127/1000 -> 0 | F136: =F76*$C$127/1000 -> 0 | G136: =G76*$C$127/1000 -> 0 | H136: =H76*$C$127/1000 -> 0 | I136: =I76*$C$127/1000 -> 0 | J136: =J76*$C$127/1000 -> 0 | K136: =K76*$C$127/1000 -> 0 | ... O136: =O76*$C$127/1000 -> 0
A137: ОМ 11 | D137: =D77*$C$127/1000 -> 0 | E137: =E77*$C$127/1000 -> 0 | F137: =F77*$C$127/1000 -> 0 | G137: =G77*$C$127/1000 -> 0 | H137: =H77*$C$127/1000 -> 0 | I137: =I77*$C$127/1000 -> 0 | J137: =J77*$C$127/1000 -> 0 | K137: =K77*$C$127/1000 -> 0 | ... O137: =O77*$C$127/1000 -> 0
A138: ОМ 12 | D138: =D78*$C$127/1000 -> 0 | E138: =E78*$C$127/1000 -> 0 | F138: =F78*$C$127/1000 -> 0 | G138: =G78*$C$127/1000 -> 0 | H138: =H78*$C$127/1000 -> 0 | I138: =I78*$C$127/1000 -> 0 | J138: =J78*$C$127/1000 -> 0 | K138: =K78*$C$127/1000 -> 0 | ... O138: =O78*$C$127/1000 -> 0
...

Sheet Исх.данные-произв
A1: Исходные данные для планирования
A3: Нормы расхода материалов на единицу
A5: Наименование | B5: Единица измерения | C5: Наименование продукции
C6: Продукт 1 | D6: Продукт 2 | E6: Продукт 3 | F6: Продукт 4 | G6: Продукт 5
A7: Основные материалы
A8: ОМ 1 | B8: шт.
A9: ОМ 2 | B9: шт.
A10: ОМ 3 | B10: шт.
A11: ОМ 4 | B11: шт.
A12: ОМ 5 | B12: шт.
A13: ОМ 6 | B13: шт.
A14: ОМ 7 | B14: шт.
A15: ОМ 8 | B15: шт.
A16: ОМ 9 | B16: шт.
A17: ОМ 10 | B17: шт.
A18: ОМ 11 | B18: шт.
A19: ОМ 12 | B19: шт.
... A22: ОМ 15 | B22: шт.
B23: шт.
A24: Вспомогательные материалы
A25: ВМ 1 | B25: шт.
A26: ВМ 2 | B26: шт.
A27: ВМ 3 | B27: шт.
A28: ВМ 4 | B28: шт.
A29: ВМ 5 | B29: шт.
A30: ВМ 6 | B30: шт.
A31: ВМ 7 | B31: шт.
A32: ВМ 8 | B32: шт.
A33: ВМ 9 | B33: шт.
A34: ВМ 10 | B34: шт.
A37: Цены на ТМЦ, с НДС
A38: (цены на ресурсы без учета транспортных расходов)
A39: Наименование | B39: Единица измерения | C39: янв | D39: фев | E39: мар | F39: апр | G39: май | H39: июн | I39: июл | J39: авг | K39: сен | L39: окт | M39: ноя | N39: дек
A41: Основные материалы
A42: ОМ 1
A43: ОМ 2
A44: ОМ 3
A45: ОМ 4
A46: ОМ 5
A47: ОМ 6
A48: ОМ 7
A49: ОМ 8
A50: ОМ 9
A51: ОМ 10
A52: ОМ 11
... A70: З/плата производственного персонала
A72: Наименование статьи | B72: янв | C72: фев | D72: мар | E72: апр | F72: май | G72: июн | H72: июл | I72: авг | J72: сен | K72: окт | L72: ноя | M72: дек
A73: ШАГ № 1:ВВОД ИСХОДНОЙ ИНФОРМАЦИИ
A74: Численность производственного персонала, чел. | B74: =SUM(B75:B89) -> 0 | C74: =SUM(C75:C89) -> 0 | D74: =SUM(D75:D89) -> 0 | E74: =SUM(E75:E89) -> 0 | F74: =SUM(F75:F89) -> 0 | G74: =SUM(G75:G89) -> 0 | H74: =SUM(H75:H89) -> 0 | I74: =SUM(I75:I89) -> 0 | ... M74: =SUM(M75:M89) -> 0 | N74: =SUM(N75:N88) -> 0 | S74: =SUM(S75:S88) -> 0
A90: Зарплата производственного персонала, руб / чел. | B90: янв | C90: фев | D90: мар | E90: апр | F90: май | G90: июн | H90: июл | I90: авг | J90: сен | K90: окт | L90: ноя | M90: дек
B136: =SUM(B75*B91,B94*B76,B77*B97,B100*B78,B79*B103,B81*B109,B82*B112,B83*B115,B84*B118,B121*B85,B86*B124,B127*B87,B88*B130,B133*B89)-'ФОТ'!C63 -> 0 | C136: =SUM(C75*C91,C94*C76,C77*C97,C100*C78,C79*C103,C81*C109,C82*C112,C83*C115,C84*C118,C121*C85,C86*C124,C127*C87,C88*C130,C133*C89)-'ФОТ'!D63 -> 0 | D136: =SUM(D75*D91,D94*D76,D77*D97,D100*D78,D79*D103,D81*D109,D82*D112,D83*D115,D84*D118,D121*D85,D86*D124,D127*D87,D88*D130,D133*D89)-'ФОТ'!E63 -> 0 | E136: =SUM(E75*E91,E94*E76,E77*E97,E100*E78,E79*E103,E81*E109,E82*E112,E83*E115,E84*E118,E121*E85,E86*E124,E127*E87,E88*E130,E133*E89)-'ФОТ'!F63 -> 0 | F136: =SUM(F75*F91,F94*F76,F77*F97,F100*F78,F79*F103,F81*F109,F82*F112,F83*F115,F84*F118,F121*F85,F86*F124,F127*F87,F88*F130,F133*F89)-'ФОТ'!G63 -> 0 | G136: =SUM(G75*G91,G94*G76,G77*G97,G100*G78,G79*G103,G81*G109,G82*G112,G83*G115,G84*G118,G121*G85,G86*G124,G127*G87,G88*G130,G133*G89)-'ФОТ'!H63 -> 0 | H136: =SUM(H75*H91,H94*H76,H77*H97,H100*H78,H79*H103,H81*H109,H82*H112,H83*H115,H84*H118,H121*H85,H86*H124,H127*H87,H88*H130,H133*H89)-'ФОТ'!I63 -> 0 | I136: =SUM(I75*I91,I94*I76,I77*I97,I100*I78,I79*I103,I81*I109,I82*I112,I83*I115,I84*I118,I121*I85,I86*I124,I127*I87,I88*I130,I133*I89)-'ФОТ'!J63 -> 0 | ... M136: =SUM(M75*M91,M94*M76,M77*M97,M100*M78,M79*M103,M81*M109,M82*M112,M83*M115,M84*M118,M121*M85,M86*M124,M127*M87,M88*M130,M133*M89)-'ФОТ'!N63 -> 0

Sheet Бюджет коммер. расходов
A1: Бюджет коммерческих расходов 2021
A2: Наименование статьи | B2: янв | C2: фев | D2: мар | E2: апр | F2: май | G2: июн | H2: июл | I2: авг | J2: сен | K2: окт | L2: ноя | M2: дек | N2: ГОД
A3: ШАГ № 1:ВВОД ИСХОДНОЙ ИНФОРМАЦИИ
A4: Реклама сайта | B4: =B11*B16 -> 0 | C4: =C11*C16 -> 0 | D4: =D11*D16 -> 0 | E4: =E11*E16 -> 0 | F4: =F11*F16 -> 0 | G4: =G11*G16 -> 0 | H4: =H11*H16 -> 0 | I4: =I11*I16 -> 0 | ... N4: =N11*N16 -> 0
A5: Таргетированная реклама
A6: Заходы на сайт
A7: Процент роста количества посещений
A8: Коэффициент сезонности
A9: Заходы на сайт с учетом коэффициента сезонности
A10: CV1 (конверсия сайта)
A11: лиды
A12: CV2 (конверсия в сделку)
A13: оформленные сделки
A14: CV3 (конверсия в оплату)
A15: Оплаченные заказы
A16: Стоимость лида
... A42: Рекламная Кампания 3
A54: ИТОГО расходы на рекламу | B54: =B4+B19+B42 -> 0 | C54: =C4+C19+C42 -> 0 | D54: =D4+D19+D42 -> 0 | E54: =E4+E19+E42 -> 0 | F54: =F4+F19+F42 -> 0 | G54: =G4+G19+G42 -> 0 | H54: =H4+H19+H42 -> 0 | I54: =I4+I19+I42 -> 0 | ... N54: =N4+N19+N42 -> 0
A57: БДДС / коммерческие расходы 2021 (с НДС)
A58: Наименование статьи | B58: янв | C58: фев | D58: мар | E58: апр | F58: май | G58: июн | H58: июл | I58: авг | J58: сен | K58: окт | L58: ноя | M58: дек | N58: ГОД
A59: ШАГ № 1:ВВОД ИСХОДНОЙ ИНФОРМАЦИИ
A60: Реклама сайта
A61: Рекламная Кампания 2
A62: Рекламная Кампания 3
A63: ИТОГО оплаты рекламы | B63: =B60+B61+B62 -> 0 | C63: =C60+C61+C62 -> 0 | D63: =D60+D61+D62 -> 0 | E63: =E60+E61+E62 -> 0 | F63: =F60+F61+F62 -> 0 | G63: =G60+G61+G62 -> 0 | H63: =H60+H61+H62 -> 0 | I63: =I60+I61+I62 -> 0 | ... N63: =N60+N61+N62 -> 0

Sheet Бюджет производственных расходо
A1: Бюджет производственных расходов 2021г
A2: Наименование статьи | B2: янв | C2: фев | D2: мар | E2: апр | F2: май | G2: июн | H2: июл | I2: авг | J2: сен | K2: окт | L2: ноя | M2: дек | N2: ГОД
A3: ШАГ № 1:ВВОД ИСХОДНОЙ ИНФОРМАЦИИ
A4: Прямые материальные расходы | B4: =B5+B6+B7 -> 0 | C4: =C5+C6+C7 -> 0 | D4: =D5+D6+D7 -> 0 | E4: =E5+E6+E7 -> 0 | F4: =F5+F6+F7 -> 0 | G4: =G5+G6+G7 -> 0 | H4: =H5+H6+H7 -> 0 | I4: =I5+I6+I7 -> 0 | ... N4: =N5+N6+N7 -> 0
A5: Основные материалы | N5: =B5+C5+D5+E5+F5+G5+H5+I5+J5+K5+L5+M5 -> 0
A6: Вспомогателные материалы | N6: =B6+C6+D6+E6+F6+G6+H6+I6+J6+K6+L6+M6 -> 0
A8: Содержание зданий | B8: =B9+B13+B14+B15 -> 0 | C8: =C9+C13+C14+C15 -> 0 | D8: =D9+D13+D14+D15 -> 0 | E8: =E9+E13+E14+E15 -> 0 | F8: =F9+F13+F14+F15 -> 0 | G8: =G9+G13+G14+G15 -> 0 | H8: =H9+H13+H14+H15 -> 0 | I8: =I9+I13+I14+I15 -> 0 | ... M8: =M9+M13+M14+M15 -> 0 | N8: =B8+C8+D8+E8+F8+G8+H8+I8+J8+K8+L8+M8 -> 0
A9: Аренда | B9: =B10 -> 0 | C9: =C10 -> 0 | D9: =D10 -> 0 | E9: =E10 -> 0 | F9: =F10 -> 0 | G9: =G10 -> 0 | H9: =H10 -> 0 | I9: =I10 -> 0 | ... N9: =N10 -> 0
A10: помещение 1 | B10: =(B11*B12)/1000 -> 0 | C10: =(C11*C12)/1000 -> 0 | D10: =(D11*D12)/1000 -> 0 | E10: =(E11*E12)/1000 -> 0 | F10: =(F11*F12)/1000 -> 0 | G10: =(G11*G12)/1000 -> 0 | H10: =(H11*H12)/1000 -> 0 | I10: =(I11*I12)/1000 -> 0 | ... M10: =(M11*M12)/1000 -> 0 | N10: =B10+C10+D10+E10+F10+G10+H10+I10+J10+K10+L10+M10 -> 0
A11: площадь
A12: стоимость 1 кв.м, руб.
A13: Коммунальные расходы | N13: =B13+C13+D13+E13+F13+G13+H13+I13+J13+K13+L13+M13 -> 0
A14: Охрана помещений | N14: =B14+C14+D14+E14+F14+G14+H14+I14+J14+K14+L14+M14 -> 0
A15: Ремонт помещений | N15: =B15+C15+D15+E15+F15+G15+H15+I15+J15+K15+L15+M15 -> 0
A16: Транспортные расходы | B16: =B17+B19 -> 0 | C16: =C17+C19 -> 0 | D16: =D17+D19 -> 0 | E16: =E17+E19 -> 0 | F16: =F17+F19 -> 0 | G16: =G17+G19 -> 0 | H16: =H17+H19 -> 0 | I16: =I17+I19 -> 0 | ... M16: =M17+M19 -> 0 | N16: =B16+C16+D16+E16+F16+G16+H16+I16+J16+K16+L16+M16 -> 0
A17: ГСМ | N17: =B17+C17+D17+E17+F17+G17+H17+I17+J17+K17+L17+M17 -> 0
A18: Содержание транспорта
A19: Прочие транспортные расходы | N19: =B19+C19+D19+E19+F19+G19+H19+I19+J19+K19+L19+M19 -> 0
A20: Расходы на содержание оборудования | B20: =B21+B22 -> 0 | C20: =C21+C22 -> 0 | D20: =D21+D22 -> 0 | E20: =E21+E22 -> 0 | F20: =F21+F22 -> 0 | G20: =G21+G22 -> 0 | H20: =H21+H22 -> 0 | I20: =I21+I22 -> 0 | ... N20: =N21+N22 -> 0
A21: Обслуживание оборудования | N21: =B21+C21+D21+E21+F21+G21+H21+I21+J21+K21+L21+M21 -> 0
A22: Ремонт оборудования | N22: =B22+C22+D22+E22+F22+G22+H22+I22+J22+K22+L22+M22 -> 0
A23: Расходы на персонал
A24: обучение сотрудников
A25: подбор персонала
A26: прочие расходы на персонал
A27: Прочие производственые расходы расходы | B27: =B28+B29+B30+B31 -> 0 | C27: =C28+C29+C30+C31 -> 0 | D27: =D28+D29+D30+D31 -> 0 | E27: =E28+E29+E30+E31 -> 0 | F27: =F28+F29+F30+F31 -> 0 | G27: =G28+G29+G30+G31 -> 0 | H27: =H28+H29+H30+H31 -> 0 | I27: =I28+I29+I30+I31 -> 0 | ... M27: =M28+M29+M30+M31 -> 0 | N27: =B27+C27+D27+E27+F27+G27+H27+I27+J27+K27+L27+M27 -> 0
A32: Спецодежда
A33: Амортизация ОС и НМА | B33: =B34+B35 -> 0 | C33: =C34+C35 -> 0 | D33: =D34+D35 -> 0 | E33: =E34+E35 -> 0 | F33: =F34+F35 -> 0 | G33: =G34+G35 -> 0 | H33: =H34+H35 -> 0 | I33: =I34+I35 -> 0 | ... M33: =M34+M35 -> 0 | N33: =B33+C33+D33+E33+F33+G33+H33+I33+J33+K33+L33+M33 -> 0
A34: Амортизация ОС | B34: ='Инвест_бюджет'!B675 | C34: ='Инвест_бюджет'!C675 | D34: ='Инвест_бюджет'!D675 | E34: ='Инвест_бюджет'!E675 | F34: ='Инвест_бюджет'!F675 | G34: ='Инвест_бюджет'!G675 | H34: ='Инвест_бюджет'!H675 | I34: ='Инвест_бюджет'!I675 | ... M34: ='Инвест_бюджет'!M675 | N34: =B34+C34+D34+E34+F34+G34+H34+I34+J34+K34+L34+M34 -> 0
A35: Списание МПЗ | B35: ='Инвест_бюджет'!B676 | C35: ='Инвест_бюджет'!C676 | D35: ='Инвест_бюджет'!D676 | E35: ='Инвест_бюджет'!E676 | F35: ='Инвест_бюджет'!F676 | G35: ='Инвест_бюджет'!G676 | H35: ='Инвест_бюджет'!H676 | I35: ='Инвест_бюджет'!I676 | ... M35: ='Инвест_бюджет'!M676 | N35: =B35+C35+D35+E35+F35+G35+H35+I35+J35+K35+L35+M35 -> 0
A36: Итого админ-управл.расходов, тыс.руб | B36: =B4+B8+B16+B20+B27+B33+B32 -> 0 | C36: =C4+C8+C16+C20+C27+C33+C32 -> 0 | D36: =D4+D8+D16+D20+D27+D33+D32 -> 0 | E36: =E4+E8+E16+E20+E27+E33+E32 -> 0 | F36: =F4+F8+F16+F20+F27+F33+F32 -> 0 | G36: =G4+G8+G16+G20+G27+G33+G32 -> 0 | H36: =H4+H8+H16+H20+H27+H33+H32 -> 0 | I36: =I4+I8+I16+I20+I27+I33+I32 -> 0 | ... N36: =N4+N8+N16+N20+N27+N33+N32 -> 0
A40: БДДС / производственных расходов 2021 г.
A41: Наименование статьи | B41: янв | C41: фев | D41: мар | E41: апр | F41: май | G41: июн | H41: июл | I41: авг | J41: сен | K41: окт | L41: ноя | M41: дек | N41: ГОД
