Workbook

Sheet Регламент
A2: Название документа: | B2: План доходов и расходов | F2: Дата формирования регламента
A3: Цель документа: | B3: Запланировать цели компании по доходам и расходам на определенный период. Оценить точность планирования и выявить причины отклонений. | F3: Дата изменения
A4: Результат отчета: | B4: Точность планирования чистой прибыли 80%-120% | F4: Дата изменения
A5: Платформа ведения: | B5: Гугл-таблицы
A8: Ответственный за ведение и проверку документа:
A9: ФИО/ Перенести в чек-лист | B9: Должность | C9: Какую часть информации заполняют/ Перенести в чек-лист | D9: Источник информации | E9: До какого срока должен быть заполнен документ за месяц/ Перенести дату в чек-лист | F9: За какой срок заполняется документ | G9: Комментарий
C10: 1. Своевременный сбор отчета 2. Проверка актуальности внесенной информации 3. Проверка правильности формирования документа 4. Резервное копирование документа
A13: Ответственные за заполнение документа:
A14: ФИО/При необходимости перенести в чек-лист | B14: Должность | C14: Какую часть информации заполняют/При необходимости перенести в чек-лист | D14: Источник информации | E14: До какого срока должен быть заполнен документ за месяц /При необходимости перенести в чек-лист | F14: За какой срок заполняется документ | G14: Комментарий
A19: Риски, которые могут сорвать сроки отчетности, и способы их решения
A20: Риск | C20: Выход из этого риска
A21: Ответственный за заполнение/ Ответственный за ведение документа уходит в отпуск | C21: Передача полномочий другому ответственному лицу (ФИО лица) на срок отпуска. / Срок сдачи отчетности переносится.
A22: Ответственный за заполнение/ Ответственный за ведение документа заболел | C22: Передача полномочий другому ответственному лицу (ФИО лица). / Срок сдачи отчетности переносится.
A23: Технический сбой | C23: Раз в месяц после презентации отчета создается резервное копирование отчетности в рабочее пространство клиента.
A24: Увольнение ответственного сотрудника | C24: Сотрудник должен передать документ в рабочем состоянии с актуальными данными, зафиксировать дату передачи.
A25: Нарушен срок заполнения отчета | C25: Информировать ответственных сотрудников о сроках заполнения отчета. Добиваться согласия ответственных лиц по срокам заполнения отчета.
A27: Правила работы с документом
A28: Название листа | B28: Описание
A29: Вкладка: Справочник | B29: Заполняется в самом начале работы с документом.
B30: Столбец А - Внести вид расходов
B31: Столбец С - Внести блоки ОПиУ
B32: Столбец D - Внести информацию по направлениям бизнеса
A34: Вкладка: Статьи | B34: Заполняется в самом начале работы с документом
B35: Заполняется только при необходимости добавить статью по согласованию с ответственным за ведение документа
B36: Столбец А - Внести наименование статьи
B37: Столбец В - Внести тип/категорию статьи
B38: Столбец С - Внести информацию об источниках информации
B39: Столбец D - Внести полное описание статьи
B40: Столбец F и далее - Внести отметку если статья относится к данному направлению
B41: ВАЖНО! При добавление статьи подробно расписывать структуру расходов или доходов, а также указать источник откуда берем информацию
A42: Вкладка:1,2,3,4,5,6,7,8,9,1,12 | B42: Рабочий документ. Данные заносятся ежемесячно
B43: Столбец B - Автоматически заполняются блоки ОПиУ из вкладки Статьи
B44: Столбец А - Автоматически отображаются источники информации статей
B45: Столбцы С-H - Внести информацию по фактическим расходам по направлениям
B46: Столбец I - Автоматически рассчитывается сумма по всем направлениям
B47: Столбцы J-O - Внести информацию по плановым расходам по направлениям
B48: Столбец P - Автоматически рассчитывается сумма по всем направлениям
B49: Столбцы Q-S - Автоматически рассчитывается отклонение от плана
B50: Важно! До 5 числа месяца следующего за отчетным: в столбцах "C", "D" (Факт) заносятся фактические данные за отчетный месяц (например: до 5 февраля заполняем Факт за январь)
B51: Важно! До 30 числа текущего месяца: в столбцах "N", "O" (План) заносятся плановые данные на следующий за отчетным месяц (например до 30 января заполняем план на февраль)
A53: Вкладка: Факт | B53: Собирается автоматически!
A55: Вкладка: Факт Анализ | B55: Собирается автоматически!
A57: Вкладка: План | B57: Собирается автоматически!
A59: Вкладка: Факт/План | B59: Собирается автоматически!
A61: Вкладка: Графики | B61: Собирается автоматически!
A64: Необходимые дополнительные инструменты:
A65: Наименование | C65: Внедрен/нет | D65: Ответственный за ведение и проверку | E65: Срок заполнения
A66: ОПиУ | C66: FALSE
C67: FALSE
C68: FALSE
C69: FALSE
C70: FALSE
C71: FALSE
C72: FALSE
C73: FALSE
A76: Реестр ознакомления
A77: ФИО | B77: Дата

Sheet Статьи
A1: Наименование статьи | B1: Тип | C1: Источник информации | D1: Описание статьи | E1: Проверка на распределение по направлениям только прямых расходов | F1: {=TRANSPOSE('Справочник'!D2:D10)} -> ООО "Весело живем" | G1: ООО "Некогда грустить" | H1: 3 | I1: 4 | J1: 5 | K1: 6 | L1: 7 | M1: 8 | N1: 9
A2: Выручка от аренды машиноместа | B2: Выручка | C2: 1С сч 90.01 убрать НДС! | E2: =if(and(OR(B2="Косвенные административные",B2="Косвенные коммерческие",B2="Расходы ниже EBITDA"),COUNTIF(F2:N2,TRUE)>0),"По направлениям распредляются только прямые расходы!","ОК") -> ОК | F2: FALSE | G2: FALSE | H2: FALSE | I2: FALSE | J2: FALSE | K2: FALSE | L2: FALSE | M2: FALSE | N2: FALSE
A3: Выручка за грузоперевозки | B3: Выручка | C3: 1С сч 90.01 убрать НДС! | E3: =if(and(OR(B3="Косвенные административные",B3="Косвенные коммерческие",B3="Расходы ниже EBITDA"),COUNTIF(F3:N3,TRUE)>0),"По направлениям распредляются только прямые расходы!","ОК") -> ОК | F3: FALSE | G3: FALSE | H3: FALSE | I3: FALSE | J3: FALSE | K3: FALSE | L3: FALSE | M3: FALSE | N3: FALSE
E4: =if(and(OR(B4="Косвенные административные",B4="Косвенные коммерческие",B4="Расходы ниже EBITDA"),COUNTIF(F4:N4,TRUE)>0),"По направлениям распредляются только прямые расходы!","ОК") -> ОК | F4: FALSE | G4: FALSE | H4: FALSE | I4: FALSE | J4: FALSE | K4: FALSE | L4: FALSE | M4: FALSE | N4: FALSE
A5: Аренда, коммунальные услуги | B5: Административные | C5: 1С | E5: =if(and(OR(B5="Косвенные административные",B5="Косвенные коммерческие",B5="Расходы ниже EBITDA"),COUNTIF(F5:N5,TRUE)>0),"По направлениям распредляются только прямые расходы!","ОК") -> ОК | F5: FALSE | G5: FALSE | H5: FALSE | I5: FALSE | J5: FALSE | K5: FALSE | L5: FALSE | M5: FALSE | N5: FALSE
A6: Аутсорсинг и прочие услуги | B6: Административные | C6: 1С | E6: =if(and(OR(B6="Косвенные административные",B6="Косвенные коммерческие",B6="Расходы ниже EBITDA"),COUNTIF(F6:N6,TRUE)>0),"По направлениям распредляются только прямые расходы!","ОК") -> ОК | F6: FALSE | G6: FALSE | H6: FALSE | I6: FALSE | J6: FALSE | K6: FALSE | L6: FALSE | M6: FALSE | N6: FALSE
A7: Зарплата производственного персонала | B7: Общепроизводственные | C7: 1С | E7: =if(and(OR(B7="Косвенные административные",B7="Косвенные коммерческие",B7="Расходы ниже EBITDA"),COUNTIF(F7:N7,TRUE)>0),"По направлениям распредляются только прямые расходы!","ОК") -> ОК | F7: FALSE | G7: FALSE | H7: FALSE | I7: FALSE | J7: FALSE | K7: FALSE | L7: FALSE | M7: FALSE | N7: FALSE
A8: Командировочные расходы | B8: Административные | C8: 1С | E8: =if(and(OR(B8="Косвенные административные",B8="Косвенные коммерческие",B8="Расходы ниже EBITDA"),COUNTIF(F8:N8,TRUE)>0),"По направлениям распредляются только прямые расходы!","ОК") -> ОК | F8: FALSE | G8: FALSE | H8: FALSE | I8: FALSE | J8: FALSE | K8: FALSE | L8: FALSE | M8: FALSE | N8: FALSE
A9: Комиссии банка | B9: Административные | C9: ДДС отчетного месяца. Без НДС! | E9: =if(and(OR(B9="Косвенные административные",B9="Косвенные коммерческие",B9="Расходы ниже EBITDA"),COUNTIF(F9:N9,TRUE)>0),"По направлениям распредляются только прямые расходы!","ОК") -> ОК | F9: FALSE | G9: FALSE | H9: FALSE | I9: FALSE | J9: FALSE | K9: FALSE | L9: FALSE | M9: FALSE | N9: FALSE
A10: Комиссия топливных компаний | B10: Переменные | C10: ДДС отчетного месяца. Без НДС! | E10: =if(and(OR(B10="Косвенные административные",B10="Косвенные коммерческие",B10="Расходы ниже EBITDA"),COUNTIF(F10:N10,TRUE)>0),"По направлениям распредляются только прямые расходы!","ОК") -> ОК | F10: FALSE | G10: FALSE | H10: FALSE | I10: FALSE | J10: FALSE | K10: FALSE | L10: FALSE | M10: FALSE | N10: FALSE
A11: Курсовые разницы | B11: Расходы ниже EBITDA | C11: ДДС отчетного месяца. Без НДС! | E11: =if(and(OR(B11="Косвенные административные",B11="Косвенные коммерческие",B11="Расходы ниже EBITDA"),COUNTIF(F11:N11,TRUE)>0),"По направлениям распредляются только прямые расходы!","ОК") -> ОК | F11: FALSE | G11: FALSE | H11: FALSE | I11: FALSE | J11: FALSE | K11: FALSE | L11: FALSE | M11: FALSE | N11: FALSE
A12: Налог на прибыль УСН 6% | B12: Расходы ниже EBITDA | C12: 1С | E12: =if(and(OR(B12="Косвенные административные",B12="Косвенные коммерческие",B12="Расходы ниже EBITDA"),COUNTIF(F12:N12,TRUE)>0),"По направлениям распредляются только прямые расходы!","ОК") -> ОК | F12: FALSE | G12: FALSE | H12: FALSE | I12: FALSE | J12: FALSE | K12: FALSE | L12: FALSE | M12: FALSE | N12: FALSE
A13: Налог на прибыль 20% | B13: Расходы ниже EBITDA | C13: 1С | E13: =if(and(OR(B13="Косвенные административные",B13="Косвенные коммерческие",B13="Расходы ниже EBITDA"),COUNTIF(F13:N13,TRUE)>0),"По направлениям распредляются только прямые расходы!","ОК") -> ОК | F13: FALSE | G13: FALSE | H13: FALSE | I13: FALSE | J13: FALSE | K13: FALSE | L13: FALSE | M13: FALSE | N13: FALSE
A14: Обучение сотрудников | B14: Административные | C14: ДДС отчетного месяца. Без НДС! | E14: =if(and(OR(B14="Косвенные административные",B14="Косвенные коммерческие",B14="Расходы ниже EBITDA"),COUNTIF(F14:N14,TRUE)>0),"По направлениям распредляются только прямые расходы!","ОК") -> ОК | F14: FALSE | G14: FALSE | H14: FALSE | I14: FALSE | J14: FALSE | K14: FALSE | L14: FALSE | M14: FALSE | N14: FALSE
A15: Подбор персонала | B15: Административные | C15: ДДС отчетного месяца. Без НДС! | E15: =if(and(OR(B15="Косвенные административные",B15="Косвенные коммерческие",B15="Расходы ниже EBITDA"),COUNTIF(F15:N15,TRUE)>0),"По направлениям распредляются только прямые расходы!","ОК") -> ОК | F15: FALSE | G15: FALSE | H15: FALSE | I15: FALSE | J15: FALSE | K15: FALSE | L15: FALSE | M15: FALSE | N15: FALSE
A16: Подписка на сайты по поиску клиентов | B16: Коммерческие | C16: ДДС отчетного месяца. Без НДС! | E16: =if(and(OR(B16="Косвенные административные",B16="Косвенные коммерческие",B16="Расходы ниже EBITDA"),COUNTIF(F16:N16,TRUE)>0),"По направлениям распредляются только прямые расходы!","ОК") -> ОК | F16: FALSE | G16: FALSE | H16: FALSE | I16: FALSE | J16: FALSE | K16: FALSE | L16: FALSE | M16: FALSE | N16: FALSE
... A30: Штрафы | B30: Административные | C30: ДДС отчетного месяца. Без НДС! | E30: =if(and(OR(B30="Косвенные административные",B30="Косвенные коммерческие",B30="Расходы ниже EBITDA"),COUNTIF(F30:N30,TRUE)>0),"По направлениям распредляются только прямые расходы!","ОК") -> ОК | F30: FALSE | G30: FALSE | H30: FALSE | I30: FALSE | J30: FALSE | K30: FALSE | L30: FALSE | M30: FALSE | N30: FALSE
A31: Оплаты % кредиты | B31: Расходы ниже EBITDA | C31: отчет Учет ФД | E31: =if(and(OR(B31="Косвенные административные",B31="Косвенные коммерческие",B31="Расходы ниже EBITDA"),COUNTIF(F31:N31,TRUE)>0),"По направлениям распредляются только прямые расходы!","ОК") -> ОК | F31: FALSE | G31: FALSE
E32: =if(and(OR(B32="Косвенные административные",B32="Косвенные коммерческие",B32="Расходы ниже EBITDA"),COUNTIF(F32:N32,TRUE)>0),"По направлениям распредляются только прямые расходы!","ОК") -> ОК
E33: =if(and(OR(B33="Косвенные административные",B33="Косвенные коммерческие",B33="Расходы ниже EBITDA"),COUNTIF(F33:N33,TRUE)>0),"По направлениям распредляются только прямые расходы!","ОК") -> ОК
E34: =if(and(OR(B34="Косвенные административные",B34="Косвенные коммерческие",B34="Расходы ниже EBITDA"),COUNTIF(F34:N34,TRUE)>0),"По направлениям распредляются только прямые расходы!","ОК") -> ОК
E35: =if(and(OR(B35="Косвенные административные",B35="Косвенные коммерческие",B35="Расходы ниже EBITDA"),COUNTIF(F35:N35,TRUE)>0),"По направлениям распредляются только прямые расходы!","ОК") -> ОК
E36: =if(and(OR(B36="Косвенные административные",B36="Косвенные коммерческие",B36="Расходы ниже EBITDA"),COUNTIF(F36:N36,TRUE)>0),"По направлениям распредляются только прямые расходы!","ОК") -> ОК
E37: =if(and(OR(B37="Косвенные административные",B37="Косвенные коммерческие",B37="Расходы ниже EBITDA"),COUNTIF(F37:N37,TRUE)>0),"По направлениям распредляются только прямые расходы!","ОК") -> ОК
E38: =if(and(OR(B38="Косвенные административные",B38="Косвенные коммерческие",B38="Расходы ниже EBITDA"),COUNTIF(F38:N38,TRUE)>0),"По направлениям распредляются только прямые расходы!","ОК") -> ОК
E39: =if(and(OR(B39="Косвенные административные",B39="Косвенные коммерческие",B39="Расходы ниже EBITDA"),COUNTIF(F39:N39,TRUE)>0),"По направлениям распредляются только прямые расходы!","ОК") -> ОК
E40: =if(and(OR(B40="Косвенные административные",B40="Косвенные коммерческие",B40="Расходы ниже EBITDA"),COUNTIF(F40:N40,TRUE)>0),"По направлениям распредляются только прямые расходы!","ОК") -> ОК
E41: =if(and(OR(B41="Косвенные административные",B41="Косвенные коммерческие",B41="Расходы ниже EBITDA"),COUNTIF(F41:N41,TRUE)>0),"По направлениям распредляются только прямые расходы!","ОК") -> ОК
E42: =if(and(OR(B42="Косвенные административные",B42="Косвенные коммерческие",B42="Расходы ниже EBITDA"),COUNTIF(F42:N42,TRUE)>0),"По направлениям распредляются только прямые расходы!","ОК") -> ОК
E43: =if(and(OR(B43="Косвенные административные",B43="Косвенные коммерческие",B43="Расходы ниже EBITDA"),COUNTIF(F43:N43,TRUE)>0),"По направлениям распредляются только прямые расходы!","ОК") -> ОК
... E45: =if(and(OR(B45="Косвенные административные",B45="Косвенные коммерческие",B45="Расходы ниже EBITDA"),COUNTIF(F45:N45,TRUE)>0),"По направлениям распредляются только прямые расходы!","ОК") -> ОК

Sheet 1
C1: ФАКТ | J1: План | Q1: Отклонения
A2: Источники | C2: {=TRANSPOSE('Справочник'!D2:D7)} -> ООО "Весело живем" | D2: ООО "Некогда грустить" | E2: 3 | F2: 4 | G2: 5 | H2: 6 | I2: Итого | J2: {=TRANSPOSE('Справочник'!D2:D7)} -> ООО "Весело живем" | K2: ООО "Некогда грустить" | L2: 3 | M2: 4 | N2: 5 | O2: 6 | P2: Итого | Q2: факт-план, руб | R2: факт/план, % | S2: Результат
B3: Выручка | C3: =SUM(C4:C10) -> 225500 | D3: =SUM(D4:D10) -> 2100 | E3: =SUM(E4:E10) -> 0 | F3: =SUM(F4:F10) -> 0 | G3: =SUM(G4:G10) -> 0 | H3: =SUM(H4:H10) -> 0 | I3: =sum(C3:H3) -> 227600 | J3: =SUM(J4:J10) -> 230400 | K3: =SUM(K4:K10) -> 0 | P3: =SUM(P4:P10) -> 230400 | Q3: =I3-P3 -> -2800 | R3: =IFERROR(I3/P3,0) -> 0.98784722 | S3: =IF(Q3=0,"",IF(R3>1,"выполнение","план не выполнен")) -> план не выполнен
A4: =IFERROR(VLOOKUP(B4,'Статьи'!$A$2:C26,3,0)," ") -> 1С сч 90.01 убрать НДС! | B4: =IFERROR(__xludf.DUMMYFUNCTION("iferror(filter('Статьи'!$A$1:$A182,'Статьи'!$B$1:$B182=$B$3))"),"Выручка от аренды машиноместа") -> Выручка от аренды машиноместа | C4: 500 | I4: =SUM(C4:H4) -> 500 | J4: 400 | P4: =SUM(J4:K4) -> 400 | Q4: =I4-P4 -> 100 | R4: =IFERROR(I4/P4,0) -> 1.25 | S4: =IF(Q4=0,"",IF(R4=0,"обратить внимание",IF(R4>1,"выполнение","план не выполнен"))) -> выполнение
A5: =IFERROR(VLOOKUP(B5,'Статьи'!$A$2:C27,3,0)," ") -> 1С сч 90.01 убрать НДС! | B5: =IFERROR(__xludf.DUMMYFUNCTION("""COMPUTED_VALUE"""),"Выручка за грузоперевозки") -> Выручка за грузоперевозки | C5: 225000 | D5: 2100 | I5: =SUM(C5:H5) -> 227100 | J5: 230000 | P5: =SUM(J5:K5) -> 230000 | Q5: =I5-P5 -> -2900 | R5: =IFERROR(I5/P5,0) -> 0.9873913 | S5: =IF(Q5=0,"",IF(R5=0,"обратить внимание",IF(R5>1,"выполнение","план не выполнен"))) -> план не выполнен
A6: =IFERROR(VLOOKUP(B6,'Статьи'!$A$2:C28,3,0)," ") | I6: =SUM(C6:H6) -> 0 | P6: =SUM(F6:J6) -> 0 | Q6: =I6-P6 -> 0 | R6: =IFERROR(I6/P6,0) -> 0 | S6: =IF(Q6=0,"",IF(R6=0,"обратить внимание",IF(R6>1,"выполнение","план не выполнен")))
A7: =IFERROR(VLOOKUP(B7,'Статьи'!$A$2:C29,3,0)," ") | I7: =SUM(C7:H7) -> 0 | P7: =SUM(F7:J7) -> 0 | Q7: =I7-P7 -> 0 | R7: =IFERROR(I7/P7,0) -> 0 | S7: =IF(Q7=0,"",IF(R7=0,"обратить внимание",IF(R7>1,"выполнение","план не выполнен")))
A8: =IFERROR(VLOOKUP(B8,'Статьи'!$A$2:C30,3,0)," ") | I8: =SUM(C8:H8) -> 0 | P8: =SUM(F8:J8) -> 0 | Q8: =I8-P8 -> 0 | R8: =IFERROR(I8/P8,0) -> 0 | S8: =IF(Q8=0,"",IF(R8=0,"обратить внимание",IF(R8>1,"выполнение","план не выполнен")))
A9: =IFERROR(VLOOKUP(B9,'Статьи'!$A$2:C31,3,0)," ") | Q9: =I9-P9 -> 0 | R9: =IFERROR(I9/P9,0) -> 0 | S9: =IF(Q9=0,"",IF(R9=0,"обратить внимание",IF(R9>1,"выполнение","план не выполнен")))
A10: =IFERROR(VLOOKUP(B10,'Статьи'!$A$2:C32,3,0)," ") | Q10: =I10-P10 -> 0 | R10: =IFERROR(I10/P10,0) -> 0 | S10: =IF(Q10=0,"",IF(R10=0,"обратить внимание",IF(R10>1,"выполнение","план не выполнен")))
B11: Производственные расходы | C11: =C12+C58 -> -60769 | D11: =D12+D58 -> -1216 | E11: =E12+E58 -> 0 | F11: =F12+F58 -> 0 | G11: =G12+G58 -> 0 | H11: =H12+H58 -> 0 | I11: =I12+I58 -> -61985 | J11: =J12+J58 -> -73525 | K11: =K12+K58 -> 0 | P11: =P12+P58 -> -73525 | Q11: =I11-P11 -> 11540 | R11: =IFERROR(I11/P11,0) -> 0.84304658 | S11: =IF(Q11=0,"",IF(R11>1,"план не выполнен","выполнение")) -> выполнение
B12: Переменные | C12: =sum(C13:C54) -> -48250 | D12: =sum(D13:D54) -> -1216 | E12: =sum(E13:E54) -> 0 | F12: =sum(F13:F54) -> 0 | G12: =sum(G13:G54) -> 0 | H12: =sum(H13:H54) -> 0 | I12: =sum(I13:I54) -> -49466 | J12: =sum(J13:J54) -> -61250 | K12: =sum(K13:K54) -> 0 | P12: =sum(P13:P54) -> -61250 | Q12: =I12-P12 -> 11784 | R12: =IFERROR(I12/P12,0) -> 0.80760816 | S12: =IF(Q12=0,"",IF(R12>1,"план не выполнен","выполнение")) -> выполнение
A13: =IFERROR(VLOOKUP(B13,'Статьи'!$A$2:C35,3,0)," ") -> ДДС отчетного месяца. Без НДС! | B13: =IFERROR(__xludf.DUMMYFUNCTION("iferror(filter('Статьи'!$A$1:$A182,'Статьи'!$B$1:$B182=$B$12))"),"Комиссия топливных компаний") -> Комиссия топливных компаний | C13: -250 | D13: -16 | I13: =sum(C13:H13) -> -266 | J13: -250 | P13: =SUM(J13:K13) -> -250 | Q13: =I13-P13 -> -16 | R13: =IFERROR(I13/P13,0) -> 1.064 | S13: =IF(Q13=0,"",IF(R13=0,"обратить внимание",IF(R13>1,"перерасход","экономия"))) -> перерасход
A14: =IFERROR(VLOOKUP(B14,'Статьи'!$A$2:C36,3,0)," ") -> 1С | B14: =IFERROR(__xludf.DUMMYFUNCTION("""COMPUTED_VALUE"""),"Топливо для грузовых авто ") -> Топливо для грузовых авто | C14: -48000 | D14: -1200 | I14: =sum(C14:H14) -> -49200 | J14: -61000 | P14: =SUM(J14:K14) -> -61000 | Q14: =I14-P14 -> 11800 | R14: =IFERROR(I14/P14,0) -> 0.80655738 | S14: =IF(Q14=0,"",IF(R14=0,"обратить внимание",IF(R14>1,"перерасход","экономия"))) -> экономия
A15: =IFERROR(VLOOKUP(B15,'Статьи'!$A$2:C37,3,0)," ") | I15: =sum(C15:H15) -> 0 | P15: =SUM(J15:K15) -> 0 | Q15: =I15-P15 -> 0 | R15: =IFERROR(I15/P15,0) -> 0 | S15: =IF(Q15=0,"",IF(R15=0,"обратить внимание",IF(R15>1,"перерасход","экономия")))
A16: =IFERROR(VLOOKUP(B16,'Статьи'!$A$2:C38,3,0)," ") | I16: =sum(C16:H16) -> 0 | P16: =SUM(J16:K16) -> 0 | Q16: =I16-P16 -> 0 | R16: =IFERROR(I16/P16,0) -> 0 | S16: =IF(Q16=0,"",IF(R16=0,"обратить внимание",IF(R16>1,"перерасход","экономия")))
A17: =IFERROR(VLOOKUP(B17,'Статьи'!$A$2:C39,3,0)," ") | I17: =sum(C17:H17) -> 0 | P17: =sum(F17:J17) -> 0 | Q17: =I17-P17 -> 0 | R17: =IFERROR(I17/P17,0) -> 0 | S17: =IF(Q17=0,"",IF(R17=0,"обратить внимание",IF(R17>1,"перерасход","экономия")))
I18: =sum(C18:H18) -> 0 | P18: =sum(F18:J18) -> 0 | Q18: =I18-P18 -> 0 | R18: =IFERROR(I18/P18,0) -> 0 | S18: =IF(Q18=0,0,IF(R18>1,"перерасход","экономия")) -> 0
I19: =sum(C19:H19) -> 0 | P19: =sum(F19:J19) -> 0 | Q19: =I19-P19 -> 0 | R19: =IFERROR(I19/P19,0) -> 0 | S19: =IF(Q19=0,0,IF(R19>1,"перерасход","экономия")) -> 0
I20: =sum(C20:H20) -> 0 | P20: =sum(F20:J20) -> 0 | Q20: =I20-P20 -> 0 | R20: =IFERROR(I20/P20,0) -> 0 | S20: =IF(Q20=0,0,IF(R20>1,"перерасход","экономия")) -> 0
I21: =sum(C21:H21) -> 0 | P21: =sum(F21:J21) -> 0 | Q21: =I21-P21 -> 0 | R21: =IFERROR(I21/P21,0) -> 0 | S21: =IF(Q21=0,0,IF(R21>1,"перерасход","экономия")) -> 0
I22: =sum(C22:H22) -> 0 | P22: =sum(F22:J22) -> 0 | Q22: =I22-P22 -> 0 | R22: =IFERROR(I22/P22,0) -> 0 | S22: =IF(Q22=0,0,IF(R22>1,"перерасход","экономия")) -> 0
I23: =sum(C23:H23) -> 0 | P23: =sum(F23:J23) -> 0 | Q23: =I23-P23 -> 0 | R23: =IFERROR(I23/P23,0) -> 0 | S23: =IF(Q23=0,0,IF(R23>1,"перерасход","экономия")) -> 0
I24: =sum(C24:H24) -> 0 | P24: =sum(F24:J24) -> 0 | Q24: =I24-P24 -> 0 | R24: =IFERROR(I24/P24,0) -> 0 | S24: =IF(Q24=0,0,IF(R24>1,"перерасход","экономия")) -> 0
I25: =sum(C25:H25) -> 0 | P25: =sum(F25:J25) -> 0 | Q25: =I25-P25 -> 0 | R25: =IFERROR(I25/P25,0) -> 0 | S25: =IF(Q25=0,0,IF(R25>1,"перерасход","экономия")) -> 0
I26: =sum(C26:H26) -> 0 | P26: =sum(F26:J26) -> 0 | Q26: =I26-P26 -> 0 | R26: =IFERROR(I26/P26,0) -> 0 | S26: =IF(Q26=0,0,IF(R26>1,"перерасход","экономия")) -> 0
I27: =sum(C27:H27) -> 0 | P27: =sum(F27:J27) -> 0 | Q27: =I27-P27 -> 0 | R27: =IFERROR(I27/P27,0) -> 0 | S27: =IF(Q27=0,0,IF(R27>1,"перерасход","экономия")) -> 0
I28: =sum(C28:H28) -> 0 | P28: =sum(F28:J28) -> 0 | Q28: =I28-P28 -> 0 | R28: =IFERROR(I28/P28,0) -> 0 | S28: =IF(Q28=0,0,IF(R28>1,"перерасход","экономия")) -> 0
I29: =sum(C29:H29) -> 0 | P29: =sum(F29:J29) -> 0 | Q29: =I29-P29 -> 0 | R29: =IFERROR(I29/P29,0) -> 0 | S29: =IF(Q29=0,0,IF(R29>1,"перерасход","экономия")) -> 0
... I54: =sum(C54:H54) -> 0 | P54: =sum(F54:J54) -> 0 | Q54: =I54-P54 -> 0 | R54: =IFERROR(I54/P54,0) -> 0 | S54: =IF(Q54=0,0,IF(R54>1,"перерасход","экономия")) -> 0
B55: Маржинальный доход | C55: =C3+C12 -> 177250 | D55: =D3+D12 -> 884 | E55: =E3+E12 -> 0 | F55: =F3+F12 -> 0 | G55: =G3+G12 -> 0 | H55: =H3+H12 -> 0 | I55: =I3+I12 -> 178134 | J55: =J3+J12 -> 169150 | K55: =K3+K12 -> 0 | P55: =P3+P12 -> 169150 | Q55: =I55-P55 -> 8984 | R55: =IFERROR(I55/P55,0) -> 1.0531126 | S55: =IF(Q55=0,"",IF(R55>1,"выполнение","план не выполнен")) -> выполнение
B56: Рентабельность по марже | C56: =IFERROR(C55/C$3,"") -> 0.78603104 | D56: =IFERROR(D55/D$3,"") -> 0.42095238 | E56: =IFERROR(E55/E$3,"") | F56: =IFERROR(F55/F$3,"") | G56: =IFERROR(G55/G$3,"") | H56: =IFERROR(H55/H$3,"") | I56: =IFERROR(I55/I$3,"") -> 0.78266257 | J56: =IFERROR(J55/J$3,"") -> 0.73415799 | K56: =IFERROR(K55/K$3,"") | P56: =IFERROR(P55/P$3,"") -> 0.73415799
B58: Общепроизводственные | C58: =sum(C59:C79) -> -12519 | D58: =sum(D59:D79) -> 0 | E58: =sum(E59:E79) -> 0 | F58: =sum(F59:F79) -> 0 | G58: =sum(G59:G79) -> 0 | H58: =sum(H59:H79) -> 0 | I58: =SUM(I59:I84) -> -12519 | J58: =SUM(J59:J84) -> -12275 | K58: =SUM(K59:K84) -> 0 | P58: =SUM(P59:P84) -> -12275 | Q58: =I58-P58 -> -244 | R58: =IFERROR(I58/P58,0) -> 1.0198778 | S58: =IF(Q58=0,"",IF(R58>1,"план не выполнен","выполнение")) -> план не выполнен
A59: =IFERROR(VLOOKUP(B59,'Статьи'!$A$2:C81,3,0)," ") -> 1С | B59: =IFERROR(__xludf.DUMMYFUNCTION("iferror(filter('Статьи'!$A$1:$A182,'Статьи'!$B$1:$B182=$B$58))"),"Зарплата производственного персонала") -> Зарплата производственного персонала | C59: -19 | I59: =SUM(C59:H59) -> -19 | J59: -55 | P59: =SUM(J59:K59) -> -55 | Q59: =I59-P59 -> 36 | R59: =IFERROR(I59/P59,0) -> 0.34545455 | S59: =IF(Q59=0,"",IF(R59=0,"обратить внимание",IF(R59>1,"перерасход","экономия"))) -> экономия
A60: =IFERROR(VLOOKUP(B60,'Статьи'!$A$2:C82,3,0)," ") -> ДДС отчетного месяца. Без НДС! | B60: =IFERROR(__xludf.DUMMYFUNCTION("""COMPUTED_VALUE"""),"Таможенные расходы") -> Таможенные расходы | C60: -12500 | I60: =SUM(C60:H60) -> -12500 | J60: -12220 | P60: =SUM(J60:K60) -> -12220 | Q60: =I60-P60 -> -280 | R60: =IFERROR(I60/P60,0) -> 1.0229133 | S60: =IF(Q60=0,"",IF(R60=0,"обратить внимание",IF(R60>1,"перерасход","экономия"))) -> перерасход
A61: =IFERROR(VLOOKUP(B61,'Статьи'!$A$2:C83,3,0)," ") | I61: =SUM(C61:H61) -> 0 | P61: =SUM(J61:K61) -> 0 | Q61: =I61-P61 -> 0 | R61: =IFERROR(I61/P61,0) -> 0 | S61: =IF(Q61=0,"",IF(R61=0,"обратить внимание",IF(R61>1,"перерасход","экономия")))
A62: =IFERROR(VLOOKUP(B62,'Статьи'!$A$2:C84,3,0)," ") | I62: =SUM(C62:H62) -> 0 | P62: =SUM(J62:K62) -> 0 | Q62: =I62-P62 -> 0 | R62: =IFERROR(I62/P62,0) -> 0 | S62: =IF(Q62=0,"",IF(R62=0,"обратить внимание",IF(R62>1,"перерасход","экономия")))
A63: =IFERROR(VLOOKUP(B63,'Статьи'!$A$2:C85,3,0)," ") | I63: =SUM(C63:H63) -> 0 | P63: =SUM(J63:K63) -> 0 | Q63: =I63-P63 -> 0 | R63: =IFERROR(I63/P63,0) -> 0 | S63: =IF(Q63=0,"",IF(R63=0,"обратить внимание",IF(R63>1,"перерасход","экономия")))
A64: =IFERROR(VLOOKUP(B64,'Статьи'!$A$2:C86,3,0)," ") | I64: =SUM(C64:H64) -> 0 | P64: =SUM(J64:K64) -> 0 | Q64: =I64-P64 -> 0 | R64: =IFERROR(I64/P64,0) -> 0 | S64: =IF(Q64=0,"",IF(R64=0,"обратить внимание",IF(R64>1,"перерасход","экономия")))
A65: =IFERROR(VLOOKUP(B65,'Статьи'!$A$2:C87,3,0)," ") | I65: =SUM(C65:H65) -> 0 | P65: =SUM(J65:K65) -> 0 | Q65: =I65-P65 -> 0 | R65: =IFERROR(I65/P65,0) -> 0 | S65: =IF(Q65=0,"",IF(R65=0,"обратить внимание",IF(R65>1,"перерасход","экономия")))
A66: =IFERROR(VLOOKUP(B66,'Статьи'!$A$2:C88,3,0)," ") | I66: =SUM(C66:H66) -> 0 | P66: =SUM(J66:K66) -> 0 | Q66: =I66-P66 -> 0 | R66: =IFERROR(I66/P66,0) -> 0 | S66: =IF(Q66=0,"",IF(R66=0,"обратить внимание",IF(R66>1,"перерасход","экономия")))
A67: =IFERROR(VLOOKUP(B67,'Статьи'!$A$2:C89,3,0)," ") | I67: =SUM(C67:H67) -> 0 | P67: =SUM(J67:K67) -> 0 | Q67: =I67-P67 -> 0 | R67: =IFERROR(I67/P67,0) -> 0 | S67: =IF(Q67=0,"",IF(R67=0,"обратить внимание",IF(R67>1,"перерасход","экономия")))
A68: =IFERROR(VLOOKUP(B68,'Статьи'!$A$2:C90,3,0)," ") | I68: =SUM(C68:H68) -> 0 | P68: =SUM(J68:K68) -> 0 | Q68: =I68-P68 -> 0 | R68: =IFERROR(I68/P68,0) -> 0 | S68: =IF(Q68=0,"",IF(R68=0,"обратить внимание",IF(R68>1,"перерасход","экономия")))
A69: =IFERROR(VLOOKUP(B69,'Статьи'!$A$2:C91,3,0)," ") | I69: =SUM(C69:H69) -> 0 | P69: =SUM(J69:K69) -> 0 | Q69: =I69-P69 -> 0 | R69: =IFERROR(I69/P69,0) -> 0 | S69: =IF(Q69=0,"",IF(R69=0,"обратить внимание",IF(R69>1,"перерасход","экономия")))
A70: =IFERROR(VLOOKUP(B70,'Статьи'!$A$2:C92,3,0)," ") | I70: =SUM(C70:H70) -> 0 | P70: =SUM(J70:K70) -> 0 | Q70: =I70-P70 -> 0 | R70: =IFERROR(I70/P70,0) -> 0 | S70: =IF(Q70=0,"",IF(R70=0,"обратить внимание",IF(R70>1,"перерасход","экономия")))
A71: =IFERROR(VLOOKUP(B71,'Статьи'!$A$2:C93,3,0)," ") | I71: =SUM(C71:H71) -> 0 | P71: =SUM(J71:K71) -> 0 | Q71: =I71-P71 -> 0 | R71: =IFERROR(I71/P71,0) -> 0 | S71: =IF(Q71=0,"",IF(R71=0,"обратить внимание",IF(R71>1,"перерасход","экономия")))
A72: =IFERROR(VLOOKUP(B72,'Статьи'!$A$2:C94,3,0)," ") | I72: =SUM(C72:H72) -> 0 | P72: =SUM(J72:K72) -> 0 | Q72: =I72-P72 -> 0 | R72: =IFERROR(I72/P72,0) -> 0 | S72: =IF(Q72=0,"",IF(R72=0,"обратить внимание",IF(R72>1,"перерасход","экономия")))
... A84: =IFERROR(VLOOKUP(B84,'Статьи'!$A$2:C106,3,0)," ") | I84: =SUM(C84:H84) -> 0 | P84: =SUM(J84:K84) -> 0 | Q84: =I84-P84 -> 0 | R84: =IFERROR(I84/P84,0) -> 0 | S84: =IF(Q84=0,"",IF(R84=0,"обратить внимание",IF(R84>1,"перерасход","экономия")))
B85: Валовая прибыль | C85: =C55+C58 -> 164731 | D85: =D55+D58 -> 884 | E85: =E55+E58 -> 0 | F85: =F55+F58 -> 0 | G85: =G55+G58 -> 0 | H85: =H55+H58 -> 0 | I85: =I55+I58 -> 165615 | J85: =J55+J58 -> 156875 | K85: =K55+K58 -> 0 | P85: =P55+P58 -> 156875 | Q85: =I85-P85 -> 8740 | R85: =IFERROR(I85/P85,0) -> 1.0557131 | S85: =IF(Q85=0,"",IF(R85>1,"выполнение","план не выполнен")) -> выполнение
B86: Рентабельность по валовой прибыли, % | C86: =IFERROR(C85/C$3,"") -> 0.73051441 | D86: =IFERROR(D85/D$3,"") -> 0.42095238 | E86: =IFERROR(E85/E$3,"") | F86: =IFERROR(F85/F$3,"") | G86: =IFERROR(G85/G$3,"") | H86: =IFERROR(H85/H$3,"") | I86: =IFERROR(I85/I$3,"") -> 0.72765817 | J86: =IFERROR(J85/J$3,"") -> 0.68088108 | K86: =IFERROR(K85/K$3,"") | P86: =IFERROR(P85/P$3,"") -> 0.68088108 | S86: =IF(Q86=0,"",IF(Q86=0,0,IF(R86>1,"перерасход","экономия")))
S87: =IF(Q87=0,"",IF(Q87=0,0,IF(R87>1,"перерасход","экономия")))
B88: Косвенные расходы | C88: =C101+C132+C89 -> -21962 | D88: =D101+D132+D89 -> -231 | E88: =E101+E132+E89 -> 0 | F88: =F101+F132+F89 -> 0 | G88: =G101+G132+G89 -> 0 | H88: =H101+H132+H89 -> 0 | I88: =I101+I132+I89 -> -22193 | J88: =J101+J132+J89 -> -14977.97 | K88: =K101+K132+K89 -> 0 | P88: =P101+P132+P89 -> -14977.97 | Q88: =I88-P88 -> -7215.03 | R88: =IFERROR(I88/P88,0) -> 1.4817095 | S88: =IF(Q88=0,"",IF(R88>1,"план не выполнен","выполнение")) -> план не выполнен
B89: Косвенные производственные | C89: =SUM(C90:C100) -> 0 | D89: =SUM(D90:D100) -> 0 | E89: =SUM(E90:E100) -> 0 | F89: =SUM(F90:F100) -> 0 | G89: =SUM(G90:G100) -> 0 | H89: =SUM(H90:H100) -> 0 | I89: =SUM(I90:I100) -> 0 | J89: =SUM(J90:J100) -> 0 | K89: =SUM(K90:K100) -> 0 | P89: =SUM(P90:P100) -> 0 | Q89: =I89-P89 -> 0 | R89: =IFERROR(I89/P89,0) -> 0 | S89: =IF(Q89=0,"",IF(Q89=0,0,IF(R89>1,"перерасход","экономия")))
A90: =IFERROR(VLOOKUP(B90,'Статьи'!$A$2:C112,3,0)," ") | B90: =IFERROR(__xludf.DUMMYFUNCTION("iferror(filter('Статьи'!$A$1:$A182,'Статьи'!$B$1:$B182=$B$89))"),"") | I90: =sum(C90:H90) -> 0 | P90: =SUM(J90:K90) -> 0 | Q90: =I90-P90 -> 0 | R90: =IFERROR(I90/P90,0) -> 0 | S90: =IF(Q90=0,"",IF(R90=0,"обратить внимание",IF(R90>1,"перерасход","экономия")))
A91: =IFERROR(VLOOKUP(B91,'Статьи'!$A$2:C113,3,0)," ") | I91: =sum(C91:H91) -> 0 | P91: =SUM(J91:K91) -> 0 | Q91: =I91-P91 -> 0 | R91: =IFERROR(I91/P91,0) -> 0 | S91: =IF(Q91=0,"",IF(R91=0,"обратить внимание",IF(R91>1,"перерасход","экономия")))
A92: =IFERROR(VLOOKUP(B92,'Статьи'!$A$2:C114,3,0)," ") | I92: =sum(C92:H92) -> 0 | P92: =SUM(J92:K92) -> 0 | Q92: =I92-P92 -> 0 | R92: =IFERROR(I92/P92,0) -> 0 | S92: =IF(Q92=0,"",IF(R92=0,"обратить внимание",IF(R92>1,"перерасход","экономия")))
A93: =IFERROR(VLOOKUP(B93,'Статьи'!$A$2:C115,3,0)," ") | I93: =sum(C93:H93) -> 0 | P93: =SUM(J93:K93) -> 0 | Q93: =I93-P93 -> 0 | R93: =IFERROR(I93/P93,0) -> 0 | S93: =IF(Q93=0,"",IF(R93=0,"обратить внимание",IF(R93>1,"перерасход","экономия")))
A94: =IFERROR(VLOOKUP(B94,'Статьи'!$A$2:C116,3,0)," ") | I94: =sum(C94:H94) -> 0 | P94: =SUM(J94:K94) -> 0 | Q94: =I94-P94 -> 0 | R94: =IFERROR(I94/P94,0) -> 0 | S94: =IF(Q94=0,"",IF(R94=0,"обратить внимание",IF(R94>1,"перерасход","экономия")))
I95: =sum(C95:H95) -> 0 | P95: =sum(F95:J95) -> 0 | Q95: =I95-P95 -> 0 | R95: =IFERROR(I95/P95,0) -> 0 | S95: =IF(Q95=0,"",IF(Q95=0,0,IF(R95>1,"перерасход","экономия")))
I96: =sum(C96:H96) -> 0 | P96: =sum(F96:J96) -> 0 | Q96: =I96-P96 -> 0 | R96: =IFERROR(I96/P96,0) -> 0 | S96: =IF(Q96=0,"",IF(Q96=0,0,IF(R96>1,"перерасход","экономия")))
I97: =sum(C97:H97) -> 0 | P97: =sum(F97:J97) -> 0 | Q97: =I97-P97 -> 0 | R97: =IFERROR(I97/P97,0) -> 0 | S97: =IF(Q97=0,"",IF(Q97=0,0,IF(R97>1,"перерасход","экономия")))
I98: =sum(C98:H98) -> 0 | P98: =sum(F98:J98) -> 0 | Q98: =I98-P98 -> 0 | R98: =IFERROR(I98/P98,0) -> 0 | S98: =IF(Q98=0,"",IF(Q98=0,0,IF(R98>1,"перерасход","экономия")))
I99: =sum(C99:H99) -> 0 | P99: =sum(F99:J99) -> 0 | Q99: =I99-P99 -> 0 | R99: =IFERROR(I99/P99,0) -> 0 | S99: =IF(Q99=0,"",IF(Q99=0,0,IF(R99>1,"перерасход","экономия")))
I100: =sum(C100:H100) -> 0 | P100: =sum(F100:J100) -> 0 | Q100: =I100-P100 -> 0 | R100: =IFERROR(I100/P100,0) -> 0 | S100: =IF(Q100=0,"",IF(Q100=0,0,IF(R100>1,"перерасход","экономия")))
B101: Административные | C101: =SUM(C102:C131) -> -21942 | D101: =SUM(D102:D131) -> -231 | E101: =SUM(E102:E131) -> 0 | F101: =SUM(F102:F131) -> 0 | G101: =SUM(G102:G131) -> 0 | H101: =SUM(H102:H131) -> 0 | I101: =SUM(I102:I131) -> -22173 | J101: =SUM(J102:J131) -> -14937.97 | K101: =SUM(K102:K131) -> 0 | P101: =SUM(P102:P131) -> -14937.97 | Q101: =I101-P101 -> -7235.03 | R101: =IFERROR(I101/P101,0) -> 1.4843382 | S101: =IF(Q101=0,"",IF(R101>1,"план не выполнен","выполнение")) -> план не выполнен
A102: =IFERROR(VLOOKUP(B102,'Статьи'!$A$2:C124,3,0)," ") -> 1С | B102: =IFERROR(__xludf.DUMMYFUNCTION("iferror(filter('Статьи'!$A$1:$A182,'Статьи'!$B$1:$B182=$B$101))"),"Аренда, коммунальные услуги") -> Аренда, коммунальные услуги | C102: -5000 | D102: -23 | I102: =sum(C102:H102) -> -5023 | J102: -4500 | P102: =SUM(J102:K102) -> -4500 | Q102: =I102-P102 -> -523 | R102: =IFERROR(I102/P102,0) -> 1.1162222 | S102: =IF(Q102=0,"",IF(R102=0,"обратить внимание",IF(R102>1,"перерасход","экономия"))) -> перерасход
A103: =IFERROR(VLOOKUP(B103,'Статьи'!$A$2:C125,3,0)," ") -> 1С | B103: =IFERROR(__xludf.DUMMYFUNCTION("""COMPUTED_VALUE"""),"Аутсорсинг и прочие услуги") -> Аутсорсинг и прочие услуги | C103: -1200 | I103: =sum(C103:H103) -> -1200 | J103: -2147 | P103: =SUM(J103:K103) -> -2147 | Q103: =I103-P103 -> 947 | R103: =IFERROR(I103/P103,0) -> 0.55891942 | S103: =IF(Q103=0,"",IF(R103=0,"обратить внимание",IF(R103>1,"перерасход","экономия"))) -> экономия
A104: =IFERROR(VLOOKUP(B104,'Статьи'!$A$2:C126,3,0)," ") -> 1С | B104: =IFERROR(__xludf.DUMMYFUNCTION("""COMPUTED_VALUE"""),"Командировочные расходы") -> Командировочные расходы | C104: -2000 | I104: =sum(C104:H104) -> -2000 | J104: -1800 | P104: =SUM(J104:K104) -> -1800 | Q104: =I104-P104 -> -200 | R104: =IFERROR(I104/P104,0) -> 1.1111111 | S104: =IF(Q104=0,"",IF(R104=0,"обратить внимание",IF(R104>1,"перерасход","экономия"))) -> перерасход
A105: =IFERROR(VLOOKUP(B105,'Статьи'!$A$2:C127,3,0)," ") -> ДДС отчетного месяца. Без НДС! | B105: =IFERROR(__xludf.DUMMYFUNCTION("""COMPUTED_VALUE"""),"Комиссии банка") -> Комиссии банка | C105: -100 | I105: =sum(C105:H105) -> -100 | J105: -100 | P105: =SUM(J105:K105) -> -100 | Q105: =I105-P105 -> 0 | R105: =IFERROR(I105/P105,0) -> 1 | S105: =IF(Q105=0,"",IF(R105=0,"обратить внимание",IF(R105>1,"перерасход","экономия")))
A106: =IFERROR(VLOOKUP(B106,'Статьи'!$A$2:C128,3,0)," ") -> ДДС отчетного месяца. Без НДС! | B106: =IFERROR(__xludf.DUMMYFUNCTION("""COMPUTED_VALUE"""),"Обучение сотрудников") -> Обучение сотрудников | C106: =-8000 -> -8000 | D106: -148 | I106: =sum(C106:H106) -> -8148 | J106: -5000 | P106: =SUM(J106:K106) -> -5000 | Q106: =I106-P106 -> -3148 | R106: =IFERROR(I106/P106,0) -> 1.6296 | S106: =IF(Q106=0,"",IF(R106=0,"обратить внимание",IF(R106>1,"перерасход","экономия"))) -> перерасход
A107: =IFERROR(VLOOKUP(B107,'Статьи'!$A$2:C129,3,0)," ") -> ДДС отчетного месяца. Без НДС! | B107: =IFERROR(__xludf.DUMMYFUNCTION("""COMPUTED_VALUE"""),"Подбор персонала") -> Подбор персонала | C107: =-4832+590 -> -4242 | I107: =sum(C107:H107) -> -4242 | J107: 0 | P107: =SUM(J107:K107) -> 0 | Q107: =I107-P107 -> -4242 | R107: =IFERROR(I107/P107,0) -> 0 | S107: =IF(Q107=0,"",IF(R107=0,"обратить внимание",IF(R107>1,"перерасход","экономия"))) -> обратить внимание
A108: =IFERROR(VLOOKUP(B108,'Статьи'!$A$2:C130,3,0)," ") -> ДДС отчетного месяца. Без НДС! | B108: =IFERROR(__xludf.DUMMYFUNCTION("""COMPUTED_VALUE"""),"Почтовые расходы") -> Почтовые расходы | C108: 0 | I108: =sum(C108:H108) -> 0 | J108: -400 | P108: =SUM(J108:K108) -> -400 | Q108: =I108-P108 -> 400 | R108: =IFERROR(I108/P108,0) -> 0 | S108: =IF(Q108=0,"",IF(R108=0,"обратить внимание",IF(R108>1,"перерасход","экономия"))) -> обратить внимание
A109: =IFERROR(VLOOKUP(B109,'Статьи'!$A$2:C131,3,0)," ") -> ДДС отчетного месяца. Без НДС! | B109: =IFERROR(__xludf.DUMMYFUNCTION("""COMPUTED_VALUE"""),"Представительские расходы") -> Представительские расходы | C109: -900 | D109: -60 | I109: =sum(C109:H109) -> -960 | J109: -500 | P109: =SUM(J109:K109) -> -500 | Q109: =I109-P109 -> -460 | R109: =IFERROR(I109/P109,0) -> 1.92 | S109: =IF(Q109=0,"",IF(R109=0,"обратить внимание",IF(R109>1,"перерасход","экономия"))) -> перерасход
A110: =IFERROR(VLOOKUP(B110,'Статьи'!$A$2:C132,3,0)," ") -> ДДС отчетного месяца. Без НДС! | B110: =IFERROR(__xludf.DUMMYFUNCTION("""COMPUTED_VALUE"""),"Содержание офиса") -> Содержание офиса | I110: =sum(C110:H110) -> 0 | J110: 0 | P110: =SUM(J110:K110) -> 0 | Q110: =I110-P110 -> 0 | R110: =IFERROR(I110/P110,0) -> 0 | S110: =IF(Q110=0,"",IF(R110=0,"обратить внимание",IF(R110>1,"перерасход","экономия")))
A111: =IFERROR(VLOOKUP(B111,'Статьи'!$A$2:C133,3,0)," ") -> ДДС отчетного месяца. Без НДС! | B111: =IFERROR(__xludf.DUMMYFUNCTION("""COMPUTED_VALUE"""),"Услуги связи + Интернет") -> Услуги связи + Интернет | C111: -500 | I111: =sum(C111:H111) -> -500 | J111: -490.97 | P111: =SUM(J111:K111) -> -490.97 | Q111: =I111-P111 -> -9.03 | R111: =IFERROR(I111/P111,0) -> 1.0183922 | S111: =IF(Q111=0,"",IF(R111=0,"обратить внимание",IF(R111>1,"перерасход","экономия"))) -> перерасход
A112: =IFERROR(VLOOKUP(B112,'Статьи'!$A$2:C134,3,0)," ") -> ДДС отчетного месяца. Без НДС! | B112: =IFERROR(__xludf.DUMMYFUNCTION("""COMPUTED_VALUE"""),"Штрафы") -> Штрафы | I112: =sum(C112:H112) -> 0 | P112: =SUM(J112:K112) -> 0 | Q112: =I112-P112 -> 0 | R112: =IFERROR(I112/P112,0) -> 0 | S112: =IF(Q112=0,"",IF(R112=0,"обратить внимание",IF(R112>1,"перерасход","экономия")))
A113: =IFERROR(VLOOKUP(B113,'Статьи'!$A$2:C135,3,0)," ") | I113: =sum(C113:H113) -> 0 | P113: =SUM(J113:K113) -> 0 | Q113: =I113-P113 -> 0 | R113: =IFERROR(I113/P113,0) -> 0 | S113: =IF(Q113=0,"",IF(R113=0,"обратить внимание",IF(R113>1,"перерасход","экономия")))
A114: =IFERROR(VLOOKUP(B114,'Статьи'!$A$2:C136,3,0)," ") | I114: =sum(C114:H114) -> 0 | P114: =SUM(J114:K114) -> 0 | Q114: =I114-P114 -> 0 | R114: =IFERROR(I114/P114,0) -> 0 | S114: =IF(Q114=0,"",IF(R114=0,"обратить внимание",IF(R114>1,"перерасход","экономия")))
A115: =IFERROR(VLOOKUP(B115,'Статьи'!$A$2:C137,3,0)," ") | I115: =sum(C115:H115) -> 0 | P115: =SUM(J115:K115) -> 0 | Q115: =I115-P115 -> 0 | R115: =IFERROR(I115/P115,0) -> 0 | S115: =IF(Q115=0,"",IF(R115=0,"обратить внимание",IF(R115>1,"перерасход","экономия")))
A116: =IFERROR(VLOOKUP(B116,'Статьи'!$A$2:C138,3,0)," ") | I116: =sum(C116:H116) -> 0 | P116: =SUM(J116:K116) -> 0 | Q116: =I116-P116 -> 0 | R116: =IFERROR(I116/P116,0) -> 0 | S116: =IF(Q116=0,"",IF(R116=0,"обратить внимание",IF(R116>1,"перерасход","экономия")))
A117: =IFERROR(VLOOKUP(B117,'Статьи'!$A$2:C139,3,0)," ") | I117: =sum(C117:H117) -> 0 | P117: =SUM(J117:K117) -> 0 | Q117: =I117-P117 -> 0 | R117: =IFERROR(I117/P117,0) -> 0 | S117: =IF(Q117=0,"",IF(R117=0,"обратить внимание",IF(R117>1,"перерасход","экономия")))
A118: =IFERROR(VLOOKUP(B118,'Статьи'!$A$2:C140,3,0)," ") | I118: =sum(C118:H118) -> 0 | P118: =SUM(J118:K118) -> 0 | Q118: =I118-P118 -> 0 | R118: =IFERROR(I118/P118,0) -> 0 | S118: =IF(Q118=0,"",IF(R118=0,"обратить внимание",IF(R118>1,"перерасход","экономия")))
A119: =IFERROR(VLOOKUP(B119,'Статьи'!$A$2:C141,3,0)," ") | I119: =sum(C119:H119) -> 0 | P119: =SUM(J119:K119) -> 0 | Q119: =I119-P119 -> 0 | R119: =IFERROR(I119/P119,0) -> 0 | S119: =IF(Q119=0,"",IF(R119=0,"обратить внимание",IF(R119>1,"перерасход","экономия")))
A120: =IFERROR(VLOOKUP(B120,'Статьи'!$A$2:C142,3,0)," ") | I120: =sum(C120:H120) -> 0 | P120: =SUM(J120:K120) -> 0 | Q120: =I120-P120 -> 0 | R120: =IFERROR(I120/P120,0) -> 0 | S120: =IF(Q120=0,"",IF(R120=0,"обратить внимание",IF(R120>1,"перерасход","экономия")))
A121: =IFERROR(VLOOKUP(B121,'Статьи'!$A$2:C143,3,0)," ") | I121: =sum(C121:H121) -> 0 | P121: =SUM(J121:K121) -> 0 | Q121: =I121-P121 -> 0 | R121: =IFERROR(I121/P121,0) -> 0 | S121: =IF(Q121=0,"",IF(R121=0,"обратить внимание",IF(R121>1,"перерасход","экономия")))
A122: =IFERROR(VLOOKUP(B122,'Статьи'!$A$2:C144,3,0)," ") | I122: =sum(C122:H122) -> 0 | P122: =SUM(J122:K122) -> 0 | Q122: =I122-P122 -> 0 | R122: =IFERROR(I122/P122,0) -> 0 | S122: =IF(Q122=0,"",IF(R122=0,"обратить внимание",IF(R122>1,"перерасход","экономия")))
A123: =IFERROR(VLOOKUP(B123,'Статьи'!$A$2:C145,3,0)," ") | I123: =sum(C123:H123) -> 0 | P123: =SUM(J123:K123) -> 0 | Q123: =I123-P123 -> 0 | R123: =IFERROR(I123/P123,0) -> 0 | S123: =IF(Q123=0,"",IF(R123=0,"обратить внимание",IF(R123>1,"перерасход","экономия")))
A124: =IFERROR(VLOOKUP(B124,'Статьи'!$A$2:C146,3,0)," ") | I124: =sum(C124:H124) -> 0 | P124: =SUM(J124:K124) -> 0 | Q124: =I124-P124 -> 0 | R124: =IFERROR(I124/P124,0) -> 0 | S124: =IF(Q124=0,"",IF(R124=0,"обратить внимание",IF(R124>1,"перерасход","экономия")))
... A131: =IFERROR(VLOOKUP(B131,'Статьи'!$A$2:C153,3,0)," ") | I131: =sum(C131:H131) -> 0 | P131: =SUM(J131:K131) -> 0 | Q131: =I131-P131 -> 0 | R131: =IFERROR(I131/P131,0) -> 0 | S131: =IF(Q131=0,"",IF(R131=0,"обратить внимание",IF(R131>1,"перерасход","экономия")))
B132: Коммерческие | C132: =SUM(C133:C141) -> -20 | D132: =SUM(D133:D141) -> 0 | E132: =SUM(E133:E141) -> 0 | F132: =SUM(F133:F141) -> 0 | G132: =SUM(G133:G141) -> 0 | H132: =SUM(H133:H141) -> 0 | I132: =sum(C132:H132) -> -20 | J132: =SUM(J133:J141) -> -40 | K132: =SUM(K133:K141) -> 0 | L132: =SUM(L133:L141) -> 0 | M132: =SUM(M133:M141) -> 0 | N132: =SUM(N133:N141) -> 0 | O132: =SUM(O133:O141) -> 0 | P132: =SUM(P133:P141) -> -40 | Q132: =I132-P132 -> 20 | R132: =IFERROR(I132/P132,0) -> 0.5 | S132: =IF(Q132=0,"",IF(R132>1,"план не выполнен","выполнение")) -> выполнение
A133: =IFERROR(VLOOKUP(B133,'Статьи'!$A$2:C155,3,0)," ") -> ДДС отчетного месяца. Без НДС! | B133: =IFERROR(__xludf.DUMMYFUNCTION("iferror(filter('Статьи'!$A$1:$A182,'Статьи'!$B$1:$B182=$B$132))"),"Подписка на сайты по поиску клиентов") -> Подписка на сайты по поиску клиентов | C133: -20 | I133: =sum(C133:H133) -> -20 | J133: -40 | P133: =SUM(J133:K133) -> -40 | Q133: =I133-P133 -> 20 | R133: =IFERROR(I133/P133,0) -> 0.5 | S133: =IF(Q133=0,"",IF(R133=0,"обратить внимание",IF(R133>1,"перерасход","экономия"))) -> экономия
A134: =IFERROR(VLOOKUP(B134,'Статьи'!$A$2:C156,3,0)," ") | I134: =sum(C134:H134) -> 0 | P134: =SUM(J134:K134) -> 0 | Q134: =I134-P134 -> 0 | R134: =IFERROR(I134/P134,0) -> 0 | S134: =IF(Q134=0,"",IF(R134=0,"обратить внимание",IF(R134>1,"перерасход","экономия")))
A135: =IFERROR(VLOOKUP(B135,'Статьи'!$A$2:C157,3,0)," ") | I135: =sum(C135:H135) -> 0 | P135: =SUM(J135:K135) -> 0 | Q135: =I135-P135 -> 0 | R135: =IFERROR(I135/P135,0) -> 0 | S135: =IF(Q135=0,"",IF(R135=0,"обратить внимание",IF(R135>1,"перерасход","экономия")))
A136: =IFERROR(VLOOKUP(B136,'Статьи'!$A$2:C158,3,0)," ") | I136: =sum(C136:H136) -> 0 | P136: =SUM(J136:K136) -> 0 | Q136: =I136-P136 -> 0 | R136: =IFERROR(I136/P136,0) -> 0 | S136: =IF(Q136=0,"",IF(R136=0,"обратить внимание",IF(R136>1,"перерасход","экономия")))
A137: =IFERROR(VLOOKUP(B137,'Статьи'!$A$2:C159,3,0)," ") | I137: =sum(C137:H137) -> 0 | P137: =SUM(J137:K137) -> 0 | Q137: =I137-P137 -> 0 | R137: =IFERROR(I137/P137,0) -> 0 | S137: =IF(Q137=0,"",IF(R137=0,"обратить внимание",IF(R137>1,"перерасход","экономия")))
A138: =IFERROR(VLOOKUP(B138,'Статьи'!$A$2:C160,3,0)," ") | I138: =sum(C138:H138) -> 0 | P138: =SUM(J138:K138) -> 0 | Q138: =I138-P138 -> 0 | R138: =IFERROR(I138/P138,0) -> 0 | S138: =IF(Q138=0,"",IF(R138=0,"обратить внимание",IF(R138>1,"перерасход","экономия")))
A139: =IFERROR(VLOOKUP(B139,'Статьи'!$A$2:C161,3,0)," ") | I139: =sum(C139:H139) -> 0 | P139: =SUM(J139:K139) -> 0 | Q139: =I139-P139 -> 0 | R139: =IFERROR(I139/P139,0) -> 0 | S139: =IF(Q139=0,"",IF(R139=0,"обратить внимание",IF(R139>1,"перерасход","экономия")))
A140: =IFERROR(VLOOKUP(B140,'Статьи'!$A$2:C162,3,0)," ") | I140: =sum(C140:H140) -> 0 | P140: =SUM(J140:K140) -> 0 | Q140: =I140-P140 -> 0 | R140: =IFERROR(I140/P140,0) -> 0 | S140: =IF(Q140=0,"",IF(R140=0,"обратить внимание",IF(R140>1,"перерасход","экономия")))
A141: =IFERROR(VLOOKUP(B141,'Статьи'!$A$2:C163,3,0)," ") | I141: =sum(C141:H141) -> 0 | P141: =sum(F141:J141) -> 0 | Q141: =I141-P141 -> 0 | R141: =IFERROR(I141/P141,0) -> 0 | S141: =IF(Q141=0,"",IF(R141=0,"обратить внимание",IF(R141>1,"перерасход","экономия")))
B142: Операционная прибыль (EBITDA) | C142: =C85+C88 -> 142769 | D142: =D85+D88 -> 653 | E142: =E85+E88 -> 0 | F142: =F85+F88 -> 0 | G142: =G85+G88 -> 0 | H142: =H85+H88 -> 0 | I142: =I85+I88 -> 143422 | J142: =J85+J88 -> 141897.03 | K142: =K85+K88 -> 0 | P142: =P85+P88 -> 141897.03 | Q142: =I142-P142 -> 1524.97 | R142: =IFERROR(I142/P142,0) -> 1.010747 | S142: =IF(Q142=0,"",IF(R142>1,"выполнение","план не выполнен")) -> выполнение
...

Sheet 2
C1: ФАКТ | J1: План | Q1: Отклонения
A2: Источники | C2: {=TRANSPOSE('Справочник'!D2:D7)} -> ООО "Весело живем" | D2: ООО "Некогда грустить" | E2: 3 | F2: 4 | G2: 5 | H2: 6 | I2: Итого | J2: {=TRANSPOSE('Справочник'!D2:D7)} -> ООО "Весело живем" | K2: ООО "Некогда грустить" | L2: 3 | M2: 4 | N2: 5 | O2: 6 | P2: Итого | Q2: факт-план, руб | R2: факт/план, % | S2: Результат
B3: Выручка | C3: =SUM(C4:C10) -> 0 | D3: =SUM(D4:D10) -> 0 | E3: =SUM(E4:E10) -> 0 | F3: =SUM(F4:F10) -> 0 | G3: =SUM(G4:G10) -> 0 | H3: =SUM(H4:H10) -> 0 | I3: =sum(C3:H3) -> 0 | J3: =SUM(J4:J10) -> 0 | K3: =SUM(K4:K10) -> 0 | P3: =SUM(P4:P10) -> 0 | Q3: =I3-P3 -> 0 | R3: =IFERROR(I3/P3,0) -> 0 | S3: =IF(Q3=0,"",IF(R3>1,"выполнение","план не выполнен"))
A4: =IFERROR(VLOOKUP(B4,'Статьи'!$A$2:C26,3,0)," ") -> 1С сч 90.01 убрать НДС! | B4: =IFERROR(__xludf.DUMMYFUNCTION("iferror(filter('Статьи'!$A$1:$A182,'Статьи'!$B$1:$B182=$B$3))"),"Выручка от аренды машиноместа") -> Выручка от аренды машиноместа | I4: =SUM(C4:H4) -> 0 | P4: =SUM(J4:K4) -> 0 | Q4: =I4-P4 -> 0 | R4: =IFERROR(I4/P4,0) -> 0 | S4: =IF(Q4=0,"",IF(R4=0,"обратить внимание",IF(R4>1,"выполнение","план не выполнен")))
A5: =IFERROR(VLOOKUP(B5,'Статьи'!$A$2:C27,3,0)," ") -> 1С сч 90.01 убрать НДС! | B5: =IFERROR(__xludf.DUMMYFUNCTION("""COMPUTED_VALUE"""),"Выручка за грузоперевозки") -> Выручка за грузоперевозки | I5: =SUM(C5:H5) -> 0 | P5: =SUM(J5:K5) -> 0 | Q5: =I5-P5 -> 0 | R5: =IFERROR(I5/P5,0) -> 0 | S5: =IF(Q5=0,"",IF(R5=0,"обратить внимание",IF(R5>1,"выполнение","план не выполнен")))
A6: =IFERROR(VLOOKUP(B6,'Статьи'!$A$2:C28,3,0)," ") | I6: =SUM(C6:H6) -> 0 | P6: =SUM(F6:J6) -> 0 | Q6: =I6-P6 -> 0 | R6: =IFERROR(I6/P6,0) -> 0 | S6: =IF(Q6=0,"",IF(R6=0,"обратить внимание",IF(R6>1,"выполнение","план не выполнен")))
A7: =IFERROR(VLOOKUP(B7,'Статьи'!$A$2:C29,3,0)," ") | I7: =SUM(C7:H7) -> 0 | P7: =SUM(F7:J7) -> 0 | Q7: =I7-P7 -> 0 | R7: =IFERROR(I7/P7,0) -> 0 | S7: =IF(Q7=0,"",IF(R7=0,"обратить внимание",IF(R7>1,"выполнение","план не выполнен")))
A8: =IFERROR(VLOOKUP(B8,'Статьи'!$A$2:C30,3,0)," ") | I8: =SUM(C8:H8) -> 0 | P8: =SUM(F8:J8) -> 0 | Q8: =I8-P8 -> 0 | R8: =IFERROR(I8/P8,0) -> 0 | S8: =IF(Q8=0,"",IF(R8=0,"обратить внимание",IF(R8>1,"выполнение","план не выполнен")))
A9: =IFERROR(VLOOKUP(B9,'Статьи'!$A$2:C31,3,0)," ") | Q9: =I9-P9 -> 0 | R9: =IFERROR(I9/P9,0) -> 0 | S9: =IF(Q9=0,"",IF(R9=0,"обратить внимание",IF(R9>1,"выполнение","план не выполнен")))
A10: =IFERROR(VLOOKUP(B10,'Статьи'!$A$2:C32,3,0)," ") | Q10: =I10-P10 -> 0 | R10: =IFERROR(I10/P10,0) -> 0 | S10: =IF(Q10=0,"",IF(R10=0,"обратить внимание",IF(R10>1,"выполнение","план не выполнен")))
B11: Производственные расходы | C11: =C12+C58 -> 0 | D11: =D12+D58 -> 0 | E11: =E12+E58 -> 0 | F11: =F12+F58 -> 0 | G11: =G12+G58 -> 0 | H11: =H12+H58 -> 0 | I11: =I12+I58 -> 0 | J11: =J12+J58 -> 0 | K11: =K12+K58 -> 0 | P11: =P12+P58 -> 0 | Q11: =I11-P11 -> 0 | R11: =IFERROR(I11/P11,0) -> 0 | S11: =IF(Q11=0,"",IF(R11>1,"план не выполнен","выполнение"))
B12: Переменные | C12: =sum(C13:C54) -> 0 | D12: =sum(D13:D54) -> 0 | E12: =sum(E13:E54) -> 0 | F12: =sum(F13:F54) -> 0 | G12: =sum(G13:G54) -> 0 | H12: =sum(H13:H54) -> 0 | I12: =sum(I13:I54) -> 0 | J12: =sum(J13:J54) -> 0 | K12: =sum(K13:K54) -> 0 | P12: =sum(P13:P54) -> 0 | Q12: =I12-P12 -> 0 | R12: =IFERROR(I12/P12,0) -> 0 | S12: =IF(Q12=0,"",IF(R12=0,"обратить внимание",IF(R12>1,"перерасход","экономия")))
A13: =IFERROR(VLOOKUP(B13,'Статьи'!$A$2:C35,3,0)," ") -> ДДС отчетного месяца. Без НДС! | B13: =IFERROR(__xludf.DUMMYFUNCTION("iferror(filter('Статьи'!$A$1:$A182,'Статьи'!$B$1:$B182=$B$12))"),"Комиссия топливных компаний") -> Комиссия топливных компаний | I13: =sum(C13:H13) -> 0 | P13: =SUM(J13:K13) -> 0 | Q13: =I13-P13 -> 0 | R13: =IFERROR(I13/P13,0) -> 0 | S13: =IF(Q13=0,"",IF(R13=0,"обратить внимание",IF(R13>1,"перерасход","экономия")))
A14: =IFERROR(VLOOKUP(B14,'Статьи'!$A$2:C36,3,0)," ") -> 1С | B14: =IFERROR(__xludf.DUMMYFUNCTION("""COMPUTED_VALUE"""),"Топливо для грузовых авто ") -> Топливо для грузовых авто | I14: =sum(C14:H14) -> 0 | P14: =SUM(J14:K14) -> 0 | Q14: =I14-P14 -> 0 | R14: =IFERROR(I14/P14,0) -> 0 | S14: =IF(Q14=0,"",IF(R14=0,"обратить внимание",IF(R14>1,"перерасход","экономия")))
A15: =IFERROR(VLOOKUP(B15,'Статьи'!$A$2:C37,3,0)," ") | I15: =sum(C15:H15) -> 0 | P15: =SUM(J15:K15) -> 0 | Q15: =I15-P15 -> 0 | R15: =IFERROR(I15/P15,0) -> 0 | S15: =IF(Q15=0,"",IF(R15=0,"обратить внимание",IF(R15>1,"перерасход","экономия")))
A16: =IFERROR(VLOOKUP(B16,'Статьи'!$A$2:C38,3,0)," ") | I16: =sum(C16:H16) -> 0 | P16: =SUM(J16:K16) -> 0 | Q16: =I16-P16 -> 0 | R16: =IFERROR(I16/P16,0) -> 0 | S16: =IF(Q16=0,"",IF(R16=0,"обратить внимание",IF(R16>1,"перерасход","экономия")))
A17: =IFERROR(VLOOKUP(B17,'Статьи'!$A$2:C39,3,0)," ") | I17: =sum(C17:H17) -> 0 | P17: =sum(F17:J17) -> 0 | Q17: =I17-P17 -> 0 | R17: =IFERROR(I17/P17,0) -> 0 | S17: =IF(Q17=0,"",IF(R17=0,"обратить внимание",IF(R17>1,"перерасход","экономия")))
I18: =sum(C18:H18) -> 0 | P18: =sum(F18:J18) -> 0 | Q18: =I18-P18 -> 0 | R18: =IFERROR(I18/P18,0) -> 0 | S18: =IF(Q18=0,0,IF(R18>1,"перерасход","экономия")) -> 0
I19: =sum(C19:H19) -> 0 | P19: =sum(F19:J19) -> 0 | Q19: =I19-P19 -> 0 | R19: =IFERROR(I19/P19,0) -> 0 | S19: =IF(Q19=0,0,IF(R19>1,"перерасход","экономия")) -> 0
I20: =sum(C20:H20) -> 0 | P20: =sum(F20:J20) -> 0 | Q20: =I20-P20 -> 0 | R20: =IFERROR(I20/P20,0) -> 0 | S20: =IF(Q20=0,0,IF(R20>1,"перерасход","экономия")) -> 0
I21: =sum(C21:H21) -> 0 | P21: =sum(F21:J21) -> 0 | Q21: =I21-P21 -> 0 | R21: =IFERROR(I21/P21,0) -> 0 | S21: =IF(Q21=0,0,IF(R21>1,"перерасход","экономия")) -> 0
I22: =sum(C22:H22) -> 0 | P22: =sum(F22:J22) -> 0 | Q22: =I22-P22 -> 0 | R22: =IFERROR(I22/P22,0) -> 0 | S22: =IF(Q22=0,0,IF(R22>1,"перерасход","экономия")) -> 0
I23: =sum(C23:H23) -> 0 | P23: =sum(F23:J23) -> 0 | Q23: =I23-P23 -> 0 | R23: =IFERROR(I23/P23,0) -> 0 | S23: =IF(Q23=0,0,IF(R23>1,"перерасход","экономия")) -> 0
I24: =sum(C24:H24) -> 0 | P24: =sum(F24:J24) -> 0 | Q24: =I24-P24 -> 0 | R24: =IFERROR(I24/P24,0) -> 0 | S24: =IF(Q24=0,0,IF(R24>1,"перерасход","экономия")) -> 0
I25: =sum(C25:H25) -> 0 | P25: =sum(F25:J25) -> 0 | Q25: =I25-P25 -> 0 | R25: =IFERROR(I25/P25,0) -> 0 | S25: =IF(Q25=0,0,IF(R25>1,"перерасход","экономия")) -> 0
I26: =sum(C26:H26) -> 0 | P26: =sum(F26:J26) -> 0 | Q26: =I26-P26 -> 0 | R26: =IFERROR(I26/P26,0) -> 0 | S26: =IF(Q26=0,0,IF(R26>1,"перерасход","экономия")) -> 0
I27: =sum(C27:H27) -> 0 | P27: =sum(F27:J27) -> 0 | Q27: =I27-P27 -> 0 | R27: =IFERROR(I27/P27,0) -> 0 | S27: =IF(Q27=0,0,IF(R27>1,"перерасход","экономия")) -> 0
I28: =sum(C28:H28) -> 0 | P28: =sum(F28:J28) -> 0 | Q28: =I28-P28 -> 0 | R28: =IFERROR(I28/P28,0) -> 0 | S28: =IF(Q28=0,0,IF(R28>1,"перерасход","экономия")) -> 0
I29: =sum(C29:H29) -> 0 | P29: =sum(F29:J29) -> 0 | Q29: =I29-P29 -> 0 | R29: =IFERROR(I29/P29,0) -> 0 | S29: =IF(Q29=0,0,IF(R29>1,"перерасход","экономия")) -> 0
... I54: =sum(C54:H54) -> 0 | P54: =sum(F54:J54) -> 0 | Q54: =I54-P54 -> 0 | R54: =IFERROR(I54/P54,0) -> 0 | S54: =IF(Q54=0,0,IF(R54>1,"перерасход","экономия")) -> 0
B55: Маржинальный доход | C55: =C3+C12 -> 0 | D55: =D3+D12 -> 0 | E55: =E3+E12 -> 0 | F55: =F3+F12 -> 0 | G55: =G3+G12 -> 0 | H55: =H3+H12 -> 0 | I55: =I3+I12 -> 0 | J55: =J3+J12 -> 0 | K55: =K3+K12 -> 0 | P55: =P3+P12 -> 0 | Q55: =I55-P55 -> 0 | R55: =IFERROR(I55/P55,0) -> 0 | S55: =IF(Q55=0,"",IF(R55>1,"выполнение","план не выполнен"))
B56: Рентабельность по марже | C56: =IFERROR(C55/C$3,"") | D56: =IFERROR(D55/D$3,"") | E56: =IFERROR(E55/E$3,"") | F56: =IFERROR(F55/F$3,"") | G56: =IFERROR(G55/G$3,"") | H56: =IFERROR(H55/H$3,"") | I56: =IFERROR(I55/I$3,"") | J56: =IFERROR(J55/J$3,"") | K56: =IFERROR(K55/K$3,"") | P56: =IFERROR(P55/P$3,"")
B58: Общепроизводственные | C58: =sum(C59:C79) -> 0 | D58: =sum(D59:D79) -> 0 | E58: =sum(E59:E79) -> 0 | F58: =sum(F59:F79) -> 0 | G58: =sum(G59:G79) -> 0 | H58: =sum(H59:H79) -> 0 | I58: =SUM(I59:I84) -> 0 | J58: =SUM(J59:J84) -> 0 | K58: =SUM(K59:K84) -> 0 | P58: =SUM(P59:P84) -> 0 | Q58: =I58-P58 -> 0 | R58: =IFERROR(I58/P58,0) -> 0 | S58: =IF(Q58=0,"",IF(R58>1,"план не выполнен","выполнение"))
A59: =IFERROR(VLOOKUP(B59,'Статьи'!$A$2:C81,3,0)," ") -> 1С | B59: =IFERROR(__xludf.DUMMYFUNCTION("iferror(filter('Статьи'!$A$1:$A182,'Статьи'!$B$1:$B182=$B$58))"),"Зарплата производственного персонала") -> Зарплата производственного персонала | I59: =SUM(C59:H59) -> 0 | P59: =SUM(J59:K59) -> 0 | Q59: =I59-P59 -> 0 | R59: =IFERROR(I59/P59,0) -> 0 | S59: =IF(Q59=0,"",IF(R59=0,"обратить внимание",IF(R59>1,"перерасход","экономия")))
A60: =IFERROR(VLOOKUP(B60,'Статьи'!$A$2:C82,3,0)," ") -> ДДС отчетного месяца. Без НДС! | B60: =IFERROR(__xludf.DUMMYFUNCTION("""COMPUTED_VALUE"""),"Таможенные расходы") -> Таможенные расходы | I60: =SUM(C60:H60) -> 0 | P60: =SUM(J60:K60) -> 0 | Q60: =I60-P60 -> 0 | R60: =IFERROR(I60/P60,0) -> 0 | S60: =IF(Q60=0,"",IF(R60=0,"обратить внимание",IF(R60>1,"перерасход","экономия")))
A61: =IFERROR(VLOOKUP(B61,'Статьи'!$A$2:C83,3,0)," ") | I61: =SUM(C61:H61) -> 0 | P61: =SUM(J61:K61) -> 0 | Q61: =I61-P61 -> 0 | R61: =IFERROR(I61/P61,0) -> 0 | S61: =IF(Q61=0,"",IF(R61=0,"обратить внимание",IF(R61>1,"перерасход","экономия")))
A62: =IFERROR(VLOOKUP(B62,'Статьи'!$A$2:C84,3,0)," ") | I62: =SUM(C62:H62) -> 0 | P62: =SUM(J62:K62) -> 0 | Q62: =I62-P62 -> 0 | R62: =IFERROR(I62/P62,0) -> 0 | S62: =IF(Q62=0,"",IF(R62=0,"обратить внимание",IF(R62>1,"перерасход","экономия")))
A63: =IFERROR(VLOOKUP(B63,'Статьи'!$A$2:C85,3,0)," ") | I63: =SUM(C63:H63) -> 0 | P63: =SUM(J63:K63) -> 0 | Q63: =I63-P63 -> 0 | R63: =IFERROR(I63/P63,0) -> 0 | S63: =IF(Q63=0,"",IF(R63=0,"обратить внимание",IF(R63>1,"перерасход","экономия")))
A64: =IFERROR(VLOOKUP(B64,'Статьи'!$A$2:C86,3,0)," ") | I64: =SUM(C64:H64) -> 0 | P64: =SUM(J64:K64) -> 0 | Q64: =I64-P64 -> 0 | R64: =IFERROR(I64/P64,0) -> 0 | S64: =IF(Q64=0,"",IF(R64=0,"обратить внимание",IF(R64>1,"перерасход","экономия")))
A65: =IFERROR(VLOOKUP(B65,'Статьи'!$A$2:C87,3,0)," ") | I65: =SUM(C65:H65) -> 0 | P65: =SUM(J65:K65) -> 0 | Q65: =I65-P65 -> 0 | R65: =IFERROR(I65/P65,0) -> 0 | S65: =IF(Q65=0,"",IF(R65=0,"обратить внимание",IF(R65>1,"перерасход","экономия")))
A66: =IFERROR(VLOOKUP(B66,'Статьи'!$A$2:C88,3,0)," ") | I66: =SUM(C66:H66) -> 0 | P66: =SUM(J66:K66) -> 0 | Q66: =I66-P66 -> 0 | R66: =IFERROR(I66/P66,0) -> 0 | S66: =IF(Q66=0,"",IF(R66=0,"обратить внимание",IF(R66>1,"перерасход","экономия")))
A67: =IFERROR(VLOOKUP(B67,'Статьи'!$A$2:C89,3,0)," ") | I67: =SUM(C67:H67) -> 0 | P67: =SUM(J67:K67) -> 0 | Q67: =I67-P67 -> 0 | R67: =IFERROR(I67/P67,0) -> 0 | S67: =IF(Q67=0,"",IF(R67=0,"обратить внимание",IF(R67>1,"перерасход","экономия")))
A68: =IFERROR(VLOOKUP(B68,'Статьи'!$A$2:C90,3,0)," ") | I68: =SUM(C68:H68) -> 0 | P68: =SUM(J68:K68) -> 0 | Q68: =I68-P68 -> 0 | R68: =IFERROR(I68/P68,0) -> 0 | S68: =IF(Q68=0,"",IF(R68=0,"обратить внимание",IF(R68>1,"перерасход","экономия")))
A69: =IFERROR(VLOOKUP(B69,'Статьи'!$A$2:C91,3,0)," ") | I69: =SUM(C69:H69) -> 0 | P69: =SUM(J69:K69) -> 0 | Q69: =I69-P69 -> 0 | R69: =IFERROR(I69/P69,0) -> 0 | S69: =IF(Q69=0,"",IF(R69=0,"обратить внимание",IF(R69>1,"перерасход","экономия")))
A70: =IFERROR(VLOOKUP(B70,'Статьи'!$A$2:C92,3,0)," ") | I70: =SUM(C70:H70) -> 0 | P70: =SUM(J70:K70) -> 0 | Q70: =I70-P70 -> 0 | R70: =IFERROR(I70/P70,0) -> 0 | S70: =IF(Q70=0,"",IF(R70=0,"обратить внимание",IF(R70>1,"перерасход","экономия")))
A71: =IFERROR(VLOOKUP(B71,'Статьи'!$A$2:C93,3,0)," ") | I71: =SUM(C71:H71) -> 0 | P71: =SUM(J71:K71) -> 0 | Q71: =I71-P71 -> 0 | R71: =IFERROR(I71/P71,0) -> 0 | S71: =IF(Q71=0,"",IF(R71=0,"обратить внимание",IF(R71>1,"перерасход","экономия")))
A72: =IFERROR(VLOOKUP(B72,'Статьи'!$A$2:C94,3,0)," ") | I72: =SUM(C72:H72) -> 0 | P72: =SUM(J72:K72) -> 0 | Q72: =I72-P72 -> 0 | R72: =IFERROR(I72/P72,0) -> 0 | S72: =IF(Q72=0,"",IF(R72=0,"обратить внимание",IF(R72>1,"перерасход","экономия")))
... A84: =IFERROR(VLOOKUP(B84,'Статьи'!$A$2:C106,3,0)," ") | I84: =SUM(C84:H84) -> 0 | P84: =SUM(J84:K84) -> 0 | Q84: =I84-P84 -> 0 | R84: =IFERROR(I84/P84,0) -> 0 | S84: =IF(Q84=0,"",IF(R84=0,"обратить внимание",IF(R84>1,"перерасход","экономия")))
B85: Валовая прибыль | C85: =C55+C58 -> 0 | D85: =D55+D58 -> 0 | E85: =E55+E58 -> 0 | F85: =F55+F58 -> 0 | G85: =G55+G58 -> 0 | H85: =H55+H58 -> 0 | I85: =I55+I58 -> 0 | J85: =J55+J58 -> 0 | K85: =K55+K58 -> 0 | P85: =P55+P58 -> 0 | Q85: =I85-P85 -> 0 | R85: =IFERROR(I85/P85,0) -> 0 | S85: =IF(Q85=0,"",IF(R85>1,"выполнение","план не выполнен"))
B86: Рентабельность по валовой прибыли, % | C86: =IFERROR(C85/C$3,"") | D86: =IFERROR(D85/D$3,"") | E86: =IFERROR(E85/E$3,"") | F86: =IFERROR(F85/F$3,"") | G86: =IFERROR(G85/G$3,"") | H86: =IFERROR(H85/H$3,"") | I86: =IFERROR(I85/I$3,"") | J86: =IFERROR(J85/J$3,"") | K86: =IFERROR(K85/K$3,"") | P86: =IFERROR(P85/P$3,"") | S86: =IF(Q86=0,"",IF(Q86=0,0,IF(R86>1,"перерасход","экономия")))
S87: =IF(Q87=0,"",IF(Q87=0,0,IF(R87>1,"перерасход","экономия")))
B88: Косвенные расходы | C88: =C101+C132+C89 -> 0 | D88: =D101+D132+D89 -> 0 | E88: =E101+E132+E89 -> 0 | F88: =F101+F132+F89 -> 0 | G88: =G101+G132+G89 -> 0 | H88: =H101+H132+H89 -> 0 | I88: =I101+I132+I89 -> 0 | J88: =J101+J132+J89 -> 0 | K88: =K101+K132+K89 -> 0 | P88: =P101+P132+P89 -> 0 | Q88: =I88-P88 -> 0 | R88: =IFERROR(I88/P88,0) -> 0 | S88: =IF(Q88=0,"",IF(R88>1,"план не выполнен","выполнение"))
B89: Косвенные производственные | C89: =SUM(C90:C100) -> 0 | D89: =SUM(D90:D100) -> 0 | E89: =SUM(E90:E100) -> 0 | F89: =SUM(F90:F100) -> 0 | G89: =SUM(G90:G100) -> 0 | H89: =SUM(H90:H100) -> 0 | I89: =SUM(I90:I100) -> 0 | J89: =SUM(J90:J100) -> 0 | K89: =SUM(K90:K100) -> 0 | P89: =SUM(P90:P100) -> 0 | Q89: =I89-P89 -> 0 | R89: =IFERROR(I89/P89,0) -> 0 | S89: =IF(Q89=0,"",IF(Q89=0,0,IF(R89>1,"перерасход","экономия")))
A90: =IFERROR(VLOOKUP(B90,'Статьи'!$A$2:C112,3,0)," ") | B90: =IFERROR(__xludf.DUMMYFUNCTION("iferror(filter('Статьи'!$A$1:$A182,'Статьи'!$B$1:$B182=$B$89))"),"") | I90: =sum(C90:H90) -> 0 | P90: =SUM(J90:K90) -> 0 | Q90: =I90-P90 -> 0 | R90: =IFERROR(I90/P90,0) -> 0 | S90: =IF(Q90=0,"",IF(R90=0,"обратить внимание",IF(R90>1,"перерасход","экономия")))
A91: =IFERROR(VLOOKUP(B91,'Статьи'!$A$2:C113,3,0)," ") | I91: =sum(C91:H91) -> 0 | P91: =SUM(J91:K91) -> 0 | Q91: =I91-P91 -> 0 | R91: =IFERROR(I91/P91,0) -> 0 | S91: =IF(Q91=0,"",IF(R91=0,"обратить внимание",IF(R91>1,"перерасход","экономия")))
A92: =IFERROR(VLOOKUP(B92,'Статьи'!$A$2:C114,3,0)," ") | I92: =sum(C92:H92) -> 0 | P92: =SUM(J92:K92) -> 0 | Q92: =I92-P92 -> 0 | R92: =IFERROR(I92/P92,0) -> 0 | S92: =IF(Q92=0,"",IF(R92=0,"обратить внимание",IF(R92>1,"перерасход","экономия")))
A93: =IFERROR(VLOOKUP(B93,'Статьи'!$A$2:C115,3,0)," ") | I93: =sum(C93:H93) -> 0 | P93: =SUM(J93:K93) -> 0 | Q93: =I93-P93 -> 0 | R93: =IFERROR(I93/P93,0) -> 0 | S93: =IF(Q93=0,"",IF(R93=0,"обратить внимание",IF(R93>1,"перерасход","экономия")))
A94: =IFERROR(VLOOKUP(B94,'Статьи'!$A$2:C116,3,0)," ") | I94: =sum(C94:H94) -> 0 | P94: =SUM(J94:K94) -> 0 | Q94: =I94-P94 -> 0 | R94: =IFERROR(I94/P94,0) -> 0 | S94: =IF(Q94=0,"",IF(R94=0,"обратить внимание",IF(R94>1,"перерасход","экономия")))
I95: =sum(C95:H95) -> 0 | P95: =sum(F95:J95) -> 0 | Q95: =I95-P95 -> 0 | R95: =IFERROR(I95/P95,0) -> 0 | S95: =IF(Q95=0,"",IF(Q95=0,0,IF(R95>1,"перерасход","экономия")))
I96: =sum(C96:H96) -> 0 | P96: =sum(F96:J96) -> 0 | Q96: =I96-P96 -> 0 | R96: =IFERROR(I96/P96,0) -> 0 | S96: =IF(Q96=0,"",IF(Q96=0,0,IF(R96>1,"перерасход","экономия")))
I97: =sum(C97:H97) -> 0 | P97: =sum(F97:J97) -> 0 | Q97: =I97-P97 -> 0 | R97: =IFERROR(I97/P97,0) -> 0 | S97: =IF(Q97=0,"",IF(Q97=0,0,IF(R97>1,"перерасход","экономия")))
I98: =sum(C98:H98) -> 0 | P98: =sum(F98:J98) -> 0 | Q98: =I98-P98 -> 0 | R98: =IFERROR(I98/P98,0) -> 0 | S98: =IF(Q98=0,"",IF(Q98=0,0,IF(R98>1,"перерасход","экономия")))
I99: =sum(C99:H99) -> 0 | P99: =sum(F99:J99) -> 0 | Q99: =I99-P99 -> 0 | R99: =IFERROR(I99/P99,0) -> 0 | S99: =IF(Q99=0,"",IF(Q99=0,0,IF(R99>1,"перерасход","экономия")))
I100: =sum(C100:H100) -> 0 | P100: =sum(F100:J100) -> 0 | Q100: =I100-P100 -> 0 | R100: =IFERROR(I100/P100,0) -> 0 | S100: =IF(Q100=0,"",IF(Q100=0,0,IF(R100>1,"перерасход","экономия")))
B101: Административные | C101: =SUM(C102:C131) -> 0 | D101: =SUM(D102:D131) -> 0 | E101: =SUM(E102:E131) -> 0 | F101: =SUM(F102:F131) -> 0 | G101: =SUM(G102:G131) -> 0 | H101: =SUM(H102:H131) -> 0 | I101: =SUM(I102:I131) -> 0 | J101: =SUM(J102:J131) -> 0 | K101: =SUM(K102:K131) -> 0 | P101: =SUM(P102:P131) -> 0 | Q101: =I101-P101 -> 0 | R101: =IFERROR(I101/P101,0) -> 0 | S101: =IF(Q101=0,"",IF(R101>1,"план не выполнен","выполнение"))
A102: =IFERROR(VLOOKUP(B102,'Статьи'!$A$2:C124,3,0)," ") -> 1С | B102: =IFERROR(__xludf.DUMMYFUNCTION("iferror(filter('Статьи'!$A$1:$A182,'Статьи'!$B$1:$B182=$B$101))"),"Аренда, коммунальные услуги") -> Аренда, коммунальные услуги | I102: =sum(C102:H102) -> 0 | P102: =SUM(J102:K102) -> 0 | Q102: =I102-P102 -> 0 | R102: =IFERROR(I102/P102,0) -> 0 | S102: =IF(Q102=0,"",IF(R102=0,"обратить внимание",IF(R102>1,"перерасход","экономия")))
A103: =IFERROR(VLOOKUP(B103,'Статьи'!$A$2:C125,3,0)," ") -> 1С | B103: =IFERROR(__xludf.DUMMYFUNCTION("""COMPUTED_VALUE"""),"Аутсорсинг и прочие услуги") -> Аутсорсинг и прочие услуги | I103: =sum(C103:H103) -> 0 | P103: =SUM(J103:K103) -> 0 | Q103: =I103-P103 -> 0 | R103: =IFERROR(I103/P103,0) -> 0 | S103: =IF(Q103=0,"",IF(R103=0,"обратить внимание",IF(R103>1,"перерасход","экономия")))
A104: =IFERROR(VLOOKUP(B104,'Статьи'!$A$2:C126,3,0)," ") -> 1С | B104: =IFERROR(__xludf.DUMMYFUNCTION("""COMPUTED_VALUE"""),"Командировочные расходы") -> Командировочные расходы | I104: =sum(C104:H104) -> 0 | P104: =SUM(J104:K104) -> 0 | Q104: =I104-P104 -> 0 | R104: =IFERROR(I104/P104,0) -> 0 | S104: =IF(Q104=0,"",IF(R104=0,"обратить внимание",IF(R104>1,"перерасход","экономия")))
A105: =IFERROR(VLOOKUP(B105,'Статьи'!$A$2:C127,3,0)," ") -> ДДС отчетного месяца. Без НДС! | B105: =IFERROR(__xludf.DUMMYFUNCTION("""COMPUTED_VALUE"""),"Комиссии банка") -> Комиссии банка | I105: =sum(C105:H105) -> 0 | P105: =SUM(J105:K105) -> 0 | Q105: =I105-P105 -> 0 | R105: =IFERROR(I105/P105,0) -> 0 | S105: =IF(Q105=0,"",IF(R105=0,"обратить внимание",IF(R105>1,"перерасход","экономия")))
A106: =IFERROR(VLOOKUP(B106,'Статьи'!$A$2:C128,3,0)," ") -> ДДС отчетного месяца. Без НДС! | B106: =IFERROR(__xludf.DUMMYFUNCTION("""COMPUTED_VALUE"""),"Обучение сотрудников") -> Обучение сотрудников | I106: =sum(C106:H106) -> 0 | P106: =SUM(J106:K106) -> 0 | Q106: =I106-P106 -> 0 | R106: =IFERROR(I106/P106,0) -> 0 | S106: =IF(Q106=0,"",IF(R106=0,"обратить внимание",IF(R106>1,"перерасход","экономия")))
A107: =IFERROR(VLOOKUP(B107,'Статьи'!$A$2:C129,3,0)," ") -> ДДС отчетного месяца. Без НДС! | B107: =IFERROR(__xludf.DUMMYFUNCTION("""COMPUTED_VALUE"""),"Подбор персонала") -> Подбор персонала | I107: =sum(C107:H107) -> 0 | P107: =SUM(J107:K107) -> 0 | Q107: =I107-P107 -> 0 | R107: =IFERROR(I107/P107,0) -> 0 | S107: =IF(Q107=0,"",IF(R107=0,"обратить внимание",IF(R107>1,"перерасход","экономия")))
A108: =IFERROR(VLOOKUP(B108,'Статьи'!$A$2:C130,3,0)," ") -> ДДС отчетного месяца. Без НДС! | B108: =IFERROR(__xludf.DUMMYFUNCTION("""COMPUTED_VALUE"""),"Почтовые расходы") -> Почтовые расходы | I108: =sum(C108:H108) -> 0 | P108: =SUM(J108:K108) -> 0 | Q108: =I108-P108 -> 0 | R108: =IFERROR(I108/P108,0) -> 0 | S108: =IF(Q108=0,"",IF(R108=0,"обратить внимание",IF(R108>1,"перерасход","экономия")))
A109: =IFERROR(VLOOKUP(B109,'Статьи'!$A$2:C131,3,0)," ") -> ДДС отчетного месяца. Без НДС! | B109: =IFERROR(__xludf.DUMMYFUNCTION("""COMPUTED_VALUE"""),"Представительские расходы") -> Представительские расходы | I109: =sum(C109:H109) -> 0 | P109: =SUM(J109:K109) -> 0 | Q109: =I109-P109 -> 0 | R109: =IFERROR(I109/P109,0) -> 0 | S109: =IF(Q109=0,"",IF(R109=0,"обратить внимание",IF(R109>1,"перерасход","экономия")))
A110: =IFERROR(VLOOKUP(B110,'Статьи'!$A$2:C132,3,0)," ") -> ДДС отчетного месяца. Без НДС! | B110: =IFERROR(__xludf.DUMMYFUNCTION("""COMPUTED_VALUE"""),"Содержание офиса") -> Содержание офиса | I110: =sum(C110:H110) -> 0 | P110: =SUM(J110:K110) -> 0 | Q110: =I110-P110 -> 0 | R110: =IFERROR(I110/P110,0) -> 0 | S110: =IF(Q110=0,"",IF(R110=0,"обратить внимание",IF(R110>1,"перерасход","экономия")))
A111: =IFERROR(VLOOKUP(B111,'Статьи'!$A$2:C133,3,0)," ") -> ДДС отчетного месяца. Без НДС! | B111: =IFERROR(__xludf.DUMMYFUNCTION("""COMPUTED_VALUE"""),"Услуги связи + Интернет") -> Услуги связи + Интернет | I111: =sum(C111:H111) -> 0 | P111: =SUM(J111:K111) -> 0 | Q111: =I111-P111 -> 0 | R111: =IFERROR(I111/P111,0) -> 0 | S111: =IF(Q111=0,"",IF(R111=0,"обратить внимание",IF(R111>1,"перерасход","экономия")))
A112: =IFERROR(VLOOKUP(B112,'Статьи'!$A$2:C134,3,0)," ") -> ДДС отчетного месяца. Без НДС! | B112: =IFERROR(__xludf.DUMMYFUNCTION("""COMPUTED_VALUE"""),"Штрафы") -> Штрафы | I112: =sum(C112:H112) -> 0 | P112: =SUM(J112:K112) -> 0 | Q112: =I112-P112 -> 0 | R112: =IFERROR(I112/P112,0) -> 0 | S112: =IF(Q112=0,"",IF(R112=0,"обратить внимание",IF(R112>1,"перерасход","экономия")))
A113: =IFERROR(VLOOKUP(B113,'Статьи'!$A$2:C135,3,0)," ") | I113: =sum(C113:H113) -> 0 | P113: =SUM(J113:K113) -> 0 | Q113: =I113-P113 -> 0 | R113: =IFERROR(I113/P113,0) -> 0 | S113: =IF(Q113=0,"",IF(R113=0,"обратить внимание",IF(R113>1,"перерасход","экономия")))
A114: =IFERROR(VLOOKUP(B114,'Статьи'!$A$2:C136,3,0)," ") | I114: =sum(C114:H114) -> 0 | P114: =SUM(J114:K114) -> 0 | Q114: =I114-P114 -> 0 | R114: =IFERROR(I114/P114,0) -> 0 | S114: =IF(Q114=0,"",IF(R114=0,"обратить внимание",IF(R114>1,"перерасход","экономия")))
A115: =IFERROR(VLOOKUP(B115,'Статьи'!$A$2:C137,3,0)," ") | I115: =sum(C115:H115) -> 0 | P115: =SUM(J115:K115) -> 0 | Q115: =I115-P115 -> 0 | R115: =IFERROR(I115/P115,0) -> 0 | S115: =IF(Q115=0,"",IF(R115=0,"обратить внимание",IF(R115>1,"перерасход","экономия")))
A116: =IFERROR(VLOOKUP(B116,'Статьи'!$A$2:C138,3,0)," ") | I116: =sum(C116:H116) -> 0 | P116: =SUM(J116:K116) -> 0 | Q116: =I116-P116 -> 0 | R116: =IFERROR(I116/P116,0) -> 0 | S116: =IF(Q116=0,"",IF(R116=0,"обратить внимание",IF(R116>1,"перерасход","экономия")))
A117: =IFERROR(VLOOKUP(B117,'Статьи'!$A$2:C139,3,0)," ") | I117: =sum(C117:H117) -> 0 | P117: =SUM(J117:K117) -> 0 | Q117: =I117-P117 -> 0 | R117: =IFERROR(I117/P117,0) -> 0 | S117: =IF(Q117=0,"",IF(R117=0,"обратить внимание",IF(R117>1,"перерасход","экономия")))
A118: =IFERROR(VLOOKUP(B118,'Статьи'!$A$2:C140,3,0)," ") | I118: =sum(C118:H118) -> 0 | P118: =SUM(J118:K118) -> 0 | Q118: =I118-P118 -> 0 | R118: =IFERROR(I118/P118,0) -> 0 | S118: =IF(Q118=0,"",IF(R118=0,"обратить внимание",IF(R118>1,"перерасход","экономия")))
A119: =IFERROR(VLOOKUP(B119,'Статьи'!$A$2:C141,3,0)," ") | I119: =sum(C119:H119) -> 0 | P119: =SUM(J119:K119) -> 0 | Q119: =I119-P119 -> 0 | R119: =IFERROR(I119/P119,0) -> 0 | S119: =IF(Q119=0,"",IF(R119=0,"обратить внимание",IF(R119>1,"перерасход","экономия")))
A120: =IFERROR(VLOOKUP(B120,'Статьи'!$A$2:C142,3,0)," ") | I120: =sum(C120:H120) -> 0 | P120: =SUM(J120:K120) -> 0 | Q120: =I120-P120 -> 0 | R120: =IFERROR(I120/P120,0) -> 0 | S120: =IF(Q120=0,"",IF(R120=0,"обратить внимание",IF(R120>1,"перерасход","экономия")))
A121: =IFERROR(VLOOKUP(B121,'Статьи'!$A$2:C143,3,0)," ") | I121: =sum(C121:H121) -> 0 | P121: =SUM(J121:K121) -> 0 | Q121: =I121-P121 -> 0 | R121: =IFERROR(I121/P121,0) -> 0 | S121: =IF(Q121=0,"",IF(R121=0,"обратить внимание",IF(R121>1,"перерасход","экономия")))
A122: =IFERROR(VLOOKUP(B122,'Статьи'!$A$2:C144,3,0)," ") | I122: =sum(C122:H122) -> 0 | P122: =SUM(J122:K122) -> 0 | Q122: =I122-P122 -> 0 | R122: =IFERROR(I122/P122,0) -> 0 | S122: =IF(Q122=0,"",IF(R122=0,"обратить внимание",IF(R122>1,"перерасход","экономия")))
A123: =IFERROR(VLOOKUP(B123,'Статьи'!$A$2:C145,3,0)," ") | I123: =sum(C123:H123) -> 0 | P123: =SUM(J123:K123) -> 0 | Q123: =I123-P123 -> 0 | R123: =IFERROR(I123/P123,0) -> 0 | S123: =IF(Q123=0,"",IF(R123=0,"обратить внимание",IF(R123>1,"перерасход","экономия")))
A124: =IFERROR(VLOOKUP(B124,'Статьи'!$A$2:C146,3,0)," ") | I124: =sum(C124:H124) -> 0 | P124: =SUM(J124:K124) -> 0 | Q124: =I124-P124 -> 0 | R124: =IFERROR(I124/P124,0) -> 0 | S124: =IF(Q124=0,"",IF(R124=0,"обратить внимание",IF(R124>1,"перерасход","экономия")))
... A131: =IFERROR(VLOOKUP(B131,'Статьи'!$A$2:C153,3,0)," ") | I131: =sum(C131:H131) -> 0 | P131: =SUM(J131:K131) -> 0 | Q131: =I131-P131 -> 0 | R131: =IFERROR(I131/P131,0) -> 0 | S131: =IF(Q131=0,"",IF(R131=0,"обратить внимание",IF(R131>1,"перерасход","экономия")))
B132: Коммерческие | C132: =SUM(C133:C141) -> 0 | D132: =SUM(D133:D141) -> 0 | E132: =SUM(E133:E141) -> 0 | F132: =SUM(F133:F141) -> 0 | G132: =SUM(G133:G141) -> 0 | H132: =SUM(H133:H141) -> 0 | I132: =sum(C132:H132) -> 0 | J132: =SUM(J133:J141) -> 0 | K132: =SUM(K133:K141) -> 0 | L132: =SUM(L133:L141) -> 0 | M132: =SUM(M133:M141) -> 0 | N132: =SUM(N133:N141) -> 0 | O132: =SUM(O133:O141) -> 0 | P132: =SUM(P133:P141) -> 0 | Q132: =I132-P132 -> 0 | R132: =IFERROR(I132/P132,0) -> 0 | S132: =IF(Q132=0,"",IF(R132>1,"план не выполнен","выполнение"))
A133: =IFERROR(VLOOKUP(B133,'Статьи'!$A$2:C155,3,0)," ") -> ДДС отчетного месяца. Без НДС! | B133: =IFERROR(__xludf.DUMMYFUNCTION("iferror(filter('Статьи'!$A$1:$A182,'Статьи'!$B$1:$B182=$B$132))"),"Подписка на сайты по поиску клиентов") -> Подписка на сайты по поиску клиентов | I133: =sum(C133:H133) -> 0 | P133: =SUM(J133:K133) -> 0 | Q133: =I133-P133 -> 0 | R133: =IFERROR(I133/P133,0) -> 0 | S133: =IF(Q133=0,"",IF(R133=0,"обратить внимание",IF(R133>1,"перерасход","экономия")))
A134: =IFERROR(VLOOKUP(B134,'Статьи'!$A$2:C156,3,0)," ") | I134: =sum(C134:H134) -> 0 | P134: =SUM(J134:K134) -> 0 | Q134: =I134-P134 -> 0 | R134: =IFERROR(I134/P134,0) -> 0 | S134: =IF(Q134=0,"",IF(R134=0,"обратить внимание",IF(R134>1,"перерасход","экономия")))
A135: =IFERROR(VLOOKUP(B135,'Статьи'!$A$2:C157,3,0)," ") | I135: =sum(C135:H135) -> 0 | P135: =SUM(J135:K135) -> 0 | Q135: =I135-P135 -> 0 | R135: =IFERROR(I135/P135,0) -> 0 | S135: =IF(Q135=0,"",IF(R135=0,"обратить внимание",IF(R135>1,"перерасход","экономия")))
A136: =IFERROR(VLOOKUP(B136,'Статьи'!$A$2:C158,3,0)," ") | I136: =sum(C136:H136) -> 0 | P136: =SUM(J136:K136) -> 0 | Q136: =I136-P136 -> 0 | R136: =IFERROR(I136/P136,0) -> 0 | S136: =IF(Q136=0,"",IF(R136=0,"обратить внимание",IF(R136>1,"перерасход","экономия")))
A137: =IFERROR(VLOOKUP(B137,'Статьи'!$A$2:C159,3,0)," ") | I137: =sum(C137:H137) -> 0 | P137: =SUM(J137:K137) -> 0 | Q137: =I137-P137 -> 0 | R137: =IFERROR(I137/P137,0) -> 0 | S137: =IF(Q137=0,"",IF(R137=0,"обратить внимание",IF(R137>1,"перерасход","экономия")))
A138: =IFERROR(VLOOKUP(B138,'Статьи'!$A$2:C160,3,0)," ") | I138: =sum(C138:H138) -> 0 | P138: =SUM(J138:K138) -> 0 | Q138: =I138-P138 -> 0 | R138: =IFERROR(I138/P138,0) -> 0 | S138: =IF(Q138=0,"",IF(R138=0,"обратить внимание",IF(R138>1,"перерасход","экономия")))
A139: =IFERROR(VLOOKUP(B139,'Статьи'!$A$2:C161,3,0)," ") | I139: =sum(C139:H139) -> 0 | P139: =SUM(J139:K139) -> 0 | Q139: =I139-P139 -> 0 | R139: =IFERROR(I139/P139,0) -> 0 | S139: =IF(Q139=0,"",IF(R139=0,"обратить внимание",IF(R139>1,"перерасход","экономия")))
A140: =IFERROR(VLOOKUP(B140,'Статьи'!$A$2:C162,3,0)," ") | I140: =sum(C140:H140) -> 0 | P140: =SUM(J140:K140) -> 0 | Q140: =I140-P140 -> 0 | R140: =IFERROR(I140/P140,0) -> 0 | S140: =IF(Q140=0,"",IF(R140=0,"обратить внимание",IF(R140>1,"перерасход","экономия")))
A141: =IFERROR(VLOOKUP(B141,'Статьи'!$A$2:C163,3,0)," ") | I141: =sum(C141:H141) -> 0 | P141: =sum(F141:J141) -> 0 | Q141: =I141-P141 -> 0 | R141: =IFERROR(I141/P141,0) -> 0 | S141: =IF(Q141=0,"",IF(R141=0,"обратить внимание",IF(R141>1,"перерасход","экономия")))
B142: Операционная прибыль (EBITDA) | C142: =C85+C88 -> 0 | D142: =D85+D88 -> 0 | E142: =E85+E88 -> 0 | F142: =F85+F88 -> 0 | G142: =G85+G88 -> 0 | H142: =H85+H88 -> 0 | I142: =I85+I88 -> 0 | J142: =J85+J88 -> 0 | K142: =K85+K88 -> 0 | P142: =P85+P88 -> 0 | Q142: =I142-P142 -> 0 | R142: =IFERROR(I142/P142,0) -> 0 | S142: =IF(Q142=0,"",IF(R142>1,"выполнение","план не выполнен"))
...

Sheet 3
C1: ФАКТ | J1: План | Q1: Отклонения
A2: Источники | C2: {=TRANSPOSE('Справочник'!D2:D7)} -> ООО "Весело живем" | D2: ООО "Некогда грустить" | E2: 3 | F2: 4 | G2: 5 | H2: 6 | I2: Итого | J2: {=TRANSPOSE('Справочник'!D2:D7)} -> ООО "Весело живем" | K2: ООО "Некогда грустить" | L2: 3 | M2: 4 | N2: 5 | O2: 6 | P2: Итого | Q2: факт-план, руб | R2: факт/план, % | S2: Результат
B3: Выручка | C3: =SUM(C4:C10) -> 0 | D3: =SUM(D4:D10) -> 0 | E3: =SUM(E4:E10) -> 0 | F3: =SUM(F4:F10) -> 0 | G3: =SUM(G4:G10) -> 0 | H3: =SUM(H4:H10) -> 0 | I3: =sum(C3:H3) -> 0 | J3: =SUM(J4:J10) -> 0 | K3: =SUM(K4:K10) -> 0 | P3: =SUM(P4:P10) -> 0 | Q3: =I3-P3 -> 0 | R3: =IFERROR(I3/P3,0) -> 0 | S3: =IF(Q3=0,"",IF(R3>1,"выполнение","план не выполнен"))
A4: =IFERROR(VLOOKUP(B4,'Статьи'!$A$2:C26,3,0)," ") -> 1С сч 90.01 убрать НДС! | B4: =IFERROR(__xludf.DUMMYFUNCTION("iferror(filter('Статьи'!$A$1:$A182,'Статьи'!$B$1:$B182=$B$3))"),"Выручка от аренды машиноместа") -> Выручка от аренды машиноместа | I4: =SUM(C4:H4) -> 0 | P4: =SUM(J4:K4) -> 0 | Q4: =I4-P4 -> 0 | R4: =IFERROR(I4/P4,0) -> 0 | S4: =IF(Q4=0,"",IF(R4=0,"обратить внимание",IF(R4>1,"выполнение","план не выполнен")))
A5: =IFERROR(VLOOKUP(B5,'Статьи'!$A$2:C27,3,0)," ") -> 1С сч 90.01 убрать НДС! | B5: =IFERROR(__xludf.DUMMYFUNCTION("""COMPUTED_VALUE"""),"Выручка за грузоперевозки") -> Выручка за грузоперевозки | I5: =SUM(C5:H5) -> 0 | P5: =SUM(J5:K5) -> 0 | Q5: =I5-P5 -> 0 | R5: =IFERROR(I5/P5,0) -> 0 | S5: =IF(Q5=0,"",IF(R5=0,"обратить внимание",IF(R5>1,"выполнение","план не выполнен")))
A6: =IFERROR(VLOOKUP(B6,'Статьи'!$A$2:C28,3,0)," ") | I6: =SUM(C6:H6) -> 0 | P6: =SUM(F6:J6) -> 0 | Q6: =I6-P6 -> 0 | R6: =IFERROR(I6/P6,0) -> 0 | S6: =IF(Q6=0,"",IF(R6=0,"обратить внимание",IF(R6>1,"выполнение","план не выполнен")))
A7: =IFERROR(VLOOKUP(B7,'Статьи'!$A$2:C29,3,0)," ") | I7: =SUM(C7:H7) -> 0 | P7: =SUM(F7:J7) -> 0 | Q7: =I7-P7 -> 0 | R7: =IFERROR(I7/P7,0) -> 0 | S7: =IF(Q7=0,"",IF(R7=0,"обратить внимание",IF(R7>1,"выполнение","план не выполнен")))
A8: =IFERROR(VLOOKUP(B8,'Статьи'!$A$2:C30,3,0)," ") | I8: =SUM(C8:H8) -> 0 | P8: =SUM(F8:J8) -> 0 | Q8: =I8-P8 -> 0 | R8: =IFERROR(I8/P8,0) -> 0 | S8: =IF(Q8=0,"",IF(R8=0,"обратить внимание",IF(R8>1,"выполнение","план не выполнен")))
A9: =IFERROR(VLOOKUP(B9,'Статьи'!$A$2:C31,3,0)," ") | Q9: =I9-P9 -> 0 | R9: =IFERROR(I9/P9,0) -> 0 | S9: =IF(Q9=0,"",IF(R9=0,"обратить внимание",IF(R9>1,"выполнение","план не выполнен")))
A10: =IFERROR(VLOOKUP(B10,'Статьи'!$A$2:C32,3,0)," ") | Q10: =I10-P10 -> 0 | R10: =IFERROR(I10/P10,0) -> 0 | S10: =IF(Q10=0,"",IF(R10=0,"обратить внимание",IF(R10>1,"выполнение","план не выполнен")))
B11: Производственные расходы | C11: =C12+C58 -> 0 | D11: =D12+D58 -> 0 | E11: =E12+E58 -> 0 | F11: =F12+F58 -> 0 | G11: =G12+G58 -> 0 | H11: =H12+H58 -> 0 | I11: =I12+I58 -> 0 | J11: =J12+J58 -> 0 | K11: =K12+K58 -> 0 | P11: =P12+P58 -> 0 | Q11: =I11-P11 -> 0 | R11: =IFERROR(I11/P11,0) -> 0 | S11: =IF(Q11=0,"",IF(R11>1,"план не выполнен","выполнение"))
B12: Переменные | C12: =sum(C13:C54) -> 0 | D12: =sum(D13:D54) -> 0 | E12: =sum(E13:E54) -> 0 | F12: =sum(F13:F54) -> 0 | G12: =sum(G13:G54) -> 0 | H12: =sum(H13:H54) -> 0 | I12: =sum(I13:I54) -> 0 | J12: =sum(J13:J54) -> 0 | K12: =sum(K13:K54) -> 0 | P12: =sum(P13:P54) -> 0 | Q12: =I12-P12 -> 0 | R12: =IFERROR(I12/P12,0) -> 0 | S12: =IF(Q12=0,"",IF(R12=0,"обратить внимание",IF(R12>1,"перерасход","экономия")))
A13: =IFERROR(VLOOKUP(B13,'Статьи'!$A$2:C35,3,0)," ") -> ДДС отчетного месяца. Без НДС! | B13: =IFERROR(__xludf.DUMMYFUNCTION("iferror(filter('Статьи'!$A$1:$A182,'Статьи'!$B$1:$B182=$B$12))"),"Комиссия топливных компаний") -> Комиссия топливных компаний | I13: =sum(C13:H13) -> 0 | P13: =SUM(J13:K13) -> 0 | Q13: =I13-P13 -> 0 | R13: =IFERROR(I13/P13,0) -> 0 | S13: =IF(Q13=0,"",IF(R13=0,"обратить внимание",IF(R13>1,"перерасход","экономия")))
A14: =IFERROR(VLOOKUP(B14,'Статьи'!$A$2:C36,3,0)," ") -> 1С | B14: =IFERROR(__xludf.DUMMYFUNCTION("""COMPUTED_VALUE"""),"Топливо для грузовых авто ") -> Топливо для грузовых авто | I14: =sum(C14:H14) -> 0 | P14: =SUM(J14:K14) -> 0 | Q14: =I14-P14 -> 0 | R14: =IFERROR(I14/P14,0) -> 0 | S14: =IF(Q14=0,"",IF(R14=0,"обратить внимание",IF(R14>1,"перерасход","экономия")))
A15: =IFERROR(VLOOKUP(B15,'Статьи'!$A$2:C37,3,0)," ") | I15: =sum(C15:H15) -> 0 | P15: =SUM(J15:K15) -> 0 | Q15: =I15-P15 -> 0 | R15: =IFERROR(I15/P15,0) -> 0 | S15: =IF(Q15=0,"",IF(R15=0,"обратить внимание",IF(R15>1,"перерасход","экономия")))
A16: =IFERROR(VLOOKUP(B16,'Статьи'!$A$2:C38,3,0)," ") | I16: =sum(C16:H16) -> 0 | P16: =SUM(J16:K16) -> 0 | Q16: =I16-P16 -> 0 | R16: =IFERROR(I16/P16,0) -> 0 | S16: =IF(Q16=0,"",IF(R16=0,"обратить внимание",IF(R16>1,"перерасход","экономия")))
A17: =IFERROR(VLOOKUP(B17,'Статьи'!$A$2:C39,3,0)," ") | I17: =sum(C17:H17) -> 0 | P17: =sum(F17:J17) -> 0 | Q17: =I17-P17 -> 0 | R17: =IFERROR(I17/P17,0) -> 0 | S17: =IF(Q17=0,"",IF(R17=0,"обратить внимание",IF(R17>1,"перерасход","экономия")))
I18: =sum(C18:H18) -> 0 | P18: =sum(F18:J18) -> 0 | Q18: =I18-P18 -> 0 | R18: =IFERROR(I18/P18,0) -> 0 | S18: =IF(Q18=0,0,IF(R18>1,"перерасход","экономия")) -> 0
I19: =sum(C19:H19) -> 0 | P19: =sum(F19:J19) -> 0 | Q19: =I19-P19 -> 0 | R19: =IFERROR(I19/P19,0) -> 0 | S19: =IF(Q19=0,0,IF(R19>1,"перерасход","экономия")) -> 0
I20: =sum(C20:H20) -> 0 | P20: =sum(F20:J20) -> 0 | Q20: =I20-P20 -> 0 | R20: =IFERROR(I20/P20,0) -> 0 | S20: =IF(Q20=0,0,IF(R20>1,"перерасход","экономия")) -> 0
I21: =sum(C21:H21) -> 0 | P21: =sum(F21:J21) -> 0 | Q21: =I21-P21 -> 0 | R21: =IFERROR(I21/P21,0) -> 0 | S21: =IF(Q21=0,0,IF(R21>1,"перерасход","экономия")) -> 0
I22: =sum(C22:H22) -> 0 | P22: =sum(F22:J22) -> 0 | Q22: =I22-P22 -> 0 | R22: =IFERROR(I22/P22,0) -> 0 | S22: =IF(Q22=0,0,IF(R22>1,"перерасход","экономия")) -> 0
I23: =sum(C23:H23) -> 0 | P23: =sum(F23:J23) -> 0 | Q23: =I23-P23 -> 0 | R23: =IFERROR(I23/P23,0) -> 0 | S23: =IF(Q23=0,0,IF(R23>1,"перерасход","экономия")) -> 0
I24: =sum(C24:H24) -> 0 | P24: =sum(F24:J24) -> 0 | Q24: =I24-P24 -> 0 | R24: =IFERROR(I24/P24,0) -> 0 | S24: =IF(Q24=0,0,IF(R24>1,"перерасход","экономия")) -> 0
I25: =sum(C25:H25) -> 0 | P25: =sum(F25:J25) -> 0 | Q25: =I25-P25 -> 0 | R25: =IFERROR(I25/P25,0) -> 0 | S25: =IF(Q25=0,0,IF(R25>1,"перерасход","экономия")) -> 0
I26: =sum(C26:H26) -> 0 | P26: =sum(F26:J26) -> 0 | Q26: =I26-P26 -> 0 | R26: =IFERROR(I26/P26,0) -> 0 | S26: =IF(Q26=0,0,IF(R26>1,"перерасход","экономия")) -> 0
I27: =sum(C27:H27) -> 0 | P27: =sum(F27:J27) -> 0 | Q27: =I27-P27 -> 0 | R27: =IFERROR(I27/P27,0) -> 0 | S27: =IF(Q27=0,0,IF(R27>1,"перерасход","экономия")) -> 0
I28: =sum(C28:H28) -> 0 | P28: =sum(F28:J28) -> 0 | Q28: =I28-P28 -> 0 | R28: =IFERROR(I28/P28,0) -> 0 | S28: =IF(Q28=0,0,IF(R28>1,"перерасход","экономия")) -> 0
I29: =sum(C29:H29) -> 0 | P29: =sum(F29:J29) -> 0 | Q29: =I29-P29 -> 0 | R29: =IFERROR(I29/P29,0) -> 0 | S29: =IF(Q29=0,0,IF(R29>1,"перерасход","экономия")) -> 0
... I54: =sum(C54:H54) -> 0 | P54: =sum(F54:J54) -> 0 | Q54: =I54-P54 -> 0 | R54: =IFERROR(I54/P54,0) -> 0 | S54: =IF(Q54=0,0,IF(R54>1,"перерасход","экономия")) -> 0
B55: Маржинальный доход | C55: =C3+C12 -> 0 | D55: =D3+D12 -> 0 | E55: =E3+E12 -> 0 | F55: =F3+F12 -> 0 | G55: =G3+G12 -> 0 | H55: =H3+H12 -> 0 | I55: =I3+I12 -> 0 | J55: =J3+J12 -> 0 | K55: =K3+K12 -> 0 | P55: =P3+P12 -> 0 | Q55: =I55-P55 -> 0 | R55: =IFERROR(I55/P55,0) -> 0 | S55: =IF(Q55=0,"",IF(R55>1,"выполнение","план не выполнен"))
B56: Рентабельность по марже | C56: =IFERROR(C55/C$3,"") | D56: =IFERROR(D55/D$3,"") | E56: =IFERROR(E55/E$3,"") | F56: =IFERROR(F55/F$3,"") | G56: =IFERROR(G55/G$3,"") | H56: =IFERROR(H55/H$3,"") | I56: =IFERROR(I55/I$3,"") | J56: =IFERROR(J55/J$3,"") | K56: =IFERROR(K55/K$3,"") | P56: =IFERROR(P55/P$3,"")
B58: Общепроизводственные | C58: =sum(C59:C79) -> 0 | D58: =sum(D59:D79) -> 0 | E58: =sum(E59:E79) -> 0 | F58: =sum(F59:F79) -> 0 | G58: =sum(G59:G79) -> 0 | H58: =sum(H59:H79) -> 0 | I58: =SUM(I59:I84) -> 0 | J58: =SUM(J59:J84) -> 0 | K58: =SUM(K59:K84) -> 0 | P58: =SUM(P59:P84) -> 0 | Q58: =I58-P58 -> 0 | R58: =IFERROR(I58/P58,0) -> 0 | S58: =IF(Q58=0,"",IF(R58>1,"план не выполнен","выполнение"))
A59: =IFERROR(VLOOKUP(B59,'Статьи'!$A$2:C81,3,0)," ") -> 1С | B59: =IFERROR(__xludf.DUMMYFUNCTION("iferror(filter('Статьи'!$A$1:$A182,'Статьи'!$B$1:$B182=$B$58))"),"Зарплата производственного персонала") -> Зарплата производственного персонала | I59: =SUM(C59:H59) -> 0 | P59: =SUM(J59:K59) -> 0 | Q59: =I59-P59 -> 0 | R59: =IFERROR(I59/P59,0) -> 0 | S59: =IF(Q59=0,"",IF(R59=0,"обратить внимание",IF(R59>1,"перерасход","экономия")))
A60: =IFERROR(VLOOKUP(B60,'Статьи'!$A$2:C82,3,0)," ") -> ДДС отчетного месяца. Без НДС! | B60: =IFERROR(__xludf.DUMMYFUNCTION("""COMPUTED_VALUE"""),"Таможенные расходы") -> Таможенные расходы | I60: =SUM(C60:H60) -> 0 | P60: =SUM(J60:K60) -> 0 | Q60: =I60-P60 -> 0 | R60: =IFERROR(I60/P60,0) -> 0 | S60: =IF(Q60=0,"",IF(R60=0,"обратить внимание",IF(R60>1,"перерасход","экономия")))
A61: =IFERROR(VLOOKUP(B61,'Статьи'!$A$2:C83,3,0)," ") | I61: =SUM(C61:H61) -> 0 | P61: =SUM(J61:K61) -> 0 | Q61: =I61-P61 -> 0 | R61: =IFERROR(I61/P61,0) -> 0 | S61: =IF(Q61=0,"",IF(R61=0,"обратить внимание",IF(R61>1,"перерасход","экономия")))
A62: =IFERROR(VLOOKUP(B62,'Статьи'!$A$2:C84,3,0)," ") | I62: =SUM(C62:H62) -> 0 | P62: =SUM(J62:K62) -> 0 | Q62: =I62-P62 -> 0 | R62: =IFERROR(I62/P62,0) -> 0 | S62: =IF(Q62=0,"",IF(R62=0,"обратить внимание",IF(R62>1,"перерасход","экономия")))
A63: =IFERROR(VLOOKUP(B63,'Статьи'!$A$2:C85,3,0)," ") | I63: =SUM(C63:H63) -> 0 | P63: =SUM(J63:K63) -> 0 | Q63: =I63-P63 -> 0 | R63: =IFERROR(I63/P63,0) -> 0 | S63: =IF(Q63=0,"",IF(R63=0,"обратить внимание",IF(R63>1,"перерасход","экономия")))
A64: =IFERROR(VLOOKUP(B64,'Статьи'!$A$2:C86,3,0)," ") | I64: =SUM(C64:H64) -> 0 | P64: =SUM(J64:K64) -> 0 | Q64: =I64-P64 -> 0 | R64: =IFERROR(I64/P64,0) -> 0 | S64: =IF(Q64=0,"",IF(R64=0,"обратить внимание",IF(R64>1,"перерасход","экономия")))
A65: =IFERROR(VLOOKUP(B65,'Статьи'!$A$2:C87,3,0)," ") | I65: =SUM(C65:H65) -> 0 | P65: =SUM(J65:K65) -> 0 | Q65: =I65-P65 -> 0 | R65: =IFERROR(I65/P65,0) -> 0 | S65: =IF(Q65=0,"",IF(R65=0,"обратить внимание",IF(R65>1,"перерасход","экономия")))
A66: =IFERROR(VLOOKUP(B66,'Статьи'!$A$2:C88,3,0)," ") | I66: =SUM(C66:H66) -> 0 | P66: =SUM(J66:K66) -> 0 | Q66: =I66-P66 -> 0 | R66: =IFERROR(I66/P66,0) -> 0 | S66: =IF(Q66=0,"",IF(R66=0,"обратить внимание",IF(R66>1,"перерасход","экономия")))
A67: =IFERROR(VLOOKUP(B67,'Статьи'!$A$2:C89,3,0)," ") | I67: =SUM(C67:H67) -> 0 | P67: =SUM(J67:K67) -> 0 | Q67: =I67-P67 -> 0 | R67: =IFERROR(I67/P67,0) -> 0 | S67: =IF(Q67=0,"",IF(R67=0,"обратить внимание",IF(R67>1,"перерасход","экономия")))
A68: =IFERROR(VLOOKUP(B68,'Статьи'!$A$2:C90,3,0)," ") | I68: =SUM(C68:H68) -> 0 | P68: =SUM(J68:K68) -> 0 | Q68: =I68-P68 -> 0 | R68: =IFERROR(I68/P68,0) -> 0 | S68: =IF(Q68=0,"",IF(R68=0,"обратить внимание",IF(R68>1,"перерасход","экономия")))
A69: =IFERROR(VLOOKUP(B69,'Статьи'!$A$2:C91,3,0)," ") | I69: =SUM(C69:H69) -> 0 | P69: =SUM(J69:K69) -> 0 | Q69: =I69-P69 -> 0 | R69: =IFERROR(I69/P69,0) -> 0 | S69: =IF(Q69=0,"",IF(R69=0,"обратить внимание",IF(R69>1,"перерасход","экономия")))
A70: =IFERROR(VLOOKUP(B70,'Статьи'!$A$2:C92,3,0)," ") | I70: =SUM(C70:H70) -> 0 | P70: =SUM(J70:K70) -> 0 | Q70: =I70-P70 -> 0 | R70: =IFERROR(I70/P70,0) -> 0 | S70: =IF(Q70=0,"",IF(R70=0,"обратить внимание",IF(R70>1,"перерасход","экономия")))
A71: =IFERROR(VLOOKUP(B71,'Статьи'!$A$2:C93,3,0)," ") | I71: =SUM(C71:H71) -> 0 | P71: =SUM(J71:K71) -> 0 | Q71: =I71-P71 -> 0 | R71: =IFERROR(I71/P71,0) -> 0 | S71: =IF(Q71=0,"",IF(R71=0,"обратить внимание",IF(R71>1,"перерасход","экономия")))
A72: =IFERROR(VLOOKUP(B72,'Статьи'!$A$2:C94,3,0)," ") | I72: =SUM(C72:H72) -> 0 | P72: =SUM(J72:K72) -> 0 | Q72: =I72-P72 -> 0 | R72: =IFERROR(I72/P72,0) -> 0 | S72: =IF(Q72=0,"",IF(R72=0,"обратить внимание",IF(R72>1,"перерасход","экономия")))
... A84: =IFERROR(VLOOKUP(B84,'Статьи'!$A$2:C106,3,0)," ") | I84: =SUM(C84:H84) -> 0 | P84: =SUM(J84:K84) -> 0 | Q84: =I84-P84 -> 0 | R84: =IFERROR(I84/P84,0) -> 0 | S84: =IF(Q84=0,"",IF(R84=0,"обратить внимание",IF(R84>1,"перерасход","экономия")))
B85: Валовая прибыль | C85: =C55+C58 -> 0 | D85: =D55+D58 -> 0 | E85: =E55+E58 -> 0 | F85: =F55+F58 -> 0 | G85: =G55+G58 -> 0 | H85: =H55+H58 -> 0 | I85: =I55+I58 -> 0 | J85: =J55+J58 -> 0 | K85: =K55+K58 -> 0 | P85: =P55+P58 -> 0 | Q85: =I85-P85 -> 0 | R85: =IFERROR(I85/P85,0) -> 0 | S85: =IF(Q85=0,"",IF(R85>1,"выполнение","план не выполнен"))
B86: Рентабельность по валовой прибыли, % | C86: =IFERROR(C85/C$3,"") | D86: =IFERROR(D85/D$3,"") | E86: =IFERROR(E85/E$3,"") | F86: =IFERROR(F85/F$3,"") | G86: =IFERROR(G85/G$3,"") | H86: =IFERROR(H85/H$3,"") | I86: =IFERROR(I85/I$3,"") | J86: =IFERROR(J85/J$3,"") | K86: =IFERROR(K85/K$3,"") | P86: =IFERROR(P85/P$3,"") | S86: =IF(Q86=0,"",IF(Q86=0,0,IF(R86>1,"перерасход","экономия")))
S87: =IF(Q87=0,"",IF(Q87=0,0,IF(R87>1,"перерасход","экономия")))
B88: Косвенные расходы | C88: =C101+C132+C89 -> 0 | D88: =D101+D132+D89 -> 0 | E88: =E101+E132+E89 -> 0 | F88: =F101+F132+F89 -> 0 | G88: =G101+G132+G89 -> 0 | H88: =H101+H132+H89 -> 0 | I88: =I101+I132+I89 -> 0 | J88: =J101+J132+J89 -> 0 | K88: =K101+K132+K89 -> 0 | P88: =P101+P132+P89 -> 0 | Q88: =I88-P88 -> 0 | R88: =IFERROR(I88/P88,0) -> 0 | S88: =IF(Q88=0,"",IF(R88>1,"план не выполнен","выполнение"))
B89: Косвенные производственные | C89: =SUM(C90:C100) -> 0 | D89: =SUM(D90:D100) -> 0 | E89: =SUM(E90:E100) -> 0 | F89: =SUM(F90:F100) -> 0 | G89: =SUM(G90:G100) -> 0 | H89: =SUM(H90:H100) -> 0 | I89: =SUM(I90:I100) -> 0 | J89: =SUM(J90:J100) -> 0 | K89: =SUM(K90:K100) -> 0 | P89: =SUM(P90:P100) -> 0 | Q89: =I89-P89 -> 0 | R89: =IFERROR(I89/P89,0) -> 0 | S89: =IF(Q89=0,"",IF(Q89=0,0,IF(R89>1,"перерасход","экономия")))
A90: =IFERROR(VLOOKUP(B90,'Статьи'!$A$2:C112,3,0)," ") | B90: =IFERROR(__xludf.DUMMYFUNCTION("iferror(filter('Статьи'!$A$1:$A182,'Статьи'!$B$1:$B182=$B$89))"),"") | I90: =sum(C90:H90) -> 0 | P90: =SUM(J90:K90) -> 0 | Q90: =I90-P90 -> 0 | R90: =IFERROR(I90/P90,0) -> 0 | S90: =IF(Q90=0,"",IF(R90=0,"обратить внимание",IF(R90>1,"перерасход","экономия")))
A91: =IFERROR(VLOOKUP(B91,'Статьи'!$A$2:C113,3,0)," ") | I91: =sum(C91:H91) -> 0 | P91: =SUM(J91:K91) -> 0 | Q91: =I91-P91 -> 0 | R91: =IFERROR(I91/P91,0) -> 0 | S91: =IF(Q91=0,"",IF(R91=0,"обратить внимание",IF(R91>1,"перерасход","экономия")))
A92: =IFERROR(VLOOKUP(B92,'Статьи'!$A$2:C114,3,0)," ") | I92: =sum(C92:H92) -> 0 | P92: =SUM(J92:K92) -> 0 | Q92: =I92-P92 -> 0 | R92: =IFERROR(I92/P92,0) -> 0 | S92: =IF(Q92=0,"",IF(R92=0,"обратить внимание",IF(R92>1,"перерасход","экономия")))
A93: =IFERROR(VLOOKUP(B93,'Статьи'!$A$2:C115,3,0)," ") | I93: =sum(C93:H93) -> 0 | P93: =SUM(J93:K93) -> 0 | Q93: =I93-P93 -> 0 | R93: =IFERROR(I93/P93,0) -> 0 | S93: =IF(Q93=0,"",IF(R93=0,"обратить внимание",IF(R93>1,"перерасход","экономия")))
A94: =IFERROR(VLOOKUP(B94,'Статьи'!$A$2:C116,3,0)," ") | I94: =sum(C94:H94) -> 0 | P94: =SUM(J94:K94) -> 0 | Q94: =I94-P94 -> 0 | R94: =IFERROR(I94/P94,0) -> 0 | S94: =IF(Q94=0,"",IF(R94=0,"обратить внимание",IF(R94>1,"перерасход","экономия")))
I95: =sum(C95:H95) -> 0 | P95: =sum(F95:J95) -> 0 | Q95: =I95-P95 -> 0 | R95: =IFERROR(I95/P95,0) -> 0 | S95: =IF(Q95=0,"",IF(Q95=0,0,IF(R95>1,"перерасход","экономия")))
I96: =sum(C96:H96) -> 0 | P96: =sum(F96:J96) -> 0 | Q96: =I96-P96 -> 0 | R96: =IFERROR(I96/P96,0) -> 0 | S96: =IF(Q96=0,"",IF(Q96=0,0,IF(R96>1,"перерасход","экономия")))
I97: =sum(C97:H97) -> 0 | P97: =sum(F97:J97) -> 0 | Q97: =I97-P97 -> 0 | R97: =IFERROR(I97/P97,0) -> 0 | S97: =IF(Q97=0,"",IF(Q97=0,0,IF(R97>1,"перерасход","экономия")))
I98: =sum(C98:H98) -> 0 | P98: =sum(F98:J98) -> 0 | Q98: =I98-P98 -> 0 | R98: =IFERROR(I98/P98,0) -> 0 | S98: =IF(Q98=0,"",IF(Q98=0,0,IF(R98>1,"перерасход","экономия")))
I99: =sum(C99:H99) -> 0 | P99: =sum(F99:J99) -> 0 | Q99: =I99-P99 -> 0 | R99: =IFERROR(I99/P99,0) -> 0 | S99: =IF(Q99=0,"",IF(Q99=0,0,IF(R99>1,"перерасход","экономия")))
I100: =sum(C100:H100) -> 0 | P100: =sum(F100:J100) -> 0 | Q100: =I100-P100 -> 0 | R100: =IFERROR(I100/P100,0) -> 0 | S100: =IF(Q100=0,"",IF(Q100=0,0,IF(R100>1,"перерасход","экономия")))
B101: Административные | C101: =SUM(C102:C131) -> 0 | D101: =SUM(D102:D131) -> 0 | E101: =SUM(E102:E131) -> 0 | F101: =SUM(F102:F131) -> 0 | G101: =SUM(G102:G131) -> 0 | H101: =SUM(H102:H131) -> 0 | I101: =SUM(I102:I131) -> 0 | J101: =SUM(J102:J131) -> 0 | K101: =SUM(K102:K131) -> 0 | P101: =SUM(P102:P131) -> 0 | Q101: =I101-P101 -> 0 | R101: =IFERROR(I101/P101,0) -> 0 | S101: =IF(Q101=0,"",IF(R101>1,"план не выполнен","выполнение"))
A102: =IFERROR(VLOOKUP(B102,'Статьи'!$A$2:C124,3,0)," ") -> 1С | B102: =IFERROR(__xludf.DUMMYFUNCTION("iferror(filter('Статьи'!$A$1:$A182,'Статьи'!$B$1:$B182=$B$101))"),"Аренда, коммунальные услуги") -> Аренда, коммунальные услуги | I102: =sum(C102:H102) -> 0 | P102: =SUM(J102:K102) -> 0 | Q102: =I102-P102 -> 0 | R102: =IFERROR(I102/P102,0) -> 0 | S102: =IF(Q102=0,"",IF(R102=0,"обратить внимание",IF(R102>1,"перерасход","экономия")))
A103: =IFERROR(VLOOKUP(B103,'Статьи'!$A$2:C125,3,0)," ") -> 1С | B103: =IFERROR(__xludf.DUMMYFUNCTION("""COMPUTED_VALUE"""),"Аутсорсинг и прочие услуги") -> Аутсорсинг и прочие услуги | I103: =sum(C103:H103) -> 0 | P103: =SUM(J103:K103) -> 0 | Q103: =I103-P103 -> 0 | R103: =IFERROR(I103/P103,0) -> 0 | S103: =IF(Q103=0,"",IF(R103=0,"обратить внимание",IF(R103>1,"перерасход","экономия")))
A104: =IFERROR(VLOOKUP(B104,'Статьи'!$A$2:C126,3,0)," ") -> 1С | B104: =IFERROR(__xludf.DUMMYFUNCTION("""COMPUTED_VALUE"""),"Командировочные расходы") -> Командировочные расходы | I104: =sum(C104:H104) -> 0 | P104: =SUM(J104:K104) -> 0 | Q104: =I104-P104 -> 0 | R104: =IFERROR(I104/P104,0) -> 0 | S104: =IF(Q104=0,"",IF(R104=0,"обратить внимание",IF(R104>1,"перерасход","экономия")))
A105: =IFERROR(VLOOKUP(B105,'Статьи'!$A$2:C127,3,0)," ") -> ДДС отчетного месяца. Без НДС! | B105: =IFERROR(__xludf.DUMMYFUNCTION("""COMPUTED_VALUE"""),"Комиссии банка") -> Комиссии банка | I105: =sum(C105:H105) -> 0 | P105: =SUM(J105:K105) -> 0 | Q105: =I105-P105 -> 0 | R105: =IFERROR(I105/P105,0) -> 0 | S105: =IF(Q105=0,"",IF(R105=0,"обратить внимание",IF(R105>1,"перерасход","экономия")))
A106: =IFERROR(VLOOKUP(B106,'Статьи'!$A$2:C128,3,0)," ") -> ДДС отчетного месяца. Без НДС! | B106: =IFERROR(__xludf.DUMMYFUNCTION("""COMPUTED_VALUE"""),"Обучение сотрудников") -> Обучение сотрудников | I106: =sum(C106:H106) -> 0 | P106: =SUM(J106:K106) -> 0 | Q106: =I106-P106 -> 0 | R106: =IFERROR(I106/P106,0) -> 0 | S106: =IF(Q106=0,"",IF(R106=0,"обратить внимание",IF(R106>1,"перерасход","экономия")))
A107: =IFERROR(VLOOKUP(B107,'Статьи'!$A$2:C129,3,0)," ") -> ДДС отчетного месяца. Без НДС! | B107: =IFERROR(__xludf.DUMMYFUNCTION("""COMPUTED_VALUE"""),"Подбор персонала") -> Подбор персонала | I107: =sum(C107:H107) -> 0 | P107: =SUM(J107:K107) -> 0 | Q107: =I107-P107 -> 0 | R107: =IFERROR(I107/P107,0) -> 0 | S107: =IF(Q107=0,"",IF(R107=0,"обратить внимание",IF(R107>1,"перерасход","экономия")))
A108: =IFERROR(VLOOKUP(B108,'Статьи'!$A$2:C130,3,0)," ") -> ДДС отчетного месяца. Без НДС! | B108: =IFERROR(__xludf.DUMMYFUNCTION("""COMPUTED_VALUE"""),"Почтовые расходы") -> Почтовые расходы | I108: =sum(C108:H108) -> 0 | P108: =SUM(J108:K108) -> 0 | Q108: =I108-P108 -> 0 | R108: =IFERROR(I108/P108,0) -> 0 | S108: =IF(Q108=0,"",IF(R108=0,"обратить внимание",IF(R108>1,"перерасход","экономия")))
A109: =IFERROR(VLOOKUP(B109,'Статьи'!$A$2:C131,3,0)," ") -> ДДС отчетного месяца. Без НДС! | B109: =IFERROR(__xludf.DUMMYFUNCTION("""COMPUTED_VALUE"""),"Представительские расходы") -> Представительские расходы | I109: =sum(C109:H109) -> 0 | P109: =SUM(J109:K109) -> 0 | Q109: =I109-P109 -> 0 | R109: =IFERROR(I109/P109,0) -> 0 | S109: =IF(Q109=0,"",IF(R109=0,"обратить внимание",IF(R109>1,"перерасход","экономия")))
A110: =IFERROR(VLOOKUP(B110,'Статьи'!$A$2:C132,3,0)," ") -> ДДС отчетного месяца. Без НДС! | B110: =IFERROR(__xludf.DUMMYFUNCTION("""COMPUTED_VALUE"""),"Содержание офиса") -> Содержание офиса | I110: =sum(C110:H110) -> 0 | P110: =SUM(J110:K110) -> 0 | Q110: =I110-P110 -> 0 | R110: =IFERROR(I110/P110,0) -> 0 | S110: =IF(Q110=0,"",IF(R110=0,"обратить внимание",IF(R110>1,"перерасход","экономия")))
A111: =IFERROR(VLOOKUP(B111,'Статьи'!$A$2:C133,3,0)," ") -> ДДС отчетного месяца. Без НДС! | B111: =IFERROR(__xludf.DUMMYFUNCTION("""COMPUTED_VALUE"""),"Услуги связи + Интернет") -> Услуги связи + Интернет | I111: =sum(C111:H111) -> 0 | P111: =SUM(J111:K111) -> 0 | Q111: =I111-P111 -> 0 | R111: =IFERROR(I111/P111,0) -> 0 | S111: =IF(Q111=0,"",IF(R111=0,"обратить внимание",IF(R111>1,"перерасход","экономия")))
A112: =IFERROR(VLOOKUP(B112,'Статьи'!$A$2:C134,3,0)," ") -> ДДС отчетного месяца. Без НДС! | B112: =IFERROR(__xludf.DUMMYFUNCTION("""COMPUTED_VALUE"""),"Штрафы") -> Штрафы | I112: =sum(C112:H112) -> 0 | P112: =SUM(J112:K112) -> 0 | Q112: =I112-P112 -> 0 | R112: =IFERROR(I112/P112,0) -> 0 | S112: =IF(Q112=0,"",IF(R112=0,"обратить внимание",IF(R112>1,"перерасход","экономия")))
A113: =IFERROR(VLOOKUP(B113,'Статьи'!$A$2:C135,3,0)," ") | I113: =sum(C113:H113) -> 0 | P113: =SUM(J113:K113) -> 0 | Q113: =I113-P113 -> 0 | R113: =IFERROR(I113/P113,0) -> 0 | S113: =IF(Q113=0,"",IF(R113=0,"обратить внимание",IF(R113>1,"перерасход","экономия")))
A114: =IFERROR(VLOOKUP(B114,'Статьи'!$A$2:C136,3,0)," ") | I114: =sum(C114:H114) -> 0 | P114: =SUM(J114:K114) -> 0 | Q114: =I114-P114 -> 0 | R114: =IFERROR(I114/P114,0) -> 0 | S114: =IF(Q114=0,"",IF(R114=0,"обратить внимание",IF(R114>1,"перерасход","экономия")))
A115: =IFERROR(VLOOKUP(B115,'Статьи'!$A$2:C137,3,0)," ") | I115: =sum(C115:H115) -> 0 | P115: =SUM(J115:K115) -> 0 | Q115: =I115-P115 -> 0 | R115: =IFERROR(I115/P115,0) -> 0 | S115: =IF(Q115=0,"",IF(R115=0,"обратить внимание",IF(R115>1,"перерасход","экономия")))
A116: =IFERROR(VLOOKUP(B116,'Статьи'!$A$2:C138,3,0)," ") | I116: =sum(C116:H116) -> 0 | P116: =SUM(J116:K116) -> 0 | Q116: =I116-P116 -> 0 | R116: =IFERROR(I116/P116,0) -> 0 | S116: =IF(Q116=0,"",IF(R116=0,"обратить внимание",IF(R116>1,"перерасход","экономия")))
A117: =IFERROR(VLOOKUP(B117,'Статьи'!$A$2:C139,3,0)," ") | I117: =sum(C117:H117) -> 0 | P117: =SUM(J117:K117) -> 0 | Q117: =I117-P117 -> 0 | R117: =IFERROR(I117/P117,0) -> 0 | S117: =IF(Q117=0,"",IF(R117=0,"обратить внимание",IF(R117>1,"перерасход","экономия")))
A118: =IFERROR(VLOOKUP(B118,'Статьи'!$A$2:C140,3,0)," ") | I118: =sum(C118:H118) -> 0 | P118: =SUM(J118:K118) -> 0 | Q118: =I118-P118 -> 0 | R118: =IFERROR(I118/P118,0) -> 0 | S118: =IF(Q118=0,"",IF(R118=0,"обратить внимание",IF(R118>1,"перерасход","экономия")))
A119: =IFERROR(VLOOKUP(B119,'Статьи'!$A$2:C141,3,0)," ") | I119: =sum(C119:H119) -> 0 | P119: =SUM(J119:K119) -> 0 | Q119: =I119-P119 -> 0 | R119: =IFERROR(I119/P119,0) -> 0 | S119: =IF(Q119=0,"",IF(R119=0,"обратить внимание",IF(R119>1,"перерасход","экономия")))
A120: =IFERROR(VLOOKUP(B120,'Статьи'!$A$2:C142,3,0)," ") | I120: =sum(C120:H120) -> 0 | P120: =SUM(J120:K120) -> 0 | Q120: =I120-P120 -> 0 | R120: =IFERROR(I120/P120,0) -> 0 | S120: =IF(Q120=0,"",IF(R120=0,"обратить внимание",IF(R120>1,"перерасход","экономия")))
A121: =IFERROR(VLOOKUP(B121,'Статьи'!$A$2:C143,3,0)," ") | I121: =sum(C121:H121) -> 0 | P121: =SUM(J121:K121) -> 0 | Q121: =I121-P121 -> 0 | R121: =IFERROR(I121/P121,0) -> 0 | S121: =IF(Q121=0,"",IF(R121=0,"обратить внимание",IF(R121>1,"перерасход","экономия")))
A122: =IFERROR(VLOOKUP(B122,'Статьи'!$A$2:C144,3,0)," ") | I122: =sum(C122:H122) -> 0 | P122: =SUM(J122:K122) -> 0 | Q122: =I122-P122 -> 0 | R122: =IFERROR(I122/P122,0) -> 0 | S122: =IF(Q122=0,"",IF(R122=0,"обратить внимание",IF(R122>1,"перерасход","экономия")))
A123: =IFERROR(VLOOKUP(B123,'Статьи'!$A$2:C145,3,0)," ") | I123: =sum(C123:H123) -> 0 | P123: =SUM(J123:K123) -> 0 | Q123: =I123-P123 -> 0 | R123: =IFERROR(I123/P123,0) -> 0 | S123: =IF(Q123=0,"",IF(R123=0,"обратить внимание",IF(R123>1,"перерасход","экономия")))
A124: =IFERROR(VLOOKUP(B124,'Статьи'!$A$2:C146,3,0)," ") | I124: =sum(C124:H124) -> 0 | P124: =SUM(J124:K124) -> 0 | Q124: =I124-P124 -> 0 | R124: =IFERROR(I124/P124,0) -> 0 | S124: =IF(Q124=0,"",IF(R124=0,"обратить внимание",IF(R124>1,"перерасход","экономия")))
... A131: =IFERROR(VLOOKUP(B131,'Статьи'!$A$2:C153,3,0)," ") | I131: =sum(C131:H131) -> 0 | P131: =SUM(J131:K131) -> 0 | Q131: =I131-P131 -> 0 | R131: =IFERROR(I131/P131,0) -> 0 | S131: =IF(Q131=0,"",IF(R131=0,"обратить внимание",IF(R131>1,"перерасход","экономия")))
B132: Коммерческие | C132: =SUM(C133:C141) -> 0 | D132: =SUM(D133:D141) -> 0 | E132: =SUM(E133:E141) -> 0 | F132: =SUM(F133:F141) -> 0 | G132: =SUM(G133:G141) -> 0 | H132: =SUM(H133:H141) -> 0 | I132: =sum(C132:H132) -> 0 | J132: =SUM(J133:J141) -> 0 | K132: =SUM(K133:K141) -> 0 | L132: =SUM(L133:L141) -> 0 | M132: =SUM(M133:M141) -> 0 | N132: =SUM(N133:N141) -> 0 | O132: =SUM(O133:O141) -> 0 | P132: =SUM(P133:P141) -> 0 | Q132: =I132-P132 -> 0 | R132: =IFERROR(I132/P132,0) -> 0 | S132: =IF(Q132=0,"",IF(R132>1,"план не выполнен","выполнение"))
A133: =IFERROR(VLOOKUP(B133,'Статьи'!$A$2:C155,3,0)," ") -> ДДС отчетного месяца. Без НДС! | B133: =IFERROR(__xludf.DUMMYFUNCTION("iferror(filter('Статьи'!$A$1:$A182,'Статьи'!$B$1:$B182=$B$132))"),"Подписка на сайты по поиску клиентов") -> Подписка на сайты по поиску клиентов | I133: =sum(C133:H133) -> 0 | P133: =SUM(J133:K133) -> 0 | Q133: =I133-P133 -> 0 | R133: =IFERROR(I133/P133,0) -> 0 | S133: =IF(Q133=0,"",IF(R133=0,"обратить внимание",IF(R133>1,"перерасход","экономия")))
A134: =IFERROR(VLOOKUP(B134,'Статьи'!$A$2:C156,3,0)," ") | I134: =sum(C134:H134) -> 0 | P134: =SUM(J134:K134) -> 0 | Q134: =I134-P134 -> 0 | R134: =IFERROR(I134/P134,0) -> 0 | S134: =IF(Q134=0,"",IF(R134=0,"обратить внимание",IF(R134>1,"перерасход","экономия")))
A135: =IFERROR(VLOOKUP(B135,'Статьи'!$A$2:C157,3,0)," ") | I135: =sum(C135:H135) -> 0 | P135: =SUM(J135:K135) -> 0 | Q135: =I135-P135 -> 0 | R135: =IFERROR(I135/P135,0) -> 0 | S135: =IF(Q135=0,"",IF(R135=0,"обратить внимание",IF(R135>1,"перерасход","экономия")))
A136: =IFERROR(VLOOKUP(B136,'Статьи'!$A$2:C158,3,0)," ") | I136: =sum(C136:H136) -> 0 | P136: =SUM(J136:K136) -> 0 | Q136: =I136-P136 -> 0 | R136: =IFERROR(I136/P136,0) -> 0 | S136: =IF(Q136=0,"",IF(R136=0,"обратить внимание",IF(R136>1,"перерасход","экономия")))
A137: =IFERROR(VLOOKUP(B137,'Статьи'!$A$2:C159,3,0)," ") | I137: =sum(C137:H137) -> 0 | P137: =SUM(J137:K137) -> 0 | Q137: =I137-P137 -> 0 | R137: =IFERROR(I137/P137,0) -> 0 | S137: =IF(Q137=0,"",IF(R137=0,"обратить внимание",IF(R137>1,"перерасход","экономия")))
A138: =IFERROR(VLOOKUP(B138,'Статьи'!$A$2:C160,3,0)," ") | I138: =sum(C138:H138) -> 0 | P138: =SUM(J138:K138) -> 0 | Q138: =I138-P138 -> 0 | R138: =IFERROR(I138/P138,0) -> 0 | S138: =IF(Q138=0,"",IF(R138=0,"обратить внимание",IF(R138>1,"перерасход","экономия")))
A139: =IFERROR(VLOOKUP(B139,'Статьи'!$A$2:C161,3,0)," ") | I139: =sum(C139:H139) -> 0 | P139: =SUM(J139:K139) -> 0 | Q139: =I139-P139 -> 0 | R139: =IFERROR(I139/P139,0) -> 0 | S139: =IF(Q139=0,"",IF(R139=0,"обратить внимание",IF(R139>1,"перерасход","экономия")))
A140: =IFERROR(VLOOKUP(B140,'Статьи'!$A$2:C162,3,0)," ") | I140: =sum(C140:H140) -> 0 | P140: =SUM(J140:K140) -> 0 | Q140: =I140-P140 -> 0 | R140: =IFERROR(I140/P140,0) -> 0 | S140: =IF(Q140=0,"",IF(R140=0,"обратить внимание",IF(R140>1,"перерасход","экономия")))
A141: =IFERROR(VLOOKUP(B141,'Статьи'!$A$2:C163,3,0)," ") | I141: =sum(C141:H141) -> 0 | P141: =sum(F141:J141) -> 0 | Q141: =I141-P141 -> 0 | R141: =IFERROR(I141/P141,0) -> 0 | S141: =IF(Q141=0,"",IF(R141=0,"обратить внимание",IF(R141>1,"перерасход","экономия")))
B142: Операционная прибыль (EBITDA) | C142: =C85+C88 -> 0 | D142: =D85+D88 -> 0 | E142: =E85+E88 -> 0 | F142: =F85+F88 -> 0 | G142: =G85+G88 -> 0 | H142: =H85+H88 -> 0 | I142: =I85+I88 -> 0 | J142: =J85+J88 -> 0 | K142: =K85+K88 -> 0 | P142: =P85+P88 -> 0 | Q142: =I142-P142 -> 0 | R142: =IFERROR(I142/P142,0) -> 0 | S142: =IF(Q142=0,"",IF(R142>1,"выполнение","план не выполнен"))
...

Sheet 4
C1: ФАКТ | J1: План | Q1: Отклонения
A2: Источники | C2: {=TRANSPOSE('Справочник'!D2:D7)} -> ООО "Весело живем" | D2: ООО "Некогда грустить" | E2: 3 | F2: 4 | G2: 5 | H2: 6 | I2: Итого | J2: {=TRANSPOSE('Справочник'!D2:D7)} -> ООО "Весело живем" | K2: ООО "Некогда грустить" | L2: 3 | M2: 4 | N2: 5 | O2: 6 | P2: Итого | Q2: факт-план, EUR | R2: факт/план, % | S2: Результат
B3: Выручка | C3: =SUM(C4:C10) -> 4 | D3: =SUM(D4:D10) -> 0 | E3: =SUM(E4:E10) -> 0 | F3: =SUM(F4:F10) -> 0 | G3: =SUM(G4:G10) -> 0 | H3: =SUM(H4:H10) -> 0 | I3: =sum(C3:H3) -> 4 | J3: =SUM(J4:J10) -> 0 | K3: =SUM(K4:K10) -> 0 | P3: =SUM(P4:P10) -> 0 | Q3: =I3-P3 -> 4 | R3: =IFERROR(I3/P3,0) -> 0 | S3: =IF(Q3=0,"",IF(R3>1,"выполнение","план не выполнен")) -> план не выполнен
A4: =IFERROR(VLOOKUP(B4,'Статьи'!$A$2:C26,3,0)," ") -> 1С сч 90.01 убрать НДС! | B4: =IFERROR(__xludf.DUMMYFUNCTION("iferror(filter('Статьи'!$A$1:$A177,'Статьи'!$B$1:$B177=$B$3))"),"Выручка от аренды машиноместа") -> Выручка от аренды машиноместа | C4: 4 | I4: =SUM(C4:H4) -> 4 | P4: =SUM(J4:K4) -> 0 | Q4: =I4-P4 -> 4 | R4: =IFERROR(I4/P4,0) -> 0 | S4: =IF(Q4=0,"",IF(R4=0,"обратить внимание",IF(R4>1,"выполнение","план не выполнен"))) -> обратить внимание
A5: =IFERROR(VLOOKUP(B5,'Статьи'!$A$2:C27,3,0)," ") -> 1С сч 90.01 убрать НДС! | B5: =IFERROR(__xludf.DUMMYFUNCTION("""COMPUTED_VALUE"""),"Выручка за грузоперевозки") -> Выручка за грузоперевозки | I5: =SUM(C5:H5) -> 0 | P5: =SUM(J5:K5) -> 0 | Q5: =I5-P5 -> 0 | R5: =IFERROR(I5/P5,0) -> 0 | S5: =IF(Q5=0,"",IF(R5=0,"обратить внимание",IF(R5>1,"выполнение","план не выполнен")))
A6: =IFERROR(VLOOKUP(B6,'Статьи'!$A$2:C28,3,0)," ") | I6: =SUM(C6:H6) -> 0 | P6: =SUM(F6:J6) -> 0 | Q6: =I6-P6 -> 0 | R6: =IFERROR(I6/P6,0) -> 0 | S6: =IF(Q6=0,"",IF(R6=0,"обратить внимание",IF(R6>1,"выполнение","план не выполнен")))
A7: =IFERROR(VLOOKUP(B7,'Статьи'!$A$2:C29,3,0)," ") | I7: =SUM(C7:H7) -> 0 | P7: =SUM(F7:J7) -> 0 | Q7: =I7-P7 -> 0 | R7: =IFERROR(I7/P7,0) -> 0 | S7: =IF(Q7=0,"",IF(R7=0,"обратить внимание",IF(R7>1,"выполнение","план не выполнен")))
A8: =IFERROR(VLOOKUP(B8,'Статьи'!$A$2:C30,3,0)," ") | I8: =SUM(C8:H8) -> 0 | P8: =SUM(F8:J8) -> 0 | Q8: =I8-P8 -> 0 | R8: =IFERROR(I8/P8,0) -> 0 | S8: =IF(Q8=0,"",IF(R8=0,"обратить внимание",IF(R8>1,"выполнение","план не выполнен")))
A9: =IFERROR(VLOOKUP(B9,'Статьи'!$A$2:C31,3,0)," ") | Q9: =I9-P9 -> 0 | R9: =IFERROR(I9/P9,0) -> 0 | S9: =IF(Q9=0,"",IF(R9=0,"обратить внимание",IF(R9>1,"выполнение","план не выполнен")))
A10: =IFERROR(VLOOKUP(B10,'Статьи'!$A$2:C32,3,0)," ") | Q10: =I10-P10 -> 0 | R10: =IFERROR(I10/P10,0) -> 0 | S10: =IF(Q10=0,"",IF(R10=0,"обратить внимание",IF(R10>1,"выполнение","план не выполнен")))
B11: Производственные расходы | C11: =C12+C58 -> 0 | D11: =D12+D58 -> 0 | E11: =E12+E58 -> 0 | F11: =F12+F58 -> 0 | G11: =G12+G58 -> 0 | H11: =H12+H58 -> 0 | I11: =I12+I58 -> 0 | J11: =J12+J58 -> 0 | K11: =K12+K58 -> 0 | P11: =P12+P58 -> 0 | Q11: =I11-P11 -> 0 | R11: =IFERROR(I11/P11,0) -> 0 | S11: =IF(Q11=0,"",IF(R11>1,"план не выполнен","выполнение"))
B12: Переменные | C12: =sum(C13:C54) -> 0 | D12: =sum(D13:D54) -> 0 | E12: =sum(E13:E54) -> 0 | F12: =sum(F13:F54) -> 0 | G12: =sum(G13:G54) -> 0 | H12: =sum(H13:H54) -> 0 | I12: =sum(I13:I54) -> 0 | J12: =sum(J13:J54) -> 0 | K12: =sum(K13:K54) -> 0 | P12: =sum(P13:P54) -> 0 | Q12: =I12-P12 -> 0 | R12: =IFERROR(I12/P12,0) -> 0 | S12: =IF(Q12=0,"",IF(R12=0,"обратить внимание",IF(R12>1,"перерасход","экономия")))
A13: =IFERROR(VLOOKUP(B13,'Статьи'!$A$2:C35,3,0)," ") -> ДДС отчетного месяца. Без НДС! | B13: =IFERROR(__xludf.DUMMYFUNCTION("iferror(filter('Статьи'!$A$1:$A177,'Статьи'!$B$1:$B177=$B$12))"),"Комиссия топливных компаний") -> Комиссия топливных компаний | I13: =sum(C13:H13) -> 0 | P13: =SUM(J13:K13) -> 0 | Q13: =I13-P13 -> 0 | R13: =IFERROR(I13/P13,0) -> 0 | S13: =IF(Q13=0,"",IF(R13=0,"обратить внимание",IF(R13>1,"перерасход","экономия")))
A14: =IFERROR(VLOOKUP(B14,'Статьи'!$A$2:C36,3,0)," ") -> 1С | B14: =IFERROR(__xludf.DUMMYFUNCTION("""COMPUTED_VALUE"""),"Топливо для грузовых авто ") -> Топливо для грузовых авто | I14: =sum(C14:H14) -> 0 | P14: =SUM(J14:K14) -> 0 | Q14: =I14-P14 -> 0 | R14: =IFERROR(I14/P14,0) -> 0 | S14: =IF(Q14=0,"",IF(R14=0,"обратить внимание",IF(R14>1,"перерасход","экономия")))
A15: =IFERROR(VLOOKUP(B15,'Статьи'!$A$2:C37,3,0)," ") | I15: =sum(C15:H15) -> 0 | P15: =SUM(J15:K15) -> 0 | Q15: =I15-P15 -> 0 | R15: =IFERROR(I15/P15,0) -> 0 | S15: =IF(Q15=0,"",IF(R15=0,"обратить внимание",IF(R15>1,"перерасход","экономия")))
A16: =IFERROR(VLOOKUP(B16,'Статьи'!$A$2:C38,3,0)," ") | I16: =sum(C16:H16) -> 0 | P16: =SUM(J16:K16) -> 0 | Q16: =I16-P16 -> 0 | R16: =IFERROR(I16/P16,0) -> 0 | S16: =IF(Q16=0,"",IF(R16=0,"обратить внимание",IF(R16>1,"перерасход","экономия")))
A17: =IFERROR(VLOOKUP(B17,'Статьи'!$A$2:C39,3,0)," ") | I17: =sum(C17:H17) -> 0 | P17: =sum(F17:J17) -> 0 | Q17: =I17-P17 -> 0 | R17: =IFERROR(I17/P17,0) -> 0 | S17: =IF(Q17=0,"",IF(R17=0,"обратить внимание",IF(R17>1,"перерасход","экономия")))
I18: =sum(C18:H18) -> 0 | P18: =sum(F18:J18) -> 0 | Q18: =I18-P18 -> 0 | R18: =IFERROR(I18/P18,0) -> 0 | S18: =IF(Q18=0,0,IF(R18>1,"перерасход","экономия")) -> 0
I19: =sum(C19:H19) -> 0 | P19: =sum(F19:J19) -> 0 | Q19: =I19-P19 -> 0 | R19: =IFERROR(I19/P19,0) -> 0 | S19: =IF(Q19=0,0,IF(R19>1,"перерасход","экономия")) -> 0
I20: =sum(C20:H20) -> 0 | P20: =sum(F20:J20) -> 0 | Q20: =I20-P20 -> 0 | R20: =IFERROR(I20/P20,0) -> 0 | S20: =IF(Q20=0,0,IF(R20>1,"перерасход","экономия")) -> 0
I21: =sum(C21:H21) -> 0 | P21: =sum(F21:J21) -> 0 | Q21: =I21-P21 -> 0 | R21: =IFERROR(I21/P21,0) -> 0 | S21: =IF(Q21=0,0,IF(R21>1,"перерасход","экономия")) -> 0
I22: =sum(C22:H22) -> 0 | P22: =sum(F22:J22) -> 0 | Q22: =I22-P22 -> 0 | R22: =IFERROR(I22/P22,0) -> 0 | S22: =IF(Q22=0,0,IF(R22>1,"перерасход","экономия")) -> 0
I23: =sum(C23:H23) -> 0 | P23: =sum(F23:J23) -> 0 | Q23: =I23-P23 -> 0 | R23: =IFERROR(I23/P23,0) -> 0 | S23: =IF(Q23=0,0,IF(R23>1,"перерасход","экономия")) -> 0
I24: =sum(C24:H24) -> 0 | P24: =sum(F24:J24) -> 0 | Q24: =I24-P24 -> 0 | R24: =IFERROR(I24/P24,0) -> 0 | S24: =IF(Q24=0,0,IF(R24>1,"перерасход","экономия")) -> 0
I25: =sum(C25:H25) -> 0 | P25: =sum(F25:J25) -> 0 | Q25: =I25-P25 -> 0 | R25: =IFERROR(I25/P25,0) -> 0 | S25: =IF(Q25=0,0,IF(R25>1,"перерасход","экономия")) -> 0
I26: =sum(C26:H26) -> 0 | P26: =sum(F26:J26) -> 0 | Q26: =I26-P26 -> 0 | R26: =IFERROR(I26/P26,0) -> 0 | S26: =IF(Q26=0,0,IF(R26>1,"перерасход","экономия")) -> 0
I27: =sum(C27:H27) -> 0 | P27: =sum(F27:J27) -> 0 | Q27: =I27-P27 -> 0 | R27: =IFERROR(I27/P27,0) -> 0 | S27: =IF(Q27=0,0,IF(R27>1,"перерасход","экономия")) -> 0
I28: =sum(C28:H28) -> 0 | P28: =sum(F28:J28) -> 0 | Q28: =I28-P28 -> 0 | R28: =IFERROR(I28/P28,0) -> 0 | S28: =IF(Q28=0,0,IF(R28>1,"перерасход","экономия")) -> 0
I29: =sum(C29:H29) -> 0 | P29: =sum(F29:J29) -> 0 | Q29: =I29-P29 -> 0 | R29: =IFERROR(I29/P29,0) -> 0 | S29: =IF(Q29=0,0,IF(R29>1,"перерасход","экономия")) -> 0
... I54: =sum(C54:H54) -> 0 | P54: =sum(F54:J54) -> 0 | Q54: =I54-P54 -> 0 | R54: =IFERROR(I54/P54,0) -> 0 | S54: =IF(Q54=0,0,IF(R54>1,"перерасход","экономия")) -> 0
B55: Маржинальный доход | C55: =C3+C12 -> 4 | D55: =D3+D12 -> 0 | E55: =E3+E12 -> 0 | F55: =F3+F12 -> 0 | G55: =G3+G12 -> 0 | H55: =H3+H12 -> 0 | I55: =I3+I12 -> 4 | J55: =J3+J12 -> 0 | K55: =K3+K12 -> 0 | P55: =P3+P12 -> 0 | Q55: =I55-P55 -> 4 | R55: =IFERROR(I55/P55,0) -> 0 | S55: =IF(Q55=0,"",IF(R55>1,"выполнение","план не выполнен")) -> план не выполнен
B56: Рентабельность по марже | C56: =IFERROR(C55/C$3,"") -> 1 | D56: =IFERROR(D55/D$3,"") | E56: =IFERROR(E55/E$3,"") | F56: =IFERROR(F55/F$3,"") | G56: =IFERROR(G55/G$3,"") | H56: =IFERROR(H55/H$3,"") | I56: =IFERROR(I55/I$3,"") -> 1 | J56: =IFERROR(J55/J$3,"") | K56: =IFERROR(K55/K$3,"") | P56: =IFERROR(P55/P$3,"")
B58: Общепроизводственные | C58: =sum(C59:C79) -> 0 | D58: =sum(D59:D79) -> 0 | E58: =sum(E59:E79) -> 0 | F58: =sum(F59:F79) -> 0 | G58: =sum(G59:G79) -> 0 | H58: =sum(H59:H79) -> 0 | I58: =SUM(I59:I84) -> 0 | J58: =SUM(J59:J84) -> 0 | K58: =SUM(K59:K84) -> 0 | P58: =SUM(P59:P84) -> 0 | Q58: =I58-P58 -> 0 | R58: =IFERROR(I58/P58,0) -> 0 | S58: =IF(Q58=0,"",IF(R58>1,"план не выполнен","выполнение"))
A59: =IFERROR(VLOOKUP(B59,'Статьи'!$A$2:C81,3,0)," ") -> 1С | B59: =IFERROR(__xludf.DUMMYFUNCTION("iferror(filter('Статьи'!$A$1:$A177,'Статьи'!$B$1:$B177=$B$58))"),"Зарплата производственного персонала") -> Зарплата производственного персонала | I59: =SUM(C59:H59) -> 0 | P59: =SUM(J59:K59) -> 0 | Q59: =I59-P59 -> 0 | R59: =IFERROR(I59/P59,0) -> 0 | S59: =IF(Q59=0,"",IF(R59=0,"обратить внимание",IF(R59>1,"перерасход","экономия")))
A60: =IFERROR(VLOOKUP(B60,'Статьи'!$A$2:C82,3,0)," ") -> ДДС отчетного месяца. Без НДС! | B60: =IFERROR(__xludf.DUMMYFUNCTION("""COMPUTED_VALUE"""),"Таможенные расходы") -> Таможенные расходы | I60: =SUM(C60:H60) -> 0 | P60: =SUM(J60:K60) -> 0 | Q60: =I60-P60 -> 0 | R60: =IFERROR(I60/P60,0) -> 0 | S60: =IF(Q60=0,"",IF(R60=0,"обратить внимание",IF(R60>1,"перерасход","экономия")))
A61: =IFERROR(VLOOKUP(B61,'Статьи'!$A$2:C83,3,0)," ") | I61: =SUM(C61:H61) -> 0 | P61: =SUM(J61:K61) -> 0 | Q61: =I61-P61 -> 0 | R61: =IFERROR(I61/P61,0) -> 0 | S61: =IF(Q61=0,"",IF(R61=0,"обратить внимание",IF(R61>1,"перерасход","экономия")))
A62: =IFERROR(VLOOKUP(B62,'Статьи'!$A$2:C84,3,0)," ") | I62: =SUM(C62:H62) -> 0 | P62: =SUM(J62:K62) -> 0 | Q62: =I62-P62 -> 0 | R62: =IFERROR(I62/P62,0) -> 0 | S62: =IF(Q62=0,"",IF(R62=0,"обратить внимание",IF(R62>1,"перерасход","экономия")))
A63: =IFERROR(VLOOKUP(B63,'Статьи'!$A$2:C85,3,0)," ") | I63: =SUM(C63:H63) -> 0 | P63: =SUM(J63:K63) -> 0 | Q63: =I63-P63 -> 0 | R63: =IFERROR(I63/P63,0) -> 0 | S63: =IF(Q63=0,"",IF(R63=0,"обратить внимание",IF(R63>1,"перерасход","экономия")))
A64: =IFERROR(VLOOKUP(B64,'Статьи'!$A$2:C86,3,0)," ") | I64: =SUM(C64:H64) -> 0 | P64: =SUM(J64:K64) -> 0 | Q64: =I64-P64 -> 0 | R64: =IFERROR(I64/P64,0) -> 0 | S64: =IF(Q64=0,"",IF(R64=0,"обратить внимание",IF(R64>1,"перерасход","экономия")))
A65: =IFERROR(VLOOKUP(B65,'Статьи'!$A$2:C87,3,0)," ") | I65: =SUM(C65:H65) -> 0 | P65: =SUM(J65:K65) -> 0 | Q65: =I65-P65 -> 0 | R65: =IFERROR(I65/P65,0) -> 0 | S65: =IF(Q65=0,"",IF(R65=0,"обратить внимание",IF(R65>1,"перерасход","экономия")))
A66: =IFERROR(VLOOKUP(B66,'Статьи'!$A$2:C88,3,0)," ") | I66: =SUM(C66:H66) -> 0 | P66: =SUM(J66:K66) -> 0 | Q66: =I66-P66 -> 0 | R66: =IFERROR(I66/P66,0) -> 0 | S66: =IF(Q66=0,"",IF(R66=0,"обратить внимание",IF(R66>1,"перерасход","экономия")))
A67: =IFERROR(VLOOKUP(B67,'Статьи'!$A$2:C89,3,0)," ") | I67: =SUM(C67:H67) -> 0 | P67: =SUM(J67:K67) -> 0 | Q67: =I67-P67 -> 0 | R67: =IFERROR(I67/P67,0) -> 0 | S67: =IF(Q67=0,"",IF(R67=0,"обратить внимание",IF(R67>1,"перерасход","экономия")))
A68: =IFERROR(VLOOKUP(B68,'Статьи'!$A$2:C90,3,0)," ") | I68: =SUM(C68:H68) -> 0 | P68: =SUM(J68:K68) -> 0 | Q68: =I68-P68 -> 0 | R68: =IFERROR(I68/P68,0) -> 0 | S68: =IF(Q68=0,"",IF(R68=0,"обратить внимание",IF(R68>1,"перерасход","экономия")))
A69: =IFERROR(VLOOKUP(B69,'Статьи'!$A$2:C91,3,0)," ") | I69: =SUM(C69:H69) -> 0 | P69: =SUM(J69:K69) -> 0 | Q69: =I69-P69 -> 0 | R69: =IFERROR(I69/P69,0) -> 0 | S69: =IF(Q69=0,"",IF(R69=0,"обратить внимание",IF(R69>1,"перерасход","экономия")))
A70: =IFERROR(VLOOKUP(B70,'Статьи'!$A$2:C92,3,0)," ") | I70: =SUM(C70:H70) -> 0 | P70: =SUM(J70:K70) -> 0 | Q70: =I70-P70 -> 0 | R70: =IFERROR(I70/P70,0) -> 0 | S70: =IF(Q70=0,"",IF(R70=0,"обратить внимание",IF(R70>1,"перерасход","экономия")))
A71: =IFERROR(VLOOKUP(B71,'Статьи'!$A$2:C93,3,0)," ") | I71: =SUM(C71:H71) -> 0 | P71: =SUM(J71:K71) -> 0 | Q71: =I71-P71 -> 0 | R71: =IFERROR(I71/P71,0) -> 0 | S71: =IF(Q71=0,"",IF(R71=0,"обратить внимание",IF(R71>1,"перерасход","экономия")))
A72: =IFERROR(VLOOKUP(B72,'Статьи'!$A$2:C94,3,0)," ") | I72: =SUM(C72:H72) -> 0 | P72: =SUM(J72:K72) -> 0 | Q72: =I72-P72 -> 0 | R72: =IFERROR(I72/P72,0) -> 0 | S72: =IF(Q72=0,"",IF(R72=0,"обратить внимание",IF(R72>1,"перерасход","экономия")))
... A84: =IFERROR(VLOOKUP(B84,'Статьи'!$A$2:C106,3,0)," ") | I84: =SUM(C84:H84) -> 0 | P84: =SUM(J84:K84) -> 0 | Q84: =I84-P84 -> 0 | R84: =IFERROR(I84/P84,0) -> 0 | S84: =IF(Q84=0,"",IF(R84=0,"обратить внимание",IF(R84>1,"перерасход","экономия")))
B85: Валовая прибыль | C85: =C55+C58 -> 4 | D85: =D55+D58 -> 0 | E85: =E55+E58 -> 0 | F85: =F55+F58 -> 0 | G85: =G55+G58 -> 0 | H85: =H55+H58 -> 0 | I85: =I55+I58 -> 4 | J85: =J55+J58 -> 0 | K85: =K55+K58 -> 0 | P85: =P55+P58 -> 0 | Q85: =I85-P85 -> 4 | R85: =IFERROR(I85/P85,0) -> 0 | S85: =IF(Q85=0,"",IF(R85>1,"выполнение","план не выполнен")) -> план не выполнен
B86: Рентабельность по валовой прибыли, % | C86: =IFERROR(C85/C$3,"") -> 1 | D86: =IFERROR(D85/D$3,"") | E86: =IFERROR(E85/E$3,"") | F86: =IFERROR(F85/F$3,"") | G86: =IFERROR(G85/G$3,"") | H86: =IFERROR(H85/H$3,"") | I86: =IFERROR(I85/I$3,"") -> 1 | J86: =IFERROR(J85/J$3,"") | K86: =IFERROR(K85/K$3,"") | P86: =IFERROR(P85/P$3,"") | S86: =IF(Q86=0,"",IF(Q86=0,0,IF(R86>1,"перерасход","экономия")))
S87: =IF(Q87=0,"",IF(Q87=0,0,IF(R87>1,"перерасход","экономия")))
B88: Косвенные расходы | C88: =C101+C132+C89 -> 0 | D88: =D101+D132+D89 -> 0 | E88: =E101+E132+E89 -> 0 | F88: =F101+F132+F89 -> 0 | G88: =G101+G132+G89 -> 0 | H88: =H101+H132+H89 -> 0 | I88: =I101+I132+I89 -> 0 | J88: =J101+J132+J89 -> 0 | K88: =K101+K132+K89 -> 0 | P88: =P101+P132+P89 -> 0 | Q88: =I88-P88 -> 0 | R88: =IFERROR(I88/P88,0) -> 0 | S88: =IF(Q88=0,"",IF(R88>1,"план не выполнен","выполнение"))
B89: Косвенные производственные | C89: =SUM(C90:C100) -> 0 | D89: =SUM(D90:D100) -> 0 | E89: =SUM(E90:E100) -> 0 | F89: =SUM(F90:F100) -> 0 | G89: =SUM(G90:G100) -> 0 | H89: =SUM(H90:H100) -> 0 | I89: =SUM(I90:I100) -> 0 | J89: =SUM(J90:J100) -> 0 | K89: =SUM(K90:K100) -> 0 | P89: =SUM(P90:P100) -> 0 | Q89: =I89-P89 -> 0 | R89: =IFERROR(I89/P89,0) -> 0 | S89: =IF(Q89=0,"",IF(Q89=0,0,IF(R89>1,"перерасход","экономия")))
A90: =IFERROR(VLOOKUP(B90,'Статьи'!$A$2:C112,3,0)," ") | B90: =IFERROR(__xludf.DUMMYFUNCTION("iferror(filter('Статьи'!$A$1:$A177,'Статьи'!$B$1:$B177=$B$89))"),"") | I90: =sum(C90:H90) -> 0 | P90: =SUM(J90:K90) -> 0 | Q90: =I90-P90 -> 0 | R90: =IFERROR(I90/P90,0) -> 0 | S90: =IF(Q90=0,"",IF(R90=0,"обратить внимание",IF(R90>1,"перерасход","экономия")))
A91: =IFERROR(VLOOKUP(B91,'Статьи'!$A$2:C113,3,0)," ") | I91: =sum(C91:H91) -> 0 | P91: =SUM(J91:K91) -> 0 | Q91: =I91-P91 -> 0 | R91: =IFERROR(I91/P91,0) -> 0 | S91: =IF(Q91=0,"",IF(R91=0,"обратить внимание",IF(R91>1,"перерасход","экономия")))
A92: =IFERROR(VLOOKUP(B92,'Статьи'!$A$2:C114,3,0)," ") | I92: =sum(C92:H92) -> 0 | P92: =SUM(J92:K92) -> 0 | Q92: =I92-P92 -> 0 | R92: =IFERROR(I92/P92,0) -> 0 | S92: =IF(Q92=0,"",IF(R92=0,"обратить внимание",IF(R92>1,"перерасход","экономия")))
A93: =IFERROR(VLOOKUP(B93,'Статьи'!$A$2:C115,3,0)," ") | I93: =sum(C93:H93) -> 0 | P93: =SUM(J93:K93) -> 0 | Q93: =I93-P93 -> 0 | R93: =IFERROR(I93/P93,0) -> 0 | S93: =IF(Q93=0,"",IF(R93=0,"обратить внимание",IF(R93>1,"перерасход","экономия")))
A94: =IFERROR(VLOOKUP(B94,'Статьи'!$A$2:C116,3,0)," ") | I94: =sum(C94:H94) -> 0 | P94: =SUM(J94:K94) -> 0 | Q94: =I94-P94 -> 0 | R94: =IFERROR(I94/P94,0) -> 0 | S94: =IF(Q94=0,"",IF(R94=0,"обратить внимание",IF(R94>1,"перерасход","экономия")))
I95: =sum(C95:H95) -> 0 | P95: =sum(F95:J95) -> 0 | Q95: =I95-P95 -> 0 | R95: =IFERROR(I95/P95,0) -> 0 | S95: =IF(Q95=0,"",IF(Q95=0,0,IF(R95>1,"перерасход","экономия")))
I96: =sum(C96:H96) -> 0 | P96: =sum(F96:J96) -> 0 | Q96: =I96-P96 -> 0 | R96: =IFERROR(I96/P96,0) -> 0 | S96: =IF(Q96=0,"",IF(Q96=0,0,IF(R96>1,"перерасход","экономия")))
I97: =sum(C97:H97) -> 0 | P97: =sum(F97:J97) -> 0 | Q97: =I97-P97 -> 0 | R97: =IFERROR(I97/P97,0) -> 0 | S97: =IF(Q97=0,"",IF(Q97=0,0,IF(R97>1,"перерасход","экономия")))
I98: =sum(C98:H98) -> 0 | P98: =sum(F98:J98) -> 0 | Q98: =I98-P98 -> 0 | R98: =IFERROR(I98/P98,0) -> 0 | S98: =IF(Q98=0,"",IF(Q98=0,0,IF(R98>1,"перерасход","экономия")))
I99: =sum(C99:H99) -> 0 | P99: =sum(F99:J99) -> 0 | Q99: =I99-P99 -> 0 | R99: =IFERROR(I99/P99,0) -> 0 | S99: =IF(Q99=0,"",IF(Q99=0,0,IF(R99>1,"перерасход","экономия")))
I100: =sum(C100:H100) -> 0 | P100: =sum(F100:J100) -> 0 | Q100: =I100-P100 -> 0 | R100: =IFERROR(I100/P100,0) -> 0 | S100: =IF(Q100=0,"",IF(Q100=0,0,IF(R100>1,"перерасход","экономия")))
B101: Административные | C101: =SUM(C102:C131) -> 0 | D101: =SUM(D102:D131) -> 0 | E101: =SUM(E102:E131) -> 0 | F101: =SUM(F102:F131) -> 0 | G101: =SUM(G102:G131) -> 0 | H101: =SUM(H102:H131) -> 0 | I101: =SUM(I102:I131) -> 0 | J101: =SUM(J102:J131) -> 0 | K101: =SUM(K102:K131) -> 0 | P101: =SUM(P102:P131) -> 0 | Q101: =I101-P101 -> 0 | R101: =IFERROR(I101/P101,0) -> 0 | S101: =IF(Q101=0,"",IF(R101>1,"план не выполнен","выполнение"))
A102: =IFERROR(VLOOKUP(B102,'Статьи'!$A$2:C124,3,0)," ") -> 1С | B102: =IFERROR(__xludf.DUMMYFUNCTION("iferror(filter('Статьи'!$A$1:$A177,'Статьи'!$B$1:$B177=$B$101))"),"Аренда, коммунальные услуги") -> Аренда, коммунальные услуги | I102: =sum(C102:H102) -> 0 | P102: =SUM(J102:K102) -> 0 | Q102: =I102-P102 -> 0 | R102: =IFERROR(I102/P102,0) -> 0 | S102: =IF(Q102=0,"",IF(R102=0,"обратить внимание",IF(R102>1,"перерасход","экономия")))
A103: =IFERROR(VLOOKUP(B103,'Статьи'!$A$2:C125,3,0)," ") -> 1С | B103: =IFERROR(__xludf.DUMMYFUNCTION("""COMPUTED_VALUE"""),"Аутсорсинг и прочие услуги") -> Аутсорсинг и прочие услуги | I103: =sum(C103:H103) -> 0 | P103: =SUM(J103:K103) -> 0 | Q103: =I103-P103 -> 0 | R103: =IFERROR(I103/P103,0) -> 0 | S103: =IF(Q103=0,"",IF(R103=0,"обратить внимание",IF(R103>1,"перерасход","экономия")))
A104: =IFERROR(VLOOKUP(B104,'Статьи'!$A$2:C126,3,0)," ") -> 1С | B104: =IFERROR(__xludf.DUMMYFUNCTION("""COMPUTED_VALUE"""),"Командировочные расходы") -> Командировочные расходы | I104: =sum(C104:H104) -> 0 | P104: =SUM(J104:K104) -> 0 | Q104: =I104-P104 -> 0 | R104: =IFERROR(I104/P104,0) -> 0 | S104: =IF(Q104=0,"",IF(R104=0,"обратить внимание",IF(R104>1,"перерасход","экономия")))
A105: =IFERROR(VLOOKUP(B105,'Статьи'!$A$2:C127,3,0)," ") -> ДДС отчетного месяца. Без НДС! | B105: =IFERROR(__xludf.DUMMYFUNCTION("""COMPUTED_VALUE"""),"Комиссии банка") -> Комиссии банка | I105: =sum(C105:H105) -> 0 | P105: =SUM(J105:K105) -> 0 | Q105: =I105-P105 -> 0 | R105: =IFERROR(I105/P105,0) -> 0 | S105: =IF(Q105=0,"",IF(R105=0,"обратить внимание",IF(R105>1,"перерасход","экономия")))
A106: =IFERROR(VLOOKUP(B106,'Статьи'!$A$2:C128,3,0)," ") -> ДДС отчетного месяца. Без НДС! | B106: =IFERROR(__xludf.DUMMYFUNCTION("""COMPUTED_VALUE"""),"Обучение сотрудников") -> Обучение сотрудников | I106: =sum(C106:H106) -> 0 | P106: =SUM(J106:K106) -> 0 | Q106: =I106-P106 -> 0 | R106: =IFERROR(I106/P106,0) -> 0 | S106: =IF(Q106=0,"",IF(R106=0,"обратить внимание",IF(R106>1,"перерасход","экономия")))
A107: =IFERROR(VLOOKUP(B107,'Статьи'!$A$2:C129,3,0)," ") -> ДДС отчетного месяца. Без НДС! | B107: =IFERROR(__xludf.DUMMYFUNCTION("""COMPUTED_VALUE"""),"Подбор персонала") -> Подбор персонала | I107: =sum(C107:H107) -> 0 | P107: =SUM(J107:K107) -> 0 | Q107: =I107-P107 -> 0 | R107: =IFERROR(I107/P107,0) -> 0 | S107: =IF(Q107=0,"",IF(R107=0,"обратить внимание",IF(R107>1,"перерасход","экономия")))
A108: =IFERROR(VLOOKUP(B108,'Статьи'!$A$2:C130,3,0)," ") -> ДДС отчетного месяца. Без НДС! | B108: =IFERROR(__xludf.DUMMYFUNCTION("""COMPUTED_VALUE"""),"Почтовые расходы") -> Почтовые расходы | I108: =sum(C108:H108) -> 0 | P108: =SUM(J108:K108) -> 0 | Q108: =I108-P108 -> 0 | R108: =IFERROR(I108/P108,0) -> 0 | S108: =IF(Q108=0,"",IF(R108=0,"обратить внимание",IF(R108>1,"перерасход","экономия")))
A109: =IFERROR(VLOOKUP(B109,'Статьи'!$A$2:C131,3,0)," ") -> ДДС отчетного месяца. Без НДС! | B109: =IFERROR(__xludf.DUMMYFUNCTION("""COMPUTED_VALUE"""),"Представительские расходы") -> Представительские расходы | I109: =sum(C109:H109) -> 0 | P109: =SUM(J109:K109) -> 0 | Q109: =I109-P109 -> 0 | R109: =IFERROR(I109/P109,0) -> 0 | S109: =IF(Q109=0,"",IF(R109=0,"обратить внимание",IF(R109>1,"перерасход","экономия")))
A110: =IFERROR(VLOOKUP(B110,'Статьи'!$A$2:C132,3,0)," ") -> ДДС отчетного месяца. Без НДС! | B110: =IFERROR(__xludf.DUMMYFUNCTION("""COMPUTED_VALUE"""),"Содержание офиса") -> Содержание офиса | I110: =sum(C110:H110) -> 0 | P110: =SUM(J110:K110) -> 0 | Q110: =I110-P110 -> 0 | R110: =IFERROR(I110/P110,0) -> 0 | S110: =IF(Q110=0,"",IF(R110=0,"обратить внимание",IF(R110>1,"перерасход","экономия")))
A111: =IFERROR(VLOOKUP(B111,'Статьи'!$A$2:C133,3,0)," ") -> ДДС отчетного месяца. Без НДС! | B111: =IFERROR(__xludf.DUMMYFUNCTION("""COMPUTED_VALUE"""),"Услуги связи + Интернет") -> Услуги связи + Интернет | I111: =sum(C111:H111) -> 0 | P111: =SUM(J111:K111) -> 0 | Q111: =I111-P111 -> 0 | R111: =IFERROR(I111/P111,0) -> 0 | S111: =IF(Q111=0,"",IF(R111=0,"обратить внимание",IF(R111>1,"перерасход","экономия")))
A112: =IFERROR(VLOOKUP(B112,'Статьи'!$A$2:C134,3,0)," ") -> ДДС отчетного месяца. Без НДС! | B112: =IFERROR(__xludf.DUMMYFUNCTION("""COMPUTED_VALUE"""),"Штрафы") -> Штрафы | I112: =sum(C112:H112) -> 0 | P112: =SUM(J112:K112) -> 0 | Q112: =I112-P112 -> 0 | R112: =IFERROR(I112/P112,0) -> 0 | S112: =IF(Q112=0,"",IF(R112=0,"обратить внимание",IF(R112>1,"перерасход","экономия")))
A113: =IFERROR(VLOOKUP(B113,'Статьи'!$A$2:C135,3,0)," ") | I113: =sum(C113:H113) -> 0 | P113: =SUM(J113:K113) -> 0 | Q113: =I113-P113 -> 0 | R113: =IFERROR(I113/P113,0) -> 0 | S113: =IF(Q113=0,"",IF(R113=0,"обратить внимание",IF(R113>1,"перерасход","экономия")))
A114: =IFERROR(VLOOKUP(B114,'Статьи'!$A$2:C136,3,0)," ") | I114: =sum(C114:H114) -> 0 | P114: =SUM(J114:K114) -> 0 | Q114: =I114-P114 -> 0 | R114: =IFERROR(I114/P114,0) -> 0 | S114: =IF(Q114=0,"",IF(R114=0,"обратить внимание",IF(R114>1,"перерасход","экономия")))
A115: =IFERROR(VLOOKUP(B115,'Статьи'!$A$2:C137,3,0)," ") | I115: =sum(C115:H115) -> 0 | P115: =SUM(J115:K115) -> 0 | Q115: =I115-P115 -> 0 | R115: =IFERROR(I115/P115,0) -> 0 | S115: =IF(Q115=0,"",IF(R115=0,"обратить внимание",IF(R115>1,"перерасход","экономия")))
A116: =IFERROR(VLOOKUP(B116,'Статьи'!$A$2:C138,3,0)," ") | I116: =sum(C116:H116) -> 0 | P116: =SUM(J116:K116) -> 0 | Q116: =I116-P116 -> 0 | R116: =IFERROR(I116/P116,0) -> 0 | S116: =IF(Q116=0,"",IF(R116=0,"обратить внимание",IF(R116>1,"перерасход","экономия")))
A117: =IFERROR(VLOOKUP(B117,'Статьи'!$A$2:C139,3,0)," ") | I117: =sum(C117:H117) -> 0 | P117: =SUM(J117:K117) -> 0 | Q117: =I117-P117 -> 0 | R117: =IFERROR(I117/P117,0) -> 0 | S117: =IF(Q117=0,"",IF(R117=0,"обратить внимание",IF(R117>1,"перерасход","экономия")))
A118: =IFERROR(VLOOKUP(B118,'Статьи'!$A$2:C140,3,0)," ") | I118: =sum(C118:H118) -> 0 | P118: =SUM(J118:K118) -> 0 | Q118: =I118-P118 -> 0 | R118: =IFERROR(I118/P118,0) -> 0 | S118: =IF(Q118=0,"",IF(R118=0,"обратить внимание",IF(R118>1,"перерасход","экономия")))
A119: =IFERROR(VLOOKUP(B119,'Статьи'!$A$2:C141,3,0)," ") | I119: =sum(C119:H119) -> 0 | P119: =SUM(J119:K119) -> 0 | Q119: =I119-P119 -> 0 | R119: =IFERROR(I119/P119,0) -> 0 | S119: =IF(Q119=0,"",IF(R119=0,"обратить внимание",IF(R119>1,"перерасход","экономия")))
A120: =IFERROR(VLOOKUP(B120,'Статьи'!$A$2:C142,3,0)," ") | I120: =sum(C120:H120) -> 0 | P120: =SUM(J120:K120) -> 0 | Q120: =I120-P120 -> 0 | R120: =IFERROR(I120/P120,0) -> 0 | S120: =IF(Q120=0,"",IF(R120=0,"обратить внимание",IF(R120>1,"перерасход","экономия")))
A121: =IFERROR(VLOOKUP(B121,'Статьи'!$A$2:C143,3,0)," ") | I121: =sum(C121:H121) -> 0 | P121: =SUM(J121:K121) -> 0 | Q121: =I121-P121 -> 0 | R121: =IFERROR(I121/P121,0) -> 0 | S121: =IF(Q121=0,"",IF(R121=0,"обратить внимание",IF(R121>1,"перерасход","экономия")))
A122: =IFERROR(VLOOKUP(B122,'Статьи'!$A$2:C144,3,0)," ") | I122: =sum(C122:H122) -> 0 | P122: =SUM(J122:K122) -> 0 | Q122: =I122-P122 -> 0 | R122: =IFERROR(I122/P122,0) -> 0 | S122: =IF(Q122=0,"",IF(R122=0,"обратить внимание",IF(R122>1,"перерасход","экономия")))
A123: =IFERROR(VLOOKUP(B123,'Статьи'!$A$2:C145,3,0)," ") | I123: =sum(C123:H123) -> 0 | P123: =SUM(J123:K123) -> 0 | Q123: =I123-P123 -> 0 | R123: =IFERROR(I123/P123,0) -> 0 | S123: =IF(Q123=0,"",IF(R123=0,"обратить внимание",IF(R123>1,"перерасход","экономия")))
A124: =IFERROR(VLOOKUP(B124,'Статьи'!$A$2:C146,3,0)," ") | I124: =sum(C124:H124) -> 0 | P124: =SUM(J124:K124) -> 0 | Q124: =I124-P124 -> 0 | R124: =IFERROR(I124/P124,0) -> 0 | S124: =IF(Q124=0,"",IF(R124=0,"обратить внимание",IF(R124>1,"перерасход","экономия")))
... A131: =IFERROR(VLOOKUP(B131,'Статьи'!$A$2:C153,3,0)," ") | I131: =sum(C131:H131) -> 0 | P131: =SUM(J131:K131) -> 0 | Q131: =I131-P131 -> 0 | R131: =IFERROR(I131/P131,0) -> 0 | S131: =IF(Q131=0,"",IF(R131=0,"обратить внимание",IF(R131>1,"перерасход","экономия")))
B132: Коммерческие | C132: =SUM(C133:C141) -> 0 | D132: =SUM(D133:D141) -> 0 | E132: =SUM(E133:E141) -> 0 | F132: =SUM(F133:F141) -> 0 | G132: =SUM(G133:G141) -> 0 | H132: =SUM(H133:H141) -> 0 | I132: =sum(C132:H132) -> 0 | J132: =SUM(J133:J141) -> 0 | K132: =SUM(K133:K141) -> 0 | L132: =SUM(L133:L141) -> 0 | M132: =SUM(M133:M141) -> 0 | N132: =SUM(N133:N141) -> 0 | O132: =SUM(O133:O141) -> 0 | P132: =SUM(P133:P141) -> 0 | Q132: =I132-P132 -> 0 | R132: =IFERROR(I132/P132,0) -> 0 | S132: =IF(Q132=0,"",IF(R132>1,"план не выполнен","выполнение"))
A133: =IFERROR(VLOOKUP(B133,'Статьи'!$A$2:C155,3,0)," ") -> ДДС отчетного месяца. Без НДС! | B133: =IFERROR(__xludf.DUMMYFUNCTION("iferror(filter('Статьи'!$A$1:$A177,'Статьи'!$B$1:$B177=$B$132))"),"Подписка на сайты по поиску клиентов") -> Подписка на сайты по поиску клиентов | I133: =sum(C133:H133) -> 0 | P133: =SUM(J133:K133) -> 0 | Q133: =I133-P133 -> 0 | R133: =IFERROR(I133/P133,0) -> 0 | S133: =IF(Q133=0,"",IF(R133=0,"обратить внимание",IF(R133>1,"перерасход","экономия")))
A134: =IFERROR(VLOOKUP(B134,'Статьи'!$A$2:C156,3,0)," ") | I134: =sum(C134:H134) -> 0 | P134: =SUM(J134:K134) -> 0 | Q134: =I134-P134 -> 0 | R134: =IFERROR(I134/P134,0) -> 0 | S134: =IF(Q134=0,"",IF(R134=0,"обратить внимание",IF(R134>1,"перерасход","экономия")))
A135: =IFERROR(VLOOKUP(B135,'Статьи'!$A$2:C157,3,0)," ") | I135: =sum(C135:H135) -> 0 | P135: =SUM(J135:K135) -> 0 | Q135: =I135-P135 -> 0 | R135: =IFERROR(I135/P135,0) -> 0 | S135: =IF(Q135=0,"",IF(R135=0,"обратить внимание",IF(R135>1,"перерасход","экономия")))
A136: =IFERROR(VLOOKUP(B136,'Статьи'!$A$2:C158,3,0)," ") | I136: =sum(C136:H136) -> 0 | P136: =SUM(J136:K136) -> 0 | Q136: =I136-P136 -> 0 | R136: =IFERROR(I136/P136,0) -> 0 | S136: =IF(Q136=0,"",IF(R136=0,"обратить внимание",IF(R136>1,"перерасход","экономия")))
A137: =IFERROR(VLOOKUP(B137,'Статьи'!$A$2:C159,3,0)," ") | I137: =sum(C137:H137) -> 0 | P137: =SUM(J137:K137) -> 0 | Q137: =I137-P137 -> 0 | R137: =IFERROR(I137/P137,0) -> 0 | S137: =IF(Q137=0,"",IF(R137=0,"обратить внимание",IF(R137>1,"перерасход","экономия")))
A138: =IFERROR(VLOOKUP(B138,'Статьи'!$A$2:C160,3,0)," ") | I138: =sum(C138:H138) -> 0 | P138: =SUM(J138:K138) -> 0 | Q138: =I138-P138 -> 0 | R138: =IFERROR(I138/P138,0) -> 0 | S138: =IF(Q138=0,"",IF(R138=0,"обратить внимание",IF(R138>1,"перерасход","экономия")))
A139: =IFERROR(VLOOKUP(B139,'Статьи'!$A$2:C161,3,0)," ") | I139: =sum(C139:H139) -> 0 | P139: =SUM(J139:K139) -> 0 | Q139: =I139-P139 -> 0 | R139: =IFERROR(I139/P139,0) -> 0 | S139: =IF(Q139=0,"",IF(R139=0,"обратить внимание",IF(R139>1,"перерасход","экономия")))
A140: =IFERROR(VLOOKUP(B140,'Статьи'!$A$2:C162,3,0)," ") | I140: =sum(C140:H140) -> 0 | P140: =SUM(J140:K140) -> 0 | Q140: =I140-P140 -> 0 | R140: =IFERROR(I140/P140,0) -> 0 | S140: =IF(Q140=0,"",IF(R140=0,"обратить внимание",IF(R140>1,"перерасход","экономия")))
A141: =IFERROR(VLOOKUP(B141,'Статьи'!$A$2:C163,3,0)," ") | I141: =sum(C141:H141) -> 0 | P141: =sum(F141:J141) -> 0 | Q141: =I141-P141 -> 0 | R141: =IFERROR(I141/P141,0) -> 0 | S141: =IF(Q141=0,"",IF(R141=0,"обратить внимание",IF(R141>1,"перерасход","экономия")))
B142: Операционная прибыль (EBITDA) | C142: =C85+C88 -> 4 | D142: =D85+D88 -> 0 | E142: =E85+E88 -> 0 | F142: =F85+F88 -> 0 | G142: =G85+G88 -> 0 | H142: =H85+H88 -> 0 | I142: =I85+I88 -> 4 | J142: =J85+J88 -> 0 | K142: =K85+K88 -> 0 | P142: =P85+P88 -> 0 | Q142: =I142-P142 -> 4 | R142: =IFERROR(I142/P142,0) -> 0 | S142: =IF(Q142=0,"",IF(R142>1,"выполнение","план не выполнен")) -> план не выполнен
...

Sheet 5
C1: ФАКТ | J1: План | Q1: Отклонения
A2: Источники | C2: {=TRANSPOSE('Справочник'!D2:D7)} -> ООО "Весело живем" | D2: ООО "Некогда грустить" | E2: 3 | F2: 4 | G2: 5 | H2: 6 | I2: Итого | J2: {=TRANSPOSE('Справочник'!D2:D7)} -> ООО "Весело живем" | K2: ООО "Некогда грустить" | L2: 3 | M2: 4 | N2: 5 | O2: 6 | P2: Итого | Q2: факт-план, EUR | R2: факт/план, % | S2: Результат
B3: Выручка | C3: =SUM(C4:C10) -> 5 | D3: =SUM(D4:D10) -> 0 | E3: =SUM(E4:E10) -> 0 | F3: =SUM(F4:F10) -> 0 | G3: =SUM(G4:G10) -> 0 | H3: =SUM(H4:H10) -> 0 | I3: =sum(C3:H3) -> 5 | J3: =SUM(J4:J10) -> 0 | K3: =SUM(K4:K10) -> 0 | P3: =SUM(P4:P10) -> 0 | Q3: =I3-P3 -> 5 | R3: =IFERROR(I3/P3,0) -> 0 | S3: =IF(Q3=0,"",IF(R3>1,"выполнение","план не выполнен")) -> план не выполнен
A4: =IFERROR(VLOOKUP(B4,'Статьи'!$A$2:C26,3,0)," ") -> 1С сч 90.01 убрать НДС! | B4: =IFERROR(__xludf.DUMMYFUNCTION("iferror(filter('Статьи'!$A$1:$A177,'Статьи'!$B$1:$B177=$B$3))"),"Выручка от аренды машиноместа") -> Выручка от аренды машиноместа | C4: 5 | I4: =SUM(C4:H4) -> 5 | P4: =SUM(J4:K4) -> 0 | Q4: =I4-P4 -> 5 | R4: =IFERROR(I4/P4,0) -> 0 | S4: =IF(Q4=0,"",IF(R4=0,"обратить внимание",IF(R4>1,"выполнение","план не выполнен"))) -> обратить внимание
A5: =IFERROR(VLOOKUP(B5,'Статьи'!$A$2:C27,3,0)," ") -> 1С сч 90.01 убрать НДС! | B5: =IFERROR(__xludf.DUMMYFUNCTION("""COMPUTED_VALUE"""),"Выручка за грузоперевозки") -> Выручка за грузоперевозки | I5: =SUM(C5:H5) -> 0 | P5: =SUM(J5:K5) -> 0 | Q5: =I5-P5 -> 0 | R5: =IFERROR(I5/P5,0) -> 0 | S5: =IF(Q5=0,"",IF(R5=0,"обратить внимание",IF(R5>1,"выполнение","план не выполнен")))
A6: =IFERROR(VLOOKUP(B6,'Статьи'!$A$2:C28,3,0)," ") | I6: =SUM(C6:H6) -> 0 | P6: =SUM(F6:J6) -> 0 | Q6: =I6-P6 -> 0 | R6: =IFERROR(I6/P6,0) -> 0 | S6: =IF(Q6=0,"",IF(R6=0,"обратить внимание",IF(R6>1,"выполнение","план не выполнен")))
A7: =IFERROR(VLOOKUP(B7,'Статьи'!$A$2:C29,3,0)," ") | I7: =SUM(C7:H7) -> 0 | P7: =SUM(F7:J7) -> 0 | Q7: =I7-P7 -> 0 | R7: =IFERROR(I7/P7,0) -> 0 | S7: =IF(Q7=0,"",IF(R7=0,"обратить внимание",IF(R7>1,"выполнение","план не выполнен")))
A8: =IFERROR(VLOOKUP(B8,'Статьи'!$A$2:C30,3,0)," ") | I8: =SUM(C8:H8) -> 0 | P8: =SUM(F8:J8) -> 0 | Q8: =I8-P8 -> 0 | R8: =IFERROR(I8/P8,0) -> 0 | S8: =IF(Q8=0,"",IF(R8=0,"обратить внимание",IF(R8>1,"выполнение","план не выполнен")))
A9: =IFERROR(VLOOKUP(B9,'Статьи'!$A$2:C31,3,0)," ") | Q9: =I9-P9 -> 0 | R9: =IFERROR(I9/P9,0) -> 0 | S9: =IF(Q9=0,"",IF(R9=0,"обратить внимание",IF(R9>1,"выполнение","план не выполнен")))
A10: =IFERROR(VLOOKUP(B10,'Статьи'!$A$2:C32,3,0)," ") | Q10: =I10-P10 -> 0 | R10: =IFERROR(I10/P10,0) -> 0 | S10: =IF(Q10=0,"",IF(R10=0,"обратить внимание",IF(R10>1,"выполнение","план не выполнен")))
B11: Производственные расходы | C11: =C12+C58 -> 0 | D11: =D12+D58 -> 0 | E11: =E12+E58 -> 0 | F11: =F12+F58 -> 0 | G11: =G12+G58 -> 0 | H11: =H12+H58 -> 0 | I11: =I12+I58 -> 0 | J11: =J12+J58 -> 0 | K11: =K12+K58 -> 0 | P11: =P12+P58 -> 0 | Q11: =I11-P11 -> 0 | R11: =IFERROR(I11/P11,0) -> 0 | S11: =IF(Q11=0,"",IF(R11>1,"план не выполнен","выполнение"))
B12: Переменные | C12: =sum(C13:C54) -> 0 | D12: =sum(D13:D54) -> 0 | E12: =sum(E13:E54) -> 0 | F12: =sum(F13:F54) -> 0 | G12: =sum(G13:G54) -> 0 | H12: =sum(H13:H54) -> 0 | I12: =sum(I13:I54) -> 0 | J12: =sum(J13:J54) -> 0 | K12: =sum(K13:K54) -> 0 | P12: =sum(P13:P54) -> 0 | Q12: =I12-P12 -> 0 | R12: =IFERROR(I12/P12,0) -> 0 | S12: =IF(Q12=0,"",IF(R12=0,"обратить внимание",IF(R12>1,"перерасход","экономия")))
A13: =IFERROR(VLOOKUP(B13,'Статьи'!$A$2:C35,3,0)," ") -> ДДС отчетного месяца. Без НДС! | B13: =IFERROR(__xludf.DUMMYFUNCTION("iferror(filter('Статьи'!$A$1:$A177,'Статьи'!$B$1:$B177=$B$12))"),"Комиссия топливных компаний") -> Комиссия топливных компаний | I13: =sum(C13:H13) -> 0 | P13: =SUM(J13:K13) -> 0 | Q13: =I13-P13 -> 0 | R13: =IFERROR(I13/P13,0) -> 0 | S13: =IF(Q13=0,"",IF(R13=0,"обратить внимание",IF(R13>1,"перерасход","экономия")))
A14: =IFERROR(VLOOKUP(B14,'Статьи'!$A$2:C36,3,0)," ") -> 1С | B14: =IFERROR(__xludf.DUMMYFUNCTION("""COMPUTED_VALUE"""),"Топливо для грузовых авто ") -> Топливо для грузовых авто | I14: =sum(C14:H14) -> 0 | P14: =SUM(J14:K14) -> 0 | Q14: =I14-P14 -> 0 | R14: =IFERROR(I14/P14,0) -> 0 | S14: =IF(Q14=0,"",IF(R14=0,"обратить внимание",IF(R14>1,"перерасход","экономия")))
A15: =IFERROR(VLOOKUP(B15,'Статьи'!$A$2:C37,3,0)," ") | I15: =sum(C15:H15) -> 0 | P15: =SUM(J15:K15) -> 0 | Q15: =I15-P15 -> 0 | R15: =IFERROR(I15/P15,0) -> 0 | S15: =IF(Q15=0,"",IF(R15=0,"обратить внимание",IF(R15>1,"перерасход","экономия")))
A16: =IFERROR(VLOOKUP(B16,'Статьи'!$A$2:C38,3,0)," ") | I16: =sum(C16:H16) -> 0 | P16: =SUM(J16:K16) -> 0 | Q16: =I16-P16 -> 0 | R16: =IFERROR(I16/P16,0) -> 0 | S16: =IF(Q16=0,"",IF(R16=0,"обратить внимание",IF(R16>1,"перерасход","экономия")))
A17: =IFERROR(VLOOKUP(B17,'Статьи'!$A$2:C39,3,0)," ") | I17: =sum(C17:H17) -> 0 | P17: =sum(F17:J17) -> 0 | Q17: =I17-P17 -> 0 | R17: =IFERROR(I17/P17,0) -> 0 | S17: =IF(Q17=0,"",IF(R17=0,"обратить внимание",IF(R17>1,"перерасход","экономия")))
I18: =sum(C18:H18) -> 0 | P18: =sum(F18:J18) -> 0 | Q18: =I18-P18 -> 0 | R18: =IFERROR(I18/P18,0) -> 0 | S18: =IF(Q18=0,0,IF(R18>1,"перерасход","экономия")) -> 0
I19: =sum(C19:H19) -> 0 | P19: =sum(F19:J19) -> 0 | Q19: =I19-P19 -> 0 | R19: =IFERROR(I19/P19,0) -> 0 | S19: =IF(Q19=0,0,IF(R19>1,"перерасход","экономия")) -> 0
I20: =sum(C20:H20) -> 0 | P20: =sum(F20:J20) -> 0 | Q20: =I20-P20 -> 0 | R20: =IFERROR(I20/P20,0) -> 0 | S20: =IF(Q20=0,0,IF(R20>1,"перерасход","экономия")) -> 0
I21: =sum(C21:H21) -> 0 | P21: =sum(F21:J21) -> 0 | Q21: =I21-P21 -> 0 | R21: =IFERROR(I21/P21,0) -> 0 | S21: =IF(Q21=0,0,IF(R21>1,"перерасход","экономия")) -> 0
I22: =sum(C22:H22) -> 0 | P22: =sum(F22:J22) -> 0 | Q22: =I22-P22 -> 0 | R22: =IFERROR(I22/P22,0) -> 0 | S22: =IF(Q22=0,0,IF(R22>1,"перерасход","экономия")) -> 0
I23: =sum(C23:H23) -> 0 | P23: =sum(F23:J23) -> 0 | Q23: =I23-P23 -> 0 | R23: =IFERROR(I23/P23,0) -> 0 | S23: =IF(Q23=0,0,IF(R23>1,"перерасход","экономия")) -> 0
I24: =sum(C24:H24) -> 0 | P24: =sum(F24:J24) -> 0 | Q24: =I24-P24 -> 0 | R24: =IFERROR(I24/P24,0) -> 0 | S24: =IF(Q24=0,0,IF(R24>1,"перерасход","экономия")) -> 0
I25: =sum(C25:H25) -> 0 | P25: =sum(F25:J25) -> 0 | Q25: =I25-P25 -> 0 | R25: =IFERROR(I25/P25,0) -> 0 | S25: =IF(Q25=0,0,IF(R25>1,"перерасход","экономия")) -> 0
I26: =sum(C26:H26) -> 0 | P26: =sum(F26:J26) -> 0 | Q26: =I26-P26 -> 0 | R26: =IFERROR(I26/P26,0) -> 0 | S26: =IF(Q26=0,0,IF(R26>1,"перерасход","экономия")) -> 0
I27: =sum(C27:H27) -> 0 | P27: =sum(F27:J27) -> 0 | Q27: =I27-P27 -> 0 | R27: =IFERROR(I27/P27,0) -> 0 | S27: =IF(Q27=0,0,IF(R27>1,"перерасход","экономия")) -> 0
I28: =sum(C28:H28) -> 0 | P28: =sum(F28:J28) -> 0 | Q28: =I28-P28 -> 0 | R28: =IFERROR(I28/P28,0) -> 0 | S28: =IF(Q28=0,0,IF(R28>1,"перерасход","экономия")) -> 0
I29: =sum(C29:H29) -> 0 | P29: =sum(F29:J29) -> 0 | Q29: =I29-P29 -> 0 | R29: =IFERROR(I29/P29,0) -> 0 | S29: =IF(Q29=0,0,IF(R29>1,"перерасход","экономия")) -> 0
... I54: =sum(C54:H54) -> 0 | P54: =sum(F54:J54) -> 0 | Q54: =I54-P54 -> 0 | R54: =IFERROR(I54/P54,0) -> 0 | S54: =IF(Q54=0,0,IF(R54>1,"перерасход","экономия")) -> 0
B55: Маржинальный доход | C55: =C3+C12 -> 5 | D55: =D3+D12 -> 0 | E55: =E3+E12 -> 0 | F55: =F3+F12 -> 0 | G55: =G3+G12 -> 0 | H55: =H3+H12 -> 0 | I55: =I3+I12 -> 5 | J55: =J3+J12 -> 0 | K55: =K3+K12 -> 0 | P55: =P3+P12 -> 0 | Q55: =I55-P55 -> 5 | R55: =IFERROR(I55/P55,0) -> 0 | S55: =IF(Q55=0,"",IF(R55>1,"выполнение","план не выполнен")) -> план не выполнен
B56: Рентабельность по марже | C56: =IFERROR(C55/C$3,"") -> 1 | D56: =IFERROR(D55/D$3,"") | E56: =IFERROR(E55/E$3,"") | F56: =IFERROR(F55/F$3,"") | G56: =IFERROR(G55/G$3,"") | H56: =IFERROR(H55/H$3,"") | I56: =IFERROR(I55/I$3,"") -> 1 | J56: =IFERROR(J55/J$3,"") | K56: =IFERROR(K55/K$3,"") | P56: =IFERROR(P55/P$3,"")
B58: Общепроизводственные | C58: =sum(C59:C79) -> 0 | D58: =sum(D59:D79) -> 0 | E58: =sum(E59:E79) -> 0 | F58: =sum(F59:F79) -> 0 | G58: =sum(G59:G79) -> 0 | H58: =sum(H59:H79) -> 0 | I58: =SUM(I59:I84) -> 0 | J58: =SUM(J59:J84) -> 0 | K58: =SUM(K59:K84) -> 0 | P58: =SUM(P59:P84) -> 0 | Q58: =I58-P58 -> 0 | R58: =IFERROR(I58/P58,0) -> 0 | S58: =IF(Q58=0,"",IF(R58>1,"план не выполнен","выполнение"))
A59: =IFERROR(VLOOKUP(B59,'Статьи'!$A$2:C81,3,0)," ") -> 1С | B59: =IFERROR(__xludf.DUMMYFUNCTION("iferror(filter('Статьи'!$A$1:$A177,'Статьи'!$B$1:$B177=$B$58))"),"Зарплата производственного персонала") -> Зарплата производственного персонала | I59: =SUM(C59:H59) -> 0 | P59: =SUM(J59:K59) -> 0 | Q59: =I59-P59 -> 0 | R59: =IFERROR(I59/P59,0) -> 0 | S59: =IF(Q59=0,"",IF(R59=0,"обратить внимание",IF(R59>1,"перерасход","экономия")))
A60: =IFERROR(VLOOKUP(B60,'Статьи'!$A$2:C82,3,0)," ") -> ДДС отчетного месяца. Без НДС! | B60: =IFERROR(__xludf.DUMMYFUNCTION("""COMPUTED_VALUE"""),"Таможенные расходы") -> Таможенные расходы | I60: =SUM(C60:H60) -> 0 | P60: =SUM(J60:K60) -> 0 | Q60: =I60-P60 -> 0 | R60: =IFERROR(I60/P60,0) -> 0 | S60: =IF(Q60=0,"",IF(R60=0,"обратить внимание",IF(R60>1,"перерасход","экономия")))
A61: =IFERROR(VLOOKUP(B61,'Статьи'!$A$2:C83,3,0)," ") | I61: =SUM(C61:H61) -> 0 | P61: =SUM(J61:K61) -> 0 | Q61: =I61-P61 -> 0 | R61: =IFERROR(I61/P61,0) -> 0 | S61: =IF(Q61=0,"",IF(R61=0,"обратить внимание",IF(R61>1,"перерасход","экономия")))
A62: =IFERROR(VLOOKUP(B62,'Статьи'!$A$2:C84,3,0)," ") | I62: =SUM(C62:H62) -> 0 | P62: =SUM(J62:K62) -> 0 | Q62: =I62-P62 -> 0 | R62: =IFERROR(I62/P62,0) -> 0 | S62: =IF(Q62=0,"",IF(R62=0,"обратить внимание",IF(R62>1,"перерасход","экономия")))
A63: =IFERROR(VLOOKUP(B63,'Статьи'!$A$2:C85,3,0)," ") | I63: =SUM(C63:H63) -> 0 | P63: =SUM(J63:K63) -> 0 | Q63: =I63-P63 -> 0 | R63: =IFERROR(I63/P63,0) -> 0 | S63: =IF(Q63=0,"",IF(R63=0,"обратить внимание",IF(R63>1,"перерасход","экономия")))
A64: =IFERROR(VLOOKUP(B64,'Статьи'!$A$2:C86,3,0)," ") | I64: =SUM(C64:H64) -> 0 | P64: =SUM(J64:K64) -> 0 | Q64: =I64-P64 -> 0 | R64: =IFERROR(I64/P64,0) -> 0 | S64: =IF(Q64=0,"",IF(R64=0,"обратить внимание",IF(R64>1,"перерасход","экономия")))
A65: =IFERROR(VLOOKUP(B65,'Статьи'!$A$2:C87,3,0)," ") | I65: =SUM(C65:H65) -> 0 | P65: =SUM(J65:K65) -> 0 | Q65: =I65-P65 -> 0 | R65: =IFERROR(I65/P65,0) -> 0 | S65: =IF(Q65=0,"",IF(R65=0,"обратить внимание",IF(R65>1,"перерасход","экономия")))
A66: =IFERROR(VLOOKUP(B66,'Статьи'!$A$2:C88,3,0)," ") | I66: =SUM(C66:H66) -> 0 | P66: =SUM(J66:K66) -> 0 | Q66: =I66-P66 -> 0 | R66: =IFERROR(I66/P66,0) -> 0 | S66: =IF(Q66=0,"",IF(R66=0,"обратить внимание",IF(R66>1,"перерасход","экономия")))
A67: =IFERROR(VLOOKUP(B67,'Статьи'!$A$2:C89,3,0)," ") | I67: =SUM(C67:H67) -> 0 | P67: =SUM(J67:K67) -> 0 | Q67: =I67-P67 -> 0 | R67: =IFERROR(I67/P67,0) -> 0 | S67: =IF(Q67=0,"",IF(R67=0,"обратить внимание",IF(R67>1,"перерасход","экономия")))
A68: =IFERROR(VLOOKUP(B68,'Статьи'!$A$2:C90,3,0)," ") | I68: =SUM(C68:H68) -> 0 | P68: =SUM(J68:K68) -> 0 | Q68: =I68-P68 -> 0 | R68: =IFERROR(I68/P68,0) -> 0 | S68: =IF(Q68=0,"",IF(R68=0,"обратить внимание",IF(R68>1,"перерасход","экономия")))
A69: =IFERROR(VLOOKUP(B69,'Статьи'!$A$2:C91,3,0)," ") | I69: =SUM(C69:H69) -> 0 | P69: =SUM(J69:K69) -> 0 | Q69: =I69-P69 -> 0 | R69: =IFERROR(I69/P69,0) -> 0 | S69: =IF(Q69=0,"",IF(R69=0,"обратить внимание",IF(R69>1,"перерасход","экономия")))
A70: =IFERROR(VLOOKUP(B70,'Статьи'!$A$2:C92,3,0)," ") | I70: =SUM(C70:H70) -> 0 | P70: =SUM(J70:K70) -> 0 | Q70: =I70-P70 -> 0 | R70: =IFERROR(I70/P70,0) -> 0 | S70: =IF(Q70=0,"",IF(R70=0,"обратить внимание",IF(R70>1,"перерасход","экономия")))
A71: =IFERROR(VLOOKUP(B71,'Статьи'!$A$2:C93,3,0)," ") | I71: =SUM(C71:H71) -> 0 | P71: =SUM(J71:K71) -> 0 | Q71: =I71-P71 -> 0 | R71: =IFERROR(I71/P71,0) -> 0 | S71: =IF(Q71=0,"",IF(R71=0,"обратить внимание",IF(R71>1,"перерасход","экономия")))
A72: =IFERROR(VLOOKUP(B72,'Статьи'!$A$2:C94,3,0)," ") | I72: =SUM(C72:H72) -> 0 | P72: =SUM(J72:K72) -> 0 | Q72: =I72-P72 -> 0 | R72: =IFERROR(I72/P72,0) -> 0 | S72: =IF(Q72=0,"",IF(R72=0,"обратить внимание",IF(R72>1,"перерасход","экономия")))
... A84: =IFERROR(VLOOKUP(B84,'Статьи'!$A$2:C106,3,0)," ") | I84: =SUM(C84:H84) -> 0 | P84: =SUM(J84:K84) -> 0 | Q84: =I84-P84 -> 0 | R84: =IFERROR(I84/P84,0) -> 0 | S84: =IF(Q84=0,"",IF(R84=0,"обратить внимание",IF(R84>1,"перерасход","экономия")))
B85: Валовая прибыль | C85: =C55+C58 -> 5 | D85: =D55+D58 -> 0 | E85: =E55+E58 -> 0 | F85: =F55+F58 -> 0 | G85: =G55+G58 -> 0 | H85: =H55+H58 -> 0 | I85: =I55+I58 -> 5 | J85: =J55+J58 -> 0 | K85: =K55+K58 -> 0 | P85: =P55+P58 -> 0 | Q85: =I85-P85 -> 5 | R85: =IFERROR(I85/P85,0) -> 0 | S85: =IF(Q85=0,"",IF(R85>1,"выполнение","план не выполнен")) -> план не выполнен
B86: Рентабельность по валовой прибыли, % | C86: =IFERROR(C85/C$3,"") -> 1 | D86: =IFERROR(D85/D$3,"") | E86: =IFERROR(E85/E$3,"") | F86: =IFERROR(F85/F$3,"") | G86: =IFERROR(G85/G$3,"") | H86: =IFERROR(H85/H$3,"") | I86: =IFERROR(I85/I$3,"") -> 1 | J86: =IFERROR(J85/J$3,"") | K86: =IFERROR(K85/K$3,"") | P86: =IFERROR(P85/P$3,"") | S86: =IF(Q86=0,"",IF(Q86=0,0,IF(R86>1,"перерасход","экономия")))
S87: =IF(Q87=0,"",IF(Q87=0,0,IF(R87>1,"перерасход","экономия")))
B88: Косвенные расходы | C88: =C101+C132+C89 -> 0 | D88: =D101+D132+D89 -> 0 | E88: =E101+E132+E89 -> 0 | F88: =F101+F132+F89 -> 0 | G88: =G101+G132+G89 -> 0 | H88: =H101+H132+H89 -> 0 | I88: =I101+I132+I89 -> 0 | J88: =J101+J132+J89 -> 0 | K88: =K101+K132+K89 -> 0 | P88: =P101+P132+P89 -> 0 | Q88: =I88-P88 -> 0 | R88: =IFERROR(I88/P88,0) -> 0 | S88: =IF(Q88=0,"",IF(R88>1,"план не выполнен","выполнение"))
B89: Косвенные производственные | C89: =SUM(C90:C100) -> 0 | D89: =SUM(D90:D100) -> 0 | E89: =SUM(E90:E100) -> 0 | F89: =SUM(F90:F100) -> 0 | G89: =SUM(G90:G100) -> 0 | H89: =SUM(H90:H100) -> 0 | I89: =SUM(I90:I100) -> 0 | J89: =SUM(J90:J100) -> 0 | K89: =SUM(K90:K100) -> 0 | P89: =SUM(P90:P100) -> 0 | Q89: =I89-P89 -> 0 | R89: =IFERROR(I89/P89,0) -> 0 | S89: =IF(Q89=0,"",IF(Q89=0,0,IF(R89>1,"перерасход","экономия")))
A90: =IFERROR(VLOOKUP(B90,'Статьи'!$A$2:C112,3,0)," ") | B90: =IFERROR(__xludf.DUMMYFUNCTION("iferror(filter('Статьи'!$A$1:$A177,'Статьи'!$B$1:$B177=$B$89))"),"") | I90: =sum(C90:H90) -> 0 | P90: =SUM(J90:K90) -> 0 | Q90: =I90-P90 -> 0 | R90: =IFERROR(I90/P90,0) -> 0 | S90: =IF(Q90=0,"",IF(R90=0,"обратить внимание",IF(R90>1,"перерасход","экономия")))
A91: =IFERROR(VLOOKUP(B91,'Статьи'!$A$2:C113,3,0)," ") | I91: =sum(C91:H91) -> 0 | P91: =SUM(J91:K91) -> 0 | Q91: =I91-P91 -> 0 | R91: =IFERROR(I91/P91,0) -> 0 | S91: =IF(Q91=0,"",IF(R91=0,"обратить внимание",IF(R91>1,"перерасход","экономия")))
A92: =IFERROR(VLOOKUP(B92,'Статьи'!$A$2:C114,3,0)," ") | I92: =sum(C92:H92) -> 0 | P92: =SUM(J92:K92) -> 0 | Q92: =I92-P92 -> 0 | R92: =IFERROR(I92/P92,0) -> 0 | S92: =IF(Q92=0,"",IF(R92=0,"обратить внимание",IF(R92>1,"перерасход","экономия")))
A93: =IFERROR(VLOOKUP(B93,'Статьи'!$A$2:C115,3,0)," ") | I93: =sum(C93:H93) -> 0 | P93: =SUM(J93:K93) -> 0 | Q93: =I93-P93 -> 0 | R93: =IFERROR(I93/P93,0) -> 0 | S93: =IF(Q93=0,"",IF(R93=0,"обратить внимание",IF(R93>1,"перерасход","экономия")))
A94: =IFERROR(VLOOKUP(B94,'Статьи'!$A$2:C116,3,0)," ") | I94: =sum(C94:H94) -> 0 | P94: =SUM(J94:K94) -> 0 | Q94: =I94-P94 -> 0 | R94: =IFERROR(I94/P94,0) -> 0 | S94: =IF(Q94=0,"",IF(R94=0,"обратить внимание",IF(R94>1,"перерасход","экономия")))
I95: =sum(C95:H95) -> 0 | P95: =sum(F95:J95) -> 0 | Q95: =I95-P95 -> 0 | R95: =IFERROR(I95/P95,0) -> 0 | S95: =IF(Q95=0,"",IF(Q95=0,0,IF(R95>1,"перерасход","экономия")))
I96: =sum(C96:H96) -> 0 | P96: =sum(F96:J96) -> 0 | Q96: =I96-P96 -> 0 | R96: =IFERROR(I96/P96,0) -> 0 | S96: =IF(Q96=0,"",IF(Q96=0,0,IF(R96>1,"перерасход","экономия")))
I97: =sum(C97:H97) -> 0 | P97: =sum(F97:J97) -> 0 | Q97: =I97-P97 -> 0 | R97: =IFERROR(I97/P97,0) -> 0 | S97: =IF(Q97=0,"",IF(Q97=0,0,IF(R97>1,"перерасход","экономия")))
I98: =sum(C98:H98) -> 0 | P98: =sum(F98:J98) -> 0 | Q98: =I98-P98 -> 0 | R98: =IFERROR(I98/P98,0) -> 0 | S98: =IF(Q98=0,"",IF(Q98=0,0,IF(R98>1,"перерасход","экономия")))
I99: =sum(C99:H99) -> 0 | P99: =sum(F99:J99) -> 0 | Q99: =I99-P99 -> 0 | R99: =IFERROR(I99/P99,0) -> 0 | S99: =IF(Q99=0,"",IF(Q99=0,0,IF(R99>1,"перерасход","экономия")))
I100: =sum(C100:H100) -> 0 | P100: =sum(F100:J100) -> 0 | Q100: =I100-P100 -> 0 | R100: =IFERROR(I100/P100,0) -> 0 | S100: =IF(Q100=0,"",IF(Q100=0,0,IF(R100>1,"перерасход","экономия")))
B101: Административные | C101: =SUM(C102:C131) -> 0 | D101: =SUM(D102:D131) -> 0 | E101: =SUM(E102:E131) -> 0 | F101: =SUM(F102:F131) -> 0 | G101: =SUM(G102:G131) -> 0 | H101: =SUM(H102:H131) -> 0 | I101: =SUM(I102:I131) -> 0 | J101: =SUM(J102:J131) -> 0 | K101: =SUM(K102:K131) -> 0 | P101: =SUM(P102:P131) -> 0 | Q101: =I101-P101 -> 0 | R101: =IFERROR(I101/P101,0) -> 0 | S101: =IF(Q101=0,"",IF(R101>1,"план не выполнен","выполнение"))
A102: =IFERROR(VLOOKUP(B102,'Статьи'!$A$2:C124,3,0)," ") -> 1С | B102: =IFERROR(__xludf.DUMMYFUNCTION("iferror(filter('Статьи'!$A$1:$A177,'Статьи'!$B$1:$B177=$B$101))"),"Аренда, коммунальные услуги") -> Аренда, коммунальные услуги | I102: =sum(C102:H102) -> 0 | P102: =SUM(J102:K102) -> 0 | Q102: =I102-P102 -> 0 | R102: =IFERROR(I102/P102,0) -> 0 | S102: =IF(Q102=0,"",IF(R102=0,"обратить внимание",IF(R102>1,"перерасход","экономия")))
A103: =IFERROR(VLOOKUP(B103,'Статьи'!$A$2:C125,3,0)," ") -> 1С | B103: =IFERROR(__xludf.DUMMYFUNCTION("""COMPUTED_VALUE"""),"Аутсорсинг и прочие услуги") -> Аутсорсинг и прочие услуги | I103: =sum(C103:H103) -> 0 | P103: =SUM(J103:K103) -> 0 | Q103: =I103-P103 -> 0 | R103: =IFERROR(I103/P103,0) -> 0 | S103: =IF(Q103=0,"",IF(R103=0,"обратить внимание",IF(R103>1,"перерасход","экономия")))
A104: =IFERROR(VLOOKUP(B104,'Статьи'!$A$2:C126,3,0)," ") -> 1С | B104: =IFERROR(__xludf.DUMMYFUNCTION("""COMPUTED_VALUE"""),"Командировочные расходы") -> Командировочные расходы | I104: =sum(C104:H104) -> 0 | P104: =SUM(J104:K104) -> 0 | Q104: =I104-P104 -> 0 | R104: =IFERROR(I104/P104,0) -> 0 | S104: =IF(Q104=0,"",IF(R104=0,"обратить внимание",IF(R104>1,"перерасход","экономия")))
A105: =IFERROR(VLOOKUP(B105,'Статьи'!$A$2:C127,3,0)," ") -> ДДС отчетного месяца. Без НДС! | B105: =IFERROR(__xludf.DUMMYFUNCTION("""COMPUTED_VALUE"""),"Комиссии банка") -> Комиссии банка | I105: =sum(C105:H105) -> 0 | P105: =SUM(J105:K105) -> 0 | Q105: =I105-P105 -> 0 | R105: =IFERROR(I105/P105,0) -> 0 | S105: =IF(Q105=0,"",IF(R105=0,"обратить внимание",IF(R105>1,"перерасход","экономия")))
A106: =IFERROR(VLOOKUP(B106,'Статьи'!$A$2:C128,3,0)," ") -> ДДС отчетного месяца. Без НДС! | B106: =IFERROR(__xludf.DUMMYFUNCTION("""COMPUTED_VALUE"""),"Обучение сотрудников") -> Обучение сотрудников | I106: =sum(C106:H106) -> 0 | P106: =SUM(J106:K106) -> 0 | Q106: =I106-P106 -> 0 | R106: =IFERROR(I106/P106,0) -> 0 | S106: =IF(Q106=0,"",IF(R106=0,"обратить внимание",IF(R106>1,"перерасход","экономия")))
A107: =IFERROR(VLOOKUP(B107,'Статьи'!$A$2:C129,3,0)," ") -> ДДС отчетного месяца. Без НДС! | B107: =IFERROR(__xludf.DUMMYFUNCTION("""COMPUTED_VALUE"""),"Подбор персонала") -> Подбор персонала | I107: =sum(C107:H107) -> 0 | P107: =SUM(J107:K107) -> 0 | Q107: =I107-P107 -> 0 | R107: =IFERROR(I107/P107,0) -> 0 | S107: =IF(Q107=0,"",IF(R107=0,"обратить внимание",IF(R107>1,"перерасход","экономия")))
A108: =IFERROR(VLOOKUP(B108,'Статьи'!$A$2:C130,3,0)," ") -> ДДС отчетного месяца. Без НДС! | B108: =IFERROR(__xludf.DUMMYFUNCTION("""COMPUTED_VALUE"""),"Почтовые расходы") -> Почтовые расходы | I108: =sum(C108:H108) -> 0 | P108: =SUM(J108:K108) -> 0 | Q108: =I108-P108 -> 0 | R108: =IFERROR(I108/P108,0) -> 0 | S108: =IF(Q108=0,"",IF(R108=0,"обратить внимание",IF(R108>1,"перерасход","экономия")))
A109: =IFERROR(VLOOKUP(B109,'Статьи'!$A$2:C131,3,0)," ") -> ДДС отчетного месяца. Без НДС! | B109: =IFERROR(__xludf.DUMMYFUNCTION("""COMPUTED_VALUE"""),"Представительские расходы") -> Представительские расходы | I109: =sum(C109:H109) -> 0 | P109: =SUM(J109:K109) -> 0 | Q109: =I109-P109 -> 0 | R109: =IFERROR(I109/P109,0) -> 0 | S109: =IF(Q109=0,"",IF(R109=0,"обратить внимание",IF(R109>1,"перерасход","экономия")))
A110: =IFERROR(VLOOKUP(B110,'Статьи'!$A$2:C132,3,0)," ") -> ДДС отчетного месяца. Без НДС! | B110: =IFERROR(__xludf.DUMMYFUNCTION("""COMPUTED_VALUE"""),"Содержание офиса") -> Содержание офиса | I110: =sum(C110:H110) -> 0 | P110: =SUM(J110:K110) -> 0 | Q110: =I110-P110 -> 0 | R110: =IFERROR(I110/P110,0) -> 0 | S110: =IF(Q110=0,"",IF(R110=0,"обратить внимание",IF(R110>1,"перерасход","экономия")))
A111: =IFERROR(VLOOKUP(B111,'Статьи'!$A$2:C133,3,0)," ") -> ДДС отчетного месяца. Без НДС! | B111: =IFERROR(__xludf.DUMMYFUNCTION("""COMPUTED_VALUE"""),"Услуги связи + Интернет") -> Услуги связи + Интернет | I111: =sum(C111:H111) -> 0 | P111: =SUM(J111:K111) -> 0 | Q111: =I111-P111 -> 0 | R111: =IFERROR(I111/P111,0) -> 0 | S111: =IF(Q111=0,"",IF(R111=0,"обратить внимание",IF(R111>1,"перерасход","экономия")))
A112: =IFERROR(VLOOKUP(B112,'Статьи'!$A$2:C134,3,0)," ") -> ДДС отчетного месяца. Без НДС! | B112: =IFERROR(__xludf.DUMMYFUNCTION("""COMPUTED_VALUE"""),"Штрафы") -> Штрафы | I112: =sum(C112:H112) -> 0 | P112: =SUM(J112:K112) -> 0 | Q112: =I112-P112 -> 0 | R112: =IFERROR(I112/P112,0) -> 0 | S112: =IF(Q112=0,"",IF(R112=0,"обратить внимание",IF(R112>1,"перерасход","экономия")))
A113: =IFERROR(VLOOKUP(B113,'Статьи'!$A$2:C135,3,0)," ") | I113: =sum(C113:H113) -> 0 | P113: =SUM(J113:K113) -> 0 | Q113: =I113-P113 -> 0 | R113: =IFERROR(I113/P113,0) -> 0 | S113: =IF(Q113=0,"",IF(R113=0,"обратить внимание",IF(R113>1,"перерасход","экономия")))
A114: =IFERROR(VLOOKUP(B114,'Статьи'!$A$2:C136,3,0)," ") | I114: =sum(C114:H114) -> 0 | P114: =SUM(J114:K114) -> 0 | Q114: =I114-P114 -> 0 | R114: =IFERROR(I114/P114,0) -> 0 | S114: =IF(Q114=0,"",IF(R114=0,"обратить внимание",IF(R114>1,"перерасход","экономия")))
A115: =IFERROR(VLOOKUP(B115,'Статьи'!$A$2:C137,3,0)," ") | I115: =sum(C115:H115) -> 0 | P115: =SUM(J115:K115) -> 0 | Q115: =I115-P115 -> 0 | R115: =IFERROR(I115/P115,0) -> 0 | S115: =IF(Q115=0,"",IF(R115=0,"обратить внимание",IF(R115>1,"перерасход","экономия")))
A116: =IFERROR(VLOOKUP(B116,'Статьи'!$A$2:C138,3,0)," ") | I116: =sum(C116:H116) -> 0 | P116: =SUM(J116:K116) -> 0 | Q116: =I116-P116 -> 0 | R116: =IFERROR(I116/P116,0) -> 0 | S116: =IF(Q116=0,"",IF(R116=0,"обратить внимание",IF(R116>1,"перерасход","экономия")))
A117: =IFERROR(VLOOKUP(B117,'Статьи'!$A$2:C139,3,0)," ") | I117: =sum(C117:H117) -> 0 | P117: =SUM(J117:K117) -> 0 | Q117: =I117-P117 -> 0 | R117: =IFERROR(I117/P117,0) -> 0 | S117: =IF(Q117=0,"",IF(R117=0,"обратить внимание",IF(R117>1,"перерасход","экономия")))
A118: =IFERROR(VLOOKUP(B118,'Статьи'!$A$2:C140,3,0)," ") | I118: =sum(C118:H118) -> 0 | P118: =SUM(J118:K118) -> 0 | Q118: =I118-P118 -> 0 | R118: =IFERROR(I118/P118,0) -> 0 | S118: =IF(Q118=0,"",IF(R118=0,"обратить внимание",IF(R118>1,"перерасход","экономия")))
A119: =IFERROR(VLOOKUP(B119,'Статьи'!$A$2:C141,3,0)," ") | I119: =sum(C119:H119) -> 0 | P119: =SUM(J119:K119) -> 0 | Q119: =I119-P119 -> 0 | R119: =IFERROR(I119/P119,0) -> 0 | S119: =IF(Q119=0,"",IF(R119=0,"обратить внимание",IF(R119>1,"перерасход","экономия")))
A120: =IFERROR(VLOOKUP(B120,'Статьи'!$A$2:C142,3,0)," ") | I120: =sum(C120:H120) -> 0 | P120: =SUM(J120:K120) -> 0 | Q120: =I120-P120 -> 0 | R120: =IFERROR(I120/P120,0) -> 0 | S120: =IF(Q120=0,"",IF(R120=0,"обратить внимание",IF(R120>1,"перерасход","экономия")))
A121: =IFERROR(VLOOKUP(B121,'Статьи'!$A$2:C143,3,0)," ") | I121: =sum(C121:H121) -> 0 | P121: =SUM(J121:K121) -> 0 | Q121: =I121-P121 -> 0 | R121: =IFERROR(I121/P121,0) -> 0 | S121: =IF(Q121=0,"",IF(R121=0,"обратить внимание",IF(R121>1,"перерасход","экономия")))
A122: =IFERROR(VLOOKUP(B122,'Статьи'!$A$2:C144,3,0)," ") | I122: =sum(C122:H122) -> 0 | P122: =SUM(J122:K122) -> 0 | Q122: =I122-P122 -> 0 | R122: =IFERROR(I122/P122,0) -> 0 | S122: =IF(Q122=0,"",IF(R122=0,"обратить внимание",IF(R122>1,"перерасход","экономия")))
A123: =IFERROR(VLOOKUP(B123,'Статьи'!$A$2:C145,3,0)," ") | I123: =sum(C123:H123) -> 0 | P123: =SUM(J123:K123) -> 0 | Q123: =I123-P123 -> 0 | R123: =IFERROR(I123/P123,0) -> 0 | S123: =IF(Q123=0,"",IF(R123=0,"обратить внимание",IF(R123>1,"перерасход","экономия")))
A124: =IFERROR(VLOOKUP(B124,'Статьи'!$A$2:C146,3,0)," ") | I124: =sum(C124:H124) -> 0 | P124: =SUM(J124:K124) -> 0 | Q124: =I124-P124 -> 0 | R124: =IFERROR(I124/P124,0) -> 0 | S124: =IF(Q124=0,"",IF(R124=0,"обратить внимание",IF(R124>1,"перерасход","экономия")))
... A131: =IFERROR(VLOOKUP(B131,'Статьи'!$A$2:C153,3,0)," ") | I131: =sum(C131:H131) -> 0 | P131: =SUM(J131:K131) -> 0 | Q131: =I131-P131 -> 0 | R131: =IFERROR(I131/P131,0) -> 0 | S131: =IF(Q131=0,"",IF(R131=0,"обратить внимание",IF(R131>1,"перерасход","экономия")))
B132: Коммерческие | C132: =SUM(C133:C141) -> 0 | D132: =SUM(D133:D141) -> 0 | E132: =SUM(E133:E141) -> 0 | F132: =SUM(F133:F141) -> 0 | G132: =SUM(G133:G141) -> 0 | H132: =SUM(H133:H141) -> 0 | I132: =sum(C132:H132) -> 0 | J132: =SUM(J133:J141) -> 0 | K132: =SUM(K133:K141) -> 0 | L132: =SUM(L133:L141) -> 0 | M132: =SUM(M133:M141) -> 0 | N132: =SUM(N133:N141) -> 0 | O132: =SUM(O133:O141) -> 0 | P132: =SUM(P133:P141) -> 0 | Q132: =I132-P132 -> 0 | R132: =IFERROR(I132/P132,0) -> 0 | S132: =IF(Q132=0,"",IF(R132>1,"план не выполнен","выполнение"))
A133: =IFERROR(VLOOKUP(B133,'Статьи'!$A$2:C155,3,0)," ") -> ДДС отчетного месяца. Без НДС! | B133: =IFERROR(__xludf.DUMMYFUNCTION("iferror(filter('Статьи'!$A$1:$A177,'Статьи'!$B$1:$B177=$B$132))"),"Подписка на сайты по поиску клиентов") -> Подписка на сайты по поиску клиентов | I133: =sum(C133:H133) -> 0 | P133: =SUM(J133:K133) -> 0 | Q133: =I133-P133 -> 0 | R133: =IFERROR(I133/P133,0) -> 0 | S133: =IF(Q133=0,"",IF(R133=0,"обратить внимание",IF(R133>1,"перерасход","экономия")))
A134: =IFERROR(VLOOKUP(B134,'Статьи'!$A$2:C156,3,0)," ") | I134: =sum(C134:H134) -> 0 | P134: =SUM(J134:K134) -> 0 | Q134: =I134-P134 -> 0 | R134: =IFERROR(I134/P134,0) -> 0 | S134: =IF(Q134=0,"",IF(R134=0,"обратить внимание",IF(R134>1,"перерасход","экономия")))
A135: =IFERROR(VLOOKUP(B135,'Статьи'!$A$2:C157,3,0)," ") | I135: =sum(C135:H135) -> 0 | P135: =SUM(J135:K135) -> 0 | Q135: =I135-P135 -> 0 | R135: =IFERROR(I135/P135,0) -> 0 | S135: =IF(Q135=0,"",IF(R135=0,"обратить внимание",IF(R135>1,"перерасход","экономия")))
A136: =IFERROR(VLOOKUP(B136,'Статьи'!$A$2:C158,3,0)," ") | I136: =sum(C136:H136) -> 0 | P136: =SUM(J136:K136) -> 0 | Q136: =I136-P136 -> 0 | R136: =IFERROR(I136/P136,0) -> 0 | S136: =IF(Q136=0,"",IF(R136=0,"обратить внимание",IF(R136>1,"перерасход","экономия")))
A137: =IFERROR(VLOOKUP(B137,'Статьи'!$A$2:C159,3,0)," ") | I137: =sum(C137:H137) -> 0 | P137: =SUM(J137:K137) -> 0 | Q137: =I137-P137 -> 0 | R137: =IFERROR(I137/P137,0) -> 0 | S137: =IF(Q137=0,"",IF(R137=0,"обратить внимание",IF(R137>1,"перерасход","экономия")))
A138: =IFERROR(VLOOKUP(B138,'Статьи'!$A$2:C160,3,0)," ") | I138: =sum(C138:H138) -> 0 | P138: =SUM(J138:K138) -> 0 | Q138: =I138-P138 -> 0 | R138: =IFERROR(I138/P138,0) -> 0 | S138: =IF(Q138=0,"",IF(R138=0,"обратить внимание",IF(R138>1,"перерасход","экономия")))
A139: =IFERROR(VLOOKUP(B139,'Статьи'!$A$2:C161,3,0)," ") | I139: =sum(C139:H139) -> 0 | P139: =SUM(J139:K139) -> 0 | Q139: =I139-P139 -> 0 | R139: =IFERROR(I139/P139,0) -> 0 | S139: =IF(Q139=0,"",IF(R139=0,"обратить внимание",IF(R139>1,"перерасход","экономия")))
A140: =IFERROR(VLOOKUP(B140,'Статьи'!$A$2:C162,3,0)," ") | I140: =sum(C140:H140) -> 0 | P140: =SUM(J140:K140) -> 0 | Q140: =I140-P140 -> 0 | R140: =IFERROR(I140/P140,0) -> 0 | S140: =IF(Q140=0,"",IF(R140=0,"обратить внимание",IF(R140>1,"перерасход","экономия")))
A141: =IFERROR(VLOOKUP(B141,'Статьи'!$A$2:C163,3,0)," ") | I141: =sum(C141:H141) -> 0 | P141: =sum(F141:J141) -> 0 | Q141: =I141-P141 -> 0 | R141: =IFERROR(I141/P141,0) -> 0 | S141: =IF(Q141=0,"",IF(R141=0,"обратить внимание",IF(R141>1,"перерасход","экономия")))
B142: Операционная прибыль (EBITDA) | C142: =C85+C88 -> 5 | D142: =D85+D88 -> 0 | E142: =E85+E88 -> 0 | F142: =F85+F88 -> 0 | G142: =G85+G88 -> 0 | H142: =H85+H88 -> 0 | I142: =I85+I88 -> 5 | J142: =J85+J88 -> 0 | K142: =K85+K88 -> 0 | P142: =P85+P88 -> 0 | Q142: =I142-P142 -> 5 | R142: =IFERROR(I142/P142,0) -> 0 | S142: =IF(Q142=0,"",IF(R142>1,"выполнение","план не выполнен")) -> план не выполнен
...

Sheet 6
C1: ФАКТ | J1: План | Q1: Отклонения
A2: Источники | C2: {=TRANSPOSE('Справочник'!D2:D7)} -> ООО "Весело живем" | D2: ООО "Некогда грустить" | E2: 3 | F2: 4 | G2: 5 | H2: 6 | I2: Итого | J2: {=TRANSPOSE('Справочник'!D2:D7)} -> ООО "Весело живем" | K2: ООО "Некогда грустить" | L2: 3 | M2: 4 | N2: 5 | O2: 6 | P2: Итого | Q2: факт-план, EUR | R2: факт/план, % | S2: Результат
B3: Выручка | C3: =SUM(C4:C10) -> 6 | D3: =SUM(D4:D10) -> 0 | E3: =SUM(E4:E10) -> 0 | F3: =SUM(F4:F10) -> 0 | G3: =SUM(G4:G10) -> 0 | H3: =SUM(H4:H10) -> 0 | I3: =sum(C3:H3) -> 6 | J3: =SUM(J4:J10) -> 0 | K3: =SUM(K4:K10) -> 0 | P3: =SUM(P4:P10) -> 0 | Q3: =I3-P3 -> 6 | R3: =IFERROR(I3/P3,0) -> 0 | S3: =IF(Q3=0,"",IF(R3>1,"выполнение","план не выполнен")) -> план не выполнен
A4: =IFERROR(VLOOKUP(B4,'Статьи'!$A$2:C26,3,0)," ") -> 1С сч 90.01 убрать НДС! | B4: =IFERROR(__xludf.DUMMYFUNCTION("iferror(filter('Статьи'!$A$1:$A177,'Статьи'!$B$1:$B177=$B$3))"),"Выручка от аренды машиноместа") -> Выручка от аренды машиноместа | C4: 6 | I4: =SUM(C4:H4) -> 6 | P4: =SUM(J4:K4) -> 0 | Q4: =I4-P4 -> 6 | R4: =IFERROR(I4/P4,0) -> 0 | S4: =IF(Q4=0,"",IF(R4=0,"обратить внимание",IF(R4>1,"выполнение","план не выполнен"))) -> обратить внимание
A5: =IFERROR(VLOOKUP(B5,'Статьи'!$A$2:C27,3,0)," ") -> 1С сч 90.01 убрать НДС! | B5: =IFERROR(__xludf.DUMMYFUNCTION("""COMPUTED_VALUE"""),"Выручка за грузоперевозки") -> Выручка за грузоперевозки | I5: =SUM(C5:H5) -> 0 | P5: =SUM(J5:K5) -> 0 | Q5: =I5-P5 -> 0 | R5: =IFERROR(I5/P5,0) -> 0 | S5: =IF(Q5=0,"",IF(R5=0,"обратить внимание",IF(R5>1,"выполнение","план не выполнен")))
A6: =IFERROR(VLOOKUP(B6,'Статьи'!$A$2:C28,3,0)," ") | I6: =SUM(C6:H6) -> 0 | P6: =SUM(F6:J6) -> 0 | Q6: =I6-P6 -> 0 | R6: =IFERROR(I6/P6,0) -> 0 | S6: =IF(Q6=0,"",IF(R6=0,"обратить внимание",IF(R6>1,"выполнение","план не выполнен")))
A7: =IFERROR(VLOOKUP(B7,'Статьи'!$A$2:C29,3,0)," ") | I7: =SUM(C7:H7) -> 0 | P7: =SUM(F7:J7) -> 0 | Q7: =I7-P7 -> 0 | R7: =IFERROR(I7/P7,0) -> 0 | S7: =IF(Q7=0,"",IF(R7=0,"обратить внимание",IF(R7>1,"выполнение","план не выполнен")))
A8: =IFERROR(VLOOKUP(B8,'Статьи'!$A$2:C30,3,0)," ") | I8: =SUM(C8:H8) -> 0 | P8: =SUM(F8:J8) -> 0 | Q8: =I8-P8 -> 0 | R8: =IFERROR(I8/P8,0) -> 0 | S8: =IF(Q8=0,"",IF(R8=0,"обратить внимание",IF(R8>1,"выполнение","план не выполнен")))
A9: =IFERROR(VLOOKUP(B9,'Статьи'!$A$2:C31,3,0)," ") | Q9: =I9-P9 -> 0 | R9: =IFERROR(I9/P9,0) -> 0 | S9: =IF(Q9=0,"",IF(R9=0,"обратить внимание",IF(R9>1,"выполнение","план не выполнен")))
A10: =IFERROR(VLOOKUP(B10,'Статьи'!$A$2:C32,3,0)," ") | Q10: =I10-P10 -> 0 | R10: =IFERROR(I10/P10,0) -> 0 | S10: =IF(Q10=0,"",IF(R10=0,"обратить внимание",IF(R10>1,"выполнение","план не выполнен")))
B11: Производственные расходы | C11: =C12+C58 -> 0 | D11: =D12+D58 -> 0 | E11: =E12+E58 -> 0 | F11: =F12+F58 -> 0 | G11: =G12+G58 -> 0 | H11: =H12+H58 -> 0 | I11: =I12+I58 -> 0 | J11: =J12+J58 -> 0 | K11: =K12+K58 -> 0 | P11: =P12+P58 -> 0 | Q11: =I11-P11 -> 0 | R11: =IFERROR(I11/P11,0) -> 0 | S11: =IF(Q11=0,"",IF(R11>1,"план не выполнен","выполнение"))
B12: Переменные | C12: =sum(C13:C54) -> 0 | D12: =sum(D13:D54) -> 0 | E12: =sum(E13:E54) -> 0 | F12: =sum(F13:F54) -> 0 | G12: =sum(G13:G54) -> 0 | H12: =sum(H13:H54) -> 0 | I12: =sum(I13:I54) -> 0 | J12: =sum(J13:J54) -> 0 | K12: =sum(K13:K54) -> 0 | P12: =sum(P13:P54) -> 0 | Q12: =I12-P12 -> 0 | R12: =IFERROR(I12/P12,0) -> 0 | S12: =IF(Q12=0,"",IF(R12=0,"обратить внимание",IF(R12>1,"перерасход","экономия")))
A13: =IFERROR(VLOOKUP(B13,'Статьи'!$A$2:C35,3,0)," ") -> ДДС отчетного месяца. Без НДС! | B13: =IFERROR(__xludf.DUMMYFUNCTION("iferror(filter('Статьи'!$A$1:$A177,'Статьи'!$B$1:$B177=$B$12))"),"Комиссия топливных компаний") -> Комиссия топливных компаний | I13: =sum(C13:H13) -> 0 | P13: =SUM(J13:K13) -> 0 | Q13: =I13-P13 -> 0 | R13: =IFERROR(I13/P13,0) -> 0 | S13: =IF(Q13=0,"",IF(R13=0,"обратить внимание",IF(R13>1,"перерасход","экономия")))
A14: =IFERROR(VLOOKUP(B14,'Статьи'!$A$2:C36,3,0)," ") -> 1С | B14: =IFERROR(__xludf.DUMMYFUNCTION("""COMPUTED_VALUE"""),"Топливо для грузовых авто ") -> Топливо для грузовых авто | I14: =sum(C14:H14) -> 0 | P14: =SUM(J14:K14) -> 0 | Q14: =I14-P14 -> 0 | R14: =IFERROR(I14/P14,0) -> 0 | S14: =IF(Q14=0,"",IF(R14=0,"обратить внимание",IF(R14>1,"перерасход","экономия")))
A15: =IFERROR(VLOOKUP(B15,'Статьи'!$A$2:C37,3,0)," ") | I15: =sum(C15:H15) -> 0 | P15: =SUM(J15:K15) -> 0 | Q15: =I15-P15 -> 0 | R15: =IFERROR(I15/P15,0) -> 0 | S15: =IF(Q15=0,"",IF(R15=0,"обратить внимание",IF(R15>1,"перерасход","экономия")))
A16: =IFERROR(VLOOKUP(B16,'Статьи'!$A$2:C38,3,0)," ") | I16: =sum(C16:H16) -> 0 | P16: =SUM(J16:K16) -> 0 | Q16: =I16-P16 -> 0 | R16: =IFERROR(I16/P16,0) -> 0 | S16: =IF(Q16=0,"",IF(R16=0,"обратить внимание",IF(R16>1,"перерасход","экономия")))
A17: =IFERROR(VLOOKUP(B17,'Статьи'!$A$2:C39,3,0)," ") | I17: =sum(C17:H17) -> 0 | P17: =sum(F17:J17) -> 0 | Q17: =I17-P17 -> 0 | R17: =IFERROR(I17/P17,0) -> 0 | S17: =IF(Q17=0,"",IF(R17=0,"обратить внимание",IF(R17>1,"перерасход","экономия")))
I18: =sum(C18:H18) -> 0 | P18: =sum(F18:J18) -> 0 | Q18: =I18-P18 -> 0 | R18: =IFERROR(I18/P18,0) -> 0 | S18: =IF(Q18=0,0,IF(R18>1,"перерасход","экономия")) -> 0
I19: =sum(C19:H19) -> 0 | P19: =sum(F19:J19) -> 0 | Q19: =I19-P19 -> 0 | R19: =IFERROR(I19/P19,0) -> 0 | S19: =IF(Q19=0,0,IF(R19>1,"перерасход","экономия")) -> 0
I20: =sum(C20:H20) -> 0 | P20: =sum(F20:J20) -> 0 | Q20: =I20-P20 -> 0 | R20: =IFERROR(I20/P20,0) -> 0 | S20: =IF(Q20=0,0,IF(R20>1,"перерасход","экономия")) -> 0
I21: =sum(C21:H21) -> 0 | P21: =sum(F21:J21) -> 0 | Q21: =I21-P21 -> 0 | R21: =IFERROR(I21/P21,0) -> 0 | S21: =IF(Q21=0,0,IF(R21>1,"перерасход","экономия")) -> 0
I22: =sum(C22:H22) -> 0 | P22: =sum(F22:J22) -> 0 | Q22: =I22-P22 -> 0 | R22: =IFERROR(I22/P22,0) -> 0 | S22: =IF(Q22=0,0,IF(R22>1,"перерасход","экономия")) -> 0
I23: =sum(C23:H23) -> 0 | P23: =sum(F23:J23) -> 0 | Q23: =I23-P23 -> 0 | R23: =IFERROR(I23/P23,0) -> 0 | S23: =IF(Q23=0,0,IF(R23>1,"перерасход","экономия")) -> 0
I24: =sum(C24:H24) -> 0 | P24: =sum(F24:J24) -> 0 | Q24: =I24-P24 -> 0 | R24: =IFERROR(I24/P24,0) -> 0 | S24: =IF(Q24=0,0,IF(R24>1,"перерасход","экономия")) -> 0
I25: =sum(C25:H25) -> 0 | P25: =sum(F25:J25) -> 0 | Q25: =I25-P25 -> 0 | R25: =IFERROR(I25/P25,0) -> 0 | S25: =IF(Q25=0,0,IF(R25>1,"перерасход","экономия")) -> 0
I26: =sum(C26:H26) -> 0 | P26: =sum(F26:J26) -> 0 | Q26: =I26-P26 -> 0 | R26: =IFERROR(I26/P26,0) -> 0 | S26: =IF(Q26=0,0,IF(R26>1,"перерасход","экономия")) -> 0
I27: =sum(C27:H27) -> 0 | P27: =sum(F27:J27) -> 0 | Q27: =I27-P27 -> 0 | R27: =IFERROR(I27/P27,0) -> 0 | S27: =IF(Q27=0,0,IF(R27>1,"перерасход","экономия")) -> 0
I28: =sum(C28:H28) -> 0 | P28: =sum(F28:J28) -> 0 | Q28: =I28-P28 -> 0 | R28: =IFERROR(I28/P28,0) -> 0 | S28: =IF(Q28=0,0,IF(R28>1,"перерасход","экономия")) -> 0
I29: =sum(C29:H29) -> 0 | P29: =sum(F29:J29) -> 0 | Q29: =I29-P29 -> 0 | R29: =IFERROR(I29/P29,0) -> 0 | S29: =IF(Q29=0,0,IF(R29>1,"перерасход","экономия")) -> 0
... I54: =sum(C54:H54) -> 0 | P54: =sum(F54:J54) -> 0 | Q54: =I54-P54 -> 0 | R54: =IFERROR(I54/P54,0) -> 0 | S54: =IF(Q54=0,0,IF(R54>1,"перерасход","экономия")) -> 0
B55: Маржинальный доход | C55: =C3+C12 -> 6 | D55: =D3+D12 -> 0 | E55: =E3+E12 -> 0 | F55: =F3+F12 -> 0 | G55: =G3+G12 -> 0 | H55: =H3+H12 -> 0 | I55: =I3+I12 -> 6 | J55: =J3+J12 -> 0 | K55: =K3+K12 -> 0 | P55: =P3+P12 -> 0 | Q55: =I55-P55 -> 6 | R55: =IFERROR(I55/P55,0) -> 0 | S55: =IF(Q55=0,"",IF(R55>1,"выполнение","план не выполнен")) -> план не выполнен
B56: Рентабельность по марже | C56: =IFERROR(C55/C$3,"") -> 1 | D56: =IFERROR(D55/D$3,"") | E56: =IFERROR(E55/E$3,"") | F56: =IFERROR(F55/F$3,"") | G56: =IFERROR(G55/G$3,"") | H56: =IFERROR(H55/H$3,"") | I56: =IFERROR(I55/I$3,"") -> 1 | J56: =IFERROR(J55/J$3,"") | K56: =IFERROR(K55/K$3,"") | P56: =IFERROR(P55/P$3,"")
B58: Общепроизводственные | C58: =sum(C59:C79) -> 0 | D58: =sum(D59:D79) -> 0 | E58: =sum(E59:E79) -> 0 | F58: =sum(F59:F79) -> 0 | G58: =sum(G59:G79) -> 0 | H58: =sum(H59:H79) -> 0 | I58: =SUM(I59:I84) -> 0 | J58: =SUM(J59:J84) -> 0 | K58: =SUM(K59:K84) -> 0 | P58: =SUM(P59:P84) -> 0 | Q58: =I58-P58 -> 0 | R58: =IFERROR(I58/P58,0) -> 0 | S58: =IF(Q58=0,"",IF(R58>1,"план не выполнен","выполнение"))
A59: =IFERROR(VLOOKUP(B59,'Статьи'!$A$2:C81,3,0)," ") -> 1С | B59: =IFERROR(__xludf.DUMMYFUNCTION("iferror(filter('Статьи'!$A$1:$A177,'Статьи'!$B$1:$B177=$B$58))"),"Зарплата производственного персонала") -> Зарплата производственного персонала | I59: =SUM(C59:H59) -> 0 | P59: =SUM(J59:K59) -> 0 | Q59: =I59-P59 -> 0 | R59: =IFERROR(I59/P59,0) -> 0 | S59: =IF(Q59=0,"",IF(R59=0,"обратить внимание",IF(R59>1,"перерасход","экономия")))
A60: =IFERROR(VLOOKUP(B60,'Статьи'!$A$2:C82,3,0)," ") -> ДДС отчетного месяца. Без НДС! | B60: =IFERROR(__xludf.DUMMYFUNCTION("""COMPUTED_VALUE"""),"Таможенные расходы") -> Таможенные расходы | I60: =SUM(C60:H60) -> 0 | P60: =SUM(J60:K60) -> 0 | Q60: =I60-P60 -> 0 | R60: =IFERROR(I60/P60,0) -> 0 | S60: =IF(Q60=0,"",IF(R60=0,"обратить внимание",IF(R60>1,"перерасход","экономия")))
A61: =IFERROR(VLOOKUP(B61,'Статьи'!$A$2:C83,3,0)," ") | I61: =SUM(C61:H61) -> 0 | P61: =SUM(J61:K61) -> 0 | Q61: =I61-P61 -> 0 | R61: =IFERROR(I61/P61,0) -> 0 | S61: =IF(Q61=0,"",IF(R61=0,"обратить внимание",IF(R61>1,"перерасход","экономия")))
A62: =IFERROR(VLOOKUP(B62,'Статьи'!$A$2:C84,3,0)," ") | I62: =SUM(C62:H62) -> 0 | P62: =SUM(J62:K62) -> 0 | Q62: =I62-P62 -> 0 | R62: =IFERROR(I62/P62,0) -> 0 | S62: =IF(Q62=0,"",IF(R62=0,"обратить внимание",IF(R62>1,"перерасход","экономия")))
A63: =IFERROR(VLOOKUP(B63,'Статьи'!$A$2:C85,3,0)," ") | I63: =SUM(C63:H63) -> 0 | P63: =SUM(J63:K63) -> 0 | Q63: =I63-P63 -> 0 | R63: =IFERROR(I63/P63,0) -> 0 | S63: =IF(Q63=0,"",IF(R63=0,"обратить внимание",IF(R63>1,"перерасход","экономия")))
A64: =IFERROR(VLOOKUP(B64,'Статьи'!$A$2:C86,3,0)," ") | I64: =SUM(C64:H64) -> 0 | P64: =SUM(J64:K64) -> 0 | Q64: =I64-P64 -> 0 | R64: =IFERROR(I64/P64,0) -> 0 | S64: =IF(Q64=0,"",IF(R64=0,"обратить внимание",IF(R64>1,"перерасход","экономия")))
A65: =IFERROR(VLOOKUP(B65,'Статьи'!$A$2:C87,3,0)," ") | I65: =SUM(C65:H65) -> 0 | P65: =SUM(J65:K65) -> 0 | Q65: =I65-P65 -> 0 | R65: =IFERROR(I65/P65,0) -> 0 | S65: =IF(Q65=0,"",IF(R65=0,"обратить внимание",IF(R65>1,"перерасход","экономия")))
A66: =IFERROR(VLOOKUP(B66,'Статьи'!$A$2:C88,3,0)," ") | I66: =SUM(C66:H66) -> 0 | P66: =SUM(J66:K66) -> 0 | Q66: =I66-P66 -> 0 | R66: =IFERROR(I66/P66,0) -> 0 | S66: =IF(Q66=0,"",IF(R66=0,"обратить внимание",IF(R66>1,"перерасход","экономия")))
A67: =IFERROR(VLOOKUP(B67,'Статьи'!$A$2:C89,3,0)," ") | I67: =SUM(C67:H67) -> 0 | P67: =SUM(J67:K67) -> 0 | Q67: =I67-P67 -> 0 | R67: =IFERROR(I67/P67,0) -> 0 | S67: =IF(Q67=0,"",IF(R67=0,"обратить внимание",IF(R67>1,"перерасход","экономия")))
A68: =IFERROR(VLOOKUP(B68,'Статьи'!$A$2:C90,3,0)," ") | I68: =SUM(C68:H68) -> 0 | P68: =SUM(J68:K68) -> 0 | Q68: =I68-P68 -> 0 | R68: =IFERROR(I68/P68,0) -> 0 | S68: =IF(Q68=0,"",IF(R68=0,"обратить внимание",IF(R68>1,"перерасход","экономия")))
A69: =IFERROR(VLOOKUP(B69,'Статьи'!$A$2:C91,3,0)," ") | I69: =SUM(C69:H69) -> 0 | P69: =SUM(J69:K69) -> 0 | Q69: =I69-P69 -> 0 | R69: =IFERROR(I69/P69,0) -> 0 | S69: =IF(Q69=0,"",IF(R69=0,"обратить внимание",IF(R69>1,"перерасход","экономия")))
A70: =IFERROR(VLOOKUP(B70,'Статьи'!$A$2:C92,3,0)," ") | I70: =SUM(C70:H70) -> 0 | P70: =SUM(J70:K70) -> 0 | Q70: =I70-P70 -> 0 | R70: =IFERROR(I70/P70,0) -> 0 | S70: =IF(Q70=0,"",IF(R70=0,"обратить внимание",IF(R70>1,"перерасход","экономия")))
A71: =IFERROR(VLOOKUP(B71,'Статьи'!$A$2:C93,3,0)," ") | I71: =SUM(C71:H71) -> 0 | P71: =SUM(J71:K71) -> 0 | Q71: =I71-P71 -> 0 | R71: =IFERROR(I71/P71,0) -> 0 | S71: =IF(Q71=0,"",IF(R71=0,"обратить внимание",IF(R71>1,"перерасход","экономия")))
A72: =IFERROR(VLOOKUP(B72,'Статьи'!$A$2:C94,3,0)," ") | I72: =SUM(C72:H72) -> 0 | P72: =SUM(J72:K72) -> 0 | Q72: =I72-P72 -> 0 | R72: =IFERROR(I72/P72,0) -> 0 | S72: =IF(Q72=0,"",IF(R72=0,"обратить внимание",IF(R72>1,"перерасход","экономия")))
... A84: =IFERROR(VLOOKUP(B84,'Статьи'!$A$2:C106,3,0)," ") | I84: =SUM(C84:H84) -> 0 | P84: =SUM(J84:K84) -> 0 | Q84: =I84-P84 -> 0 | R84: =IFERROR(I84/P84,0) -> 0 | S84: =IF(Q84=0,"",IF(R84=0,"обратить внимание",IF(R84>1,"перерасход","экономия")))
B85: Валовая прибыль | C85: =C55+C58 -> 6 | D85: =D55+D58 -> 0 | E85: =E55+E58 -> 0 | F85: =F55+F58 -> 0 | G85: =G55+G58 -> 0 | H85: =H55+H58 -> 0 | I85: =I55+I58 -> 6 | J85: =J55+J58 -> 0 | K85: =K55+K58 -> 0 | P85: =P55+P58 -> 0 | Q85: =I85-P85 -> 6 | R85: =IFERROR(I85/P85,0) -> 0 | S85: =IF(Q85=0,"",IF(R85>1,"выполнение","план не выполнен")) -> план не выполнен
B86: Рентабельность по валовой прибыли, % | C86: =IFERROR(C85/C$3,"") -> 1 | D86: =IFERROR(D85/D$3,"") | E86: =IFERROR(E85/E$3,"") | F86: =IFERROR(F85/F$3,"") | G86: =IFERROR(G85/G$3,"") | H86: =IFERROR(H85/H$3,"") | I86: =IFERROR(I85/I$3,"") -> 1 | J86: =IFERROR(J85/J$3,"") | K86: =IFERROR(K85/K$3,"") | P86: =IFERROR(P85/P$3,"") | S86: =IF(Q86=0,"",IF(Q86=0,0,IF(R86>1,"перерасход","экономия")))
S87: =IF(Q87=0,"",IF(Q87=0,0,IF(R87>1,"перерасход","экономия")))
B88: Косвенные расходы | C88: =C101+C132+C89 -> 0 | D88: =D101+D132+D89 -> 0 | E88: =E101+E132+E89 -> 0 | F88: =F101+F132+F89 -> 0 | G88: =G101+G132+G89 -> 0 | H88: =H101+H132+H89 -> 0 | I88: =I101+I132+I89 -> 0 | J88: =J101+J132+J89 -> 0 | K88: =K101+K132+K89 -> 0 | P88: =P101+P132+P89 -> 0 | Q88: =I88-P88 -> 0 | R88: =IFERROR(I88/P88,0) -> 0 | S88: =IF(Q88=0,"",IF(R88>1,"план не выполнен","выполнение"))
B89: Косвенные производственные | C89: =SUM(C90:C100) -> 0 | D89: =SUM(D90:D100) -> 0 | E89: =SUM(E90:E100) -> 0 | F89: =SUM(F90:F100) -> 0 | G89: =SUM(G90:G100) -> 0 | H89: =SUM(H90:H100) -> 0 | I89: =SUM(I90:I100) -> 0 | J89: =SUM(J90:J100) -> 0 | K89: =SUM(K90:K100) -> 0 | P89: =SUM(P90:P100) -> 0 | Q89: =I89-P89 -> 0 | R89: =IFERROR(I89/P89,0) -> 0 | S89: =IF(Q89=0,"",IF(Q89=0,0,IF(R89>1,"перерасход","экономия")))
A90: =IFERROR(VLOOKUP(B90,'Статьи'!$A$2:C112,3,0)," ") | B90: =IFERROR(__xludf.DUMMYFUNCTION("iferror(filter('Статьи'!$A$1:$A177,'Статьи'!$B$1:$B177=$B$89))"),"") | I90: =sum(C90:H90) -> 0 | P90: =SUM(J90:K90) -> 0 | Q90: =I90-P90 -> 0 | R90: =IFERROR(I90/P90,0) -> 0 | S90: =IF(Q90=0,"",IF(R90=0,"обратить внимание",IF(R90>1,"перерасход","экономия")))
A91: =IFERROR(VLOOKUP(B91,'Статьи'!$A$2:C113,3,0)," ") | I91: =sum(C91:H91) -> 0 | P91: =SUM(J91:K91) -> 0 | Q91: =I91-P91 -> 0 | R91: =IFERROR(I91/P91,0) -> 0 | S91: =IF(Q91=0,"",IF(R91=0,"обратить внимание",IF(R91>1,"перерасход","экономия")))
A92: =IFERROR(VLOOKUP(B92,'Статьи'!$A$2:C114,3,0)," ") | I92: =sum(C92:H92) -> 0 | P92: =SUM(J92:K92) -> 0 | Q92: =I92-P92 -> 0 | R92: =IFERROR(I92/P92,0) -> 0 | S92: =IF(Q92=0,"",IF(R92=0,"обратить внимание",IF(R92>1,"перерасход","экономия")))
A93: =IFERROR(VLOOKUP(B93,'Статьи'!$A$2:C115,3,0)," ") | I93: =sum(C93:H93) -> 0 | P93: =SUM(J93:K93) -> 0 | Q93: =I93-P93 -> 0 | R93: =IFERROR(I93/P93,0) -> 0 | S93: =IF(Q93=0,"",IF(R93=0,"обратить внимание",IF(R93>1,"перерасход","экономия")))
A94: =IFERROR(VLOOKUP(B94,'Статьи'!$A$2:C116,3,0)," ") | I94: =sum(C94:H94) -> 0 | P94: =SUM(J94:K94) -> 0 | Q94: =I94-P94 -> 0 | R94: =IFERROR(I94/P94,0) -> 0 | S94: =IF(Q94=0,"",IF(R94=0,"обратить внимание",IF(R94>1,"перерасход","экономия")))
I95: =sum(C95:H95) -> 0 | P95: =sum(F95:J95) -> 0 | Q95: =I95-P95 -> 0 | R95: =IFERROR(I95/P95,0) -> 0 | S95: =IF(Q95=0,"",IF(Q95=0,0,IF(R95>1,"перерасход","экономия")))
I96: =sum(C96:H96) -> 0 | P96: =sum(F96:J96) -> 0 | Q96: =I96-P96 -> 0 | R96: =IFERROR(I96/P96,0) -> 0 | S96: =IF(Q96=0,"",IF(Q96=0,0,IF(R96>1,"перерасход","экономия")))
I97: =sum(C97:H97) -> 0 | P97: =sum(F97:J97) -> 0 | Q97: =I97-P97 -> 0 | R97: =IFERROR(I97/P97,0) -> 0 | S97: =IF(Q97=0,"",IF(Q97=0,0,IF(R97>1,"перерасход","экономия")))
I98: =sum(C98:H98) -> 0 | P98: =sum(F98:J98) -> 0 | Q98: =I98-P98 -> 0 | R98: =IFERROR(I98/P98,0) -> 0 | S98: =IF(Q98=0,"",IF(Q98=0,0,IF(R98>1,"перерасход","экономия")))
I99: =sum(C99:H99) -> 0 | P99: =sum(F99:J99) -> 0 | Q99: =I99-P99 -> 0 | R99: =IFERROR(I99/P99,0) -> 0 | S99: =IF(Q99=0,"",IF(Q99=0,0,IF(R99>1,"перерасход","экономия")))
I100: =sum(C100:H100) -> 0 | P100: =sum(F100:J100) -> 0 | Q100: =I100-P100 -> 0 | R100: =IFERROR(I100/P100,0) -> 0 | S100: =IF(Q100=0,"",IF(Q100=0,0,IF(R100>1,"перерасход","экономия")))
B101: Административные | C101: =SUM(C102:C131) -> 0 | D101: =SUM(D102:D131) -> 0 | E101: =SUM(E102:E131) -> 0 | F101: =SUM(F102:F131) -> 0 | G101: =SUM(G102:G131) -> 0 | H101: =SUM(H102:H131) -> 0 | I101: =SUM(I102:I131) -> 0 | J101: =SUM(J102:J131) -> 0 | K101: =SUM(K102:K131) -> 0 | P101: =SUM(P102:P131) -> 0 | Q101: =I101-P101 -> 0 | R101: =IFERROR(I101/P101,0) -> 0 | S101: =IF(Q101=0,"",IF(R101>1,"план не выполнен","выполнение"))
A102: =IFERROR(VLOOKUP(B102,'Статьи'!$A$2:C124,3,0)," ") -> 1С | B102: =IFERROR(__xludf.DUMMYFUNCTION("iferror(filter('Статьи'!$A$1:$A177,'Статьи'!$B$1:$B177=$B$101))"),"Аренда, коммунальные услуги") -> Аренда, коммунальные услуги | I102: =sum(C102:H102) -> 0 | P102: =SUM(J102:K102) -> 0 | Q102: =I102-P102 -> 0 | R102: =IFERROR(I102/P102,0) -> 0 | S102: =IF(Q102=0,"",IF(R102=0,"обратить внимание",IF(R102>1,"перерасход","экономия")))
A103: =IFERROR(VLOOKUP(B103,'Статьи'!$A$2:C125,3,0)," ") -> 1С | B103: =IFERROR(__xludf.DUMMYFUNCTION("""COMPUTED_VALUE"""),"Аутсорсинг и прочие услуги") -> Аутсорсинг и прочие услуги | I103: =sum(C103:H103) -> 0 | P103: =SUM(J103:K103) -> 0 | Q103: =I103-P103 -> 0 | R103: =IFERROR(I103/P103,0) -> 0 | S103: =IF(Q103=0,"",IF(R103=0,"обратить внимание",IF(R103>1,"перерасход","экономия")))
A104: =IFERROR(VLOOKUP(B104,'Статьи'!$A$2:C126,3,0)," ") -> 1С | B104: =IFERROR(__xludf.DUMMYFUNCTION("""COMPUTED_VALUE"""),"Командировочные расходы") -> Командировочные расходы | I104: =sum(C104:H104) -> 0 | P104: =SUM(J104:K104) -> 0 | Q104: =I104-P104 -> 0 | R104: =IFERROR(I104/P104,0) -> 0 | S104: =IF(Q104=0,"",IF(R104=0,"обратить внимание",IF(R104>1,"перерасход","экономия")))
A105: =IFERROR(VLOOKUP(B105,'Статьи'!$A$2:C127,3,0)," ") -> ДДС отчетного месяца. Без НДС! | B105: =IFERROR(__xludf.DUMMYFUNCTION("""COMPUTED_VALUE"""),"Комиссии банка") -> Комиссии банка | I105: =sum(C105:H105) -> 0 | P105: =SUM(J105:K105) -> 0 | Q105: =I105-P105 -> 0 | R105: =IFERROR(I105/P105,0) -> 0 | S105: =IF(Q105=0,"",IF(R105=0,"обратить внимание",IF(R105>1,"перерасход","экономия")))
A106: =IFERROR(VLOOKUP(B106,'Статьи'!$A$2:C128,3,0)," ") -> ДДС отчетного месяца. Без НДС! | B106: =IFERROR(__xludf.DUMMYFUNCTION("""COMPUTED_VALUE"""),"Обучение сотрудников") -> Обучение сотрудников | I106: =sum(C106:H106) -> 0 | P106: =SUM(J106:K106) -> 0 | Q106: =I106-P106 -> 0 | R106: =IFERROR(I106/P106,0) -> 0 | S106: =IF(Q106=0,"",IF(R106=0,"обратить внимание",IF(R106>1,"перерасход","экономия")))
A107: =IFERROR(VLOOKUP(B107,'Статьи'!$A$2:C129,3,0)," ") -> ДДС отчетного месяца. Без НДС! | B107: =IFERROR(__xludf.DUMMYFUNCTION("""COMPUTED_VALUE"""),"Подбор персонала") -> Подбор персонала | I107: =sum(C107:H107) -> 0 | P107: =SUM(J107:K107) -> 0 | Q107: =I107-P107 -> 0 | R107: =IFERROR(I107/P107,0) -> 0 | S107: =IF(Q107=0,"",IF(R107=0,"обратить внимание",IF(R107>1,"перерасход","экономия")))
A108: =IFERROR(VLOOKUP(B108,'Статьи'!$A$2:C130,3,0)," ") -> ДДС отчетного месяца. Без НДС! | B108: =IFERROR(__xludf.DUMMYFUNCTION("""COMPUTED_VALUE"""),"Почтовые расходы") -> Почтовые расходы | I108: =sum(C108:H108) -> 0 | P108: =SUM(J108:K108) -> 0 | Q108: =I108-P108 -> 0 | R108: =IFERROR(I108/P108,0) -> 0 | S108: =IF(Q108=0,"",IF(R108=0,"обратить внимание",IF(R108>1,"перерасход","экономия")))
A109: =IFERROR(VLOOKUP(B109,'Статьи'!$A$2:C131,3,0)," ") -> ДДС отчетного месяца. Без НДС! | B109: =IFERROR(__xludf.DUMMYFUNCTION("""COMPUTED_VALUE"""),"Представительские расходы") -> Представительские расходы | I109: =sum(C109:H109) -> 0 | P109: =SUM(J109:K109) -> 0 | Q109: =I109-P109 -> 0 | R109: =IFERROR(I109/P109,0) -> 0 | S109: =IF(Q109=0,"",IF(R109=0,"обратить внимание",IF(R109>1,"перерасход","экономия")))
A110: =IFERROR(VLOOKUP(B110,'Статьи'!$A$2:C132,3,0)," ") -> ДДС отчетного месяца. Без НДС! | B110: =IFERROR(__xludf.DUMMYFUNCTION("""COMPUTED_VALUE"""),"Содержание офиса") -> Содержание офиса | I110: =sum(C110:H110) -> 0 | P110: =SUM(J110:K110) -> 0 | Q110: =I110-P110 -> 0 | R110: =IFERROR(I110/P110,0) -> 0 | S110: =IF(Q110=0,"",IF(R110=0,"обратить внимание",IF(R110>1,"перерасход","экономия")))
A111: =IFERROR(VLOOKUP(B111,'Статьи'!$A$2:C133,3,0)," ") -> ДДС отчетного месяца. Без НДС! | B111: =IFERROR(__xludf.DUMMYFUNCTION("""COMPUTED_VALUE"""),"Услуги связи + Интернет") -> Услуги связи + Интернет | I111: =sum(C111:H111) -> 0 | P111: =SUM(J111:K111) -> 0 | Q111: =I111-P111 -> 0 | R111: =IFERROR(I111/P111,0) -> 0 | S111: =IF(Q111=0,"",IF(R111=0,"обратить внимание",IF(R111>1,"перерасход","экономия")))
A112: =IFERROR(VLOOKUP(B112,'Статьи'!$A$2:C134,3,0)," ") -> ДДС отчетного месяца. Без НДС! | B112: =IFERROR(__xludf.DUMMYFUNCTION("""COMPUTED_VALUE"""),"Штрафы") -> Штрафы | I112: =sum(C112:H112) -> 0 | P112: =SUM(J112:K112) -> 0 | Q112: =I112-P112 -> 0 | R112: =IFERROR(I112/P112,0) -> 0 | S112: =IF(Q112=0,"",IF(R112=0,"обратить внимание",IF(R112>1,"перерасход","экономия")))
A113: =IFERROR(VLOOKUP(B113,'Статьи'!$A$2:C135,3,0)," ") | I113: =sum(C113:H113) -> 0 | P113: =SUM(J113:K113) -> 0 | Q113: =I113-P113 -> 0 | R113: =IFERROR(I113/P113,0) -> 0 | S113: =IF(Q113=0,"",IF(R113=0,"обратить внимание",IF(R113>1,"перерасход","экономия")))
A114: =IFERROR(VLOOKUP(B114,'Статьи'!$A$2:C136,3,0)," ") | I114: =sum(C114:H114) -> 0 | P114: =SUM(J114:K114) -> 0 | Q114: =I114-P114 -> 0 | R114: =IFERROR(I114/P114,0) -> 0 | S114: =IF(Q114=0,"",IF(R114=0,"обратить внимание",IF(R114>1,"перерасход","экономия")))
A115: =IFERROR(VLOOKUP(B115,'Статьи'!$A$2:C137,3,0)," ") | I115: =sum(C115:H115) -> 0 | P115: =SUM(J115:K115) -> 0 | Q115: =I115-P115 -> 0 | R115: =IFERROR(I115/P115,0) -> 0 | S115: =IF(Q115=0,"",IF(R115=0,"обратить внимание",IF(R115>1,"перерасход","экономия")))
A116: =IFERROR(VLOOKUP(B116,'Статьи'!$A$2:C138,3,0)," ") | I116: =sum(C116:H116) -> 0 | P116: =SUM(J116:K116) -> 0 | Q116: =I116-P116 -> 0 | R116: =IFERROR(I116/P116,0) -> 0 | S116: =IF(Q116=0,"",IF(R116=0,"обратить внимание",IF(R116>1,"перерасход","экономия")))
A117: =IFERROR(VLOOKUP(B117,'Статьи'!$A$2:C139,3,0)," ") | I117: =sum(C117:H117) -> 0 | P117: =SUM(J117:K117) -> 0 | Q117: =I117-P117 -> 0 | R117: =IFERROR(I117/P117,0) -> 0 | S117: =IF(Q117=0,"",IF(R117=0,"обратить внимание",IF(R117>1,"перерасход","экономия")))
A118: =IFERROR(VLOOKUP(B118,'Статьи'!$A$2:C140,3,0)," ") | I118: =sum(C118:H118) -> 0 | P118: =SUM(J118:K118) -> 0 | Q118: =I118-P118 -> 0 | R118: =IFERROR(I118/P118,0) -> 0 | S118: =IF(Q118=0,"",IF(R118=0,"обратить внимание",IF(R118>1,"перерасход","экономия")))
A119: =IFERROR(VLOOKUP(B119,'Статьи'!$A$2:C141,3,0)," ") | I119: =sum(C119:H119) -> 0 | P119: =SUM(J119:K119) -> 0 | Q119: =I119-P119 -> 0 | R119: =IFERROR(I119/P119,0) -> 0 | S119: =IF(Q119=0,"",IF(R119=0,"обратить внимание",IF(R119>1,"перерасход","экономия")))
A120: =IFERROR(VLOOKUP(B120,'Статьи'!$A$2:C142,3,0)," ") | I120: =sum(C120:H120) -> 0 | P120: =SUM(J120:K120) -> 0 | Q120: =I120-P120 -> 0 | R120: =IFERROR(I120/P120,0) -> 0 | S120: =IF(Q120=0,"",IF(R120=0,"обратить внимание",IF(R120>1,"перерасход","экономия")))
A121: =IFERROR(VLOOKUP(B121,'Статьи'!$A$2:C143,3,0)," ") | I121: =sum(C121:H121) -> 0 | P121: =SUM(J121:K121) -> 0 | Q121: =I121-P121 -> 0 | R121: =IFERROR(I121/P121,0) -> 0 | S121: =IF(Q121=0,"",IF(R121=0,"обратить внимание",IF(R121>1,"перерасход","экономия")))
A122: =IFERROR(VLOOKUP(B122,'Статьи'!$A$2:C144,3,0)," ") | I122: =sum(C122:H122) -> 0 | P122: =SUM(J122:K122) -> 0 | Q122: =I122-P122 -> 0 | R122: =IFERROR(I122/P122,0) -> 0 | S122: =IF(Q122=0,"",IF(R122=0,"обратить внимание",IF(R122>1,"перерасход","экономия")))
A123: =IFERROR(VLOOKUP(B123,'Статьи'!$A$2:C145,3,0)," ") | I123: =sum(C123:H123) -> 0 | P123: =SUM(J123:K123) -> 0 | Q123: =I123-P123 -> 0 | R123: =IFERROR(I123/P123,0) -> 0 | S123: =IF(Q123=0,"",IF(R123=0,"обратить внимание",IF(R123>1,"перерасход","экономия")))
A124: =IFERROR(VLOOKUP(B124,'Статьи'!$A$2:C146,3,0)," ") | I124: =sum(C124:H124) -> 0 | P124: =SUM(J124:K124) -> 0 | Q124: =I124-P124 -> 0 | R124: =IFERROR(I124/P124,0) -> 0 | S124: =IF(Q124=0,"",IF(R124=0,"обратить внимание",IF(R124>1,"перерасход","экономия")))
... A131: =IFERROR(VLOOKUP(B131,'Статьи'!$A$2:C153,3,0)," ") | I131: =sum(C131:H131) -> 0 | P131: =SUM(J131:K131) -> 0 | Q131: =I131-P131 -> 0 | R131: =IFERROR(I131/P131,0) -> 0 | S131: =IF(Q131=0,"",IF(R131=0,"обратить внимание",IF(R131>1,"перерасход","экономия")))
B132: Коммерческие | C132: =SUM(C133:C141) -> 0 | D132: =SUM(D133:D141) -> 0 | E132: =SUM(E133:E141) -> 0 | F132: =SUM(F133:F141) -> 0 | G132: =SUM(G133:G141) -> 0 | H132: =SUM(H133:H141) -> 0 | I132: =sum(C132:H132) -> 0 | J132: =SUM(J133:J141) -> 0 | K132: =SUM(K133:K141) -> 0 | L132: =SUM(L133:L141) -> 0 | M132: =SUM(M133:M141) -> 0 | N132: =SUM(N133:N141) -> 0 | O132: =SUM(O133:O141) -> 0 | P132: =SUM(P133:P141) -> 0 | Q132: =I132-P132 -> 0 | R132: =IFERROR(I132/P132,0) -> 0 | S132: =IF(Q132=0,"",IF(R132>1,"план не выполнен","выполнение"))
A133: =IFERROR(VLOOKUP(B133,'Статьи'!$A$2:C155,3,0)," ") -> ДДС отчетного месяца. Без НДС! | B133: =IFERROR(__xludf.DUMMYFUNCTION("iferror(filter('Статьи'!$A$1:$A177,'Статьи'!$B$1:$B177=$B$132))"),"Подписка на сайты по поиску клиентов") -> Подписка на сайты по поиску клиентов | I133: =sum(C133:H133) -> 0 | P133: =SUM(J133:K133) -> 0 | Q133: =I133-P133 -> 0 | R133: =IFERROR(I133/P133,0) -> 0 | S133: =IF(Q133=0,"",IF(R133=0,"обратить внимание",IF(R133>1,"перерасход","экономия")))
A134: =IFERROR(VLOOKUP(B134,'Статьи'!$A$2:C156,3,0)," ") | I134: =sum(C134:H134) -> 0 | P134: =SUM(J134:K134) -> 0 | Q134: =I134-P134 -> 0 | R134: =IFERROR(I134/P134,0) -> 0 | S134: =IF(Q134=0,"",IF(R134=0,"обратить внимание",IF(R134>1,"перерасход","экономия")))
A135: =IFERROR(VLOOKUP(B135,'Статьи'!$A$2:C157,3,0)," ") | I135: =sum(C135:H135) -> 0 | P135: =SUM(J135:K135) -> 0 | Q135: =I135-P135 -> 0 | R135: =IFERROR(I135/P135,0) -> 0 | S135: =IF(Q135=0,"",IF(R135=0,"обратить внимание",IF(R135>1,"перерасход","экономия")))
A136: =IFERROR(VLOOKUP(B136,'Статьи'!$A$2:C158,3,0)," ") | I136: =sum(C136:H136) -> 0 | P136: =SUM(J136:K136) -> 0 | Q136: =I136-P136 -> 0 | R136: =IFERROR(I136/P136,0) -> 0 | S136: =IF(Q136=0,"",IF(R136=0,"обратить внимание",IF(R136>1,"перерасход","экономия")))
A137: =IFERROR(VLOOKUP(B137,'Статьи'!$A$2:C159,3,0)," ") | I137: =sum(C137:H137) -> 0 | P137: =SUM(J137:K137) -> 0 | Q137: =I137-P137 -> 0 | R137: =IFERROR(I137/P137,0) -> 0 | S137: =IF(Q137=0,"",IF(R137=0,"обратить внимание",IF(R137>1,"перерасход","экономия")))
A138: =IFERROR(VLOOKUP(B138,'Статьи'!$A$2:C160,3,0)," ") | I138: =sum(C138:H138) -> 0 | P138: =SUM(J138:K138) -> 0 | Q138: =I138-P138 -> 0 | R138: =IFERROR(I138/P138,0) -> 0 | S138: =IF(Q138=0,"",IF(R138=0,"обратить внимание",IF(R138>1,"перерасход","экономия")))
A139: =IFERROR(VLOOKUP(B139,'Статьи'!$A$2:C161,3,0)," ") | I139: =sum(C139:H139) -> 0 | P139: =SUM(J139:K139) -> 0 | Q139: =I139-P139 -> 0 | R139: =IFERROR(I139/P139,0) -> 0 | S139: =IF(Q139=0,"",IF(R139=0,"обратить внимание",IF(R139>1,"перерасход","экономия")))
A140: =IFERROR(VLOOKUP(B140,'Статьи'!$A$2:C162,3,0)," ") | I140: =sum(C140:H140) -> 0 | P140: =SUM(J140:K140) -> 0 | Q140: =I140-P140 -> 0 | R140: =IFERROR(I140/P140,0) -> 0 | S140: =IF(Q140=0,"",IF(R140=0,"обратить внимание",IF(R140>1,"перерасход","экономия")))
A141: =IFERROR(VLOOKUP(B141,'Статьи'!$A$2:C163,3,0)," ") | I141: =sum(C141:H141) -> 0 | P141: =sum(F141:J141) -> 0 | Q141: =I141-P141 -> 0 | R141: =IFERROR(I141/P141,0) -> 0 | S141: =IF(Q141=0,"",IF(R141=0,"обратить внимание",IF(R141>1,"перерасход","экономия")))
B142: Операционная прибыль (EBITDA) | C142: =C85+C88 -> 6 | D142: =D85+D88 -> 0 | E142: =E85+E88 -> 0 | F142: =F85+F88 -> 0 | G142: =G85+G88 -> 0 | H142: =H85+H88 -> 0 | I142: =I85+I88 -> 6 | J142: =J85+J88 -> 0 | K142: =K85+K88 -> 0 | P142: =P85+P88 -> 0 | Q142: =I142-P142 -> 6 | R142: =IFERROR(I142/P142,0) -> 0 | S142: =IF(Q142=0,"",IF(R142>1,"выполнение","план не выполнен")) -> план не выполнен
...

Sheet 7
C1: ФАКТ | J1: План | Q1: Отклонения
A2: Источники | C2: {=TRANSPOSE('Справочник'!D2:D7)} -> ООО "Весело живем" | D2: ООО "Некогда грустить" | E2: 3 | F2: 4 | G2: 5 | H2: 6 | I2: Итого | J2: {=TRANSPOSE('Справочник'!D2:D7)} -> ООО "Весело живем" | K2: ООО "Некогда грустить" | L2: 3 | M2: 4 | N2: 5 | O2: 6 | P2: Итого | Q2: факт-план, EUR | R2: факт/план, % | S2: Результат
B3: Выручка | C3: =SUM(C4:C10) -> 7 | D3: =SUM(D4:D10) -> 0 | E3: =SUM(E4:E10) -> 0 | F3: =SUM(F4:F10) -> 0 | G3: =SUM(G4:G10) -> 0 | H3: =SUM(H4:H10) -> 0 | I3: =sum(C3:H3) -> 7 | J3: =SUM(J4:J10) -> 0 | K3: =SUM(K4:K10) -> 0 | P3: =SUM(P4:P10) -> 0 | Q3: =I3-P3 -> 7 | R3: =IFERROR(I3/P3,0) -> 0 | S3: =IF(Q3=0,"",IF(R3>1,"выполнение","план не выполнен")) -> план не выполнен
A4: =IFERROR(VLOOKUP(B4,'Статьи'!$A$2:C26,3,0)," ") -> 1С сч 90.01 убрать НДС! | B4: =IFERROR(__xludf.DUMMYFUNCTION("iferror(filter('Статьи'!$A$1:$A177,'Статьи'!$B$1:$B177=$B$3))"),"Выручка от аренды машиноместа") -> Выручка от аренды машиноместа | C4: 7 | I4: =SUM(C4:H4) -> 7 | P4: =SUM(J4:K4) -> 0 | Q4: =I4-P4 -> 7 | R4: =IFERROR(I4/P4,0) -> 0 | S4: =IF(Q4=0,"",IF(R4=0,"обратить внимание",IF(R4>1,"выполнение","план не выполнен"))) -> обратить внимание
A5: =IFERROR(VLOOKUP(B5,'Статьи'!$A$2:C27,3,0)," ") -> 1С сч 90.01 убрать НДС! | B5: =IFERROR(__xludf.DUMMYFUNCTION("""COMPUTED_VALUE"""),"Выручка за грузоперевозки") -> Выручка за грузоперевозки | I5: =SUM(C5:H5) -> 0 | P5: =SUM(J5:K5) -> 0 | Q5: =I5-P5 -> 0 | R5: =IFERROR(I5/P5,0) -> 0 | S5: =IF(Q5=0,"",IF(R5=0,"обратить внимание",IF(R5>1,"выполнение","план не выполнен")))
A6: =IFERROR(VLOOKUP(B6,'Статьи'!$A$2:C28,3,0)," ") | I6: =SUM(C6:H6) -> 0 | P6: =SUM(F6:J6) -> 0 | Q6: =I6-P6 -> 0 | R6: =IFERROR(I6/P6,0) -> 0 | S6: =IF(Q6=0,"",IF(R6=0,"обратить внимание",IF(R6>1,"выполнение","план не выполнен")))
A7: =IFERROR(VLOOKUP(B7,'Статьи'!$A$2:C29,3,0)," ") | I7: =SUM(C7:H7) -> 0 | P7: =SUM(F7:J7) -> 0 | Q7: =I7-P7 -> 0 | R7: =IFERROR(I7/P7,0) -> 0 | S7: =IF(Q7=0,"",IF(R7=0,"обратить внимание",IF(R7>1,"выполнение","план не выполнен")))
A8: =IFERROR(VLOOKUP(B8,'Статьи'!$A$2:C30,3,0)," ") | I8: =SUM(C8:H8) -> 0 | P8: =SUM(F8:J8) -> 0 | Q8: =I8-P8 -> 0 | R8: =IFERROR(I8/P8,0) -> 0 | S8: =IF(Q8=0,"",IF(R8=0,"обратить внимание",IF(R8>1,"выполнение","план не выполнен")))
A9: =IFERROR(VLOOKUP(B9,'Статьи'!$A$2:C31,3,0)," ") | Q9: =I9-P9 -> 0 | R9: =IFERROR(I9/P9,0) -> 0 | S9: =IF(Q9=0,"",IF(R9=0,"обратить внимание",IF(R9>1,"выполнение","план не выполнен")))
A10: =IFERROR(VLOOKUP(B10,'Статьи'!$A$2:C32,3,0)," ") | Q10: =I10-P10 -> 0 | R10: =IFERROR(I10/P10,0) -> 0 | S10: =IF(Q10=0,"",IF(R10=0,"обратить внимание",IF(R10>1,"выполнение","план не выполнен")))
B11: Производственные расходы | C11: =C12+C58 -> 0 | D11: =D12+D58 -> 0 | E11: =E12+E58 -> 0 | F11: =F12+F58 -> 0 | G11: =G12+G58 -> 0 | H11: =H12+H58 -> 0 | I11: =I12+I58 -> 0 | J11: =J12+J58 -> 0 | K11: =K12+K58 -> 0 | P11: =P12+P58 -> 0 | Q11: =I11-P11 -> 0 | R11: =IFERROR(I11/P11,0) -> 0 | S11: =IF(Q11=0,"",IF(R11>1,"план не выполнен","выполнение"))
B12: Переменные | C12: =sum(C13:C54) -> 0 | D12: =sum(D13:D54) -> 0 | E12: =sum(E13:E54) -> 0 | F12: =sum(F13:F54) -> 0 | G12: =sum(G13:G54) -> 0 | H12: =sum(H13:H54) -> 0 | I12: =sum(I13:I54) -> 0 | J12: =sum(J13:J54) -> 0 | K12: =sum(K13:K54) -> 0 | P12: =sum(P13:P54) -> 0 | Q12: =I12-P12 -> 0 | R12: =IFERROR(I12/P12,0) -> 0 | S12: =IF(Q12=0,"",IF(R12=0,"обратить внимание",IF(R12>1,"перерасход","экономия")))
A13: =IFERROR(VLOOKUP(B13,'Статьи'!$A$2:C35,3,0)," ") -> ДДС отчетного месяца. Без НДС! | B13: =IFERROR(__xludf.DUMMYFUNCTION("iferror(filter('Статьи'!$A$1:$A177,'Статьи'!$B$1:$B177=$B$12))"),"Комиссия топливных компаний") -> Комиссия топливных компаний | I13: =sum(C13:H13) -> 0 | P13: =SUM(J13:K13) -> 0 | Q13: =I13-P13 -> 0 | R13: =IFERROR(I13/P13,0) -> 0 | S13: =IF(Q13=0,"",IF(R13=0,"обратить внимание",IF(R13>1,"перерасход","экономия")))
A14: =IFERROR(VLOOKUP(B14,'Статьи'!$A$2:C36,3,0)," ") -> 1С | B14: =IFERROR(__xludf.DUMMYFUNCTION("""COMPUTED_VALUE"""),"Топливо для грузовых авто ") -> Топливо для грузовых авто | I14: =sum(C14:H14) -> 0 | P14: =SUM(J14:K14) -> 0 | Q14: =I14-P14 -> 0 | R14: =IFERROR(I14/P14,0) -> 0 | S14: =IF(Q14=0,"",IF(R14=0,"обратить внимание",IF(R14>1,"перерасход","экономия")))
A15: =IFERROR(VLOOKUP(B15,'Статьи'!$A$2:C37,3,0)," ") | I15: =sum(C15:H15) -> 0 | P15: =SUM(J15:K15) -> 0 | Q15: =I15-P15 -> 0 | R15: =IFERROR(I15/P15,0) -> 0 | S15: =IF(Q15=0,"",IF(R15=0,"обратить внимание",IF(R15>1,"перерасход","экономия")))
A16: =IFERROR(VLOOKUP(B16,'Статьи'!$A$2:C38,3,0)," ") | I16: =sum(C16:H16) -> 0 | P16: =SUM(J16:K16) -> 0 | Q16: =I16-P16 -> 0 | R16: =IFERROR(I16/P16,0) -> 0 | S16: =IF(Q16=0,"",IF(R16=0,"обратить внимание",IF(R16>1,"перерасход","экономия")))
A17: =IFERROR(VLOOKUP(B17,'Статьи'!$A$2:C39,3,0)," ") | I17: =sum(C17:H17) -> 0 | P17: =sum(F17:J17) -> 0 | Q17: =I17-P17 -> 0 | R17: =IFERROR(I17/P17,0) -> 0 | S17: =IF(Q17=0,"",IF(R17=0,"обратить внимание",IF(R17>1,"перерасход","экономия")))
I18: =sum(C18:H18) -> 0 | P18: =sum(F18:J18) -> 0 | Q18: =I18-P18 -> 0 | R18: =IFERROR(I18/P18,0) -> 0 | S18: =IF(Q18=0,0,IF(R18>1,"перерасход","экономия")) -> 0
I19: =sum(C19:H19) -> 0 | P19: =sum(F19:J19) -> 0 | Q19: =I19-P19 -> 0 | R19: =IFERROR(I19/P19,0) -> 0 | S19: =IF(Q19=0,0,IF(R19>1,"перерасход","экономия")) -> 0
I20: =sum(C20:H20) -> 0 | P20: =sum(F20:J20) -> 0 | Q20: =I20-P20 -> 0 | R20: =IFERROR(I20/P20,0) -> 0 | S20: =IF(Q20=0,0,IF(R20>1,"перерасход","экономия")) -> 0
I21: =sum(C21:H21) -> 0 | P21: =sum(F21:J21) -> 0 | Q21: =I21-P21 -> 0 | R21: =IFERROR(I21/P21,0) -> 0 | S21: =IF(Q21=0,0,IF(R21>1,"перерасход","экономия")) -> 0
I22: =sum(C22:H22) -> 0 | P22: =sum(F22:J22) -> 0 | Q22: =I22-P22 -> 0 | R22: =IFERROR(I22/P22,0) -> 0 | S22: =IF(Q22=0,0,IF(R22>1,"перерасход","экономия")) -> 0
I23: =sum(C23:H23) -> 0 | P23: =sum(F23:J23) -> 0 | Q23: =I23-P23 -> 0 | R23: =IFERROR(I23/P23,0) -> 0 | S23: =IF(Q23=0,0,IF(R23>1,"перерасход","экономия")) -> 0
I24: =sum(C24:H24) -> 0 | P24: =sum(F24:J24) -> 0 | Q24: =I24-P24 -> 0 | R24: =IFERROR(I24/P24,0) -> 0 | S24: =IF(Q24=0,0,IF(R24>1,"перерасход","экономия")) -> 0
I25: =sum(C25:H25) -> 0 | P25: =sum(F25:J25) -> 0 | Q25: =I25-P25 -> 0 | R25: =IFERROR(I25/P25,0) -> 0 | S25: =IF(Q25=0,0,IF(R25>1,"перерасход","экономия")) -> 0
I26: =sum(C26:H26) -> 0 | P26: =sum(F26:J26) -> 0 | Q26: =I26-P26 -> 0 | R26: =IFERROR(I26/P26,0) -> 0 | S26: =IF(Q26=0,0,IF(R26>1,"перерасход","экономия")) -> 0
I27: =sum(C27:H27) -> 0 | P27: =sum(F27:J27) -> 0 | Q27: =I27-P27 -> 0 | R27: =IFERROR(I27/P27,0) -> 0 | S27: =IF(Q27=0,0,IF(R27>1,"перерасход","экономия")) -> 0
I28: =sum(C28:H28) -> 0 | P28: =sum(F28:J28) -> 0 | Q28: =I28-P28 -> 0 | R28: =IFERROR(I28/P28,0) -> 0 | S28: =IF(Q28=0,0,IF(R28>1,"перерасход","экономия")) -> 0
I29: =sum(C29:H29) -> 0 | P29: =sum(F29:J29) -> 0 | Q29: =I29-P29 -> 0 | R29: =IFERROR(I29/P29,0) -> 0 | S29: =IF(Q29=0,0,IF(R29>1,"перерасход","экономия")) -> 0
... I54: =sum(C54:H54) -> 0 | P54: =sum(F54:J54) -> 0 | Q54: =I54-P54 -> 0 | R54: =IFERROR(I54/P54,0) -> 0 | S54: =IF(Q54=0,0,IF(R54>1,"перерасход","экономия")) -> 0
B55: Маржинальный доход | C55: =C3+C12 -> 7 | D55: =D3+D12 -> 0 | E55: =E3+E12 -> 0 | F55: =F3+F12 -> 0 | G55: =G3+G12 -> 0 | H55: =H3+H12 -> 0 | I55: =I3+I12 -> 7 | J55: =J3+J12 -> 0 | K55: =K3+K12 -> 0 | P55: =P3+P12 -> 0 | Q55: =I55-P55 -> 7 | R55: =IFERROR(I55/P55,0) -> 0 | S55: =IF(Q55=0,"",IF(R55>1,"выполнение","план не выполнен")) -> план не выполнен
B56: Рентабельность по марже | C56: =IFERROR(C55/C$3,"") -> 1 | D56: =IFERROR(D55/D$3,"") | E56: =IFERROR(E55/E$3,"") | F56: =IFERROR(F55/F$3,"") | G56: =IFERROR(G55/G$3,"") | H56: =IFERROR(H55/H$3,"") | I56: =IFERROR(I55/I$3,"") -> 1 | J56: =IFERROR(J55/J$3,"") | K56: =IFERROR(K55/K$3,"") | P56: =IFERROR(P55/P$3,"")
B58: Общепроизводственные | C58: =sum(C59:C79) -> 0 | D58: =sum(D59:D79) -> 0 | E58: =sum(E59:E79) -> 0 | F58: =sum(F59:F79) -> 0 | G58: =sum(G59:G79) -> 0 | H58: =sum(H59:H79) -> 0 | I58: =SUM(I59:I84) -> 0 | J58: =SUM(J59:J84) -> 0 | K58: =SUM(K59:K84) -> 0 | P58: =SUM(P59:P84) -> 0 | Q58: =I58-P58 -> 0 | R58: =IFERROR(I58/P58,0) -> 0 | S58: =IF(Q58=0,"",IF(R58>1,"план не выполнен","выполнение"))
A59: =IFERROR(VLOOKUP(B59,'Статьи'!$A$2:C81,3,0)," ") -> 1С | B59: =IFERROR(__xludf.DUMMYFUNCTION("iferror(filter('Статьи'!$A$1:$A177,'Статьи'!$B$1:$B177=$B$58))"),"Зарплата производственного персонала") -> Зарплата производственного персонала | I59: =SUM(C59:H59) -> 0 | P59: =SUM(J59:K59) -> 0 | Q59: =I59-P59 -> 0 | R59: =IFERROR(I59/P59,0) -> 0 | S59: =IF(Q59=0,"",IF(R59=0,"обратить внимание",IF(R59>1,"перерасход","экономия")))
A60: =IFERROR(VLOOKUP(B60,'Статьи'!$A$2:C82,3,0)," ") -> ДДС отчетного месяца. Без НДС! | B60: =IFERROR(__xludf.DUMMYFUNCTION("""COMPUTED_VALUE"""),"Таможенные расходы") -> Таможенные расходы | I60: =SUM(C60:H60) -> 0 | P60: =SUM(J60:K60) -> 0 | Q60: =I60-P60 -> 0 | R60: =IFERROR(I60/P60,0) -> 0 | S60: =IF(Q60=0,"",IF(R60=0,"обратить внимание",IF(R60>1,"перерасход","экономия")))
A61: =IFERROR(VLOOKUP(B61,'Статьи'!$A$2:C83,3,0)," ") | I61: =SUM(C61:H61) -> 0 | P61: =SUM(J61:K61) -> 0 | Q61: =I61-P61 -> 0 | R61: =IFERROR(I61/P61,0) -> 0 | S61: =IF(Q61=0,"",IF(R61=0,"обратить внимание",IF(R61>1,"перерасход","экономия")))
A62: =IFERROR(VLOOKUP(B62,'Статьи'!$A$2:C84,3,0)," ") | I62: =SUM(C62:H62) -> 0 | P62: =SUM(J62:K62) -> 0 | Q62: =I62-P62 -> 0 | R62: =IFERROR(I62/P62,0) -> 0 | S62: =IF(Q62=0,"",IF(R62=0,"обратить внимание",IF(R62>1,"перерасход","экономия")))
A63: =IFERROR(VLOOKUP(B63,'Статьи'!$A$2:C85,3,0)," ") | I63: =SUM(C63:H63) -> 0 | P63: =SUM(J63:K63) -> 0 | Q63: =I63-P63 -> 0 | R63: =IFERROR(I63/P63,0) -> 0 | S63: =IF(Q63=0,"",IF(R63=0,"обратить внимание",IF(R63>1,"перерасход","экономия")))
A64: =IFERROR(VLOOKUP(B64,'Статьи'!$A$2:C86,3,0)," ") | I64: =SUM(C64:H64) -> 0 | P64: =SUM(J64:K64) -> 0 | Q64: =I64-P64 -> 0 | R64: =IFERROR(I64/P64,0) -> 0 | S64: =IF(Q64=0,"",IF(R64=0,"обратить внимание",IF(R64>1,"перерасход","экономия")))
A65: =IFERROR(VLOOKUP(B65,'Статьи'!$A$2:C87,3,0)," ") | I65: =SUM(C65:H65) -> 0 | P65: =SUM(J65:K65) -> 0 | Q65: =I65-P65 -> 0 | R65: =IFERROR(I65/P65,0) -> 0 | S65: =IF(Q65=0,"",IF(R65=0,"обратить внимание",IF(R65>1,"перерасход","экономия")))
A66: =IFERROR(VLOOKUP(B66,'Статьи'!$A$2:C88,3,0)," ") | I66: =SUM(C66:H66) -> 0 | P66: =SUM(J66:K66) -> 0 | Q66: =I66-P66 -> 0 | R66: =IFERROR(I66/P66,0) -> 0 | S66: =IF(Q66=0,"",IF(R66=0,"обратить внимание",IF(R66>1,"перерасход","экономия")))
A67: =IFERROR(VLOOKUP(B67,'Статьи'!$A$2:C89,3,0)," ") | I67: =SUM(C67:H67) -> 0 | P67: =SUM(J67:K67) -> 0 | Q67: =I67-P67 -> 0 | R67: =IFERROR(I67/P67,0) -> 0 | S67: =IF(Q67=0,"",IF(R67=0,"обратить внимание",IF(R67>1,"перерасход","экономия")))
A68: =IFERROR(VLOOKUP(B68,'Статьи'!$A$2:C90,3,0)," ") | I68: =SUM(C68:H68) -> 0 | P68: =SUM(J68:K68) -> 0 | Q68: =I68-P68 -> 0 | R68: =IFERROR(I68/P68,0) -> 0 | S68: =IF(Q68=0,"",IF(R68=0,"обратить внимание",IF(R68>1,"перерасход","экономия")))
A69: =IFERROR(VLOOKUP(B69,'Статьи'!$A$2:C91,3,0)," ") | I69: =SUM(C69:H69) -> 0 | P69: =SUM(J69:K69) -> 0 | Q69: =I69-P69 -> 0 | R69: =IFERROR(I69/P69,0) -> 0 | S69: =IF(Q69=0,"",IF(R69=0,"обратить внимание",IF(R69>1,"перерасход","экономия")))
A70: =IFERROR(VLOOKUP(B70,'Статьи'!$A$2:C92,3,0)," ") | I70: =SUM(C70:H70) -> 0 | P70: =SUM(J70:K70) -> 0 | Q70: =I70-P70 -> 0 | R70: =IFERROR(I70/P70,0) -> 0 | S70: =IF(Q70=0,"",IF(R70=0,"обратить внимание",IF(R70>1,"перерасход","экономия")))
A71: =IFERROR(VLOOKUP(B71,'Статьи'!$A$2:C93,3,0)," ") | I71: =SUM(C71:H71) -> 0 | P71: =SUM(J71:K71) -> 0 | Q71: =I71-P71 -> 0 | R71: =IFERROR(I71/P71,0) -> 0 | S71: =IF(Q71=0,"",IF(R71=0,"обратить внимание",IF(R71>1,"перерасход","экономия")))
A72: =IFERROR(VLOOKUP(B72,'Статьи'!$A$2:C94,3,0)," ") | I72: =SUM(C72:H72) -> 0 | P72: =SUM(J72:K72) -> 0 | Q72: =I72-P72 -> 0 | R72: =IFERROR(I72/P72,0) -> 0 | S72: =IF(Q72=0,"",IF(R72=0,"обратить внимание",IF(R72>1,"перерасход","экономия")))
... A84: =IFERROR(VLOOKUP(B84,'Статьи'!$A$2:C106,3,0)," ") | I84: =SUM(C84:H84) -> 0 | P84: =SUM(J84:K84) -> 0 | Q84: =I84-P84 -> 0 | R84: =IFERROR(I84/P84,0) -> 0 | S84: =IF(Q84=0,"",IF(R84=0,"обратить внимание",IF(R84>1,"перерасход","экономия")))
B85: Валовая прибыль | C85: =C55+C58 -> 7 | D85: =D55+D58 -> 0 | E85: =E55+E58 -> 0 | F85: =F55+F58 -> 0 | G85: =G55+G58 -> 0 | H85: =H55+H58 -> 0 | I85: =I55+I58 -> 7 | J85: =J55+J58 -> 0 | K85: =K55+K58 -> 0 | P85: =P55+P58 -> 0 | Q85: =I85-P85 -> 7 | R85: =IFERROR(I85/P85,0) -> 0 | S85: =IF(Q85=0,"",IF(R85>1,"выполнение","план не выполнен")) -> план не выполнен
B86: Рентабельность по валовой прибыли, % | C86: =IFERROR(C85/C$3,"") -> 1 | D86: =IFERROR(D85/D$3,"") | E86: =IFERROR(E85/E$3,"") | F86: =IFERROR(F85/F$3,"") | G86: =IFERROR(G85/G$3,"") | H86: =IFERROR(H85/H$3,"") | I86: =IFERROR(I85/I$3,"") -> 1 | J86: =IFERROR(J85/J$3,"") | K86: =IFERROR(K85/K$3,"") | P86: =IFERROR(P85/P$3,"") | S86: =IF(Q86=0,"",IF(Q86=0,0,IF(R86>1,"перерасход","экономия")))
S87: =IF(Q87=0,"",IF(Q87=0,0,IF(R87>1,"перерасход","экономия")))
B88: Косвенные расходы | C88: =C101+C132+C89 -> 0 | D88: =D101+D132+D89 -> 0 | E88: =E101+E132+E89 -> 0 | F88: =F101+F132+F89 -> 0 | G88: =G101+G132+G89 -> 0 | H88: =H101+H132+H89 -> 0 | I88: =I101+I132+I89 -> 0 | J88: =J101+J132+J89 -> 0 | K88: =K101+K132+K89 -> 0 | P88: =P101+P132+P89 -> 0 | Q88: =I88-P88 -> 0 | R88: =IFERROR(I88/P88,0) -> 0 | S88: =IF(Q88=0,"",IF(R88>1,"план не выполнен","выполнение"))
B89: Косвенные производственные | C89: =SUM(C90:C100) -> 0 | D89: =SUM(D90:D100) -> 0 | E89: =SUM(E90:E100) -> 0 | F89: =SUM(F90:F100) -> 0 | G89: =SUM(G90:G100) -> 0 | H89: =SUM(H90:H100) -> 0 | I89: =SUM(I90:I100) -> 0 | J89: =SUM(J90:J100) -> 0 | K89: =SUM(K90:K100) -> 0 | P89: =SUM(P90:P100) -> 0 | Q89: =I89-P89 -> 0 | R89: =IFERROR(I89/P89,0) -> 0 | S89: =IF(Q89=0,"",IF(Q89=0,0,IF(R89>1,"перерасход","экономия")))
A90: =IFERROR(VLOOKUP(B90,'Статьи'!$A$2:C112,3,0)," ") | B90: =IFERROR(__xludf.DUMMYFUNCTION("iferror(filter('Статьи'!$A$1:$A177,'Статьи'!$B$1:$B177=$B$89))"),"") | I90: =sum(C90:H90) -> 0 | P90: =SUM(J90:K90) -> 0 | Q90: =I90-P90 -> 0 | R90: =IFERROR(I90/P90,0) -> 0 | S90: =IF(Q90=0,"",IF(R90=0,"обратить внимание",IF(R90>1,"перерасход","экономия")))
A91: =IFERROR(VLOOKUP(B91,'Статьи'!$A$2:C113,3,0)," ") | I91: =sum(C91:H91) -> 0 | P91: =SUM(J91:K91) -> 0 | Q91: =I91-P91 -> 0 | R91: =IFERROR(I91/P91,0) -> 0 | S91: =IF(Q91=0,"",IF(R91=0,"обратить внимание",IF(R91>1,"перерасход","экономия")))
A92: =IFERROR(VLOOKUP(B92,'Статьи'!$A$2:C114,3,0)," ") | I92: =sum(C92:H92) -> 0 | P92: =SUM(J92:K92) -> 0 | Q92: =I92-P92 -> 0 | R92: =IFERROR(I92/P92,0) -> 0 | S92: =IF(Q92=0,"",IF(R92=0,"обратить внимание",IF(R92>1,"перерасход","экономия")))
A93: =IFERROR(VLOOKUP(B93,'Статьи'!$A$2:C115,3,0)," ") | I93: =sum(C93:H93) -> 0 | P93: =SUM(J93:K93) -> 0 | Q93: =I93-P93 -> 0 | R93: =IFERROR(I93/P93,0) -> 0 | S93: =IF(Q93=0,"",IF(R93=0,"обратить внимание",IF(R93>1,"перерасход","экономия")))
A94: =IFERROR(VLOOKUP(B94,'Статьи'!$A$2:C116,3,0)," ") | I94: =sum(C94:H94) -> 0 | P94: =SUM(J94:K94) -> 0 | Q94: =I94-P94 -> 0 | R94: =IFERROR(I94/P94,0) -> 0 | S94: =IF(Q94=0,"",IF(R94=0,"обратить внимание",IF(R94>1,"перерасход","экономия")))
I95: =sum(C95:H95) -> 0 | P95: =sum(F95:J95) -> 0 | Q95: =I95-P95 -> 0 | R95: =IFERROR(I95/P95,0) -> 0 | S95: =IF(Q95=0,"",IF(Q95=0,0,IF(R95>1,"перерасход","экономия")))
I96: =sum(C96:H96) -> 0 | P96: =sum(F96:J96) -> 0 | Q96: =I96-P96 -> 0 | R96: =IFERROR(I96/P96,0) -> 0 | S96: =IF(Q96=0,"",IF(Q96=0,0,IF(R96>1,"перерасход","экономия")))
I97: =sum(C97:H97) -> 0 | P97: =sum(F97:J97) -> 0 | Q97: =I97-P97 -> 0 | R97: =IFERROR(I97/P97,0) -> 0 | S97: =IF(Q97=0,"",IF(Q97=0,0,IF(R97>1,"перерасход","экономия")))
I98: =sum(C98:H98) -> 0 | P98: =sum(F98:J98) -> 0 | Q98: =I98-P98 -> 0 | R98: =IFERROR(I98/P98,0) -> 0 | S98: =IF(Q98=0,"",IF(Q98=0,0,IF(R98>1,"перерасход","экономия")))
I99: =sum(C99:H99) -> 0 | P99: =sum(F99:J99) -> 0 | Q99: =I99-P99 -> 0 | R99: =IFERROR(I99/P99,0) -> 0 | S99: =IF(Q99=0,"",IF(Q99=0,0,IF(R99>1,"перерасход","экономия")))
I100: =sum(C100:H100) -> 0 | P100: =sum(F100:J100) -> 0 | Q100: =I100-P100 -> 0 | R100: =IFERROR(I100/P100,0) -> 0 | S100: =IF(Q100=0,"",IF(Q100=0,0,IF(R100>1,"перерасход","экономия")))
